Workbook

Sheet LCOE
A1: LCOE and learning effects calculator v2.2 (2024) | D1: Good comparison of different LCOE methodologies: Foster, J., Wagner, L., & Bratanova, A. (2014). LCOE models: A comparison of the theoretical frameworks and key assumptions. CSIRO. https://www.researchgate.net/publication/264311516_LCOE_models_A_comparison_of_the_theoretical_frameworks_and_key_assumptions
A2: Link to OneDrive version (view only) | D2: Alter ONLY inputs in GREEN CELLS!
A3: Power plant details | D3: LCOE 1 | E3: LCOE 2 | F3: LCOE 3 | G3: LCOE 4 | H3: LCOE 5 | I3: LCOE 6 | J3: LCOE 7 | K3: LCOE 8 | L3: Explanations
C4: Type | D4: Gas Combined Cycle Turbine (CCGT) | E4: Gas Combined Cycle Turbine (CCGT) | F4: Gas Combined Cycle Turbine (CCGT) | G4: Gas Combined Cycle Turbine (CCGT) | H4: Gas Combined Cycle Turbine (CCGT) | I4: Gas Combined Cycle Turbine (CCGT) | J4: Gas Combined Cycle Turbine (CCGT) | K4: Gas Combined Cycle Turbine (CCGT) | L4: Type of power plant
C5: Name | D5: CCGT in Belgium (2020) | E5: CCGT in Belgium (2020) | F5: CCGT in Belgium (2020) | G5: CCGT in Belgium (2020) | H5: CCGT in Belgium (2020) | I5: CCGT in Belgium (2020) | J5: CCGT in Belgium (2020) | K5: CCGT in Belgium (2020) | L5: The name of the calculation. Will be used in the Results.
B6: Currency | C6: Currency used for LCOE calculations | D6: USD | E6: USD | F6: USD | G6: USD | H6: USD | I6: USD | J6: USD | K6: USD | L6: Currency used for calculations. Most international studies use USD.
C7: Price reference year | L7: Reference year to use in currency conversion.
C8: Currency used | D8: USD | E8: USD | F8: USD | G8: USD | H8: USD | I8: USD | J8: USD | K8: USD | L8: Currency used to report the results and in the learning curve calculations
C9: Conversion rate at reference year | D9: 1 | E9: 1 | F9: 1 | G9: 1 | H9: 1 | I9: 1 | J9: 1 | K9: 1 | L9: The conversion rate during reference year, from currency used in calculations to currency used in the results.
B10: Financing | C10: Debt % | D10: 0.9 | E10: 0.9 | F10: 0.9 | G10: 0.9 | H10: 0.9 | I10: 0.9 | J10: 0.9 | K10: 0.9 | L10: How the project is financed? The share of debt of total financing.
C11: Cost of debt (private discount rate) | D11: 0 | E11: 0.03 | F11: 0.05 | G11: 0.07 | H11: 0.08 | I11: 0.1 | J11: 0.12 | K11: 0.14 | L11: The discount rate used for debt; the interest rate that banks will charge the consumer. Also known as the private discount rate (PDR) or opportunity cost of capital
C12: Cost of equity (discount rate) | D12: 0 | E12: 0.03 | F12: 0.05 | G12: 0.07 | H12: 0.08 | I12: 0.1 | J12: 0.12 | K12: 0.14 | L12: The discount rate used for equity. Typically higher than discount rate for debt.
B13: Cost | C13: Construction cost per kW | D13: 1009 | E13: 1009 | F13: 1009 | G13: 1009 | H13: 1009 | I13: 1009 | J13: 1009 | K13: 1009 | L13: Upfront cost of the power plant, per kW of maximum power (electricity if electric of CHP producer, heat if maximum electric power = 0)
B14: Power | C14: Maximum electric power, in MW_e | D14: 500 | E14: 500 | F14: 500 | G14: 500 | H14: 500 | I14: 500 | J14: 500 | K14: 500 | L14: Maximum electricity output of the plant
C15: Maximum heat power, in MW_h | D15: 0 | E15: 0 | F15: 0 | G15: 0 | H15: 0 | I15: 0 | J15: 0 | K15: 0 | L15: Maximum heat output of the plant, for e.g. district heating
B16: Lifetime | C16: Plant lifetime | D16: 30 | E16: 30 | F16: 30 | G16: 30 | H16: 30 | I16: 30 | J16: 30 | K16: 30 | L16: Maximum economical lifetime of the plant. Maximum 100 years.
B17: Build time | C17: Construction period, years | D17: 3 | E17: 3 | F17: 3 | G17: 3 | H17: 3 | I17: 3 | J17: 3 | K17: 3 | L17: Years required to construct the plant. Overnight cost is divided equally to these years and IDC is applied. Set to 1 to obtain Overnight costs.
B18: CF | C18: Capacity factor (settled down) | D18: 0.9 | E18: 0.9 | F18: 0.9 | G18: 0.9 | H18: 0.9 | I18: 0.9 | J18: 0.9 | K18: 0.9 | L18: Capacity factor (also known as load factor) once the plant has completed its testing cycle and operates normally
C19: Capacity factor ramp-up on startup, per year | D19: 0.6 | E19: 0.6 | F19: 0.6 | G19: 0.6 | H19: 0.6 | I19: 0.6 | J19: 0.6 | K19: 0.6 | L19: How rapidly the capacity factor ramps up to settled down rate, improvement per year. Plants start at 50 % of their maximum capacity factor.
B20: OPEX | C20: Fixed OPEX/MW capacity at project start | D20: 40000 | E20: 40000 | F20: 40000 | G20: 40000 | H20: 40000 | I20: 40000 | J20: 40000 | K20: 40000 | L20: Operational expenditure that isn't dependent on the amount of energy generated. If max electric power > 0, the OPEX is calculated from maximum electric power; otherwise from maximum heat power.
C21: Variable OPEX/MWh produced at project start | D21: 0 | E21: 0 | F21: 0 | G21: 0 | H21: 0 | I21: 0 | J21: 0 | K21: 0 | L21: Variable operational costs (costs dependent on amount of energy generated). If max electric power > 0, the OPEX is calculated from electricity output; otherwise from heat output.
C22: OPEX escalator | D22: 0 | E22: 0 | F22: 0 | G22: 0 | H22: 0 | I22: 0 | J22: 0 | K22: 0 | L22: Increase in OPEX per year
B23: Fuel costs | C23: FUELEX/MWh produced at project start | D23: 42.66 | E23: 42.66 | F23: 42.66 | G23: 42.66 | H23: 42.66 | I23: 42.66 | J23: 42.66 | K23: 42.66 | L23: Cost of fuel, per MWh of electricity generated if maximum electric power >0, otherwise per MWh of heat produced
C24: FUELEX escalator | D24: 0 | E24: 0 | F24: 0 | G24: 0 | H24: 0 | I24: 0 | J24: 0 | K24: 0 | L24: Increase in fuel costs per year
C25: Efficiency loss/year | D25: 0 | E25: 0 | F25: 0 | G25: 0 | H25: 0 | I25: 0 | J25: 0 | K25: 0 | L25: Loss of production as the plant ages. Used mostly fro solar PV.
B26: Midlife | C26: Refurbishment year | D26: 101 | E26: 101 | F26: 101 | G26: 101 | H26: 101 | I26: 101 | J26: 101 | K26: 101 | L26: Year when plant is refurbished. Set to 101 or more if no refurbishment needed.
C27: Refurbishment time required, years | D27: 1 | E27: 1 | F27: 1 | G27: 1 | H27: 1 | I27: 1 | J27: 1 | K27: 1 | L27: Time required for refurbishment, in years. Cost of refurbishment is divided equally to these years.
C28: Refurbishment cost, per kW | D28: 0 | E28: 0 | F28: 0 | G28: 0 | H28: 0 | I28: 0 | J28: 0 | K28: 0 | L28: Cost to refurbish the plant, per kW of maximum original capacity (electric if max electric power >0, heat otherwiase)
B29: Emissions | C29: Emission factor, gCO2e/kWh | D29: 313.75 | E29: 313.75 | F29: 313.75 | G29: 313.75 | H29: 313.75 | I29: 313.75 | J29: 313.75 | K29: 313.75 | L29: CO2 equivalent emissions produced per kWh of electricity generated if max electric power >0, otherwise per kWh of heat generated. From e.g. IPCC reports.
C30: Emissions taxed starting from year | D30: 0 | E30: 0 | F30: 0 | G30: 0 | H30: 0 | I30: 0 | J30: 0 | K30: 0 | L30: If emissions are taxed (see below for CO2 prices), when the plant is subject to taxation? Set to "0' for immediately, "101" if never
B31: Taxes | C31: Taxes, per MWh produced | D31: 0 | E31: 0 | F31: 0 | G31: 0 | H31: 0 | I31: 0 | J31: 0 | K31: 0 | L31: Taxes levied per MWh produced, electricity if max electric power >0, heat otherwise. DOES NOT INCLUDE CARBON TAX OR EMISSION TRADING
C32: Waste fee, per MWh produced | D32: 0 | E32: 0 | F32: 0 | G32: 0 | H32: 0 | I32: 0 | J32: 0 | K32: 0 | L32: Waste fees levied per MWh produced, electricity if max electric power >0, heat otherwise
C33: Heat credit, per MWh produced | D33: 30 | E33: 30 | F33: 30 | G33: 30 | H33: 30 | I33: 30 | J33: 30 | K33: 30 | L33: Income from selling a MWh of heat
C34: Outage at year | D34: 101 | E34: 101 | F34: 101 | G34: 101 | H34: 101 | I34: 101 | J34: 101 | K34: 101 | L34: This can be used to introduce a year-long outage. Number denotes the year after startup for outages. Set to "101" for no outages. Outages can also be introduced via Overrides below.
B35: EOL costs | C35: Decommissioning costs, % of initial capital cost | D35: 0.05 | E35: 0.05 | F35: 0.05 | G35: 0.05 | H35: 0.05 | I35: 0.05 | J35: 0.05 | K35: 0.05 | L35: Decommissioning cost as a fraction of initial capital cost (overnight costs)
C36: Decommissioning delay, years | D36: 25 | E36: 1 | F36: 1 | G36: 2 | H36: 2 | I36: 2 | J36: 2 | K36: 2 | L36: Delay after plant is closed, but before decommissioning begins. Influences LCOE due to discount rate. Maximum 25 years
C37: Results reference year/LC start year | D37: 2020 | E37: 2020 | F37: 2020 | G37: 2020 | H37: 2020 | I37: 2020 | J37: 2020 | K37: 2020 | L37: Reference year to use in currency conversion and in LC timeline
C38: Total cost | D38: =IF(D14>0,D13*1000*D14,D13*1000*D15) -> 504500000 | E38: =IF(E14>0,E13*1000*E14,E13*1000*E15) -> 504500000 | F38: =IF(F14>0,F13*1000*F14,F13*1000*F15) -> 504500000 | G38: =IF(G14>0,G13*1000*G14,G13*1000*G15) -> 504500000 | H38: =IF(H14>0,H13*1000*H14,H13*1000*H15) -> 504500000 | I38: =IF(I14>0,I13*1000*I14,I13*1000*I15) -> 504500000 | J38: =IF(J14>0,J13*1000*J14,J13*1000*J15) -> 504500000 | K38: =IF(K14>0,K13*1000*K14,K13*1000*K15) -> 504500000 | L38: DO NOT ALTER. Calculates the total overnight cost (maximum electric power * overnight cost per kW if max electric power >0; otherwise max heat power * overnight cost per kW)
C39: Equity share | D39: =100%-D10 -> 0.1 | E39: =100%-E10 -> 0.1 | F39: =100%-F10 -> 0.1 | G39: =100%-G10 -> 0.1 | H39: =100%-H10 -> 0.1 | I39: =100%-I10 -> 0.1 | J39: =100%-J10 -> 0.1 | K39: =100%-K10 -> 0.1 | L39: DO NOT ALTER. Shows the share of equity, just for completeness' sake
C40: WACC (average discount rate) | D40: =D10*D11+D39*D12 -> 0 | E40: =E10*E11+E39*E12 -> 0.03 | F40: =F10*F11+F39*F12 -> 0.05 | G40: =G10*G11+G39*G12 -> 0.07 | H40: =H10*H11+H39*H12 -> 0.08 | I40: =I10*I11+I39*I12 -> 0.1 | J40: =J10*J11+J39*J12 -> 0.12 | K40: =K10*K11+K39*K12 -> 0.14 | L40: DO NOT ALTER. Shows the weighted average discount rate that is used in calculations
C41: Interest during construction (IDC) | D41: =D40 -> 0 | E41: =E40 -> 0.03 | F41: =F40 -> 0.05 | G41: =G40 -> 0.07 | H41: =H40 -> 0.08 | I41: =I40 -> 0.1 | J41: =J40 -> 0.12 | K41: =K40 -> 0.14 | L41: Interest accrued during the construction period (t<0), set automatically to WACC
C42: Total overnight cost of refurbishment | D42: =1000*IF(D14>0,D28*D13,D13*D15) -> 0 | E42: =1000*IF(E14>0,E28*E13,E13*E15) -> 0 | F42: =1000*IF(F14>0,F28*F13,F13*F15) -> 0 | G42: =1000*IF(G14>0,G28*G13,G13*G15) -> 0 | H42: =1000*IF(H14>0,H28*H13,H13*H15) -> 0 | I42: =1000*IF(I14>0,I28*I13,I13*I15) -> 0 | J42: =1000*IF(J14>0,J28*J13,J13*J15) -> 0 | K42: =1000*IF(K14>0,K28*K13,K13*K15) -> 0 | L42: DO NOT ALTER. Calculates the total cost of refurbishment.
C43: Overrides | D43: =IF(COUNTA(C71:AB196)>0,"CHECK OVERRIDES","OVERRIDES CLEAR") -> OVERRIDES CLEAR | L43: If overrides (see below) are active, this lights up - meant to warn against inadvertently altering the results by forgetting the overrides
A45: Results (See Results for full results) | D45: ='LCOE 1'!J3 -> USD/MWh | E45: ='LCOE 2'!J3 -> USD/MWh | F45: ='LCOE 3'!J3 -> USD/MWh | G45: ='LCOE 4'!J3 -> USD/MWh | H45: ='LCOE 5'!J3 -> USD/MWh | I45: ='LCOE 6'!J3 -> USD/MWh | J45: ='LCOE 7'!J3 -> USD/MWh | K45: ='LCOE 8'!J3 -> USD/MWh
C46: LCOE (LCOHeat for pure heat plants) | D46: ='LCOE 1'!I3 -> 71.201772 | E46: ='LCOE 2'!I3 -> 64.075543 | F46: ='LCOE 3'!I3 -> 66.035232 | G46: ='LCOE 4'!I3 -> 68.258027 | H46: ='LCOE 5'!I3 -> 69.460824 | I46: ='LCOE 6'!I3 -> 72.022033 | J46: ='LCOE 7'!I3 -> 74.762467 | K46: ='LCOE 8'!I3 -> 77.652831
C47: Of which: Capital costs | D47: ='LCOE 1'!I4 -> 13.938494 | E47: ='LCOE 2'!I4 -> 6.7525504 | F47: ='LCOE 3'!I4 -> 8.6657769 | G47: ='LCOE 4'!I4 -> 10.838019 | H47: ='LCOE 5'!I4 -> 12.014364 | I47: ='LCOE 6'!I4 -> 14.520992 | J47: ='LCOE 7'!I4 -> 17.205402 | K47: ='LCOE 8'!I4 -> 20.039072
C48: O&M | D48: ='LCOE 1'!I5 -> 5.1907778 | E48: ='LCOE 2'!I5 -> 5.250493 | F48: ='LCOE 3'!I5 -> 5.2969555 | G48: ='LCOE 4'!I5 -> 5.3475079 | H48: ='LCOE 5'!I5 -> 5.3739602 | I48: ='LCOE 6'!I5 -> 5.4285401 | J48: ='LCOE 7'!I5 -> 5.4845655 | K48: ='LCOE 8'!I5 -> 5.5412584
C49: Fuel | D49: ='LCOE 1'!I6 -> 42.66 | E49: ='LCOE 2'!I6 -> 42.66 | F49: ='LCOE 3'!I6 -> 42.66 | G49: ='LCOE 4'!I6 -> 42.66 | H49: ='LCOE 5'!I6 -> 42.66 | I49: ='LCOE 6'!I6 -> 42.66 | J49: ='LCOE 7'!I6 -> 42.66 | K49: ='LCOE 8'!I6 -> 42.66
C50: Taxes and fees | D50: ='LCOE 1'!I7 -> 0 | E50: ='LCOE 2'!I7 -> 0 | F50: ='LCOE 3'!I7 -> 0 | G50: ='LCOE 4'!I7 -> 0 | H50: ='LCOE 5'!I7 -> 0 | I50: ='LCOE 6'!I7 -> 0 | J50: ='LCOE 7'!I7 -> 0 | K50: ='LCOE 8'!I7 -> 0
C51: Emission costs | D51: ='LCOE 1'!I8 -> 9.4125 | E51: ='LCOE 2'!I8 -> 9.4125 | F51: ='LCOE 3'!I8 -> 9.4125 | G51: ='LCOE 4'!I8 -> 9.4125 | H51: ='LCOE 5'!I8 -> 9.4125 | I51: ='LCOE 6'!I8 -> 9.4125 | J51: ='LCOE 7'!I8 -> 9.4125 | K51: ='LCOE 8'!I8 -> 9.4125
C52: Heat credit (for CHP plants) | D52: ='LCOE 1'!I9 -> 0 | E52: ='LCOE 2'!I9 -> 0 | F52: ='LCOE 3'!I9 -> 0 | G52: ='LCOE 4'!I9 -> 0 | H52: ='LCOE 5'!I9 -> 0 | I52: ='LCOE 6'!I9 -> 0 | J52: ='LCOE 7'!I9 -> 0 | K52: ='LCOE 8'!I9 -> 0
C53: WACC average over lifetime | D53: ='LCOE 1'!I10 -> 0 | E53: ='LCOE 2'!I10 -> 0.03 | F53: ='LCOE 3'!I10 -> 0.05 | G53: ='LCOE 4'!I10 -> 0.07 | H53: ='LCOE 5'!I10 -> 0.08 | I53: ='LCOE 6'!I10 -> 0.1 | J53: ='LCOE 7'!I10 -> 0.12 | K53: ='LCOE 8'!I10 -> 0.14
C54: Plant type | D54: ='LCOE 1'!I11 -> Electric only | E54: ='LCOE 2'!I11 -> Electric only | F54: ='LCOE 3'!I11 -> Electric only | G54: ='LCOE 4'!I11 -> Electric only | H54: ='LCOE 5'!I11 -> Electric only | I54: ='LCOE 6'!I11 -> Electric only | J54: ='LCOE 7'!I11 -> Electric only | K54: ='LCOE 8'!I11 -> Electric only
A56: Fuel cost assumptions
A58: Nuclear fuel cost calculator (Based on WNA data from 2022, prices in USD) | G58: Source: WNA 2022 | K58: Fuel cost calculator | L58: USD | M58: EUR
C59: Fuel cost calculator: 1 kg fuel | D59: Units needed | E59: Cost/unit | F59: Cost | G59: Proportion of total | K59: Fuel cost per MBTU | L59: 8 | M59: =L59*L$63 -> 7.608
C60: UO2 (kg) | D60: 8.9 | E60: =94.6 -> 94.6 | F60: =D60*E60 -> 841.94 | G60: =F60/SUM(F60:F63) -> 0.50614389 | H60: Cost of uranium oxide | K60: Fuel cost per MWh(t) | L60: =L59/0.293 -> 27.303754 | M60: =L60*L$63 -> 25.96587
C61: Conversion (kg) | D61: 7.5 | E61: 16 | F61: =D61*E61 -> 120 | G61: =F61/SUM(F60:F63) -> 0.072139662 | H61: Conversion cost | K61: Plant efficiency | L61: 0.64
C62: Enrichment (per SWU) | D62: 7.3 | E62: 55 | F62: =D62*E62 -> 401.5 | G62: =F62/SUM(F60:F63) -> 0.24136729 | H62: Enrichment cost | K62: Fuel cost per MWh produced | L62: =L60/L61 -> 42.662116 | M62: =L62*L$63 -> 40.571672
C63: Fabrication (per kg) | D63: 1 | E63: 300 | F63: =D63*E63 -> 300 | G63: =F63/SUM(F60:F63) -> 0.18034916 | H63: Fuel element fabrication cost | K63: Conversion USD to EUR | L63: 0.951
C64: Total cost of fuel, per kg | D64: =SUM(F60:F63) -> 1663.44 | E64: USD/kg | H64: Total cost of fuel | K64: Emissions per kWh of primary energy | L64: 200.8
C65: Burn-up MWd/t | D65: 45000 | E65: MWd/t uranium metal | H65: How much energy can be extracted from a ton of fuel | K65: Emissions, gCO2/kWh | L65: =L64/L61 -> 313.75
C66: MWh per kg | D66: =D65*8/1000 -> 360 | E66: MWh/kg of fuel | H66: How much energy can be extracted from a kg of fuel
C67: Fuel cost/MWh | D67: =SUM(F60:F63)/D66 -> 4.6206667 | E67: USD/MWh
A69: CO2 costs and overrides | D69: OVERRIDES: These will add the value in the cell below at the set year to ALL of the LCOE calculations (1-8) | J69: To ease checking, empty cells are ORANGE | M69: Non-empty cells are highlighted in YELLOW
A70: Year | B70: Emission cost, per ton of CO2e (affects all calculations) | C70: CAPEXconstr | D70: CAPEXrefurb and CAPEXdecom | E70: Discount rate (WACC) | F70: Interest during construction (IDC) | G70: Operational% | H70: Max electric power, MW_e | I70: Max heat power, MW_h | J70: Capacity factor | K70: Electricity produced (MWh_e) | L70: Heat produced (MWh_h) | M70: Fixed OPEX | N70: Variable OPEX | O70: OPEX relative to startup (%) | P70: FUELEX | Q70: FUELEX relative to startup (%) | R70: Efficiency relative to startup (%) | S70: Emission factor, gCO2/kWh | T70: % of emissions taxed | U70: Emissions, tCO2e | V70: Cost of emissions levied | W70: Tax per MWh produced | X70: Taxes levied | Y70: Waste fee per MWh produced | Z70: Waste fee levied | AA70: Heat credit per MWh_h produced | AB70: Heat credit total
A71: -25
A72: -24
A73: -23
A74: -22
A75: -21
A76: -20
A77: -19
A78: -18
A79: -17
A80: -16
A81: -15
A82: -14
... A95: -1
A96: 0 | B96: 30
A97: 1 | B97: 30
A98: 2 | B98: 30
A99: 3 | B99: 30
A100: 4 | B100: 30
A101: 5 | B101: 30
A102: 6 | B102: 30
A103: 7 | B103: 30
A104: 8 | B104: 30
A105: 9 | B105: 30
A106: 10 | B106: 30
A107: 11 | B107: 30
... A196: 100 | B196: 30

Sheet Learning curve parameters
C2: Start year: | D2: =LCOE!D37 -> 2020
C4: Case | D4: LC Case 1 | E4: LC Case 2 | F4: LC Case 3 | G4: LC Case 4 | H4: LC Case 5 | I4: LC Case 6 | J4: LC Case 7 | K4: LC Case 8
C5: LCOE calc | D5: =LCOE!D3 -> LCOE 1 | E5: =LCOE!E3 -> LCOE 2 | F5: =LCOE!F3 -> LCOE 3 | G5: =LCOE!G3 -> LCOE 4 | H5: =LCOE!H3 -> LCOE 5 | I5: =LCOE!I3 -> LCOE 6 | J5: =LCOE!J3 -> LCOE 7 | K5: =LCOE!K3 -> LCOE 8
C6: LCOE name | D6: =LCOE!D5 -> CCGT in Belgium (2020) | E6: =LCOE!E5 -> CCGT in Belgium (2020) | F6: =LCOE!F5 -> CCGT in Belgium (2020) | G6: =LCOE!G5 -> CCGT in Belgium (2020) | H6: =LCOE!H5 -> CCGT in Belgium (2020) | I6: =LCOE!I5 -> CCGT in Belgium (2020) | J6: =LCOE!J5 -> CCGT in Belgium (2020) | K6: =LCOE!K5 -> CCGT in Belgium (2020)
C7: Cumulative production at t=0 | D7: 95782 | E7: 95782 | F7: 95782 | G7: 95782 | H7: 95782 | I7: 95782 | J7: 95782 | K7: 95782
C8: Cumulative production unit | D8: TWh | E8: TWh | F8: TWh | G8: TWh | H8: TWh | I8: TWh | J8: TWh | K8: TWh
D27: Experience exponent ω | M27: Production growth rate
A28: Year | B28: Year | C28: Emission costs, per tCO2e | D28: =D4 -> LC Case 1 | E28: =E4 -> LC Case 2 | F28: =F4 -> LC Case 3 | G28: =G4 -> LC Case 4 | H28: =H4 -> LC Case 5 | I28: =I4 -> LC Case 6 | J28: =J4 -> LC Case 7 | K28: =K4 -> LC Case 8 | M28: =D4 -> LC Case 1 | N28: =E4 -> LC Case 2 | O28: =F4 -> LC Case 3 | P28: =G4 -> LC Case 4 | Q28: =H4 -> LC Case 5 | R28: =I4 -> LC Case 6 | S28: =J4 -> LC Case 7 | T28: =K4 -> LC Case 8
A29: 0 | B29: =A29+D$2 -> 2020 | D29: 0.05 | E29: 0.05 | F29: 0.05 | G29: 0.05 | H29: 0.05 | I29: 0.05 | J29: 0.05 | K29: 0.05 | M29: 0.01 | N29: 0.01 | O29: 0.01 | P29: 0.01 | Q29: 0.01 | R29: 0.01 | S29: 0.01 | T29: 0.01
A30: 1 | B30: =A30+D$2 -> 2021 | D30: 0.05 | E30: 0.05 | F30: 0.05 | G30: 0.05 | H30: 0.05 | I30: 0.05 | J30: 0.05 | K30: 0.05 | M30: 0.01 | N30: 0.01 | O30: 0.01 | P30: 0.01 | Q30: 0.01 | R30: 0.01 | S30: 0.01 | T30: 0.01
A31: 2 | B31: =A31+D$2 -> 2022 | D31: 0.05 | E31: 0.05 | F31: 0.05 | G31: 0.05 | H31: 0.05 | I31: 0.05 | J31: 0.05 | K31: 0.05 | M31: 0.01 | N31: 0.01 | O31: 0.01 | P31: 0.01 | Q31: 0.01 | R31: 0.01 | S31: 0.01 | T31: 0.01
A32: 3 | B32: =A32+D$2 -> 2023 | D32: 0.05 | E32: 0.05 | F32: 0.05 | G32: 0.05 | H32: 0.05 | I32: 0.05 | J32: 0.05 | K32: 0.05 | M32: 0.01 | N32: 0.01 | O32: 0.01 | P32: 0.01 | Q32: 0.01 | R32: 0.01 | S32: 0.01 | T32: 0.01
A33: 4 | B33: =A33+D$2 -> 2024 | D33: 0.05 | E33: 0.05 | F33: 0.05 | G33: 0.05 | H33: 0.05 | I33: 0.05 | J33: 0.05 | K33: 0.05 | M33: 0.01 | N33: 0.01 | O33: 0.01 | P33: 0.01 | Q33: 0.01 | R33: 0.01 | S33: 0.01 | T33: 0.01
A34: 5 | B34: =A34+D$2 -> 2025 | D34: 0.05 | E34: 0.05 | F34: 0.05 | G34: 0.05 | H34: 0.05 | I34: 0.05 | J34: 0.05 | K34: 0.05 | M34: 0.01 | N34: 0.01 | O34: 0.01 | P34: 0.01 | Q34: 0.01 | R34: 0.01 | S34: 0.01 | T34: 0.01
A35: 6 | B35: =A35+D$2 -> 2026 | D35: 0.05 | E35: 0.05 | F35: 0.05 | G35: 0.05 | H35: 0.05 | I35: 0.05 | J35: 0.05 | K35: 0.05 | M35: 0.01 | N35: 0.01 | O35: 0.01 | P35: 0.01 | Q35: 0.01 | R35: 0.01 | S35: 0.01 | T35: 0.01
A36: 7 | B36: =A36+D$2 -> 2027 | D36: 0.05 | E36: 0.05 | F36: 0.05 | G36: 0.05 | H36: 0.05 | I36: 0.05 | J36: 0.05 | K36: 0.05 | M36: 0.01 | N36: 0.01 | O36: 0.01 | P36: 0.01 | Q36: 0.01 | R36: 0.01 | S36: 0.01 | T36: 0.01
A37: 8 | B37: =A37+D$2 -> 2028 | D37: 0.05 | E37: 0.05 | F37: 0.05 | G37: 0.05 | H37: 0.05 | I37: 0.05 | J37: 0.05 | K37: 0.05 | M37: 0.01 | N37: 0.01 | O37: 0.01 | P37: 0.01 | Q37: 0.01 | R37: 0.01 | S37: 0.01 | T37: 0.01
A38: 9 | B38: =A38+D$2 -> 2029 | D38: 0.05 | E38: 0.05 | F38: 0.05 | G38: 0.05 | H38: 0.05 | I38: 0.05 | J38: 0.05 | K38: 0.05 | M38: 0.01 | N38: 0.01 | O38: 0.01 | P38: 0.01 | Q38: 0.01 | R38: 0.01 | S38: 0.01 | T38: 0.01
A39: 10 | B39: =A39+D$2 -> 2030 | D39: 0.05 | E39: 0.05 | F39: 0.05 | G39: 0.05 | H39: 0.05 | I39: 0.05 | J39: 0.05 | K39: 0.05 | M39: 0.01 | N39: 0.01 | O39: 0.01 | P39: 0.01 | Q39: 0.01 | R39: 0.01 | S39: 0.01 | T39: 0.01
A40: 11 | B40: =A40+D$2 -> 2031 | D40: 0.05 | E40: 0.05 | F40: 0.05 | G40: 0.05 | H40: 0.05 | I40: 0.05 | J40: 0.05 | K40: 0.05 | M40: 0.01 | N40: 0.01 | O40: 0.01 | P40: 0.01 | Q40: 0.01 | R40: 0.01 | S40: 0.01 | T40: 0.01
... A129: 100 | B129: =A129+D$2 -> 2120 | D129: 0.05 | E129: 0.05 | F129: 0.05 | G129: 0.05 | H129: 0.05 | I129: 0.05 | J129: 0.05 | K129: 0.05 | M129: 0.01 | N129: 0.01 | O129: 0.01 | P129: 0.01 | Q129: 0.01 | R129: 0.01 | S129: 0.01 | T129: 0.01

Sheet Results
B6: Calculation | C6: =LCOE!D3 -> LCOE 1 | D6: =LCOE!E3 -> LCOE 2 | E6: =LCOE!F3 -> LCOE 3 | F6: =LCOE!G3 -> LCOE 4 | G6: =LCOE!H3 -> LCOE 5 | H6: =LCOE!I3 -> LCOE 6 | I6: =LCOE!J3 -> LCOE 7 | J6: =LCOE!K3 -> LCOE 8
B7: Name | C7: =LCOE!D5 -> CCGT in Belgium (2020) | D7: =LCOE!E5 -> CCGT in Belgium (2020) | E7: =LCOE!F5 -> CCGT in Belgium (2020) | F7: =LCOE!G5 -> CCGT in Belgium (2020) | G7: =LCOE!H5 -> CCGT in Belgium (2020) | H7: =LCOE!I5 -> CCGT in Belgium (2020) | I7: =LCOE!J5 -> CCGT in Belgium (2020) | J7: =LCOE!K5 -> CCGT in Belgium (2020)
B8: =LCOE!C6 -> Currency used for LCOE calculations
A10: LCOE
B11: =LCOE!C13 -> Construction cost per kW | C11: =LCOE!D13 -> 1009 | D11: =LCOE!E13 -> 1009 | E11: =LCOE!F13 -> 1009 | F11: =LCOE!G13 -> 1009 | G11: =LCOE!H13 -> 1009 | H11: =LCOE!I13 -> 1009 | I11: =LCOE!J13 -> 1009 | J11: =LCOE!K13 -> 1009
B12: =LCOE!C14 -> Maximum electric power, in MW_e | C12: =LCOE!D14 -> 500 | D12: =LCOE!E14 -> 500 | E12: =LCOE!F14 -> 500 | F12: =LCOE!G14 -> 500 | G12: =LCOE!H14 -> 500 | H12: =LCOE!I14 -> 500 | I12: =LCOE!J14 -> 500 | J12: =LCOE!K14 -> 500
B13: =LCOE!C15 -> Maximum heat power, in MW_h | C13: =LCOE!D15 -> 0 | D13: =LCOE!E15 -> 0 | E13: =LCOE!F15 -> 0 | F13: =LCOE!G15 -> 0 | G13: =LCOE!H15 -> 0 | H13: =LCOE!I15 -> 0 | I13: =LCOE!J15 -> 0 | J13: =LCOE!K15 -> 0
B14: =LCOE!C52 -> Heat credit (for CHP plants) | C14: =LCOE!D52 -> 0 | D14: =LCOE!E52 -> 0 | E14: =LCOE!F52 -> 0 | F14: =LCOE!G52 -> 0 | G14: =LCOE!H52 -> 0 | H14: =LCOE!I52 -> 0 | I14: =LCOE!J52 -> 0 | J14: =LCOE!K52 -> 0
C15: =LCOE!D45 -> USD/MWh | D15: =LCOE!E45 -> USD/MWh | E15: =LCOE!F45 -> USD/MWh | F15: =LCOE!G45 -> USD/MWh | G15: =LCOE!H45 -> USD/MWh | H15: =LCOE!I45 -> USD/MWh | I15: =LCOE!J45 -> USD/MWh | J15: =LCOE!K45 -> USD/MWh
B16: =LCOE!C46 -> LCOE (LCOHeat for pure heat plants) | C16: =LCOE!D46 -> 71.201772 | D16: =LCOE!E46 -> 64.075543 | E16: =LCOE!F46 -> 66.035232 | F16: =LCOE!G46 -> 68.258027 | G16: =LCOE!H46 -> 69.460824 | H16: =LCOE!I46 -> 72.022033 | I16: =LCOE!J46 -> 74.762467 | J16: =LCOE!K46 -> 77.652831
B17: =LCOE!C47 -> Of which: Capital costs | C17: =LCOE!D47 -> 13.938494 | D17: =LCOE!E47 -> 6.7525504 | E17: =LCOE!F47 -> 8.6657769 | F17: =LCOE!G47 -> 10.838019 | G17: =LCOE!H47 -> 12.014364 | H17: =LCOE!I47 -> 14.520992 | I17: =LCOE!J47 -> 17.205402 | J17: =LCOE!K47 -> 20.039072
B18: =LCOE!C48 -> O&M | C18: =LCOE!D48 -> 5.1907778 | D18: =LCOE!E48 -> 5.250493 | E18: =LCOE!F48 -> 5.2969555 | F18: =LCOE!G48 -> 5.3475079 | G18: =LCOE!H48 -> 5.3739602 | H18: =LCOE!I48 -> 5.4285401 | I18: =LCOE!J48 -> 5.4845655 | J18: =LCOE!K48 -> 5.5412584
B19: =LCOE!C49 -> Fuel | C19: =LCOE!D49 -> 42.66 | D19: =LCOE!E49 -> 42.66 | E19: =LCOE!F49 -> 42.66 | F19: =LCOE!G49 -> 42.66 | G19: =LCOE!H49 -> 42.66 | H19: =LCOE!I49 -> 42.66 | I19: =LCOE!J49 -> 42.66 | J19: =LCOE!K49 -> 42.66
B20: =LCOE!C50 -> Taxes and fees | C20: =LCOE!D50 -> 0 | D20: =LCOE!E50 -> 0 | E20: =LCOE!F50 -> 0 | F20: =LCOE!G50 -> 0 | G20: =LCOE!H50 -> 0 | H20: =LCOE!I50 -> 0 | I20: =LCOE!J50 -> 0 | J20: =LCOE!K50 -> 0
B21: =LCOE!C51 -> Emission costs | C21: =LCOE!D51 -> 9.4125 | D21: =LCOE!E51 -> 9.4125 | E21: =LCOE!F51 -> 9.4125 | F21: =LCOE!G51 -> 9.4125 | G21: =LCOE!H51 -> 9.4125 | H21: =LCOE!I51 -> 9.4125 | I21: =LCOE!J51 -> 9.4125 | J21: =LCOE!K51 -> 9.4125
B22: =LCOE!C52 -> Heat credit (for CHP plants) | C22: =LCOE!D52 -> 0 | D22: =LCOE!E52 -> 0 | E22: =LCOE!F52 -> 0 | F22: =LCOE!G52 -> 0 | G22: =LCOE!H52 -> 0 | H22: =LCOE!I52 -> 0 | I22: =LCOE!J52 -> 0 | J22: =LCOE!K52 -> 0
B23: =LCOE!C53 -> WACC average over lifetime | C23: =LCOE!D53 -> 0 | D23: =LCOE!E53 -> 0.03 | E23: =LCOE!F53 -> 0.05 | F23: =LCOE!G53 -> 0.07 | G23: =LCOE!H53 -> 0.08 | H23: =LCOE!I53 -> 0.1 | I23: =LCOE!J53 -> 0.12 | J23: =LCOE!K53 -> 0.14
B24: =LCOE!C54 -> Plant type | C24: =LCOE!D54 -> Electric only | D24: =LCOE!E54 -> Electric only | E24: =LCOE!F54 -> Electric only | F24: =LCOE!G54 -> Electric only | G24: =LCOE!H54 -> Electric only | H24: =LCOE!I54 -> Electric only | I24: =LCOE!J54 -> Electric only | J24: =LCOE!K54 -> Electric only
A26: Learning curve
B28: ='Learning curve calcs'!B21 -> Case | C28: ='Learning curve calcs'!C21 -> LC Case 1 | D28: ='Learning curve calcs'!D21 -> LC Case 2 | E28: ='Learning curve calcs'!E21 -> LC Case 3 | F28: ='Learning curve calcs'!F21 -> LC Case 4 | G28: ='Learning curve calcs'!G21 -> LC Case 5 | H28: ='Learning curve calcs'!H21 -> LC Case 6 | I28: ='Learning curve calcs'!I21 -> LC Case 7 | J28: ='Learning curve calcs'!J21 -> LC Case 8
B29: ='Learning curve calcs'!B22 -> LCOE calc | C29: ='Learning curve calcs'!C22 -> LCOE 1 | D29: ='Learning curve calcs'!D22 -> LCOE 2 | E29: ='Learning curve calcs'!E22 -> LCOE 3 | F29: ='Learning curve calcs'!F22 -> LCOE 4 | G29: ='Learning curve calcs'!G22 -> LCOE 5 | H29: ='Learning curve calcs'!H22 -> LCOE 6 | I29: ='Learning curve calcs'!I22 -> LCOE 7 | J29: ='Learning curve calcs'!J22 -> LCOE 8
B30: ='Learning curve calcs'!B23 -> Name | C30: ='Learning curve calcs'!C23 -> CCGT in Belgium (2020) | D30: ='Learning curve calcs'!D23 -> CCGT in Belgium (2020) | E30: ='Learning curve calcs'!E23 -> CCGT in Belgium (2020) | F30: ='Learning curve calcs'!F23 -> CCGT in Belgium (2020) | G30: ='Learning curve calcs'!G23 -> CCGT in Belgium (2020) | H30: ='Learning curve calcs'!H23 -> CCGT in Belgium (2020) | I30: ='Learning curve calcs'!I23 -> CCGT in Belgium (2020) | J30: ='Learning curve calcs'!J23 -> CCGT in Belgium (2020)
C32: ='Learning curve calcs'!C24 -> USD/MWh | D32: ='Learning curve calcs'!D24 -> USD/MWh | E32: ='Learning curve calcs'!E24 -> USD/MWh | F32: ='Learning curve calcs'!F24 -> USD/MWh | G32: ='Learning curve calcs'!G24 -> USD/MWh | H32: ='Learning curve calcs'!H24 -> USD/MWh | I32: ='Learning curve calcs'!I24 -> USD/MWh | J32: ='Learning curve calcs'!J24 -> USD/MWh
B33: ='Learning curve calcs'!B24 -> Year | C33: =_xlfn.CONCAT(C30,", WACC ",100*ROUND(C14,2)," %, ",C28) -> CCGT in Belgium (2020), WACC 0 %, LC Case 1 | D33: =_xlfn.CONCAT(D30,", WACC ",100*ROUND(D14,2)," %, ",D28) -> CCGT in Belgium (2020), WACC 0 %, LC Case 2 | E33: =_xlfn.CONCAT(E30,", WACC ",100*ROUND(E14,2)," %, ",E28) -> CCGT in Belgium (2020), WACC 0 %, LC Case 3 | F33: =_xlfn.CONCAT(F30,", WACC ",100*ROUND(F14,2)," %, ",F28) -> CCGT in Belgium (2020), WACC 0 %, LC Case 4 | G33: =_xlfn.CONCAT(G30,", WACC ",100*ROUND(G14,2)," %, ",G28) -> CCGT in Belgium (2020), WACC 0 %, LC Case 5 | H33: =_xlfn.CONCAT(H30,", WACC ",100*ROUND(H14,2)," %, ",H28) -> CCGT in Belgium (2020), WACC 0 %, LC Case 6 | I33: =_xlfn.CONCAT(I30,", WACC ",100*ROUND(I14,2)," %, ",I28) -> CCGT in Belgium (2020), WACC 0 %, LC Case 7 | J33: =_xlfn.CONCAT(J30,", WACC ",100*ROUND(J14,2)," %, ",J28) -> CCGT in Belgium (2020), WACC 0 %, LC Case 8
B34: ='Learning curve calcs'!B25 -> 2020 | C34: ='Learning curve calcs'!C25 -> 71.201772 | D34: ='Learning curve calcs'!D25 -> 64.075543 | E34: ='Learning curve calcs'!E25 -> 66.035232 | F34: ='Learning curve calcs'!F25 -> 68.258027 | G34: ='Learning curve calcs'!G25 -> 69.460824 | H34: ='Learning curve calcs'!H25 -> 72.022033 | I34: ='Learning curve calcs'!I25 -> 74.762467 | J34: ='Learning curve calcs'!J25 -> 77.652831
B35: ='Learning curve calcs'!B26 -> 2021 | C35: ='Learning curve calcs'!C26 -> 71.206621 | D35: ='Learning curve calcs'!D26 -> 64.080392 | E35: ='Learning curve calcs'!E26 -> 66.040081 | F35: ='Learning curve calcs'!F26 -> 68.262876 | G35: ='Learning curve calcs'!G26 -> 69.465672 | H35: ='Learning curve calcs'!H26 -> 72.026881 | I35: ='Learning curve calcs'!I26 -> 74.767316 | J35: ='Learning curve calcs'!J26 -> 77.65768
B36: ='Learning curve calcs'!B27 -> 2022 | C36: ='Learning curve calcs'!C27 -> 71.211469 | D36: ='Learning curve calcs'!D27 -> 64.085241 | E36: ='Learning curve calcs'!E27 -> 66.04493 | F36: ='Learning curve calcs'!F27 -> 68.267724 | G36: ='Learning curve calcs'!G27 -> 69.470521 | H36: ='Learning curve calcs'!H27 -> 72.03173 | I36: ='Learning curve calcs'!I27 -> 74.772165 | J36: ='Learning curve calcs'!J27 -> 77.662528
B37: ='Learning curve calcs'!B28 -> 2023 | C37: ='Learning curve calcs'!C28 -> 71.216318 | D37: ='Learning curve calcs'!D28 -> 64.090089 | E37: ='Learning curve calcs'!E28 -> 66.049778 | F37: ='Learning curve calcs'!F28 -> 68.272573 | G37: ='Learning curve calcs'!G28 -> 69.47537 | H37: ='Learning curve calcs'!H28 -> 72.036578 | I37: ='Learning curve calcs'!I28 -> 74.777013 | J37: ='Learning curve calcs'!J28 -> 77.667377
B38: ='Learning curve calcs'!B29 -> 2024 | C38: ='Learning curve calcs'!C29 -> 71.221167 | D38: ='Learning curve calcs'!D29 -> 64.094938 | E38: ='Learning curve calcs'!E29 -> 66.054627 | F38: ='Learning curve calcs'!F29 -> 68.277422 | G38: ='Learning curve calcs'!G29 -> 69.480218 | H38: ='Learning curve calcs'!H29 -> 72.041427 | I38: ='Learning curve calcs'!I29 -> 74.781862 | J38: ='Learning curve calcs'!J29 -> 77.672225
B39: ='Learning curve calcs'!B30 -> 2025 | C39: ='Learning curve calcs'!C30 -> 71.226015 | D39: ='Learning curve calcs'!D30 -> 64.099787 | E39: ='Learning curve calcs'!E30 -> 66.059476 | F39: ='Learning curve calcs'!F30 -> 68.28227 | G39: ='Learning curve calcs'!G30 -> 69.485067 | H39: ='Learning curve calcs'!H30 -> 72.046276 | I39: ='Learning curve calcs'!I30 -> 74.786711 | J39: ='Learning curve calcs'!J30 -> 77.677074
B40: ='Learning curve calcs'!B31 -> 2026 | C40: ='Learning curve calcs'!C31 -> 71.230864 | D40: ='Learning curve calcs'!D31 -> 64.104635 | E40: ='Learning curve calcs'!E31 -> 66.064324 | F40: ='Learning curve calcs'!F31 -> 68.287119 | G40: ='Learning curve calcs'!G31 -> 69.489916 | H40: ='Learning curve calcs'!H31 -> 72.051124 | I40: ='Learning curve calcs'!I31 -> 74.791559 | J40: ='Learning curve calcs'!J31 -> 77.681923
B41: ='Learning curve calcs'!B32 -> 2027 | C41: ='Learning curve calcs'!C32 -> 71.235713 | D41: ='Learning curve calcs'!D32 -> 64.109484 | E41: ='Learning curve calcs'!E32 -> 66.069173 | F41: ='Learning curve calcs'!F32 -> 68.291968 | G41: ='Learning curve calcs'!G32 -> 69.494764 | H41: ='Learning curve calcs'!H32 -> 72.055973 | I41: ='Learning curve calcs'!I32 -> 74.796408 | J41: ='Learning curve calcs'!J32 -> 77.686771
B42: ='Learning curve calcs'!B33 -> 2028 | C42: ='Learning curve calcs'!C33 -> 71.240561 | D42: ='Learning curve calcs'!D33 -> 64.114333 | E42: ='Learning curve calcs'!E33 -> 66.074022 | F42: ='Learning curve calcs'!F33 -> 68.296816 | G42: ='Learning curve calcs'!G33 -> 69.499613 | H42: ='Learning curve calcs'!H33 -> 72.060822 | I42: ='Learning curve calcs'!I33 -> 74.801257 | J42: ='Learning curve calcs'!J33 -> 77.69162
B43: ='Learning curve calcs'!B34 -> 2029 | C43: ='Learning curve calcs'!C34 -> 71.24541 | D43: ='Learning curve calcs'!D34 -> 64.119181 | E43: ='Learning curve calcs'!E34 -> 66.07887 | F43: ='Learning curve calcs'!F34 -> 68.301665 | G43: ='Learning curve calcs'!G34 -> 69.504462 | H43: ='Learning curve calcs'!H34 -> 72.06567 | I43: ='Learning curve calcs'!I34 -> 74.806105 | J43: ='Learning curve calcs'!J34 -> 77.696469
B44: ='Learning curve calcs'!B35 -> 2030 | C44: ='Learning curve calcs'!C35 -> 71.250259 | D44: ='Learning curve calcs'!D35 -> 64.12403 | E44: ='Learning curve calcs'!E35 -> 66.083719 | F44: ='Learning curve calcs'!F35 -> 68.306514 | G44: ='Learning curve calcs'!G35 -> 69.50931 | H44: ='Learning curve calcs'!H35 -> 72.070519 | I44: ='Learning curve calcs'!I35 -> 74.810954 | J44: ='Learning curve calcs'!J35 -> 77.701317
B45: ='Learning curve calcs'!B36 -> 2031 | C45: ='Learning curve calcs'!C36 -> 71.255107 | D45: ='Learning curve calcs'!D36 -> 64.128879 | E45: ='Learning curve calcs'!E36 -> 66.088568 | F45: ='Learning curve calcs'!F36 -> 68.311362 | G45: ='Learning curve calcs'!G36 -> 69.514159 | H45: ='Learning curve calcs'!H36 -> 72.075368 | I45: ='Learning curve calcs'!I36 -> 74.815803 | J45: ='Learning curve calcs'!J36 -> 77.706166
... B114: ='Learning curve calcs'!B105 -> 2100 | C114: ='Learning curve calcs'!C105 -> 71.589665 | D114: ='Learning curve calcs'!D105 -> 64.463436 | E114: ='Learning curve calcs'!E105 -> 66.423125 | F114: ='Learning curve calcs'!F105 -> 68.64592 | G114: ='Learning curve calcs'!G105 -> 69.848717 | H114: ='Learning curve calcs'!H105 -> 72.409925 | I114: ='Learning curve calcs'!I105 -> 75.15036 | J114: ='Learning curve calcs'!J105 -> 78.040724

Sheet Examples
A4: Power plants
B5: Explanation | C5: Westinghouse winning bid for 3+3 reactors in Poland, 2022 | D5: EDF bid for 4 reactors in Poland, 2022 | E5: CCGT gas turbine in Belgium, 2020, from IEA 2020
B6: Sources | C6: Construction costs from Deutsche Welle via Helsingin Sanomat, 1.2.2023. | D6: Construction costs from Deutsche Welle via Helsingin Sanomat, 1.2.2023 | E6: IEA (2020) Projected Costs of Generating Electricity, pp. 50-57. Converted to EUR ( 1 USD = 0,951 EUR)
J7: 2022
B8: =LCOE!C4 -> Type | C8: Nuclear | D8: Nuclear | E8: Gas Combined Cycle Turbine (CCGT) | J8: Sanmen 1 | K8: 91.3
B9: =LCOE!C5 -> Name | C9: Polish AP1000 bid (2022) | D9: Polish EPR bid (2022) | E9: CCGT in Belgium (2020) | J9: Sanmen 2 | K9: 90.5
B10: =LCOE!C6 -> Currency used for LCOE calculations | C10: EUR | D10: EUR | E10: EUR | J10: 3
B11: =LCOE!C7 -> Price reference year
B12: =LCOE!C8 -> Currency used | C12: EUR | D12: EUR | E12: EUR
B13: =LCOE!C9 -> Conversion rate at reference year | C13: 1 | D13: 1 | E13: 1
B14: =LCOE!C10 -> Debt % | C14: 0.9 | D14: 0.9 | E14: 0.9
B15: =LCOE!C11 -> Cost of debt (private discount rate) | C15: 0.05 | D15: 0.05 | E15: 0.05
B16: =LCOE!C12 -> Cost of equity (discount rate) | C16: 0.05 | D16: 0.05 | E16: 0.05
B17: =LCOE!C13 -> Construction cost per kW | C17: 4441.17 | D17: 4755 | E17: 960
B18: =LCOE!C14 -> Maximum electric power, in MW_e | C18: 1117 | D18: 1650 | E18: 500
B19: =LCOE!C15 -> Maximum heat power, in MW_h | C19: 0 | D19: 0 | E19: 0
B20: =LCOE!C16 -> Plant lifetime | C20: 60 | D20: 60 | E20: 30
B21: =LCOE!C17 -> Construction period, years | C21: 7 | D21: 7 | E21: 3
B22: =LCOE!C18 -> Capacity factor (settled down) | C22: 0.9 | D22: 0.9 | E22: 0.85
B23: =LCOE!C19 -> Capacity factor ramp-up on startup, per year | C23: 0.6 | D23: 0.6 | E23: 1
B24: =LCOE!C20 -> Fixed OPEX/MW capacity at project start | C24: 80835 | D24: 9034.5
B25: =LCOE!C21 -> Variable OPEX/MWh produced at project start | C25: 1426 | D25: 6.55
B26: =LCOE!C22 -> OPEX escalator | C26: 0 | D26: 0
B27: =LCOE!C23 -> FUELEX/MWh produced at project start | C27: 8.87 | D27: 8.87
B28: =LCOE!C24 -> FUELEX escalator | C28: 0 | D28: 0
B29: =LCOE!C25 -> Efficiency loss/year | C29: 0 | D29: 0
B30: =LCOE!C26 -> Refurbishment year | C30: 40 | D30: 40
B31: =LCOE!C27 -> Refurbishment time required, years | C31: 1 | D31: 1
B32: =LCOE!C28 -> Refurbishment cost, per kW | C32: 500 | D32: 500
B33: =LCOE!C29 -> Emission factor, gCO2e/kWh | C33: 12 | D33: 12 | E33: 313.75
B34: =LCOE!C30 -> Emissions taxed starting from year | C34: 101 | D34: 101
B35: =LCOE!C31 -> Taxes, per MWh produced | C35: 0 | D35: 0
B36: =LCOE!C32 -> Waste fee, per MWh produced | C36: 1 | D36: 1
B37: =LCOE!C33 -> Heat credit, per MWh produced | C37: 30 | D37: 30 | E37: 0
B38: =LCOE!C34 -> Outage at year | C38: 101 | D38: 101 | E38: 101
B39: =LCOE!C35 -> Decommissioning costs, % of initial capital cost | C39: 0.15 | D39: 0.15 | E39: 0.05
B40: =LCOE!C36 -> Decommissioning delay, years | C40: 10 | D40: 10 | E40: 2

Sheet LCOE 1
B2: Parameter recap (not used in calcs) | C2: =LCOE!D3 -> LCOE 1 | F2: RESULTS | G2: =C4 -> USD | I2: =C6 -> USD
B3: =LCOE!C5 -> Name | C3: =LCOE!D5 -> CCGT in Belgium (2020) | F3: =LCOE!C46 -> LCOE (LCOHeat for pure heat plants) | G3: =SUM(AH45:AM170)/SUM(AN45:AN170) -> 71.201772 | H3: =_xlfn.CONCAT(C$4,"/MWh") -> USD/MWh | I3: =G3*C$7 -> 71.201772 | J3: =_xlfn.CONCAT(C$6,"/MWh") -> USD/MWh
B4: =LCOE!C6 -> Currency used for LCOE calculations | C4: =LCOE!D6 -> USD | F4: =LCOE!C47 -> Of which: Capital costs | G4: =SUM(AH45:AH170)/SUM(AN45:AN170) -> 13.938494 | H4: =_xlfn.CONCAT(C$4,"/MWh") -> USD/MWh | I4: =G4*C$7 -> 13.938494 | J4: =_xlfn.CONCAT(C$6,"/MWh") -> USD/MWh
B5: =LCOE!C7 -> Price reference year | C5: =LCOE!D7 -> 0 | F5: =LCOE!C48 -> O&M | G5: =SUM(AI45:AI170)/SUM(AN45:AN170) -> 5.1907778 | H5: =_xlfn.CONCAT(C$4,"/MWh") -> USD/MWh | I5: =G5*C$7 -> 5.1907778 | J5: =_xlfn.CONCAT(C$6,"/MWh") -> USD/MWh
B6: =LCOE!C8 -> Currency used | C6: =LCOE!D8 -> USD | F6: =LCOE!C49 -> Fuel | G6: =SUM(AJ45:AJ170)/SUM(AN45:AN170) -> 42.66 | H6: =_xlfn.CONCAT(C$4,"/MWh") -> USD/MWh | I6: =G6*C$7 -> 42.66 | J6: =_xlfn.CONCAT(C$6,"/MWh") -> USD/MWh
B7: =LCOE!C9 -> Conversion rate at reference year | C7: =LCOE!D9 -> 1 | F7: =LCOE!C50 -> Taxes and fees | G7: =SUM(AK45:AK170)/SUM(AN45:AN170) -> 0 | H7: =_xlfn.CONCAT(C$4,"/MWh") -> USD/MWh | I7: =G7*C$7 -> 0 | J7: =_xlfn.CONCAT(C$6,"/MWh") -> USD/MWh
B8: =LCOE!C10 -> Debt % | C8: =LCOE!D10 -> 0.9 | F8: =LCOE!C51 -> Emission costs | G8: =SUM(AL45:AL170)/SUM(AN45:AN170) -> 9.4125 | H8: =_xlfn.CONCAT(C$4,"/MWh") -> USD/MWh | I8: =G8*C$7 -> 9.4125 | J8: =_xlfn.CONCAT(C$6,"/MWh") -> USD/MWh
B9: =LCOE!C11 -> Cost of debt (private discount rate) | C9: =LCOE!D11 -> 0 | F9: =LCOE!C52 -> Heat credit (for CHP plants) | G9: =IF(C15>0,SUM(AM45:AM170)/SUM(AN45:AN170),0) -> 0 | H9: =_xlfn.CONCAT(C$4,"/MWh") -> USD/MWh | I9: =G9*C$7 -> 0 | J9: =_xlfn.CONCAT(C$6,"/MWh") -> USD/MWh
B10: =LCOE!C12 -> Cost of equity (discount rate) | C10: =LCOE!D12 -> 0 | F10: =LCOE!C53 -> WACC average over lifetime | G10: =AVERAGE(AF70:AF170) -> 0 | I10: =G10 -> 0
B11: =LCOE!C13 -> Construction cost per kW | C11: =LCOE!D13 -> 1009 | F11: =LCOE!C54 -> Plant type | G11: =IF(AND(LCOE!D$14>0,LCOE!D$15=0),"Electric only",IF(AND(LCOE!D$14>0,LCOE!D$15>0),"CHP",IF(AND(LCOE!D$14=0,LCOE!D$15>0),"Heat only","Error: no generation"))) -> Electric only | I11: =G11 -> Electric only
B12: =LCOE!C14 -> Maximum electric power, in MW_e | C12: =LCOE!D14 -> 500
B13: =LCOE!C15 -> Maximum heat power, in MW_h | C13: =LCOE!D15 -> 0
B14: =LCOE!C16 -> Plant lifetime | C14: =LCOE!D16 -> 30
B15: =LCOE!C17 -> Construction period, years | C15: =LCOE!D17 -> 3
B16: =LCOE!C18 -> Capacity factor (settled down) | C16: =LCOE!D18 -> 0.9
B17: =LCOE!C19 -> Capacity factor ramp-up on startup, per year | C17: =LCOE!D19 -> 0.6
B18: =LCOE!C20 -> Fixed OPEX/MW capacity at project start | C18: =LCOE!D20 -> 40000
B19: =LCOE!C21 -> Variable OPEX/MWh produced at project start | C19: =LCOE!D21 -> 0
B20: =LCOE!C22 -> OPEX escalator | C20: =LCOE!D22 -> 0
B21: =LCOE!C23 -> FUELEX/MWh produced at project start | C21: =LCOE!D23 -> 42.66
B22: =LCOE!C24 -> FUELEX escalator | C22: =LCOE!D24 -> 0
B23: =LCOE!C25 -> Efficiency loss/year | C23: =LCOE!D25 -> 0
... B41: =LCOE!C43 -> Overrides | C41: =LCOE!D43 -> OVERRIDES CLEAR
Z43: SUMMARY OF COSTS
A44: Year (t) | B44: CAPEXconstr | C44: CAPEXrefurb/decom | D44: Lifetime left? | E44: Operational% | F44: Capacity factor | G44: Electricity produced (MWh_e) | H44: Heat produced (MWh_h) | I44: Fixed OPEX | J44: Variable OPEX | K44: OPEX relative to startup | L44: FUELEX | M44: FUELEX relative to startup | N44: Efficiency relative to startup | O44: Total emission factor, gCO2/kWh | P44: % of emissions taxed | Q44: Total emissions, tCO2e | R44: Cost of tCO2e | S44: Cost of emissions levied, E | T44: Tax per MWh produced | U44: Taxes levied | V44: Waste fee per MWh produced | W44: Waste fee levied | X44: Heat credit per MWh_h | Y44: Heat credit total | Z44: Total capital expenditure, I | AA44: Total operation and maintenance expenditure, M | AB44: Total fuel expenditure, F | AC44: Total taxes, T | AD44: Total emission fees, E | AE44: Lifetime expended at start of year | AF44: Discount rate r (IDC when t<0) | AG44: Discount factor (1+r)^t | AH44: I discounted | AI44: M discounted | AJ44: F discounted | AK44: T discounted | AL44: E discounted | AM44: Heat credit, discounted | AN44: Production (MWh), discounted
A45: -25 | B45: =LCOE!C71+IF(A45>=((LCOE!D$17*-1)+1),LCOE!D$38/LCOE!D$17,0) -> 0 | Z45: =SUM(B45:C45) -> 0 | AA45: =SUM(I45:J45) -> 0 | AB45: =L45 -> 0 | AC45: =SUM(S45:W45) -> 0 | AD45: =S45 -> 0 | AE45: -25 | AF45: =LCOE!E71+LCOE!D$40 -> 0 | AG45: =(1+AF45)^A45 -> 1 | AH45: =Z45/AG45 -> 0 | AI45: =AA45/AG45 -> 0 | AJ45: =AB45/AG45 -> 0 | AK45: =AC45/AG45 -> 0 | AL45: =AD45/AG45 -> 0
A46: -24 | B46: =LCOE!C72+IF(A46>=((LCOE!D$17*-1)+1),LCOE!D$38/LCOE!D$17,0) -> 0 | Z46: =SUM(B46:C46) -> 0 | AA46: =SUM(I46:J46) -> 0 | AB46: =L46 -> 0 | AC46: =SUM(S46:W46) -> 0 | AD46: =S46 -> 0 | AE46: -24 | AF46: =LCOE!E72+LCOE!D$40 -> 0 | AG46: =(1+AF46)^A46 -> 1 | AH46: =Z46/AG46 -> 0 | AI46: =AA46/AG46 -> 0 | AJ46: =AB46/AG46 -> 0 | AK46: =AC46/AG46 -> 0 | AL46: =AD46/AG46 -> 0
A47: -23 | B47: =LCOE!C73+IF(A47>=((LCOE!D$17*-1)+1),LCOE!D$38/LCOE!D$17,0) -> 0 | Z47: =SUM(B47:C47) -> 0 | AA47: =SUM(I47:J47) -> 0 | AB47: =L47 -> 0 | AC47: =SUM(S47:W47) -> 0 | AD47: =S47 -> 0 | AE47: -23 | AF47: =LCOE!E73+LCOE!D$40 -> 0 | AG47: =(1+AF47)^A47 -> 1 | AH47: =Z47/AG47 -> 0 | AI47: =AA47/AG47 -> 0 | AJ47: =AB47/AG47 -> 0 | AK47: =AC47/AG47 -> 0 | AL47: =AD47/AG47 -> 0
A48: -22 | B48: =LCOE!C74+IF(A48>=((LCOE!D$17*-1)+1),LCOE!D$38/LCOE!D$17,0) -> 0 | Z48: =SUM(B48:C48) -> 0 | AA48: =SUM(I48:J48) -> 0 | AB48: =L48 -> 0 | AC48: =SUM(S48:W48) -> 0 | AD48: =S48 -> 0 | AE48: -22 | AF48: =LCOE!E74+LCOE!D$40 -> 0 | AG48: =(1+AF48)^A48 -> 1 | AH48: =Z48/AG48 -> 0 | AI48: =AA48/AG48 -> 0 | AJ48: =AB48/AG48 -> 0 | AK48: =AC48/AG48 -> 0 | AL48: =AD48/AG48 -> 0
A49: -21 | B49: =LCOE!C75+IF(A49>=((LCOE!D$17*-1)+1),LCOE!D$38/LCOE!D$17,0) -> 0 | Z49: =SUM(B49:C49) -> 0 | AA49: =SUM(I49:J49) -> 0 | AB49: =L49 -> 0 | AC49: =SUM(S49:W49) -> 0 | AD49: =S49 -> 0 | AE49: -21 | AF49: =LCOE!E75+LCOE!D$40 -> 0 | AG49: =(1+AF49)^A49 -> 1 | AH49: =Z49/AG49 -> 0 | AI49: =AA49/AG49 -> 0 | AJ49: =AB49/AG49 -> 0 | AK49: =AC49/AG49 -> 0 | AL49: =AD49/AG49 -> 0
A50: -20 | B50: =LCOE!C76+IF(A50>=((LCOE!D$17*-1)+1),LCOE!D$38/LCOE!D$17,0) -> 0 | Z50: =SUM(B50:C50) -> 0 | AA50: =SUM(I50:J50) -> 0 | AB50: =L50 -> 0 | AC50: =SUM(S50:W50) -> 0 | AD50: =S50 -> 0 | AE50: -20 | AF50: =LCOE!E76+LCOE!D$40 -> 0 | AG50: =(1+AF50)^A50 -> 1 | AH50: =Z50/AG50 -> 0 | AI50: =AA50/AG50 -> 0 | AJ50: =AB50/AG50 -> 0 | AK50: =AC50/AG50 -> 0 | AL50: =AD50/AG50 -> 0
A51: -19 | B51: =LCOE!C77+IF(A51>=((LCOE!D$17*-1)+1),LCOE!D$38/LCOE!D$17,0) -> 0 | Z51: =SUM(B51:C51) -> 0 | AA51: =SUM(I51:J51) -> 0 | AB51: =L51 -> 0 | AC51: =SUM(S51:W51) -> 0 | AD51: =S51 -> 0 | AE51: -19 | AF51: =LCOE!E77+LCOE!D$40 -> 0 | AG51: =(1+AF51)^A51 -> 1 | AH51: =Z51/AG51 -> 0 | AI51: =AA51/AG51 -> 0 | AJ51: =AB51/AG51 -> 0 | AK51: =AC51/AG51 -> 0 | AL51: =AD51/AG51 -> 0
A52: -18 | B52: =LCOE!C78+IF(A52>=((LCOE!D$17*-1)+1),LCOE!D$38/LCOE!D$17,0) -> 0 | Z52: =SUM(B52:C52) -> 0 | AA52: =SUM(I52:J52) -> 0 | AB52: =L52 -> 0 | AC52: =SUM(S52:W52) -> 0 | AD52: =S52 -> 0 | AE52: -18 | AF52: =LCOE!E78+LCOE!D$40 -> 0 | AG52: =(1+AF52)^A52 -> 1 | AH52: =Z52/AG52 -> 0 | AI52: =AA52/AG52 -> 0 | AJ52: =AB52/AG52 -> 0 | AK52: =AC52/AG52 -> 0 | AL52: =AD52/AG52 -> 0
A53: -17 | B53: =LCOE!C79+IF(A53>=((LCOE!D$17*-1)+1),LCOE!D$38/LCOE!D$17,0) -> 0 | Z53: =SUM(B53:C53) -> 0 | AA53: =SUM(I53:J53) -> 0 | AB53: =L53 -> 0 | AC53: =SUM(S53:W53) -> 0 | AD53: =S53 -> 0 | AE53: -17 | AF53: =LCOE!E79+LCOE!D$40 -> 0 | AG53: =(1+AF53)^A53 -> 1 | AH53: =Z53/AG53 -> 0 | AI53: =AA53/AG53 -> 0 | AJ53: =AB53/AG53 -> 0 | AK53: =AC53/AG53 -> 0 | AL53: =AD53/AG53 -> 0
A54: -16 | B54: =LCOE!C80+IF(A54>=((LCOE!D$17*-1)+1),LCOE!D$38/LCOE!D$17,0) -> 0 | Z54: =SUM(B54:C54) -> 0 | AA54: =SUM(I54:J54) -> 0 | AB54: =L54 -> 0 | AC54: =SUM(S54:W54) -> 0 | AD54: =S54 -> 0 | AE54: -16 | AF54: =LCOE!E80+LCOE!D$40 -> 0 | AG54: =(1+AF54)^A54 -> 1 | AH54: =Z54/AG54 -> 0 | AI54: =AA54/AG54 -> 0 | AJ54: =AB54/AG54 -> 0 | AK54: =AC54/AG54 -> 0 | AL54: =AD54/AG54 -> 0
A55: -15 | B55: =LCOE!C81+IF(A55>=((LCOE!D$17*-1)+1),LCOE!D$38/LCOE!D$17,0) -> 0 | Z55: =SUM(B55:C55) -> 0 | AA55: =SUM(I55:J55) -> 0 | AB55: =L55 -> 0 | AC55: =SUM(S55:W55) -> 0 | AD55: =S55 -> 0 | AE55: -15 | AF55: =LCOE!E81+LCOE!D$40 -> 0 | AG55: =(1+AF55)^A55 -> 1 | AH55: =Z55/AG55 -> 0 | AI55: =AA55/AG55 -> 0 | AJ55: =AB55/AG55 -> 0 | AK55: =AC55/AG55 -> 0 | AL55: =AD55/AG55 -> 0
A56: -14 | B56: =LCOE!C82+IF(A56>=((LCOE!D$17*-1)+1),LCOE!D$38/LCOE!D$17,0) -> 0 | Z56: =SUM(B56:C56) -> 0 | AA56: =SUM(I56:J56) -> 0 | AB56: =L56 -> 0 | AC56: =SUM(S56:W56) -> 0 | AD56: =S56 -> 0 | AE56: -14 | AF56: =LCOE!E82+LCOE!D$40 -> 0 | AG56: =(1+AF56)^A56 -> 1 | AH56: =Z56/AG56 -> 0 | AI56: =AA56/AG56 -> 0 | AJ56: =AB56/AG56 -> 0 | AK56: =AC56/AG56 -> 0 | AL56: =AD56/AG56 -> 0
... A69: -1 | B69: =LCOE!C95+IF(A69>=((LCOE!D$17*-1)+1),LCOE!D$38/LCOE!D$17,0) -> 1.6816667e+08 | Z69: =SUM(B69:C69) -> 1.6816667e+08 | AA69: =SUM(I69:J69) -> 0 | AB69: =L69 -> 0 | AC69: =SUM(S69:W69) -> 0 | AD69: =S69 -> 0 | AE69: -1 | AF69: =LCOE!E95+LCOE!D$40 -> 0 | AG69: =(1+AF69)^A69 -> 1 | AH69: =Z69/AG69 -> 1.6816667e+08 | AI69: =AA69/AG69 -> 0 | AJ69: =AB69/AG69 -> 0 | AK69: =AC69/AG69 -> 0 | AL69: =AD69/AG69 -> 0
A70: 0 | B70: =LCOE!C96+IF(A70>=((LCOE!D$17*-1)+1),LCOE!D$38/LCOE!D$17,0) -> 1.6816667e+08 | C70: =LCOE!D96+IF(AND(LCOE!D$26>0,A70>=LCOE!D$26,A70<=(LCOE!D$26+LCOE!D$27-1)),LCOE!D$42/LCOE!D$27,0)+IF(AND(AE70>=LCOE!D$16,COUNTIF(AE45:AE70,LCOE!D$16)=LCOE!D$36+1),LCOE!D$35*LCOE!D$38,0) -> 0 | D70: =IF(AE69<LCOE!D$16,1,0) -> 1 | E70: =LCOE!G96+IF(AND(A70>=LCOE!D$26,A70<=(LCOE!D$26+LCOE!D$27-1)),0,1)*IF(A70=LCOE!D$34,0,1)*D70 -> 1 | F70: =LCOE!D$18*50%+LCOE!J96 -> 0.45 | G70: =LCOE!K96+E70*F70*N70*(LCOE!D$14+LCOE!H96)*24*365*D70 -> 1971000 | H70: =LCOE!L96+F70*(LCOE!D$15+LCOE!I96)*E70*24*365*D70*N70 -> 0 | I70: =LCOE!M96+LCOE!D$20*IF(LCOE!D$14>0,(LCOE!D$14+LCOE!H96),(LCOE!D$15+LCOE!I96))*K70*D70 -> 20000000 | J70: =LCOE!N96+LCOE!D$21*IF(LCOE!D$14>0,G70,H70)*K70*D70 -> 0 | K70: =LCOE!O96+100% -> 1 | L70: =LCOE!P96+LCOE!D$23*IF(LCOE!D$14>0,G70,H70)*M70*D70 -> 84082860 | M70: =LCOE!Q96+100% -> 1 | N70: =LCOE!R96+100% -> 1 | O70: =LCOE!S96+LCOE!D$29 -> 313.75 | P70: =LCOE!T96+IF(A70>=LCOE!D$30,100%,0%) -> 1 | Q70: =LCOE!U96+O70/1000*IF(LCOE!D$14>0,G70,H70) -> 618401.25 | R70: =LCOE!B96 -> 30 | S70: =LCOE!V96+Q70*P70*R70 -> 18552038 | T70: =LCOE!W96+LCOE!D$31 -> 0 | U70: =LCOE!X96+T70*IF(LCOE!D$14>0,G70,H70) -> 0 | V70: =LCOE!Y96+LCOE!D$32 -> 0 | W70: =LCOE!Z96+V70*IF(LCOE!D$14>0,G70,H70) -> 0 | X70: =LCOE!AA96+LCOE!D$34 -> 101 | Y70: =X70*H70 -> 0 | Z70: =SUM(B70:C70) -> 1.6816667e+08 | AA70: =SUM(I70:J70) -> 20000000 | AB70: =L70 -> 84082860 | AC70: =U70+W70 -> 0 | AD70: =S70 -> 18552038 | AE70: 0 | AF70: =LCOE!E96+LCOE!D$40 -> 0 | AG70: =(1+AF70)^A70 -> 1 | AH70: =Z70/AG70 -> 1.6816667e+08 | AI70: =AA70/AG70 -> 20000000 | AJ70: =AB70/AG70 -> 84082860 | AK70: =AC70/AG70 -> 0 | AL70: =AD70/AG70 -> 18552038 | AM70: =(-1)*Y70/AG70 -> 0 | AN70: =IF(LCOE!D$14>0,G70,H70)/AG70 -> 1971000
A71: 1 | C71: =LCOE!D97+IF(AND(LCOE!D$26>0,A71>=LCOE!D$26,A71<=(LCOE!D$26+LCOE!D$27-1)),LCOE!D$42/LCOE!D$27,0)+IF(AND(AE71>=LCOE!D$16,COUNTIF(AE46:AE71,LCOE!D$16)=LCOE!D$36+1),LCOE!D$35*LCOE!D$38,0) -> 0 | D71: =IF(AE70<LCOE!D$16,1,0) -> 1 | E71: =LCOE!G97+IF(AND(A71>=LCOE!D$26,A71<=(LCOE!D$26+LCOE!D$27-1)),0,1)*IF(A71=LCOE!D$34,0,1)*D71 -> 1 | F71: =IF(F70<LCOE!D$18,MIN(F70*(1+LCOE!D$19),LCOE!D$18),LCOE!D$18)+LCOE!J97 -> 0.72 | G71: =LCOE!K97+E71*F71*N71*(LCOE!D$14+LCOE!H97)*24*365*D71 -> 3153600 | H71: =LCOE!L97+F71*(LCOE!D$15+LCOE!I97)*E71*24*365*D71*N71 -> 0 | I71: =LCOE!M97+LCOE!D$20*IF(LCOE!D$14>0,(LCOE!D$14+LCOE!H97),(LCOE!D$15+LCOE!I97))*K71*D71 -> 20000000 | J71: =LCOE!N97+LCOE!D$21*IF(LCOE!D$14>0,G71,H71)*K71*D71 -> 0 | K71: =LCOE!O97+K70+K70*LCOE!D$22 -> 1 | L71: =LCOE!P97+LCOE!D$23*IF(LCOE!D$14>0,G71,H71)*M71*D71 -> 134532576 | M71: =LCOE!Q97+M70+M70*LCOE!D$24 -> 1 | N71: =LCOE!R97+N70-N70*LCOE!D$25 -> 1 | O71: =LCOE!S97+LCOE!D$29 -> 313.75 | P71: =LCOE!T97+IF(A71>=LCOE!D$30,100%,0%) -> 1 | Q71: =LCOE!U97+O71/1000*IF(LCOE!D$14>0,G71,H71) -> 989442 | R71: =LCOE!B97 -> 30 | S71: =LCOE!V97+Q71*P71*R71 -> 29683260 | T71: =LCOE!W97+LCOE!D$31 -> 0 | U71: =LCOE!X97+T71*IF(LCOE!D$14>0,G71,H71) -> 0 | V71: =LCOE!Y97+LCOE!D$32 -> 0 | W71: =LCOE!Z97+V71*IF(LCOE!D$14>0,G71,H71) -> 0 | X71: =LCOE!AA97+LCOE!D$34 -> 101 | Y71: =X71*H71 -> 0 | Z71: =SUM(B71:C71) -> 0 | AA71: =SUM(I71:J71) -> 20000000 | AB71: =L71 -> 134532576 | AC71: =U71+W71 -> 0 | AD71: =S71 -> 29683260 | AE71: =AE70+1*E71 -> 1 | AF71: =LCOE!E97+LCOE!D$40 -> 0 | AG71: =(1+AF71)^A71 -> 1 | AH71: =Z71/AG71 -> 0 | AI71: =AA71/AG71 -> 20000000 | AJ71: =AB71/AG71 -> 134532576 | AK71: =AC71/AG71 -> 0 | AL71: =AD71/AG71 -> 29683260 | AM71: =(-1)*Y71/AG71 -> 0 | AN71: =IF(LCOE!D$14>0,G71,H71)/AG71 -> 3153600
A72: 2 | C72: =LCOE!D98+IF(AND(LCOE!D$26>0,A72>=LCOE!D$26,A72<=(LCOE!D$26+LCOE!D$27-1)),LCOE!D$42/LCOE!D$27,0)+IF(AND(AE72>=LCOE!D$16,COUNTIF(AE47:AE72,LCOE!D$16)=LCOE!D$36+1),LCOE!D$35*LCOE!D$38,0) -> 0 | D72: =IF(AE71<LCOE!D$16,1,0) -> 1 | E72: =LCOE!G98+IF(AND(A72>=LCOE!D$26,A72<=(LCOE!D$26+LCOE!D$27-1)),0,1)*IF(A72=LCOE!D$34,0,1)*D72 -> 1 | F72: =IF(F71<LCOE!D$18,MIN(F71*(1+LCOE!D$19),LCOE!D$18),LCOE!D$18)+LCOE!J98 -> 0.9 | G72: =LCOE!K98+E72*F72*N72*(LCOE!D$14+LCOE!H98)*24*365*D72 -> 3942000 | H72: =LCOE!L98+F72*(LCOE!D$15+LCOE!I98)*E72*24*365*D72*N72 -> 0 | I72: =LCOE!M98+LCOE!D$20*IF(LCOE!D$14>0,(LCOE!D$14+LCOE!H98),(LCOE!D$15+LCOE!I98))*K72*D72 -> 20000000 | J72: =LCOE!N98+LCOE!D$21*IF(LCOE!D$14>0,G72,H72)*K72*D72 -> 0 | K72: =LCOE!O98+K71+K71*LCOE!D$22 -> 1 | L72: =LCOE!P98+LCOE!D$23*IF(LCOE!D$14>0,G72,H72)*M72*D72 -> 168165720 | M72: =LCOE!Q98+M71+M71*LCOE!D$24 -> 1 | N72: =LCOE!R98+N71-N71*LCOE!D$25 -> 1 | O72: =LCOE!S98+LCOE!D$29 -> 313.75 | P72: =LCOE!T98+IF(A72>=LCOE!D$30,100%,0%) -> 1 | Q72: =LCOE!U98+O72/1000*IF(LCOE!D$14>0,G72,H72) -> 1236802.5 | R72: =LCOE!B98 -> 30 | S72: =LCOE!V98+Q72*P72*R72 -> 37104075 | T72: =LCOE!W98+LCOE!D$31 -> 0 | U72: =LCOE!X98+T72*IF(LCOE!D$14>0,G72,H72) -> 0 | V72: =LCOE!Y98+LCOE!D$32 -> 0 | W72: =LCOE!Z98+V72*IF(LCOE!D$14>0,G72,H72) -> 0 | X72: =LCOE!AA98+LCOE!D$34 -> 101 | Y72: =X72*H72 -> 0 | Z72: =SUM(B72:C72) -> 0 | AA72: =SUM(I72:J72) -> 20000000 | AB72: =L72 -> 168165720 | AC72: =U72+W72 -> 0 | AD72: =S72 -> 37104075 | AE72: =AE71+1*E72 -> 2 | AF72: =LCOE!E98+LCOE!D$40 -> 0 | AG72: =(1+AF72)^A72 -> 1 | AH72: =Z72/AG72 -> 0 | AI72: =AA72/AG72 -> 20000000 | AJ72: =AB72/AG72 -> 168165720 | AK72: =AC72/AG72 -> 0 | AL72: =AD72/AG72 -> 37104075 | AM72: =(-1)*Y72/AG72 -> 0 | AN72: =IF(LCOE!D$14>0,G72,H72)/AG72 -> 3942000
A73: 3 | C73: =LCOE!D99+IF(AND(LCOE!D$26>0,A73>=LCOE!D$26,A73<=(LCOE!D$26+LCOE!D$27-1)),LCOE!D$42/LCOE!D$27,0)+IF(AND(AE73>=LCOE!D$16,COUNTIF(AE48:AE73,LCOE!D$16)=LCOE!D$36+1),LCOE!D$35*LCOE!D$38,0) -> 0 | D73: =IF(AE72<LCOE!D$16,1,0) -> 1 | E73: =LCOE!G99+IF(AND(A73>=LCOE!D$26,A73<=(LCOE!D$26+LCOE!D$27-1)),0,1)*IF(A73=LCOE!D$34,0,1)*D73 -> 1 | F73: =IF(F72<LCOE!D$18,MIN(F72*(1+LCOE!D$19),LCOE!D$18),LCOE!D$18)+LCOE!J99 -> 0.9 | G73: =LCOE!K99+E73*F73*N73*(LCOE!D$14+LCOE!H99)*24*365*D73 -> 3942000 | H73: =LCOE!L99+F73*(LCOE!D$15+LCOE!I99)*E73*24*365*D73*N73 -> 0 | I73: =LCOE!M99+LCOE!D$20*IF(LCOE!D$14>0,(LCOE!D$14+LCOE!H99),(LCOE!D$15+LCOE!I99))*K73*D73 -> 20000000 | J73: =LCOE!N99+LCOE!D$21*IF(LCOE!D$14>0,G73,H73)*K73*D73 -> 0 | K73: =LCOE!O99+K72+K72*LCOE!D$22 -> 1 | L73: =LCOE!P99+LCOE!D$23*IF(LCOE!D$14>0,G73,H73)*M73*D73 -> 168165720 | M73: =LCOE!Q99+M72+M72*LCOE!D$24 -> 1 | N73: =LCOE!R99+N72-N72*LCOE!D$25 -> 1 | O73: =LCOE!S99+LCOE!D$29 -> 313.75 | P73: =LCOE!T99+IF(A73>=LCOE!D$30,100%,0%) -> 1 | Q73: =LCOE!U99+O73/1000*IF(LCOE!D$14>0,G73,H73) -> 1236802.5 | R73: =LCOE!B99 -> 30 | S73: =LCOE!V99+Q73*P73*R73 -> 37104075 | T73: =LCOE!W99+LCOE!D$31 -> 0 | U73: =LCOE!X99+T73*IF(LCOE!D$14>0,G73,H73) -> 0 | V73: =LCOE!Y99+LCOE!D$32 -> 0 | W73: =LCOE!Z99+V73*IF(LCOE!D$14>0,G73,H73) -> 0 | X73: =LCOE!AA99+LCOE!D$34 -> 101 | Y73: =X73*H73 -> 0 | Z73: =SUM(B73:C73) -> 0 | AA73: =SUM(I73:J73) -> 20000000 | AB73: =L73 -> 168165720 | AC73: =U73+W73 -> 0 | AD73: =S73 -> 37104075 | AE73: =AE72+1*E73 -> 3 | AF73: =LCOE!E99+LCOE!D$40 -> 0 | AG73: =(1+AF73)^A73 -> 1 | AH73: =Z73/AG73 -> 0 | AI73: =AA73/AG73 -> 20000000 | AJ73: =AB73/AG73 -> 168165720 | AK73: =AC73/AG73 -> 0 | AL73: =AD73/AG73 -> 37104075 | AM73: =(-1)*Y73/AG73 -> 0 | AN73: =IF(LCOE!D$14>0,G73,H73)/AG73 -> 3942000
A74: 4 | C74: =LCOE!D100+IF(AND(LCOE!D$26>0,A74>=LCOE!D$26,A74<=(LCOE!D$26+LCOE!D$27-1)),LCOE!D$42/LCOE!D$27,0)+IF(AND(AE74>=LCOE!D$16,COUNTIF(AE49:AE74,LCOE!D$16)=LCOE!D$36+1),LCOE!D$35*LCOE!D$38,0) -> 0 | D74: =IF(AE73<LCOE!D$16,1,0) -> 1 | E74: =LCOE!G100+IF(AND(A74>=LCOE!D$26,A74<=(LCOE!D$26+LCOE!D$27-1)),0,1)*IF(A74=LCOE!D$34,0,1)*D74 -> 1 | F74: =IF(F73<LCOE!D$18,MIN(F73*(1+LCOE!D$19),LCOE!D$18),LCOE!D$18)+LCOE!J100 -> 0.9 | G74: =LCOE!K100+E74*F74*N74*(LCOE!D$14+LCOE!H100)*24*365*D74 -> 3942000 | H74: =LCOE!L100+F74*(LCOE!D$15+LCOE!I100)*E74*24*365*D74*N74 -> 0 | I74: =LCOE!M100+LCOE!D$20*IF(LCOE!D$14>0,(LCOE!D$14+LCOE!H100),(LCOE!D$15+LCOE!I100))*K74*D74 -> 20000000 | J74: =LCOE!N100+LCOE!D$21*IF(LCOE!D$14>0,G74,H74)*K74*D74 -> 0 | K74: =LCOE!O100+K73+K73*LCOE!D$22 -> 1 | L74: =LCOE!P100+LCOE!D$23*IF(LCOE!D$14>0,G74,H74)*M74*D74 -> 168165720 | M74: =LCOE!Q100+M73+M73*LCOE!D$24 -> 1 | N74: =LCOE!R100+N73-N73*LCOE!D$25 -> 1 | O74: =LCOE!S100+LCOE!D$29 -> 313.75 | P74: =LCOE!T100+IF(A74>=LCOE!D$30,100%,0%) -> 1 | Q74: =LCOE!U100+O74/1000*IF(LCOE!D$14>0,G74,H74) -> 1236802.5 | R74: =LCOE!B100 -> 30 | S74: =LCOE!V100+Q74*P74*R74 -> 37104075 | T74: =LCOE!W100+LCOE!D$31 -> 0 | U74: =LCOE!X100+T74*IF(LCOE!D$14>0,G74,H74) -> 0 | V74: =LCOE!Y100+LCOE!D$32 -> 0 | W74: =LCOE!Z100+V74*IF(LCOE!D$14>0,G74,H74) -> 0 | X74: =LCOE!AA100+LCOE!D$34 -> 101 | Y74: =X74*H74 -> 0 | Z74: =SUM(B74:C74) -> 0 | AA74: =SUM(I74:J74) -> 20000000 | AB74: =L74 -> 168165720 | AC74: =U74+W74 -> 0 | AD74: =S74 -> 37104075 | AE74: =AE73+1*E74 -> 4 | AF74: =LCOE!E100+LCOE!D$40 -> 0 | AG74: =(1+AF74)^A74 -> 1 | AH74: =Z74/AG74 -> 0 | AI74: =AA74/AG74 -> 20000000 | AJ74: =AB74/AG74 -> 168165720 | AK74: =AC74/AG74 -> 0 | AL74: =AD74/AG74 -> 37104075 | AM74: =(-1)*Y74/AG74 -> 0 | AN74: =IF(LCOE!D$14>0,G74,H74)/AG74 -> 3942000
A75: 5 | C75: =LCOE!D101+IF(AND(LCOE!D$26>0,A75>=LCOE!D$26,A75<=(LCOE!D$26+LCOE!D$27-1)),LCOE!D$42/LCOE!D$27,0)+IF(AND(AE75>=LCOE!D$16,COUNTIF(AE50:AE75,LCOE!D$16)=LCOE!D$36+1),LCOE!D$35*LCOE!D$38,0) -> 0 | D75: =IF(AE74<LCOE!D$16,1,0) -> 1 | E75: =LCOE!G101+IF(AND(A75>=LCOE!D$26,A75<=(LCOE!D$26+LCOE!D$27-1)),0,1)*IF(A75=LCOE!D$34,0,1)*D75 -> 1 | F75: =IF(F74<LCOE!D$18,MIN(F74*(1+LCOE!D$19),LCOE!D$18),LCOE!D$18)+LCOE!J101 -> 0.9 | G75: =LCOE!K101+E75*F75*N75*(LCOE!D$14+LCOE!H101)*24*365*D75 -> 3942000 | H75: =LCOE!L101+F75*(LCOE!D$15+LCOE!I101)*E75*24*365*D75*N75 -> 0 | I75: =LCOE!M101+LCOE!D$20*IF(LCOE!D$14>0,(LCOE!D$14+LCOE!H101),(LCOE!D$15+LCOE!I101))*K75*D75 -> 20000000 | J75: =LCOE!N101+LCOE!D$21*IF(LCOE!D$14>0,G75,H75)*K75*D75 -> 0 | K75: =LCOE!O101+K74+K74*LCOE!D$22 -> 1 | L75: =LCOE!P101+LCOE!D$23*IF(LCOE!D$14>0,G75,H75)*M75*D75 -> 168165720 | M75: =LCOE!Q101+M74+M74*LCOE!D$24 -> 1 | N75: =LCOE!R101+N74-N74*LCOE!D$25 -> 1 | O75: =LCOE!S101+LCOE!D$29 -> 313.75 | P75: =LCOE!T101+IF(A75>=LCOE!D$30,100%,0%) -> 1 | Q75: =LCOE!U101+O75/1000*IF(LCOE!D$14>0,G75,H75) -> 1236802.5 | R75: =LCOE!B101 -> 30 | S75: =LCOE!V101+Q75*P75*R75 -> 37104075 | T75: =LCOE!W101+LCOE!D$31 -> 0 | U75: =LCOE!X101+T75*IF(LCOE!D$14>0,G75,H75) -> 0 | V75: =LCOE!Y101+LCOE!D$32 -> 0 | W75: =LCOE!Z101+V75*IF(LCOE!D$14>0,G75,H75) -> 0 | X75: =LCOE!AA101+LCOE!D$34 -> 101 | Y75: =X75*H75 -> 0 | Z75: =SUM(B75:C75) -> 0 | AA75: =SUM(I75:J75) -> 20000000 | AB75: =L75 -> 168165720 | AC75: =U75+W75 -> 0 | AD75: =S75 -> 37104075 | AE75: =AE74+1*E75 -> 5 | AF75: =LCOE!E101+LCOE!D$40 -> 0 | AG75: =(1+AF75)^A75 -> 1 | AH75: =Z75/AG75 -> 0 | AI75: =AA75/AG75 -> 20000000 | AJ75: =AB75/AG75 -> 168165720 | AK75: =AC75/AG75 -> 0 | AL75: =AD75/AG75 -> 37104075 | AM75: =(-1)*Y75/AG75 -> 0 | AN75: =IF(LCOE!D$14>0,G75,H75)/AG75 -> 3942000
A76: 6 | C76: =LCOE!D102+IF(AND(LCOE!D$26>0,A76>=LCOE!D$26,A76<=(LCOE!D$26+LCOE!D$27-1)),LCOE!D$42/LCOE!D$27,0)+IF(AND(AE76>=LCOE!D$16,COUNTIF(AE51:AE76,LCOE!D$16)=LCOE!D$36+1),LCOE!D$35*LCOE!D$38,0) -> 0 | D76: =IF(AE75<LCOE!D$16,1,0) -> 1 | E76: =LCOE!G102+IF(AND(A76>=LCOE!D$26,A76<=(LCOE!D$26+LCOE!D$27-1)),0,1)*IF(A76=LCOE!D$34,0,1)*D76 -> 1 | F76: =IF(F75<LCOE!D$18,MIN(F75*(1+LCOE!D$19),LCOE!D$18),LCOE!D$18)+LCOE!J102 -> 0.9 | G76: =LCOE!K102+E76*F76*N76*(LCOE!D$14+LCOE!H102)*24*365*D76 -> 3942000 | H76: =LCOE!L102+F76*(LCOE!D$15+LCOE!I102)*E76*24*365*D76*N76 -> 0 | I76: =LCOE!M102+LCOE!D$20*IF(LCOE!D$14>0,(LCOE!D$14+LCOE!H102),(LCOE!D$15+LCOE!I102))*K76*D76 -> 20000000 | J76: =LCOE!N102+LCOE!D$21*IF(LCOE!D$14>0,G76,H76)*K76*D76 -> 0 | K76: =LCOE!O102+K75+K75*LCOE!D$22 -> 1 | L76: =LCOE!P102+LCOE!D$23*IF(LCOE!D$14>0,G76,H76)*M76*D76 -> 168165720 | M76: =LCOE!Q102+M75+M75*LCOE!D$24 -> 1 | N76: =LCOE!R102+N75-N75*LCOE!D$25 -> 1 | O76: =LCOE!S102+LCOE!D$29 -> 313.75 | P76: =LCOE!T102+IF(A76>=LCOE!D$30,100%,0%) -> 1 | Q76: =LCOE!U102+O76/1000*IF(LCOE!D$14>0,G76,H76) -> 1236802.5 | R76: =LCOE!B102 -> 30 | S76: =LCOE!V102+Q76*P76*R76 -> 37104075 | T76: =LCOE!W102+LCOE!D$31 -> 0 | U76: =LCOE!X102+T76*IF(LCOE!D$14>0,G76,H76) -> 0 | V76: =LCOE!Y102+LCOE!D$32 -> 0 | W76: =LCOE!Z102+V76*IF(LCOE!D$14>0,G76,H76) -> 0 | X76: =LCOE!AA102+LCOE!D$34 -> 101 | Y76: =X76*H76 -> 0 | Z76: =SUM(B76:C76) -> 0 | AA76: =SUM(I76:J76) -> 20000000 | AB76: =L76 -> 168165720 | AC76: =U76+W76 -> 0 | AD76: =S76 -> 37104075 | AE76: =AE75+1*E76 -> 6 | AF76: =LCOE!E102+LCOE!D$40 -> 0 | AG76: =(1+AF76)^A76 -> 1 | AH76: =Z76/AG76 -> 0 | AI76: =AA76/AG76 -> 20000000 | AJ76: =AB76/AG76 -> 168165720 | AK76: =AC76/AG76 -> 0 | AL76: =AD76/AG76 -> 37104075 | AM76: =(-1)*Y76/AG76 -> 0 | AN76: =IF(LCOE!D$14>0,G76,H76)/AG76 -> 3942000
A77: 7 | C77: =LCOE!D103+IF(AND(LCOE!D$26>0,A77>=LCOE!D$26,A77<=(LCOE!D$26+LCOE!D$27-1)),LCOE!D$42/LCOE!D$27,0)+IF(AND(AE77>=LCOE!D$16,COUNTIF(AE52:AE77,LCOE!D$16)=LCOE!D$36+1),LCOE!D$35*LCOE!D$38,0) -> 0 | D77: =IF(AE76<LCOE!D$16,1,0) -> 1 | E77: =LCOE!G103+IF(AND(A77>=LCOE!D$26,A77<=(LCOE!D$26+LCOE!D$27-1)),0,1)*IF(A77=LCOE!D$34,0,1)*D77 -> 1 | F77: =IF(F76<LCOE!D$18,MIN(F76*(1+LCOE!D$19),LCOE!D$18),LCOE!D$18)+LCOE!J103 -> 0.9 | G77: =LCOE!K103+E77*F77*N77*(LCOE!D$14+LCOE!H103)*24*365*D77 -> 3942000 | H77: =LCOE!L103+F77*(LCOE!D$15+LCOE!I103)*E77*24*365*D77*N77 -> 0 | I77: =LCOE!M103+LCOE!D$20*IF(LCOE!D$14>0,(LCOE!D$14+LCOE!H103),(LCOE!D$15+LCOE!I103))*K77*D77 -> 20000000 | J77: =LCOE!N103+LCOE!D$21*IF(LCOE!D$14>0,G77,H77)*K77*D77 -> 0 | K77: =LCOE!O103+K76+K76*LCOE!D$22 -> 1 | L77: =LCOE!P103+LCOE!D$23*IF(LCOE!D$14>0,G77,H77)*M77*D77 -> 168165720 | M77: =LCOE!Q103+M76+M76*LCOE!D$24 -> 1 | N77: =LCOE!R103+N76-N76*LCOE!D$25 -> 1 | O77: =LCOE!S103+LCOE!D$29 -> 313.75 | P77: =LCOE!T103+IF(A77>=LCOE!D$30,100%,0%) -> 1 | Q77: =LCOE!U103+O77/1000*IF(LCOE!D$14>0,G77,H77) -> 1236802.5 | R77: =LCOE!B103 -> 30 | S77: =LCOE!V103+Q77*P77*R77 -> 37104075 | T77: =LCOE!W103+LCOE!D$31 -> 0 | U77: =LCOE!X103+T77*IF(LCOE!D$14>0,G77,H77) -> 0 | V77: =LCOE!Y103+LCOE!D$32 -> 0 | W77: =LCOE!Z103+V77*IF(LCOE!D$14>0,G77,H77) -> 0 | X77: =LCOE!AA103+LCOE!D$34 -> 101 | Y77: =X77*H77 -> 0 | Z77: =SUM(B77:C77) -> 0 | AA77: =SUM(I77:J77) -> 20000000 | AB77: =L77 -> 168165720 | AC77: =U77+W77 -> 0 | AD77: =S77 -> 37104075 | AE77: =AE76+1*E77 -> 7 | AF77: =LCOE!E103+LCOE!D$40 -> 0 | AG77: =(1+AF77)^A77 -> 1 | AH77: =Z77/AG77 -> 0 | AI77: =AA77/AG77 -> 20000000 | AJ77: =AB77/AG77 -> 168165720 | AK77: =AC77/AG77 -> 0 | AL77: =AD77/AG77 -> 37104075 | AM77: =(-1)*Y77/AG77 -> 0 | AN77: =IF(LCOE!D$14>0,G77,H77)/AG77 -> 3942000
A78: 8 | C78: =LCOE!D104+IF(AND(LCOE!D$26>0,A78>=LCOE!D$26,A78<=(LCOE!D$26+LCOE!D$27-1)),LCOE!D$42/LCOE!D$27,0)+IF(AND(AE78>=LCOE!D$16,COUNTIF(AE53:AE78,LCOE!D$16)=LCOE!D$36+1),LCOE!D$35*LCOE!D$38,0) -> 0 | D78: =IF(AE77<LCOE!D$16,1,0) -> 1 | E78: =LCOE!G104+IF(AND(A78>=LCOE!D$26,A78<=(LCOE!D$26+LCOE!D$27-1)),0,1)*IF(A78=LCOE!D$34,0,1)*D78 -> 1 | F78: =IF(F77<LCOE!D$18,MIN(F77*(1+LCOE!D$19),LCOE!D$18),LCOE!D$18)+LCOE!J104 -> 0.9 | G78: =LCOE!K104+E78*F78*N78*(LCOE!D$14+LCOE!H104)*24*365*D78 -> 3942000 | H78: =LCOE!L104+F78*(LCOE!D$15+LCOE!I104)*E78*24*365*D78*N78 -> 0 | I78: =LCOE!M104+LCOE!D$20*IF(LCOE!D$14>0,(LCOE!D$14+LCOE!H104),(LCOE!D$15+LCOE!I104))*K78*D78 -> 20000000 | J78: =LCOE!N104+LCOE!D$21*IF(LCOE!D$14>0,G78,H78)*K78*D78 -> 0 | K78: =LCOE!O104+K77+K77*LCOE!D$22 -> 1 | L78: =LCOE!P104+LCOE!D$23*IF(LCOE!D$14>0,G78,H78)*M78*D78 -> 168165720 | M78: =LCOE!Q104+M77+M77*LCOE!D$24 -> 1 | N78: =LCOE!R104+N77-N77*LCOE!D$25 -> 1 | O78: =LCOE!S104+LCOE!D$29 -> 313.75 | P78: =LCOE!T104+IF(A78>=LCOE!D$30,100%,0%) -> 1 | Q78: =LCOE!U104+O78/1000*IF(LCOE!D$14>0,G78,H78) -> 1236802.5 | R78: =LCOE!B104 -> 30 | S78: =LCOE!V104+Q78*P78*R78 -> 37104075 | T78: =LCOE!W104+LCOE!D$31 -> 0 | U78: =LCOE!X104+T78*IF(LCOE!D$14>0,G78,H78) -> 0 | V78: =LCOE!Y104+LCOE!D$32 -> 0 | W78: =LCOE!Z104+V78*IF(LCOE!D$14>0,G78,H78) -> 0 | X78: =LCOE!AA104+LCOE!D$34 -> 101 | Y78: =X78*H78 -> 0 | Z78: =SUM(B78:C78) -> 0 | AA78: =SUM(I78:J78) -> 20000000 | AB78: =L78 -> 168165720 | AC78: =U78+W78 -> 0 | AD78: =S78 -> 37104075 | AE78: =AE77+1*E78 -> 8 | AF78: =LCOE!E104+LCOE!D$40 -> 0 | AG78: =(1+AF78)^A78 -> 1 | AH78: =Z78/AG78 -> 0 | AI78: =AA78/AG78 -> 20000000 | AJ78: =AB78/AG78 -> 168165720 | AK78: =AC78/AG78 -> 0 | AL78: =AD78/AG78 -> 37104075 | AM78: =(-1)*Y78/AG78 -> 0 | AN78: =IF(LCOE!D$14>0,G78,H78)/AG78 -> 3942000
A79: 9 | C79: =LCOE!D105+IF(AND(LCOE!D$26>0,A79>=LCOE!D$26,A79<=(LCOE!D$26+LCOE!D$27-1)),LCOE!D$42/LCOE!D$27,0)+IF(AND(AE79>=LCOE!D$16,COUNTIF(AE54:AE79,LCOE!D$16)=LCOE!D$36+1),LCOE!D$35*LCOE!D$38,0) -> 0 | D79: =IF(AE78<LCOE!D$16,1,0) -> 1 | E79: =LCOE!G105+IF(AND(A79>=LCOE!D$26,A79<=(LCOE!D$26+LCOE!D$27-1)),0,1)*IF(A79=LCOE!D$34,0,1)*D79 -> 1 | F79: =IF(F78<LCOE!D$18,MIN(F78*(1+LCOE!D$19),LCOE!D$18),LCOE!D$18)+LCOE!J105 -> 0.9 | G79: =LCOE!K105+E79*F79*N79*(LCOE!D$14+LCOE!H105)*24*365*D79 -> 3942000 | H79: =LCOE!L105+F79*(LCOE!D$15+LCOE!I105)*E79*24*365*D79*N79 -> 0 | I79: =LCOE!M105+LCOE!D$20*IF(LCOE!D$14>0,(LCOE!D$14+LCOE!H105),(LCOE!D$15+LCOE!I105))*K79*D79 -> 20000000 | J79: =LCOE!N105+LCOE!D$21*IF(LCOE!D$14>0,G79,H79)*K79*D79 -> 0 | K79: =LCOE!O105+K78+K78*LCOE!D$22 -> 1 | L79: =LCOE!P105+LCOE!D$23*IF(LCOE!D$14>0,G79,H79)*M79*D79 -> 168165720 | M79: =LCOE!Q105+M78+M78*LCOE!D$24 -> 1 | N79: =LCOE!R105+N78-N78*LCOE!D$25 -> 1 | O79: =LCOE!S105+LCOE!D$29 -> 313.75 | P79: =LCOE!T105+IF(A79>=LCOE!D$30,100%,0%) -> 1 | Q79: =LCOE!U105+O79/1000*IF(LCOE!D$14>0,G79,H79) -> 1236802.5 | R79: =LCOE!B105 -> 30 | S79: =LCOE!V105+Q79*P79*R79 -> 37104075 | T79: =LCOE!W105+LCOE!D$31 -> 0 | U79: =LCOE!X105+T79*IF(LCOE!D$14>0,G79,H79) -> 0 | V79: =LCOE!Y105+LCOE!D$32 -> 0 | W79: =LCOE!Z105+V79*IF(LCOE!D$14>0,G79,H79) -> 0 | X79: =LCOE!AA105+LCOE!D$34 -> 101 | Y79: =X79*H79 -> 0 | Z79: =SUM(B79:C79) -> 0 | AA79: =SUM(I79:J79) -> 20000000 | AB79: =L79 -> 168165720 | AC79: =U79+W79 -> 0 | AD79: =S79 -> 37104075 | AE79: =AE78+1*E79 -> 9 | AF79: =LCOE!E105+LCOE!D$40 -> 0 | AG79: =(1+AF79)^A79 -> 1 | AH79: =Z79/AG79 -> 0 | AI79: =AA79/AG79 -> 20000000 | AJ79: =AB79/AG79 -> 168165720 | AK79: =AC79/AG79 -> 0 | AL79: =AD79/AG79 -> 37104075 | AM79: =(-1)*Y79/AG79 -> 0 | AN79: =IF(LCOE!D$14>0,G79,H79)/AG79 -> 3942000
A80: 10 | C80: =LCOE!D106+IF(AND(LCOE!D$26>0,A80>=LCOE!D$26,A80<=(LCOE!D$26+LCOE!D$27-1)),LCOE!D$42/LCOE!D$27,0)+IF(AND(AE80>=LCOE!D$16,COUNTIF(AE55:AE80,LCOE!D$16)=LCOE!D$36+1),LCOE!D$35*LCOE!D$38,0) -> 0 | D80: =IF(AE79<LCOE!D$16,1,0) -> 1 | E80: =LCOE!G106+IF(AND(A80>=LCOE!D$26,A80<=(LCOE!D$26+LCOE!D$27-1)),0,1)*IF(A80=LCOE!D$34,0,1)*D80 -> 1 | F80: =IF(F79<LCOE!D$18,MIN(F79*(1+LCOE!D$19),LCOE!D$18),LCOE!D$18)+LCOE!J106 -> 0.9 | G80: =LCOE!K106+E80*F80*N80*(LCOE!D$14+LCOE!H106)*24*365*D80 -> 3942000 | H80: =LCOE!L106+F80*(LCOE!D$15+LCOE!I106)*E80*24*365*D80*N80 -> 0 | I80: =LCOE!M106+LCOE!D$20*IF(LCOE!D$14>0,(LCOE!D$14+LCOE!H106),(LCOE!D$15+LCOE!I106))*K80*D80 -> 20000000 | J80: =LCOE!N106+LCOE!D$21*IF(LCOE!D$14>0,G80,H80)*K80*D80 -> 0 | K80: =LCOE!O106+K79+K79*LCOE!D$22 -> 1 | L80: =LCOE!P106+LCOE!D$23*IF(LCOE!D$14>0,G80,H80)*M80*D80 -> 168165720 | M80: =LCOE!Q106+M79+M79*LCOE!D$24 -> 1 | N80: =LCOE!R106+N79-N79*LCOE!D$25 -> 1 | O80: =LCOE!S106+LCOE!D$29 -> 313.75 | P80: =LCOE!T106+IF(A80>=LCOE!D$30,100%,0%) -> 1 | Q80: =LCOE!U106+O80/1000*IF(LCOE!D$14>0,G80,H80) -> 1236802.5 | R80: =LCOE!B106 -> 30 | S80: =LCOE!V106+Q80*P80*R80 -> 37104075 | T80: =LCOE!W106+LCOE!D$31 -> 0 | U80: =LCOE!X106+T80*IF(LCOE!D$14>0,G80,H80) -> 0 | V80: =LCOE!Y106+LCOE!D$32 -> 0 | W80: =LCOE!Z106+V80*IF(LCOE!D$14>0,G80,H80) -> 0 | X80: =LCOE!AA106+LCOE!D$34 -> 101 | Y80: =X80*H80 -> 0 | Z80: =SUM(B80:C80) -> 0 | AA80: =SUM(I80:J80) -> 20000000 | AB80: =L80 -> 168165720 | AC80: =U80+W80 -> 0 | AD80: =S80 -> 37104075 | AE80: =AE79+1*E80 -> 10 | AF80: =LCOE!E106+LCOE!D$40 -> 0 | AG80: =(1+AF80)^A80 -> 1 | AH80: =Z80/AG80 -> 0 | AI80: =AA80/AG80 -> 20000000 | AJ80: =AB80/AG80 -> 168165720 | AK80: =AC80/AG80 -> 0 | AL80: =AD80/AG80 -> 37104075 | AM80: =(-1)*Y80/AG80 -> 0 | AN80: =IF(LCOE!D$14>0,G80,H80)/AG80 -> 3942000
A81: 11 | C81: =LCOE!D107+IF(AND(LCOE!D$26>0,A81>=LCOE!D$26,A81<=(LCOE!D$26+LCOE!D$27-1)),LCOE!D$42/LCOE!D$27,0)+IF(AND(AE81>=LCOE!D$16,COUNTIF(AE56:AE81,LCOE!D$16)=LCOE!D$36+1),LCOE!D$35*LCOE!D$38,0) -> 0 | D81: =IF(AE80<LCOE!D$16,1,0) -> 1 | E81: =LCOE!G107+IF(AND(A81>=LCOE!D$26,A81<=(LCOE!D$26+LCOE!D$27-1)),0,1)*IF(A81=LCOE!D$34,0,1)*D81 -> 1 | F81: =IF(F80<LCOE!D$18,MIN(F80*(1+LCOE!D$19),LCOE!D$18),LCOE!D$18)+LCOE!J107 -> 0.9 | G81: =LCOE!K107+E81*F81*N81*(LCOE!D$14+LCOE!H107)*24*365*D81 -> 3942000 | H81: =LCOE!L107+F81*(LCOE!D$15+LCOE!I107)*E81*24*365*D81*N81 -> 0 | I81: =LCOE!M107+LCOE!D$20*IF(LCOE!D$14>0,(LCOE!D$14+LCOE!H107),(LCOE!D$15+LCOE!I107))*K81*D81 -> 20000000 | J81: =LCOE!N107+LCOE!D$21*IF(LCOE!D$14>0,G81,H81)*K81*D81 -> 0 | K81: =LCOE!O107+K80+K80*LCOE!D$22 -> 1 | L81: =LCOE!P107+LCOE!D$23*IF(LCOE!D$14>0,G81,H81)*M81*D81 -> 168165720 | M81: =LCOE!Q107+M80+M80*LCOE!D$24 -> 1 | N81: =LCOE!R107+N80-N80*LCOE!D$25 -> 1 | O81: =LCOE!S107+LCOE!D$29 -> 313.75 | P81: =LCOE!T107+IF(A81>=LCOE!D$30,100%,0%) -> 1 | Q81: =LCOE!U107+O81/1000*IF(LCOE!D$14>0,G81,H81) -> 1236802.5 | R81: =LCOE!B107 -> 30 | S81: =LCOE!V107+Q81*P81*R81 -> 37104075 | T81: =LCOE!W107+LCOE!D$31 -> 0 | U81: =LCOE!X107+T81*IF(LCOE!D$14>0,G81,H81) -> 0 | V81: =LCOE!Y107+LCOE!D$32 -> 0 | W81: =LCOE!Z107+V81*IF(LCOE!D$14>0,G81,H81) -> 0 | X81: =LCOE!AA107+LCOE!D$34 -> 101 | Y81: =X81*H81 -> 0 | Z81: =SUM(B81:C81) -> 0 | AA81: =SUM(I81:J81) -> 20000000 | AB81: =L81 -> 168165720 | AC81: =U81+W81 -> 0 | AD81: =S81 -> 37104075 | AE81: =AE80+1*E81 -> 11 | AF81: =LCOE!E107+LCOE!D$40 -> 0 | AG81: =(1+AF81)^A81 -> 1 | AH81: =Z81/AG81 -> 0 | AI81: =AA81/AG81 -> 20000000 | AJ81: =AB81/AG81 -> 168165720 | AK81: =AC81/AG81 -> 0 | AL81: =AD81/AG81 -> 37104075 | AM81: =(-1)*Y81/AG81 -> 0 | AN81: =IF(LCOE!D$14>0,G81,H81)/AG81 -> 3942000
A82: 12 | C82: =LCOE!D108+IF(AND(LCOE!D$26>0,A82>=LCOE!D$26,A82<=(LCOE!D$26+LCOE!D$27-1)),LCOE!D$42/LCOE!D$27,0)+IF(AND(AE82>=LCOE!D$16,COUNTIF(AE57:AE82,LCOE!D$16)=LCOE!D$36+1),LCOE!D$35*LCOE!D$38,0) -> 0 | D82: =IF(AE81<LCOE!D$16,1,0) -> 1 | E82: =LCOE!G108+IF(AND(A82>=LCOE!D$26,A82<=(LCOE!D$26+LCOE!D$27-1)),0,1)*IF(A82=LCOE!D$34,0,1)*D82 -> 1 | F82: =IF(F81<LCOE!D$18,MIN(F81*(1+LCOE!D$19),LCOE!D$18),LCOE!D$18)+LCOE!J108 -> 0.9 | G82: =LCOE!K108+E82*F82*N82*(LCOE!D$14+LCOE!H108)*24*365*D82 -> 3942000 | H82: =LCOE!L108+F82*(LCOE!D$15+LCOE!I108)*E82*24*365*D82*N82 -> 0 | I82: =LCOE!M108+LCOE!D$20*IF(LCOE!D$14>0,(LCOE!D$14+LCOE!H108),(LCOE!D$15+LCOE!I108))*K82*D82 -> 20000000 | J82: =LCOE!N108+LCOE!D$21*IF(LCOE!D$14>0,G82,H82)*K82*D82 -> 0 | K82: =LCOE!O108+K81+K81*LCOE!D$22 -> 1 | L82: =LCOE!P108+LCOE!D$23*IF(LCOE!D$14>0,G82,H82)*M82*D82 -> 168165720 | M82: =LCOE!Q108+M81+M81*LCOE!D$24 -> 1 | N82: =LCOE!R108+N81-N81*LCOE!D$25 -> 1 | O82: =LCOE!S108+LCOE!D$29 -> 313.75 | P82: =LCOE!T108+IF(A82>=LCOE!D$30,100%,0%) -> 1 | Q82: =LCOE!U108+O82/1000*IF(LCOE!D$14>0,G82,H82) -> 1236802.5 | R82: =LCOE!B108 -> 30 | S82: =LCOE!V108+Q82*P82*R82 -> 37104075 | T82: =LCOE!W108+LCOE!D$31 -> 0 | U82: =LCOE!X108+T82*IF(LCOE!D$14>0,G82,H82) -> 0 | V82: =LCOE!Y108+LCOE!D$32 -> 0 | W82: =LCOE!Z108+V82*IF(LCOE!D$14>0,G82,H82) -> 0 | X82: =LCOE!AA108+LCOE!D$34 -> 101 | Y82: =X82*H82 -> 0 | Z82: =SUM(B82:C82) -> 0 | AA82: =SUM(I82:J82) -> 20000000 | AB82: =L82 -> 168165720 | AC82: =U82+W82 -> 0 | AD82: =S82 -> 37104075 | AE82: =AE81+1*E82 -> 12 | AF82: =LCOE!E108+LCOE!D$40 -> 0 | AG82: =(1+AF82)^A82 -> 1 | AH82: =Z82/AG82 -> 0 | AI82: =AA82/AG82 -> 20000000 | AJ82: =AB82/AG82 -> 168165720 | AK82: =AC82/AG82 -> 0 | AL82: =AD82/AG82 -> 37104075 | AM82: =(-1)*Y82/AG82 -> 0 | AN82: =IF(LCOE!D$14>0,G82,H82)/AG82 -> 3942000
... A170: 100 | C170: =LCOE!D196+IF(AND(LCOE!D$26>0,A170>=LCOE!D$26,A170<=(LCOE!D$26+LCOE!D$27-1)),LCOE!D$42/LCOE!D$27,0)+IF(AND(AE170>=LCOE!D$16,COUNTIF(AE145:AE170,LCOE!D$16)=LCOE!D$36+1),LCOE!D$35*LCOE!D$38,0) -> 25225000 | D170: =IF(AE169<LCOE!D$16,1,0) -> 0 | E170: =LCOE!G196+IF(AND(A170>=LCOE!D$26,A170<=(LCOE!D$26+LCOE!D$27-1)),0,1)*IF(A170=LCOE!D$34,0,1)*D170 -> 0 | F170: =IF(F169<LCOE!D$18,MIN(F169*(1+LCOE!D$19),LCOE!D$18),LCOE!D$18)+LCOE!J196 -> 0.9 | G170: =LCOE!K196+E170*F170*N170*(LCOE!D$14+LCOE!H196)*24*365*D170 -> 0 | H170: =LCOE!L196+F170*(LCOE!D$15+LCOE!I196)*E170*24*365*D170*N170 -> 0 | I170: =LCOE!M196+LCOE!D$20*IF(LCOE!D$14>0,(LCOE!D$14+LCOE!H196),(LCOE!D$15+LCOE!I196))*K170*D170 -> 0 | J170: =LCOE!N196+LCOE!D$21*IF(LCOE!D$14>0,G170,H170)*K170*D170 -> 0 | K170: =LCOE!O196+K169+K169*LCOE!D$22 -> 1 | L170: =LCOE!P196+LCOE!D$23*IF(LCOE!D$14>0,G170,H170)*M170*D170 -> 0 | M170: =LCOE!Q196+M169+M169*LCOE!D$24 -> 1 | N170: =LCOE!R196+N169-N169*LCOE!D$25 -> 1 | O170: =LCOE!S196+LCOE!D$29 -> 313.75 | P170: =LCOE!T196+IF(A170>=LCOE!D$30,100%,0%) -> 1 | Q170: =LCOE!U196+O170/1000*IF(LCOE!D$14>0,G170,H170) -> 0 | R170: =LCOE!B196 -> 30 | S170: =LCOE!V196+Q170*P170*R170 -> 0 | T170: =LCOE!W196+LCOE!D$31 -> 0 | U170: =LCOE!X196+T170*IF(LCOE!D$14>0,G170,H170) -> 0 | V170: =LCOE!Y196+LCOE!D$32 -> 0 | W170: =LCOE!Z196+V170*IF(LCOE!D$14>0,G170,H170) -> 0 | X170: =LCOE!AA196+LCOE!D$34 -> 101 | Y170: =X170*H170 -> 0 | Z170: =SUM(B170:C170) -> 25225000 | AA170: =SUM(I170:J170) -> 0 | AB170: =L170 -> 0 | AC170: =U170+W170 -> 0 | AD170: =S170 -> 0 | AE170: =AE169+1*E170 -> 30 | AF170: =LCOE!E196+LCOE!D$40 -> 0 | AG170: =(1+AF170)^A170 -> 1 | AH170: =Z170/AG170 -> 25225000 | AI170: =AA170/AG170 -> 0 | AJ170: =AB170/AG170 -> 0 | AK170: =AC170/AG170 -> 0 | AL170: =AD170/AG170 -> 0 | AM170: =(-1)*Y170/AG170 -> 0 | AN170: =IF(LCOE!D$14>0,G170,H170)/AG170 -> 0

Sheet LCOE 2
B2: Parameter recap (not used in calcs) | C2: =LCOE!E3 -> LCOE 2 | F2: RESULTS | G2: =C4 -> USD | I2: =C6 -> USD
B3: =LCOE!C5 -> Name | C3: =LCOE!E5 -> CCGT in Belgium (2020) | F3: =LCOE!C46 -> LCOE (LCOHeat for pure heat plants) | G3: =SUM(AH45:AM170)/SUM(AN45:AN170) -> 64.075543 | H3: =_xlfn.CONCAT(C$4,"/MWh") -> USD/MWh | I3: =G3*C$7 -> 64.075543 | J3: =_xlfn.CONCAT(C$6,"/MWh") -> USD/MWh
B4: =LCOE!C6 -> Currency used for LCOE calculations | C4: =LCOE!E6 -> USD | F4: =LCOE!C47 -> Of which: Capital costs | G4: =SUM(AH45:AH170)/SUM(AN45:AN170) -> 6.7525504 | H4: =_xlfn.CONCAT(C$4,"/MWh") -> USD/MWh | I4: =G4*C$7 -> 6.7525504 | J4: =_xlfn.CONCAT(C$6,"/MWh") -> USD/MWh
B5: =LCOE!C7 -> Price reference year | C5: =LCOE!E7 -> 0 | F5: =LCOE!C48 -> O&M | G5: =SUM(AI45:AI170)/SUM(AN45:AN170) -> 5.250493 | H5: =_xlfn.CONCAT(C$4,"/MWh") -> USD/MWh | I5: =G5*C$7 -> 5.250493 | J5: =_xlfn.CONCAT(C$6,"/MWh") -> USD/MWh
B6: =LCOE!C8 -> Currency used | C6: =LCOE!E8 -> USD | F6: =LCOE!C49 -> Fuel | G6: =SUM(AJ45:AJ170)/SUM(AN45:AN170) -> 42.66 | H6: =_xlfn.CONCAT(C$4,"/MWh") -> USD/MWh | I6: =G6*C$7 -> 42.66 | J6: =_xlfn.CONCAT(C$6,"/MWh") -> USD/MWh
B7: =LCOE!C9 -> Conversion rate at reference year | C7: =LCOE!E9 -> 1 | F7: =LCOE!C50 -> Taxes and fees | G7: =SUM(AK45:AK170)/SUM(AN45:AN170) -> 0 | H7: =_xlfn.CONCAT(C$4,"/MWh") -> USD/MWh | I7: =G7*C$7 -> 0 | J7: =_xlfn.CONCAT(C$6,"/MWh") -> USD/MWh
B8: =LCOE!C10 -> Debt % | C8: =LCOE!E10 -> 0.9 | F8: =LCOE!C51 -> Emission costs | G8: =SUM(AL45:AL170)/SUM(AN45:AN170) -> 9.4125 | H8: =_xlfn.CONCAT(C$4,"/MWh") -> USD/MWh | I8: =G8*C$7 -> 9.4125 | J8: =_xlfn.CONCAT(C$6,"/MWh") -> USD/MWh
B9: =LCOE!C11 -> Cost of debt (private discount rate) | C9: =LCOE!E11 -> 0.03 | F9: =LCOE!C52 -> Heat credit (for CHP plants) | G9: =IF(C15>0,SUM(AM45:AM170)/SUM(AN45:AN170),0) -> 0 | H9: =_xlfn.CONCAT(C$4,"/MWh") -> USD/MWh | I9: =G9*C$7 -> 0 | J9: =_xlfn.CONCAT(C$6,"/MWh") -> USD/MWh
B10: =LCOE!C12 -> Cost of equity (discount rate) | C10: =LCOE!E12 -> 0.03 | F10: =LCOE!C53 -> WACC average over lifetime | G10: =AVERAGE(AF70:AF170) -> 0.03 | I10: =G10 -> 0.03
B11: =LCOE!C13 -> Construction cost per kW | C11: =LCOE!E13 -> 1009 | F11: =LCOE!C54 -> Plant type | G11: =IF(AND(LCOE!E$14>0,LCOE!E$15=0),"Electric only",IF(AND(LCOE!E$14>0,LCOE!E$15>0),"CHP",IF(AND(LCOE!E$14=0,LCOE!E$15>0),"Heat only","Error: no generation"))) -> Electric only | I11: =G11 -> Electric only
B12: =LCOE!C14 -> Maximum electric power, in MW_e | C12: =LCOE!E14 -> 500
B13: =LCOE!C15 -> Maximum heat power, in MW_h | C13: =LCOE!E15 -> 0
B14: =LCOE!C16 -> Plant lifetime | C14: =LCOE!E16 -> 30
B15: =LCOE!C17 -> Construction period, years | C15: =LCOE!E17 -> 3
B16: =LCOE!C18 -> Capacity factor (settled down) | C16: =LCOE!E18 -> 0.9
B17: =LCOE!C19 -> Capacity factor ramp-up on startup, per year | C17: =LCOE!E19 -> 0.6
B18: =LCOE!C20 -> Fixed OPEX/MW capacity at project start | C18: =LCOE!E20 -> 40000
B19: =LCOE!C21 -> Variable OPEX/MWh produced at project start | C19: =LCOE!E21 -> 0
B20: =LCOE!C22 -> OPEX escalator | C20: =LCOE!E22 -> 0
B21: =LCOE!C23 -> FUELEX/MWh produced at project start | C21: =LCOE!E23 -> 42.66
B22: =LCOE!C24 -> FUELEX escalator | C22: =LCOE!E24 -> 0
B23: =LCOE!C25 -> Efficiency loss/year | C23: =LCOE!E25 -> 0
... B41: =LCOE!C43 -> Overrides | C41: =LCOE!E43 -> 0
Z43: SUMMARY OF COSTS
A44: Year (t) | B44: CAPEXconstr | C44: CAPEXrefurb/decom | D44: Lifetime left? | E44: Operational% | F44: Capacity factor | G44: Electricity produced (MWh_e) | H44: Heat produced (MWh_h) | I44: Fixed OPEX | J44: Variable OPEX | K44: OPEX relative to startup | L44: FUELEX | M44: FUELEX relative to startup | N44: Efficiency relative to startup | O44: Total emission factor, gCO2/kWh | P44: % of emissions taxed | Q44: Total emissions, tCO2e | R44: Cost of tCO2e | S44: Cost of emissions levied, E | T44: Tax per MWh produced | U44: Taxes levied | V44: Waste fee per MWh produced | W44: Waste fee levied | X44: Heat credit per MWh_h | Y44: Heat credit total | Z44: Total capital expenditure, I | AA44: Total operation and maintenance expenditure, M | AB44: Total fuel expenditure, F | AC44: Total taxes, T | AD44: Total emission fees, E | AE44: Lifetime expended at start of year | AF44: Discount rate r (IDC when t<0) | AG44: Discount factor (1+r)^t | AH44: I discounted | AI44: M discounted | AJ44: F discounted | AK44: T discounted | AL44: E discounted | AM44: Heat credit, discounted | AN44: Production (MWh), discounted
A45: -25 | B45: =LCOE!C71+IF(A45>=((LCOE!E$17*-1)+1),LCOE!E$38/LCOE!E$17,0) -> 0 | Z45: =SUM(B45:C45) -> 0 | AA45: =SUM(I45:J45) -> 0 | AB45: =L45 -> 0 | AC45: =SUM(S45:W45) -> 0 | AD45: =S45 -> 0 | AE45: -25 | AF45: =LCOE!E71+LCOE!E$40 -> 0.03 | AG45: =(1+AF45)^A45 -> 0.47760557 | AH45: =Z45/AG45 -> 0 | AI45: =AA45/AG45 -> 0 | AJ45: =AB45/AG45 -> 0 | AK45: =AC45/AG45 -> 0 | AL45: =AD45/AG45 -> 0
A46: -24 | B46: =LCOE!C72+IF(A46>=((LCOE!E$17*-1)+1),LCOE!E$38/LCOE!E$17,0) -> 0 | Z46: =SUM(B46:C46) -> 0 | AA46: =SUM(I46:J46) -> 0 | AB46: =L46 -> 0 | AC46: =SUM(S46:W46) -> 0 | AD46: =S46 -> 0 | AE46: -24 | AF46: =LCOE!E72+LCOE!E$40 -> 0.03 | AG46: =(1+AF46)^A46 -> 0.49193374 | AH46: =Z46/AG46 -> 0 | AI46: =AA46/AG46 -> 0 | AJ46: =AB46/AG46 -> 0 | AK46: =AC46/AG46 -> 0 | AL46: =AD46/AG46 -> 0
A47: -23 | B47: =LCOE!C73+IF(A47>=((LCOE!E$17*-1)+1),LCOE!E$38/LCOE!E$17,0) -> 0 | Z47: =SUM(B47:C47) -> 0 | AA47: =SUM(I47:J47) -> 0 | AB47: =L47 -> 0 | AC47: =SUM(S47:W47) -> 0 | AD47: =S47 -> 0 | AE47: -23 | AF47: =LCOE!E73+LCOE!E$40 -> 0.03 | AG47: =(1+AF47)^A47 -> 0.50669175 | AH47: =Z47/AG47 -> 0 | AI47: =AA47/AG47 -> 0 | AJ47: =AB47/AG47 -> 0 | AK47: =AC47/AG47 -> 0 | AL47: =AD47/AG47 -> 0
A48: -22 | B48: =LCOE!C74+IF(A48>=((LCOE!E$17*-1)+1),LCOE!E$38/LCOE!E$17,0) -> 0 | Z48: =SUM(B48:C48) -> 0 | AA48: =SUM(I48:J48) -> 0 | AB48: =L48 -> 0 | AC48: =SUM(S48:W48) -> 0 | AD48: =S48 -> 0 | AE48: -22 | AF48: =LCOE!E74+LCOE!E$40 -> 0.03 | AG48: =(1+AF48)^A48 -> 0.5218925 | AH48: =Z48/AG48 -> 0 | AI48: =AA48/AG48 -> 0 | AJ48: =AB48/AG48 -> 0 | AK48: =AC48/AG48 -> 0 | AL48: =AD48/AG48 -> 0
A49: -21 | B49: =LCOE!C75+IF(A49>=((LCOE!E$17*-1)+1),LCOE!E$38/LCOE!E$17,0) -> 0 | Z49: =SUM(B49:C49) -> 0 | AA49: =SUM(I49:J49) -> 0 | AB49: =L49 -> 0 | AC49: =SUM(S49:W49) -> 0 | AD49: =S49 -> 0 | AE49: -21 | AF49: =LCOE!E75+LCOE!E$40 -> 0.03 | AG49: =(1+AF49)^A49 -> 0.53754928 | AH49: =Z49/AG49 -> 0 | AI49: =AA49/AG49 -> 0 | AJ49: =AB49/AG49 -> 0 | AK49: =AC49/AG49 -> 0 | AL49: =AD49/AG49 -> 0
A50: -20 | B50: =LCOE!C76+IF(A50>=((LCOE!E$17*-1)+1),LCOE!E$38/LCOE!E$17,0) -> 0 | Z50: =SUM(B50:C50) -> 0 | AA50: =SUM(I50:J50) -> 0 | AB50: =L50 -> 0 | AC50: =SUM(S50:W50) -> 0 | AD50: =S50 -> 0 | AE50: -20 | AF50: =LCOE!E76+LCOE!E$40 -> 0.03 | AG50: =(1+AF50)^A50 -> 0.55367575 | AH50: =Z50/AG50 -> 0 | AI50: =AA50/AG50 -> 0 | AJ50: =AB50/AG50 -> 0 | AK50: =AC50/AG50 -> 0 | AL50: =AD50/AG50 -> 0
A51: -19 | B51: =LCOE!C77+IF(A51>=((LCOE!E$17*-1)+1),LCOE!E$38/LCOE!E$17,0) -> 0 | Z51: =SUM(B51:C51) -> 0 | AA51: =SUM(I51:J51) -> 0 | AB51: =L51 -> 0 | AC51: =SUM(S51:W51) -> 0 | AD51: =S51 -> 0 | AE51: -19 | AF51: =LCOE!E77+LCOE!E$40 -> 0.03 | AG51: =(1+AF51)^A51 -> 0.57028603 | AH51: =Z51/AG51 -> 0 | AI51: =AA51/AG51 -> 0 | AJ51: =AB51/AG51 -> 0 | AK51: =AC51/AG51 -> 0 | AL51: =AD51/AG51 -> 0
A52: -18 | B52: =LCOE!C78+IF(A52>=((LCOE!E$17*-1)+1),LCOE!E$38/LCOE!E$17,0) -> 0 | Z52: =SUM(B52:C52) -> 0 | AA52: =SUM(I52:J52) -> 0 | AB52: =L52 -> 0 | AC52: =SUM(S52:W52) -> 0 | AD52: =S52 -> 0 | AE52: -18 | AF52: =LCOE!E78+LCOE!E$40 -> 0.03 | AG52: =(1+AF52)^A52 -> 0.58739461 | AH52: =Z52/AG52 -> 0 | AI52: =AA52/AG52 -> 0 | AJ52: =AB52/AG52 -> 0 | AK52: =AC52/AG52 -> 0 | AL52: =AD52/AG52 -> 0
A53: -17 | B53: =LCOE!C79+IF(A53>=((LCOE!E$17*-1)+1),LCOE!E$38/LCOE!E$17,0) -> 0 | Z53: =SUM(B53:C53) -> 0 | AA53: =SUM(I53:J53) -> 0 | AB53: =L53 -> 0 | AC53: =SUM(S53:W53) -> 0 | AD53: =S53 -> 0 | AE53: -17 | AF53: =LCOE!E79+LCOE!E$40 -> 0.03 | AG53: =(1+AF53)^A53 -> 0.60501645 | AH53: =Z53/AG53 -> 0 | AI53: =AA53/AG53 -> 0 | AJ53: =AB53/AG53 -> 0 | AK53: =AC53/AG53 -> 0 | AL53: =AD53/AG53 -> 0
A54: -16 | B54: =LCOE!C80+IF(A54>=((LCOE!E$17*-1)+1),LCOE!E$38/LCOE!E$17,0) -> 0 | Z54: =SUM(B54:C54) -> 0 | AA54: =SUM(I54:J54) -> 0 | AB54: =L54 -> 0 | AC54: =SUM(S54:W54) -> 0 | AD54: =S54 -> 0 | AE54: -16 | AF54: =LCOE!E80+LCOE!E$40 -> 0.03 | AG54: =(1+AF54)^A54 -> 0.62316694 | AH54: =Z54/AG54 -> 0 | AI54: =AA54/AG54 -> 0 | AJ54: =AB54/AG54 -> 0 | AK54: =AC54/AG54 -> 0 | AL54: =AD54/AG54 -> 0
A55: -15 | B55: =LCOE!C81+IF(A55>=((LCOE!E$17*-1)+1),LCOE!E$38/LCOE!E$17,0) -> 0 | Z55: =SUM(B55:C55) -> 0 | AA55: =SUM(I55:J55) -> 0 | AB55: =L55 -> 0 | AC55: =SUM(S55:W55) -> 0 | AD55: =S55 -> 0 | AE55: -15 | AF55: =LCOE!E81+LCOE!E$40 -> 0.03 | AG55: =(1+AF55)^A55 -> 0.64186195 | AH55: =Z55/AG55 -> 0 | AI55: =AA55/AG55 -> 0 | AJ55: =AB55/AG55 -> 0 | AK55: =AC55/AG55 -> 0 | AL55: =AD55/AG55 -> 0
A56: -14 | B56: =LCOE!C82+IF(A56>=((LCOE!E$17*-1)+1),LCOE!E$38/LCOE!E$17,0) -> 0 | Z56: =SUM(B56:C56) -> 0 | AA56: =SUM(I56:J56) -> 0 | AB56: =L56 -> 0 | AC56: =SUM(S56:W56) -> 0 | AD56: =S56 -> 0 | AE56: -14 | AF56: =LCOE!E82+LCOE!E$40 -> 0.03 | AG56: =(1+AF56)^A56 -> 0.66111781 | AH56: =Z56/AG56 -> 0 | AI56: =AA56/AG56 -> 0 | AJ56: =AB56/AG56 -> 0 | AK56: =AC56/AG56 -> 0 | AL56: =AD56/AG56 -> 0
... A69: -1 | B69: =LCOE!C95+IF(A69>=((LCOE!E$17*-1)+1),LCOE!E$38/LCOE!E$17,0) -> 1.6816667e+08 | Z69: =SUM(B69:C69) -> 1.6816667e+08 | AA69: =SUM(I69:J69) -> 0 | AB69: =L69 -> 0 | AC69: =SUM(S69:W69) -> 0 | AD69: =S69 -> 0 | AE69: -1 | AF69: =LCOE!E95+LCOE!E$40 -> 0.03 | AG69: =(1+AF69)^A69 -> 0.97087379 | AH69: =Z69/AG69 -> 1.7321167e+08 | AI69: =AA69/AG69 -> 0 | AJ69: =AB69/AG69 -> 0 | AK69: =AC69/AG69 -> 0 | AL69: =AD69/AG69 -> 0
A70: 0 | B70: =LCOE!C96+IF(A70>=((LCOE!E$17*-1)+1),LCOE!E$38/LCOE!E$17,0) -> 1.6816667e+08 | C70: =LCOE!E96+IF(AND(LCOE!E$26>0,A70>=LCOE!E$26,A70<=(LCOE!E$26+LCOE!E$27-1)),LCOE!E$42/LCOE!E$27,0)+IF(AND(D70=0,AE70>=LCOE!E$16,COUNTIF(D45:D70,0)=LCOE!E$36),LCOE!E$35*LCOE!E$38,0) -> 0 | D70: =IF(AE69<LCOE!E$16,1,0) -> 1 | E70: =LCOE!G96+IF(AND(A70>=LCOE!E$26,A70<=(LCOE!E$26+LCOE!E$27-1)),0,1)*IF(A70=LCOE!E$34,0,1)*D70 -> 1 | F70: =LCOE!E$18*50%+LCOE!J96 -> 0.45 | G70: =LCOE!K96+E70*F70*N70*(LCOE!E$14+LCOE!H96)*24*365*D70 -> 1971000 | H70: =LCOE!L96+F70*(LCOE!E$15+LCOE!I96)*E70*24*365*D70*N70 -> 0 | I70: =LCOE!M96+LCOE!E$20*IF(LCOE!E$14>0,(LCOE!E$14+LCOE!H96),(LCOE!E$15+LCOE!I96))*K70*D70 -> 20000000 | J70: =LCOE!N96+LCOE!E$21*IF(LCOE!E$14>0,G70,H70)*K70*D70 -> 0 | K70: =LCOE!O96+100% -> 1 | L70: =LCOE!P96+LCOE!E$23*IF(LCOE!E$14>0,G70,H70)*M70*D70 -> 84082860 | M70: =LCOE!Q96+100% -> 1 | N70: =LCOE!R96+100% -> 1 | O70: =LCOE!S96+LCOE!E$29 -> 313.75 | P70: =LCOE!T96+IF(A70>=LCOE!E$30,100%,0%) -> 1 | Q70: =LCOE!U96+O70/1000*IF(LCOE!E$14>0,G70,H70) -> 618401.25 | R70: =LCOE!B96 -> 30 | S70: =LCOE!V96+Q70*P70*R70 -> 18552038 | T70: =LCOE!W96+LCOE!E$31 -> 0 | U70: =LCOE!X96+T70*IF(LCOE!E$14>0,G70,H70) -> 0 | V70: =LCOE!Y96+LCOE!E$32 -> 0 | W70: =LCOE!Z96+V70*IF(LCOE!E$14>0,G70,H70) -> 0 | X70: =LCOE!AA96+LCOE!E$34 -> 101 | Y70: =X70*H70 -> 0 | Z70: =SUM(B70:C70) -> 1.6816667e+08 | AA70: =SUM(I70:J70) -> 20000000 | AB70: =L70 -> 84082860 | AC70: =U70+W70 -> 0 | AD70: =S70 -> 18552038 | AE70: 0 | AF70: =LCOE!E96+LCOE!E$40 -> 0.03 | AG70: =(1+AF70)^A70 -> 1 | AH70: =Z70/AG70 -> 1.6816667e+08 | AI70: =AA70/AG70 -> 20000000 | AJ70: =AB70/AG70 -> 84082860 | AK70: =AC70/AG70 -> 0 | AL70: =AD70/AG70 -> 18552038 | AM70: =(-1)*Y70/AG70 -> 0 | AN70: =IF(LCOE!E$14>0,G70,H70)/AG70 -> 1971000
A71: 1 | C71: =LCOE!E97+IF(AND(LCOE!E$26>0,A71>=LCOE!E$26,A71<=(LCOE!E$26+LCOE!E$27-1)),LCOE!E$42/LCOE!E$27,0)+IF(AND(D71=0,AE71>=LCOE!E$16,COUNTIF(D46:D71,0)=LCOE!E$36),LCOE!E$35*LCOE!E$38,0) -> 0 | D71: =IF(AE70<LCOE!E$16,1,0) -> 1 | E71: =LCOE!G97+IF(AND(A71>=LCOE!E$26,A71<=(LCOE!E$26+LCOE!E$27-1)),0,1)*IF(A71=LCOE!E$34,0,1)*D71 -> 1 | F71: =IF(F70<LCOE!E$18,MIN(F70*(1+LCOE!E$19),LCOE!E$18),LCOE!E$18)+LCOE!J97 -> 0.72 | G71: =LCOE!K97+E71*F71*N71*(LCOE!E$14+LCOE!H97)*24*365*D71 -> 3153600 | H71: =LCOE!L97+F71*(LCOE!E$15+LCOE!I97)*E71*24*365*D71*N71 -> 0 | I71: =LCOE!M97+LCOE!E$20*IF(LCOE!E$14>0,(LCOE!E$14+LCOE!H97),(LCOE!E$15+LCOE!I97))*K71*D71 -> 20000000 | J71: =LCOE!N97+LCOE!E$21*IF(LCOE!E$14>0,G71,H71)*K71*D71 -> 0 | K71: =LCOE!O97+K70+K70*LCOE!E$22 -> 1 | L71: =LCOE!P97+LCOE!E$23*IF(LCOE!E$14>0,G71,H71)*M71*D71 -> 134532576 | M71: =LCOE!Q97+M70+M70*LCOE!E$24 -> 1 | N71: =LCOE!R97+N70-N70*LCOE!E$25 -> 1 | O71: =LCOE!S97+LCOE!E$29 -> 313.75 | P71: =LCOE!T97+IF(A71>=LCOE!E$30,100%,0%) -> 1 | Q71: =LCOE!U97+O71/1000*IF(LCOE!E$14>0,G71,H71) -> 989442 | R71: =LCOE!B97 -> 30 | S71: =LCOE!V97+Q71*P71*R71 -> 29683260 | T71: =LCOE!W97+LCOE!E$31 -> 0 | U71: =LCOE!X97+T71*IF(LCOE!E$14>0,G71,H71) -> 0 | V71: =LCOE!Y97+LCOE!E$32 -> 0 | W71: =LCOE!Z97+V71*IF(LCOE!E$14>0,G71,H71) -> 0 | X71: =LCOE!AA97+LCOE!E$34 -> 101 | Y71: =X71*H71 -> 0 | Z71: =SUM(B71:C71) -> 0 | AA71: =SUM(I71:J71) -> 20000000 | AB71: =L71 -> 134532576 | AC71: =U71+W71 -> 0 | AD71: =S71 -> 29683260 | AE71: =AE70+1*E71 -> 1 | AF71: =LCOE!E97+LCOE!E$40 -> 0.03 | AG71: =(1+AF71)^A71 -> 1.03 | AH71: =Z71/AG71 -> 0 | AI71: =AA71/AG71 -> 19417476 | AJ71: =AB71/AG71 -> 1.3061415e+08 | AK71: =AC71/AG71 -> 0 | AL71: =AD71/AG71 -> 28818699 | AM71: =(-1)*Y71/AG71 -> 0 | AN71: =IF(LCOE!E$14>0,G71,H71)/AG71 -> 3061747.6
A72: 2 | C72: =LCOE!E98+IF(AND(LCOE!E$26>0,A72>=LCOE!E$26,A72<=(LCOE!E$26+LCOE!E$27-1)),LCOE!E$42/LCOE!E$27,0)+IF(AND(D72=0,AE72>=LCOE!E$16,COUNTIF(D47:D72,0)=LCOE!E$36),LCOE!E$35*LCOE!E$38,0) -> 0 | D72: =IF(AE71<LCOE!E$16,1,0) -> 1 | E72: =LCOE!G98+IF(AND(A72>=LCOE!E$26,A72<=(LCOE!E$26+LCOE!E$27-1)),0,1)*IF(A72=LCOE!E$34,0,1)*D72 -> 1 | F72: =IF(F71<LCOE!E$18,MIN(F71*(1+LCOE!E$19),LCOE!E$18),LCOE!E$18)+LCOE!J98 -> 0.9 | G72: =LCOE!K98+E72*F72*N72*(LCOE!E$14+LCOE!H98)*24*365*D72 -> 3942000 | H72: =LCOE!L98+F72*(LCOE!E$15+LCOE!I98)*E72*24*365*D72*N72 -> 0 | I72: =LCOE!M98+LCOE!E$20*IF(LCOE!E$14>0,(LCOE!E$14+LCOE!H98),(LCOE!E$15+LCOE!I98))*K72*D72 -> 20000000 | J72: =LCOE!N98+LCOE!E$21*IF(LCOE!E$14>0,G72,H72)*K72*D72 -> 0 | K72: =LCOE!O98+K71+K71*LCOE!E$22 -> 1 | L72: =LCOE!P98+LCOE!E$23*IF(LCOE!E$14>0,G72,H72)*M72*D72 -> 168165720 | M72: =LCOE!Q98+M71+M71*LCOE!E$24 -> 1 | N72: =LCOE!R98+N71-N71*LCOE!E$25 -> 1 | O72: =LCOE!S98+LCOE!E$29 -> 313.75 | P72: =LCOE!T98+IF(A72>=LCOE!E$30,100%,0%) -> 1 | Q72: =LCOE!U98+O72/1000*IF(LCOE!E$14>0,G72,H72) -> 1236802.5 | R72: =LCOE!B98 -> 30 | S72: =LCOE!V98+Q72*P72*R72 -> 37104075 | T72: =LCOE!W98+LCOE!E$31 -> 0 | U72: =LCOE!X98+T72*IF(LCOE!E$14>0,G72,H72) -> 0 | V72: =LCOE!Y98+LCOE!E$32 -> 0 | W72: =LCOE!Z98+V72*IF(LCOE!E$14>0,G72,H72) -> 0 | X72: =LCOE!AA98+LCOE!E$34 -> 101 | Y72: =X72*H72 -> 0 | Z72: =SUM(B72:C72) -> 0 | AA72: =SUM(I72:J72) -> 20000000 | AB72: =L72 -> 168165720 | AC72: =U72+W72 -> 0 | AD72: =S72 -> 37104075 | AE72: =AE71+1*E72 -> 2 | AF72: =LCOE!E98+LCOE!E$40 -> 0.03 | AG72: =(1+AF72)^A72 -> 1.0609 | AH72: =Z72/AG72 -> 0 | AI72: =AA72/AG72 -> 18851918 | AJ72: =AB72/AG72 -> 1.5851232e+08 | AK72: =AC72/AG72 -> 0 | AL72: =AD72/AG72 -> 34974149 | AM72: =(-1)*Y72/AG72 -> 0 | AN72: =IF(LCOE!E$14>0,G72,H72)/AG72 -> 3715713.1
A73: 3 | C73: =LCOE!E99+IF(AND(LCOE!E$26>0,A73>=LCOE!E$26,A73<=(LCOE!E$26+LCOE!E$27-1)),LCOE!E$42/LCOE!E$27,0)+IF(AND(D73=0,AE73>=LCOE!E$16,COUNTIF(D48:D73,0)=LCOE!E$36),LCOE!E$35*LCOE!E$38,0) -> 0 | D73: =IF(AE72<LCOE!E$16,1,0) -> 1 | E73: =LCOE!G99+IF(AND(A73>=LCOE!E$26,A73<=(LCOE!E$26+LCOE!E$27-1)),0,1)*IF(A73=LCOE!E$34,0,1)*D73 -> 1 | F73: =IF(F72<LCOE!E$18,MIN(F72*(1+LCOE!E$19),LCOE!E$18),LCOE!E$18)+LCOE!J99 -> 0.9 | G73: =LCOE!K99+E73*F73*N73*(LCOE!E$14+LCOE!H99)*24*365*D73 -> 3942000 | H73: =LCOE!L99+F73*(LCOE!E$15+LCOE!I99)*E73*24*365*D73*N73 -> 0 | I73: =LCOE!M99+LCOE!E$20*IF(LCOE!E$14>0,(LCOE!E$14+LCOE!H99),(LCOE!E$15+LCOE!I99))*K73*D73 -> 20000000 | J73: =LCOE!N99+LCOE!E$21*IF(LCOE!E$14>0,G73,H73)*K73*D73 -> 0 | K73: =LCOE!O99+K72+K72*LCOE!E$22 -> 1 | L73: =LCOE!P99+LCOE!E$23*IF(LCOE!E$14>0,G73,H73)*M73*D73 -> 168165720 | M73: =LCOE!Q99+M72+M72*LCOE!E$24 -> 1 | N73: =LCOE!R99+N72-N72*LCOE!E$25 -> 1 | O73: =LCOE!S99+LCOE!E$29 -> 313.75 | P73: =LCOE!T99+IF(A73>=LCOE!E$30,100%,0%) -> 1 | Q73: =LCOE!U99+O73/1000*IF(LCOE!E$14>0,G73,H73) -> 1236802.5 | R73: =LCOE!B99 -> 30 | S73: =LCOE!V99+Q73*P73*R73 -> 37104075 | T73: =LCOE!W99+LCOE!E$31 -> 0 | U73: =LCOE!X99+T73*IF(LCOE!E$14>0,G73,H73) -> 0 | V73: =LCOE!Y99+LCOE!E$32 -> 0 | W73: =LCOE!Z99+V73*IF(LCOE!E$14>0,G73,H73) -> 0 | X73: =LCOE!AA99+LCOE!E$34 -> 101 | Y73: =X73*H73 -> 0 | Z73: =SUM(B73:C73) -> 0 | AA73: =SUM(I73:J73) -> 20000000 | AB73: =L73 -> 168165720 | AC73: =U73+W73 -> 0 | AD73: =S73 -> 37104075 | AE73: =AE72+1*E73 -> 3 | AF73: =LCOE!E99+LCOE!E$40 -> 0.03 | AG73: =(1+AF73)^A73 -> 1.092727 | AH73: =Z73/AG73 -> 0 | AI73: =AA73/AG73 -> 18302833 | AJ73: =AB73/AG73 -> 1.5389546e+08 | AK73: =AC73/AG73 -> 0 | AL73: =AD73/AG73 -> 33955485 | AM73: =(-1)*Y73/AG73 -> 0 | AN73: =IF(LCOE!E$14>0,G73,H73)/AG73 -> 3607488.4
A74: 4 | C74: =LCOE!E100+IF(AND(LCOE!E$26>0,A74>=LCOE!E$26,A74<=(LCOE!E$26+LCOE!E$27-1)),LCOE!E$42/LCOE!E$27,0)+IF(AND(D74=0,AE74>=LCOE!E$16,COUNTIF(D49:D74,0)=LCOE!E$36),LCOE!E$35*LCOE!E$38,0) -> 0 | D74: =IF(AE73<LCOE!E$16,1,0) -> 1 | E74: =LCOE!G100+IF(AND(A74>=LCOE!E$26,A74<=(LCOE!E$26+LCOE!E$27-1)),0,1)*IF(A74=LCOE!E$34,0,1)*D74 -> 1 | F74: =IF(F73<LCOE!E$18,MIN(F73*(1+LCOE!E$19),LCOE!E$18),LCOE!E$18)+LCOE!J100 -> 0.9 | G74: =LCOE!K100+E74*F74*N74*(LCOE!E$14+LCOE!H100)*24*365*D74 -> 3942000 | H74: =LCOE!L100+F74*(LCOE!E$15+LCOE!I100)*E74*24*365*D74*N74 -> 0 | I74: =LCOE!M100+LCOE!E$20*IF(LCOE!E$14>0,(LCOE!E$14+LCOE!H100),(LCOE!E$15+LCOE!I100))*K74*D74 -> 20000000 | J74: =LCOE!N100+LCOE!E$21*IF(LCOE!E$14>0,G74,H74)*K74*D74 -> 0 | K74: =LCOE!O100+K73+K73*LCOE!E$22 -> 1 | L74: =LCOE!P100+LCOE!E$23*IF(LCOE!E$14>0,G74,H74)*M74*D74 -> 168165720 | M74: =LCOE!Q100+M73+M73*LCOE!E$24 -> 1 | N74: =LCOE!R100+N73-N73*LCOE!E$25 -> 1 | O74: =LCOE!S100+LCOE!E$29 -> 313.75 | P74: =LCOE!T100+IF(A74>=LCOE!E$30,100%,0%) -> 1 | Q74: =LCOE!U100+O74/1000*IF(LCOE!E$14>0,G74,H74) -> 1236802.5 | R74: =LCOE!B100 -> 30 | S74: =LCOE!V100+Q74*P74*R74 -> 37104075 | T74: =LCOE!W100+LCOE!E$31 -> 0 | U74: =LCOE!X100+T74*IF(LCOE!E$14>0,G74,H74) -> 0 | V74: =LCOE!Y100+LCOE!E$32 -> 0 | W74: =LCOE!Z100+V74*IF(LCOE!E$14>0,G74,H74) -> 0 | X74: =LCOE!AA100+LCOE!E$34 -> 101 | Y74: =X74*H74 -> 0 | Z74: =SUM(B74:C74) -> 0 | AA74: =SUM(I74:J74) -> 20000000 | AB74: =L74 -> 168165720 | AC74: =U74+W74 -> 0 | AD74: =S74 -> 37104075 | AE74: =AE73+1*E74 -> 4 | AF74: =LCOE!E100+LCOE!E$40 -> 0.03 | AG74: =(1+AF74)^A74 -> 1.1255088 | AH74: =Z74/AG74 -> 0 | AI74: =AA74/AG74 -> 17769741 | AJ74: =AB74/AG74 -> 1.4941306e+08 | AK74: =AC74/AG74 -> 0 | AL74: =AD74/AG74 -> 32966490 | AM74: =(-1)*Y74/AG74 -> 0 | AN74: =IF(LCOE!E$14>0,G74,H74)/AG74 -> 3502415.9
A75: 5 | C75: =LCOE!E101+IF(AND(LCOE!E$26>0,A75>=LCOE!E$26,A75<=(LCOE!E$26+LCOE!E$27-1)),LCOE!E$42/LCOE!E$27,0)+IF(AND(D75=0,AE75>=LCOE!E$16,COUNTIF(D50:D75,0)=LCOE!E$36),LCOE!E$35*LCOE!E$38,0) -> 0 | D75: =IF(AE74<LCOE!E$16,1,0) -> 1 | E75: =LCOE!G101+IF(AND(A75>=LCOE!E$26,A75<=(LCOE!E$26+LCOE!E$27-1)),0,1)*IF(A75=LCOE!E$34,0,1)*D75 -> 1 | F75: =IF(F74<LCOE!E$18,MIN(F74*(1+LCOE!E$19),LCOE!E$18),LCOE!E$18)+LCOE!J101 -> 0.9 | G75: =LCOE!K101+E75*F75*N75*(LCOE!E$14+LCOE!H101)*24*365*D75 -> 3942000 | H75: =LCOE!L101+F75*(LCOE!E$15+LCOE!I101)*E75*24*365*D75*N75 -> 0 | I75: =LCOE!M101+LCOE!E$20*IF(LCOE!E$14>0,(LCOE!E$14+LCOE!H101),(LCOE!E$15+LCOE!I101))*K75*D75 -> 20000000 | J75: =LCOE!N101+LCOE!E$21*IF(LCOE!E$14>0,G75,H75)*K75*D75 -> 0 | K75: =LCOE!O101+K74+K74*LCOE!E$22 -> 1 | L75: =LCOE!P101+LCOE!E$23*IF(LCOE!E$14>0,G75,H75)*M75*D75 -> 168165720 | M75: =LCOE!Q101+M74+M74*LCOE!E$24 -> 1 | N75: =LCOE!R101+N74-N74*LCOE!E$25 -> 1 | O75: =LCOE!S101+LCOE!E$29 -> 313.75 | P75: =LCOE!T101+IF(A75>=LCOE!E$30,100%,0%) -> 1 | Q75: =LCOE!U101+O75/1000*IF(LCOE!E$14>0,G75,H75) -> 1236802.5 | R75: =LCOE!B101 -> 30 | S75: =LCOE!V101+Q75*P75*R75 -> 37104075 | T75: =LCOE!W101+LCOE!E$31 -> 0 | U75: =LCOE!X101+T75*IF(LCOE!E$14>0,G75,H75) -> 0 | V75: =LCOE!Y101+LCOE!E$32 -> 0 | W75: =LCOE!Z101+V75*IF(LCOE!E$14>0,G75,H75) -> 0 | X75: =LCOE!AA101+LCOE!E$34 -> 101 | Y75: =X75*H75 -> 0 | Z75: =SUM(B75:C75) -> 0 | AA75: =SUM(I75:J75) -> 20000000 | AB75: =L75 -> 168165720 | AC75: =U75+W75 -> 0 | AD75: =S75 -> 37104075 | AE75: =AE74+1*E75 -> 5 | AF75: =LCOE!E101+LCOE!E$40 -> 0.03 | AG75: =(1+AF75)^A75 -> 1.1592741 | AH75: =Z75/AG75 -> 0 | AI75: =AA75/AG75 -> 17252176 | AJ75: =AB75/AG75 -> 1.4506123e+08 | AK75: =AC75/AG75 -> 0 | AL75: =AD75/AG75 -> 32006301 | AM75: =(-1)*Y75/AG75 -> 0 | AN75: =IF(LCOE!E$14>0,G75,H75)/AG75 -> 3400403.8
A76: 6 | C76: =LCOE!E102+IF(AND(LCOE!E$26>0,A76>=LCOE!E$26,A76<=(LCOE!E$26+LCOE!E$27-1)),LCOE!E$42/LCOE!E$27,0)+IF(AND(D76=0,AE76>=LCOE!E$16,COUNTIF(D51:D76,0)=LCOE!E$36),LCOE!E$35*LCOE!E$38,0) -> 0 | D76: =IF(AE75<LCOE!E$16,1,0) -> 1 | E76: =LCOE!G102+IF(AND(A76>=LCOE!E$26,A76<=(LCOE!E$26+LCOE!E$27-1)),0,1)*IF(A76=LCOE!E$34,0,1)*D76 -> 1 | F76: =IF(F75<LCOE!E$18,MIN(F75*(1+LCOE!E$19),LCOE!E$18),LCOE!E$18)+LCOE!J102 -> 0.9 | G76: =LCOE!K102+E76*F76*N76*(LCOE!E$14+LCOE!H102)*24*365*D76 -> 3942000 | H76: =LCOE!L102+F76*(LCOE!E$15+LCOE!I102)*E76*24*365*D76*N76 -> 0 | I76: =LCOE!M102+LCOE!E$20*IF(LCOE!E$14>0,(LCOE!E$14+LCOE!H102),(LCOE!E$15+LCOE!I102))*K76*D76 -> 20000000 | J76: =LCOE!N102+LCOE!E$21*IF(LCOE!E$14>0,G76,H76)*K76*D76 -> 0 | K76: =LCOE!O102+K75+K75*LCOE!E$22 -> 1 | L76: =LCOE!P102+LCOE!E$23*IF(LCOE!E$14>0,G76,H76)*M76*D76 -> 168165720 | M76: =LCOE!Q102+M75+M75*LCOE!E$24 -> 1 | N76: =LCOE!R102+N75-N75*LCOE!E$25 -> 1 | O76: =LCOE!S102+LCOE!E$29 -> 313.75 | P76: =LCOE!T102+IF(A76>=LCOE!E$30,100%,0%) -> 1 | Q76: =LCOE!U102+O76/1000*IF(LCOE!E$14>0,G76,H76) -> 1236802.5 | R76: =LCOE!B102 -> 30 | S76: =LCOE!V102+Q76*P76*R76 -> 37104075 | T76: =LCOE!W102+LCOE!E$31 -> 0 | U76: =LCOE!X102+T76*IF(LCOE!E$14>0,G76,H76) -> 0 | V76: =LCOE!Y102+LCOE!E$32 -> 0 | W76: =LCOE!Z102+V76*IF(LCOE!E$14>0,G76,H76) -> 0 | X76: =LCOE!AA102+LCOE!E$34 -> 101 | Y76: =X76*H76 -> 0 | Z76: =SUM(B76:C76) -> 0 | AA76: =SUM(I76:J76) -> 20000000 | AB76: =L76 -> 168165720 | AC76: =U76+W76 -> 0 | AD76: =S76 -> 37104075 | AE76: =AE75+1*E76 -> 6 | AF76: =LCOE!E102+LCOE!E$40 -> 0.03 | AG76: =(1+AF76)^A76 -> 1.1940523 | AH76: =Z76/AG76 -> 0 | AI76: =AA76/AG76 -> 16749685 | AJ76: =AB76/AG76 -> 1.4083614e+08 | AK76: =AC76/AG76 -> 0 | AL76: =AD76/AG76 -> 31074079 | AM76: =(-1)*Y76/AG76 -> 0 | AN76: =IF(LCOE!E$14>0,G76,H76)/AG76 -> 3301362.9
A77: 7 | C77: =LCOE!E103+IF(AND(LCOE!E$26>0,A77>=LCOE!E$26,A77<=(LCOE!E$26+LCOE!E$27-1)),LCOE!E$42/LCOE!E$27,0)+IF(AND(D77=0,AE77>=LCOE!E$16,COUNTIF(D52:D77,0)=LCOE!E$36),LCOE!E$35*LCOE!E$38,0) -> 0 | D77: =IF(AE76<LCOE!E$16,1,0) -> 1 | E77: =LCOE!G103+IF(AND(A77>=LCOE!E$26,A77<=(LCOE!E$26+LCOE!E$27-1)),0,1)*IF(A77=LCOE!E$34,0,1)*D77 -> 1 | F77: =IF(F76<LCOE!E$18,MIN(F76*(1+LCOE!E$19),LCOE!E$18),LCOE!E$18)+LCOE!J103 -> 0.9 | G77: =LCOE!K103+E77*F77*N77*(LCOE!E$14+LCOE!H103)*24*365*D77 -> 3942000 | H77: =LCOE!L103+F77*(LCOE!E$15+LCOE!I103)*E77*24*365*D77*N77 -> 0 | I77: =LCOE!M103+LCOE!E$20*IF(LCOE!E$14>0,(LCOE!E$14+LCOE!H103),(LCOE!E$15+LCOE!I103))*K77*D77 -> 20000000 | J77: =LCOE!N103+LCOE!E$21*IF(LCOE!E$14>0,G77,H77)*K77*D77 -> 0 | K77: =LCOE!O103+K76+K76*LCOE!E$22 -> 1 | L77: =LCOE!P103+LCOE!E$23*IF(LCOE!E$14>0,G77,H77)*M77*D77 -> 168165720 | M77: =LCOE!Q103+M76+M76*LCOE!E$24 -> 1 | N77: =LCOE!R103+N76-N76*LCOE!E$25 -> 1 | O77: =LCOE!S103+LCOE!E$29 -> 313.75 | P77: =LCOE!T103+IF(A77>=LCOE!E$30,100%,0%) -> 1 | Q77: =LCOE!U103+O77/1000*IF(LCOE!E$14>0,G77,H77) -> 1236802.5 | R77: =LCOE!B103 -> 30 | S77: =LCOE!V103+Q77*P77*R77 -> 37104075 | T77: =LCOE!W103+LCOE!E$31 -> 0 | U77: =LCOE!X103+T77*IF(LCOE!E$14>0,G77,H77) -> 0 | V77: =LCOE!Y103+LCOE!E$32 -> 0 | W77: =LCOE!Z103+V77*IF(LCOE!E$14>0,G77,H77) -> 0 | X77: =LCOE!AA103+LCOE!E$34 -> 101 | Y77: =X77*H77 -> 0 | Z77: =SUM(B77:C77) -> 0 | AA77: =SUM(I77:J77) -> 20000000 | AB77: =L77 -> 168165720 | AC77: =U77+W77 -> 0 | AD77: =S77 -> 37104075 | AE77: =AE76+1*E77 -> 7 | AF77: =LCOE!E103+LCOE!E$40 -> 0.03 | AG77: =(1+AF77)^A77 -> 1.2298739 | AH77: =Z77/AG77 -> 0 | AI77: =AA77/AG77 -> 16261830 | AJ77: =AB77/AG77 -> 1.3673412e+08 | AK77: =AC77/AG77 -> 0 | AL77: =AD77/AG77 -> 30169008 | AM77: =(-1)*Y77/AG77 -> 0 | AN77: =IF(LCOE!E$14>0,G77,H77)/AG77 -> 3205206.7
A78: 8 | C78: =LCOE!E104+IF(AND(LCOE!E$26>0,A78>=LCOE!E$26,A78<=(LCOE!E$26+LCOE!E$27-1)),LCOE!E$42/LCOE!E$27,0)+IF(AND(D78=0,AE78>=LCOE!E$16,COUNTIF(D53:D78,0)=LCOE!E$36),LCOE!E$35*LCOE!E$38,0) -> 0 | D78: =IF(AE77<LCOE!E$16,1,0) -> 1 | E78: =LCOE!G104+IF(AND(A78>=LCOE!E$26,A78<=(LCOE!E$26+LCOE!E$27-1)),0,1)*IF(A78=LCOE!E$34,0,1)*D78 -> 1 | F78: =IF(F77<LCOE!E$18,MIN(F77*(1+LCOE!E$19),LCOE!E$18),LCOE!E$18)+LCOE!J104 -> 0.9 | G78: =LCOE!K104+E78*F78*N78*(LCOE!E$14+LCOE!H104)*24*365*D78 -> 3942000 | H78: =LCOE!L104+F78*(LCOE!E$15+LCOE!I104)*E78*24*365*D78*N78 -> 0 | I78: =LCOE!M104+LCOE!E$20*IF(LCOE!E$14>0,(LCOE!E$14+LCOE!H104),(LCOE!E$15+LCOE!I104))*K78*D78 -> 20000000 | J78: =LCOE!N104+LCOE!E$21*IF(LCOE!E$14>0,G78,H78)*K78*D78 -> 0 | K78: =LCOE!O104+K77+K77*LCOE!E$22 -> 1 | L78: =LCOE!P104+LCOE!E$23*IF(LCOE!E$14>0,G78,H78)*M78*D78 -> 168165720 | M78: =LCOE!Q104+M77+M77*LCOE!E$24 -> 1 | N78: =LCOE!R104+N77-N77*LCOE!E$25 -> 1 | O78: =LCOE!S104+LCOE!E$29 -> 313.75 | P78: =LCOE!T104+IF(A78>=LCOE!E$30,100%,0%) -> 1 | Q78: =LCOE!U104+O78/1000*IF(LCOE!E$14>0,G78,H78) -> 1236802.5 | R78: =LCOE!B104 -> 30 | S78: =LCOE!V104+Q78*P78*R78 -> 37104075 | T78: =LCOE!W104+LCOE!E$31 -> 0 | U78: =LCOE!X104+T78*IF(LCOE!E$14>0,G78,H78) -> 0 | V78: =LCOE!Y104+LCOE!E$32 -> 0 | W78: =LCOE!Z104+V78*IF(LCOE!E$14>0,G78,H78) -> 0 | X78: =LCOE!AA104+LCOE!E$34 -> 101 | Y78: =X78*H78 -> 0 | Z78: =SUM(B78:C78) -> 0 | AA78: =SUM(I78:J78) -> 20000000 | AB78: =L78 -> 168165720 | AC78: =U78+W78 -> 0 | AD78: =S78 -> 37104075 | AE78: =AE77+1*E78 -> 8 | AF78: =LCOE!E104+LCOE!E$40 -> 0.03 | AG78: =(1+AF78)^A78 -> 1.2667701 | AH78: =Z78/AG78 -> 0 | AI78: =AA78/AG78 -> 15788185 | AJ78: =AB78/AG78 -> 1.3275157e+08 | AK78: =AC78/AG78 -> 0 | AL78: =AD78/AG78 -> 29290299 | AM78: =(-1)*Y78/AG78 -> 0 | AN78: =IF(LCOE!E$14>0,G78,H78)/AG78 -> 3111851.2
A79: 9 | C79: =LCOE!E105+IF(AND(LCOE!E$26>0,A79>=LCOE!E$26,A79<=(LCOE!E$26+LCOE!E$27-1)),LCOE!E$42/LCOE!E$27,0)+IF(AND(D79=0,AE79>=LCOE!E$16,COUNTIF(D54:D79,0)=LCOE!E$36),LCOE!E$35*LCOE!E$38,0) -> 0 | D79: =IF(AE78<LCOE!E$16,1,0) -> 1 | E79: =LCOE!G105+IF(AND(A79>=LCOE!E$26,A79<=(LCOE!E$26+LCOE!E$27-1)),0,1)*IF(A79=LCOE!E$34,0,1)*D79 -> 1 | F79: =IF(F78<LCOE!E$18,MIN(F78*(1+LCOE!E$19),LCOE!E$18),LCOE!E$18)+LCOE!J105 -> 0.9 | G79: =LCOE!K105+E79*F79*N79*(LCOE!E$14+LCOE!H105)*24*365*D79 -> 3942000 | H79: =LCOE!L105+F79*(LCOE!E$15+LCOE!I105)*E79*24*365*D79*N79 -> 0 | I79: =LCOE!M105+LCOE!E$20*IF(LCOE!E$14>0,(LCOE!E$14+LCOE!H105),(LCOE!E$15+LCOE!I105))*K79*D79 -> 20000000 | J79: =LCOE!N105+LCOE!E$21*IF(LCOE!E$14>0,G79,H79)*K79*D79 -> 0 | K79: =LCOE!O105+K78+K78*LCOE!E$22 -> 1 | L79: =LCOE!P105+LCOE!E$23*IF(LCOE!E$14>0,G79,H79)*M79*D79 -> 168165720 | M79: =LCOE!Q105+M78+M78*LCOE!E$24 -> 1 | N79: =LCOE!R105+N78-N78*LCOE!E$25 -> 1 | O79: =LCOE!S105+LCOE!E$29 -> 313.75 | P79: =LCOE!T105+IF(A79>=LCOE!E$30,100%,0%) -> 1 | Q79: =LCOE!U105+O79/1000*IF(LCOE!E$14>0,G79,H79) -> 1236802.5 | R79: =LCOE!B105 -> 30 | S79: =LCOE!V105+Q79*P79*R79 -> 37104075 | T79: =LCOE!W105+LCOE!E$31 -> 0 | U79: =LCOE!X105+T79*IF(LCOE!E$14>0,G79,H79) -> 0 | V79: =LCOE!Y105+LCOE!E$32 -> 0 | W79: =LCOE!Z105+V79*IF(LCOE!E$14>0,G79,H79) -> 0 | X79: =LCOE!AA105+LCOE!E$34 -> 101 | Y79: =X79*H79 -> 0 | Z79: =SUM(B79:C79) -> 0 | AA79: =SUM(I79:J79) -> 20000000 | AB79: =L79 -> 168165720 | AC79: =U79+W79 -> 0 | AD79: =S79 -> 37104075 | AE79: =AE78+1*E79 -> 9 | AF79: =LCOE!E105+LCOE!E$40 -> 0.03 | AG79: =(1+AF79)^A79 -> 1.3047732 | AH79: =Z79/AG79 -> 0 | AI79: =AA79/AG79 -> 15328335 | AJ79: =AB79/AG79 -> 1.2888502e+08 | AK79: =AC79/AG79 -> 0 | AL79: =AD79/AG79 -> 28437184 | AM79: =(-1)*Y79/AG79 -> 0 | AN79: =IF(LCOE!E$14>0,G79,H79)/AG79 -> 3021214.8
A80: 10 | C80: =LCOE!E106+IF(AND(LCOE!E$26>0,A80>=LCOE!E$26,A80<=(LCOE!E$26+LCOE!E$27-1)),LCOE!E$42/LCOE!E$27,0)+IF(AND(D80=0,AE80>=LCOE!E$16,COUNTIF(D55:D80,0)=LCOE!E$36),LCOE!E$35*LCOE!E$38,0) -> 0 | D80: =IF(AE79<LCOE!E$16,1,0) -> 1 | E80: =LCOE!G106+IF(AND(A80>=LCOE!E$26,A80<=(LCOE!E$26+LCOE!E$27-1)),0,1)*IF(A80=LCOE!E$34,0,1)*D80 -> 1 | F80: =IF(F79<LCOE!E$18,MIN(F79*(1+LCOE!E$19),LCOE!E$18),LCOE!E$18)+LCOE!J106 -> 0.9 | G80: =LCOE!K106+E80*F80*N80*(LCOE!E$14+LCOE!H106)*24*365*D80 -> 3942000 | H80: =LCOE!L106+F80*(LCOE!E$15+LCOE!I106)*E80*24*365*D80*N80 -> 0 | I80: =LCOE!M106+LCOE!E$20*IF(LCOE!E$14>0,(LCOE!E$14+LCOE!H106),(LCOE!E$15+LCOE!I106))*K80*D80 -> 20000000 | J80: =LCOE!N106+LCOE!E$21*IF(LCOE!E$14>0,G80,H80)*K80*D80 -> 0 | K80: =LCOE!O106+K79+K79*LCOE!E$22 -> 1 | L80: =LCOE!P106+LCOE!E$23*IF(LCOE!E$14>0,G80,H80)*M80*D80 -> 168165720 | M80: =LCOE!Q106+M79+M79*LCOE!E$24 -> 1 | N80: =LCOE!R106+N79-N79*LCOE!E$25 -> 1 | O80: =LCOE!S106+LCOE!E$29 -> 313.75 | P80: =LCOE!T106+IF(A80>=LCOE!E$30,100%,0%) -> 1 | Q80: =LCOE!U106+O80/1000*IF(LCOE!E$14>0,G80,H80) -> 1236802.5 | R80: =LCOE!B106 -> 30 | S80: =LCOE!V106+Q80*P80*R80 -> 37104075 | T80: =LCOE!W106+LCOE!E$31 -> 0 | U80: =LCOE!X106+T80*IF(LCOE!E$14>0,G80,H80) -> 0 | V80: =LCOE!Y106+LCOE!E$32 -> 0 | W80: =LCOE!Z106+V80*IF(LCOE!E$14>0,G80,H80) -> 0 | X80: =LCOE!AA106+LCOE!E$34 -> 101 | Y80: =X80*H80 -> 0 | Z80: =SUM(B80:C80) -> 0 | AA80: =SUM(I80:J80) -> 20000000 | AB80: =L80 -> 168165720 | AC80: =U80+W80 -> 0 | AD80: =S80 -> 37104075 | AE80: =AE79+1*E80 -> 10 | AF80: =LCOE!E106+LCOE!E$40 -> 0.03 | AG80: =(1+AF80)^A80 -> 1.3439164 | AH80: =Z80/AG80 -> 0 | AI80: =AA80/AG80 -> 14881878 | AJ80: =AB80/AG80 -> 1.2513109e+08 | AK80: =AC80/AG80 -> 0 | AL80: =AD80/AG80 -> 27608916 | AM80: =(-1)*Y80/AG80 -> 0 | AN80: =IF(LCOE!E$14>0,G80,H80)/AG80 -> 2933218.2
A81: 11 | C81: =LCOE!E107+IF(AND(LCOE!E$26>0,A81>=LCOE!E$26,A81<=(LCOE!E$26+LCOE!E$27-1)),LCOE!E$42/LCOE!E$27,0)+IF(AND(D81=0,AE81>=LCOE!E$16,COUNTIF(D56:D81,0)=LCOE!E$36),LCOE!E$35*LCOE!E$38,0) -> 0 | D81: =IF(AE80<LCOE!E$16,1,0) -> 1 | E81: =LCOE!G107+IF(AND(A81>=LCOE!E$26,A81<=(LCOE!E$26+LCOE!E$27-1)),0,1)*IF(A81=LCOE!E$34,0,1)*D81 -> 1 | F81: =IF(F80<LCOE!E$18,MIN(F80*(1+LCOE!E$19),LCOE!E$18),LCOE!E$18)+LCOE!J107 -> 0.9 | G81: =LCOE!K107+E81*F81*N81*(LCOE!E$14+LCOE!H107)*24*365*D81 -> 3942000 | H81: =LCOE!L107+F81*(LCOE!E$15+LCOE!I107)*E81*24*365*D81*N81 -> 0 | I81: =LCOE!M107+LCOE!E$20*IF(LCOE!E$14>0,(LCOE!E$14+LCOE!H107),(LCOE!E$15+LCOE!I107))*K81*D81 -> 20000000 | J81: =LCOE!N107+LCOE!E$21*IF(LCOE!E$14>0,G81,H81)*K81*D81 -> 0 | K81: =LCOE!O107+K80+K80*LCOE!E$22 -> 1 | L81: =LCOE!P107+LCOE!E$23*IF(LCOE!E$14>0,G81,H81)*M81*D81 -> 168165720 | M81: =LCOE!Q107+M80+M80*LCOE!E$24 -> 1 | N81: =LCOE!R107+N80-N80*LCOE!E$25 -> 1 | O81: =LCOE!S107+LCOE!E$29 -> 313.75 | P81: =LCOE!T107+IF(A81>=LCOE!E$30,100%,0%) -> 1 | Q81: =LCOE!U107+O81/1000*IF(LCOE!E$14>0,G81,H81) -> 1236802.5 | R81: =LCOE!B107 -> 30 | S81: =LCOE!V107+Q81*P81*R81 -> 37104075 | T81: =LCOE!W107+LCOE!E$31 -> 0 | U81: =LCOE!X107+T81*IF(LCOE!E$14>0,G81,H81) -> 0 | V81: =LCOE!Y107+LCOE!E$32 -> 0 | W81: =LCOE!Z107+V81*IF(LCOE!E$14>0,G81,H81) -> 0 | X81: =LCOE!AA107+LCOE!E$34 -> 101 | Y81: =X81*H81 -> 0 | Z81: =SUM(B81:C81) -> 0 | AA81: =SUM(I81:J81) -> 20000000 | AB81: =L81 -> 168165720 | AC81: =U81+W81 -> 0 | AD81: =S81 -> 37104075 | AE81: =AE80+1*E81 -> 11 | AF81: =LCOE!E107+LCOE!E$40 -> 0.03 | AG81: =(1+AF81)^A81 -> 1.3842339 | AH81: =Z81/AG81 -> 0 | AI81: =AA81/AG81 -> 14448426 | AJ81: =AB81/AG81 -> 1.2148649e+08 | AK81: =AC81/AG81 -> 0 | AL81: =AD81/AG81 -> 26804773 | AM81: =(-1)*Y81/AG81 -> 0 | AN81: =IF(LCOE!E$14>0,G81,H81)/AG81 -> 2847784.7
A82: 12 | C82: =LCOE!E108+IF(AND(LCOE!E$26>0,A82>=LCOE!E$26,A82<=(LCOE!E$26+LCOE!E$27-1)),LCOE!E$42/LCOE!E$27,0)+IF(AND(D82=0,AE82>=LCOE!E$16,COUNTIF(D57:D82,0)=LCOE!E$36),LCOE!E$35*LCOE!E$38,0) -> 0 | D82: =IF(AE81<LCOE!E$16,1,0) -> 1 | E82: =LCOE!G108+IF(AND(A82>=LCOE!E$26,A82<=(LCOE!E$26+LCOE!E$27-1)),0,1)*IF(A82=LCOE!E$34,0,1)*D82 -> 1 | F82: =IF(F81<LCOE!E$18,MIN(F81*(1+LCOE!E$19),LCOE!E$18),LCOE!E$18)+LCOE!J108 -> 0.9 | G82: =LCOE!K108+E82*F82*N82*(LCOE!E$14+LCOE!H108)*24*365*D82 -> 3942000 | H82: =LCOE!L108+F82*(LCOE!E$15+LCOE!I108)*E82*24*365*D82*N82 -> 0 | I82: =LCOE!M108+LCOE!E$20*IF(LCOE!E$14>0,(LCOE!E$14+LCOE!H108),(LCOE!E$15+LCOE!I108))*K82*D82 -> 20000000 | J82: =LCOE!N108+LCOE!E$21*IF(LCOE!E$14>0,G82,H82)*K82*D82 -> 0 | K82: =LCOE!O108+K81+K81*LCOE!E$22 -> 1 | L82: =LCOE!P108+LCOE!E$23*IF(LCOE!E$14>0,G82,H82)*M82*D82 -> 168165720 | M82: =LCOE!Q108+M81+M81*LCOE!E$24 -> 1 | N82: =LCOE!R108+N81-N81*LCOE!E$25 -> 1 | O82: =LCOE!S108+LCOE!E$29 -> 313.75 | P82: =LCOE!T108+IF(A82>=LCOE!E$30,100%,0%) -> 1 | Q82: =LCOE!U108+O82/1000*IF(LCOE!E$14>0,G82,H82) -> 1236802.5 | R82: =LCOE!B108 -> 30 | S82: =LCOE!V108+Q82*P82*R82 -> 37104075 | T82: =LCOE!W108+LCOE!E$31 -> 0 | U82: =LCOE!X108+T82*IF(LCOE!E$14>0,G82,H82) -> 0 | V82: =LCOE!Y108+LCOE!E$32 -> 0 | W82: =LCOE!Z108+V82*IF(LCOE!E$14>0,G82,H82) -> 0 | X82: =LCOE!AA108+LCOE!E$34 -> 101 | Y82: =X82*H82 -> 0 | Z82: =SUM(B82:C82) -> 0 | AA82: =SUM(I82:J82) -> 20000000 | AB82: =L82 -> 168165720 | AC82: =U82+W82 -> 0 | AD82: =S82 -> 37104075 | AE82: =AE81+1*E82 -> 12 | AF82: =LCOE!E108+LCOE!E$40 -> 0.03 | AG82: =(1+AF82)^A82 -> 1.4257609 | AH82: =Z82/AG82 -> 0 | AI82: =AA82/AG82 -> 14027598 | AJ82: =AB82/AG82 -> 1.1794805e+08 | AK82: =AC82/AG82 -> 0 | AL82: =AD82/AG82 -> 26024052 | AM82: =(-1)*Y82/AG82 -> 0 | AN82: =IF(LCOE!E$14>0,G82,H82)/AG82 -> 2764839.5
... A170: 100 | C170: =LCOE!E196+IF(AND(LCOE!E$26>0,A170>=LCOE!E$26,A170<=(LCOE!E$26+LCOE!E$27-1)),LCOE!E$42/LCOE!E$27,0)+IF(AND(D170=0,AE170>=LCOE!E$16,COUNTIF(D145:D170,0)=LCOE!E$36),LCOE!E$35*LCOE!E$38,0) -> 0 | D170: =IF(AE169<LCOE!E$16,1,0) -> 0 | E170: =LCOE!G196+IF(AND(A170>=LCOE!E$26,A170<=(LCOE!E$26+LCOE!E$27-1)),0,1)*IF(A170=LCOE!E$34,0,1)*D170 -> 0 | F170: =IF(F169<LCOE!E$18,MIN(F169*(1+LCOE!E$19),LCOE!E$18),LCOE!E$18)+LCOE!J196 -> 0.9 | G170: =LCOE!K196+E170*F170*N170*(LCOE!E$14+LCOE!H196)*24*365*D170 -> 0 | H170: =LCOE!L196+F170*(LCOE!E$15+LCOE!I196)*E170*24*365*D170*N170 -> 0 | I170: =LCOE!M196+LCOE!E$20*IF(LCOE!E$14>0,(LCOE!E$14+LCOE!H196),(LCOE!E$15+LCOE!I196))*K170*D170 -> 0 | J170: =LCOE!N196+LCOE!E$21*IF(LCOE!E$14>0,G170,H170)*K170*D170 -> 0 | K170: =LCOE!O196+K169+K169*LCOE!E$22 -> 1 | L170: =LCOE!P196+LCOE!E$23*IF(LCOE!E$14>0,G170,H170)*M170*D170 -> 0 | M170: =LCOE!Q196+M169+M169*LCOE!E$24 -> 1 | N170: =LCOE!R196+N169-N169*LCOE!E$25 -> 1 | O170: =LCOE!S196+LCOE!E$29 -> 313.75 | P170: =LCOE!T196+IF(A170>=LCOE!E$30,100%,0%) -> 1 | Q170: =LCOE!U196+O170/1000*IF(LCOE!E$14>0,G170,H170) -> 0 | R170: =LCOE!B196 -> 30 | S170: =LCOE!V196+Q170*P170*R170 -> 0 | T170: =LCOE!W196+LCOE!E$31 -> 0 | U170: =LCOE!X196+T170*IF(LCOE!E$14>0,G170,H170) -> 0 | V170: =LCOE!Y196+LCOE!E$32 -> 0 | W170: =LCOE!Z196+V170*IF(LCOE!E$14>0,G170,H170) -> 0 | X170: =LCOE!AA196+LCOE!E$34 -> 101 | Y170: =X170*H170 -> 0 | Z170: =SUM(B170:C170) -> 0 | AA170: =SUM(I170:J170) -> 0 | AB170: =L170 -> 0 | AC170: =U170+W170 -> 0 | AD170: =S170 -> 0 | AE170: =AE169+1*E170 -> 30 | AF170: =LCOE!E196+LCOE!E$40 -> 0.03 | AG170: =(1+AF170)^A170 -> 19.218632 | AH170: =Z170/AG170 -> 0 | AI170: =AA170/AG170 -> 0 | AJ170: =AB170/AG170 -> 0 | AK170: =AC170/AG170 -> 0 | AL170: =AD170/AG170 -> 0 | AM170: =(-1)*Y170/AG170 -> 0 | AN170: =IF(LCOE!E$14>0,G170,H170)/AG170 -> 0

Sheet LCOE 3
B2: Parameter recap (not used in calcs) | C2: =LCOE!F3 -> LCOE 3 | F2: RESULTS | G2: =C4 -> USD | I2: =C6 -> USD
B3: =LCOE!C5 -> Name | C3: =LCOE!F5 -> CCGT in Belgium (2020) | F3: =LCOE!C46 -> LCOE (LCOHeat for pure heat plants) | G3: =SUM(AH45:AM170)/SUM(AN45:AN170) -> 66.035232 | H3: =_xlfn.CONCAT(C$4,"/MWh") -> USD/MWh | I3: =G3*C$7 -> 66.035232 | J3: =_xlfn.CONCAT(C$6,"/MWh") -> USD/MWh
B4: =LCOE!C6 -> Currency used for LCOE calculations | C4: =LCOE!F6 -> USD | F4: =LCOE!C47 -> Of which: Capital costs | G4: =SUM(AH45:AH170)/SUM(AN45:AN170) -> 8.6657769 | H4: =_xlfn.CONCAT(C$4,"/MWh") -> USD/MWh | I4: =G4*C$7 -> 8.6657769 | J4: =_xlfn.CONCAT(C$6,"/MWh") -> USD/MWh
B5: =LCOE!C7 -> Price reference year | C5: =LCOE!F7 -> 0 | F5: =LCOE!C48 -> O&M | G5: =SUM(AI45:AI170)/SUM(AN45:AN170) -> 5.2969555 | H5: =_xlfn.CONCAT(C$4,"/MWh") -> USD/MWh | I5: =G5*C$7 -> 5.2969555 | J5: =_xlfn.CONCAT(C$6,"/MWh") -> USD/MWh
B6: =LCOE!C8 -> Currency used | C6: =LCOE!F8 -> USD | F6: =LCOE!C49 -> Fuel | G6: =SUM(AJ45:AJ170)/SUM(AN45:AN170) -> 42.66 | H6: =_xlfn.CONCAT(C$4,"/MWh") -> USD/MWh | I6: =G6*C$7 -> 42.66 | J6: =_xlfn.CONCAT(C$6,"/MWh") -> USD/MWh
B7: =LCOE!C9 -> Conversion rate at reference year | C7: =LCOE!F9 -> 1 | F7: =LCOE!C50 -> Taxes and fees | G7: =SUM(AK45:AK170)/SUM(AN45:AN170) -> 0 | H7: =_xlfn.CONCAT(C$4,"/MWh") -> USD/MWh | I7: =G7*C$7 -> 0 | J7: =_xlfn.CONCAT(C$6,"/MWh") -> USD/MWh
B8: =LCOE!C10 -> Debt % | C8: =LCOE!F10 -> 0.9 | F8: =LCOE!C51 -> Emission costs | G8: =SUM(AL45:AL170)/SUM(AN45:AN170) -> 9.4125 | H8: =_xlfn.CONCAT(C$4,"/MWh") -> USD/MWh | I8: =G8*C$7 -> 9.4125 | J8: =_xlfn.CONCAT(C$6,"/MWh") -> USD/MWh
B9: =LCOE!C11 -> Cost of debt (private discount rate) | C9: =LCOE!F11 -> 0.05 | F9: =LCOE!C52 -> Heat credit (for CHP plants) | G9: =IF(C15>0,SUM(AM45:AM170)/SUM(AN45:AN170),0) -> 0 | H9: =_xlfn.CONCAT(C$4,"/MWh") -> USD/MWh | I9: =G9*C$7 -> 0 | J9: =_xlfn.CONCAT(C$6,"/MWh") -> USD/MWh
B10: =LCOE!C12 -> Cost of equity (discount rate) | C10: =LCOE!F12 -> 0.05 | F10: =LCOE!C53 -> WACC average over lifetime | G10: =AVERAGE(AF70:AF170) -> 0.05 | I10: =G10 -> 0.05
B11: =LCOE!C13 -> Construction cost per kW | C11: =LCOE!F13 -> 1009 | F11: =LCOE!C54 -> Plant type | G11: =IF(AND(LCOE!F$14>0,LCOE!F$15=0),"Electric only",IF(AND(LCOE!F$14>0,LCOE!F$15>0),"CHP",IF(AND(LCOE!F$14=0,LCOE!F$15>0),"Heat only","Error: no generation"))) -> Electric only | I11: =G11 -> Electric only
B12: =LCOE!C14 -> Maximum electric power, in MW_e | C12: =LCOE!F14 -> 500
B13: =LCOE!C15 -> Maximum heat power, in MW_h | C13: =LCOE!F15 -> 0
B14: =LCOE!C16 -> Plant lifetime | C14: =LCOE!F16 -> 30
B15: =LCOE!C17 -> Construction period, years | C15: =LCOE!F17 -> 3
B16: =LCOE!C18 -> Capacity factor (settled down) | C16: =LCOE!F18 -> 0.9
B17: =LCOE!C19 -> Capacity factor ramp-up on startup, per year | C17: =LCOE!F19 -> 0.6
B18: =LCOE!C20 -> Fixed OPEX/MW capacity at project start | C18: =LCOE!F20 -> 40000
B19: =LCOE!C21 -> Variable OPEX/MWh produced at project start | C19: =LCOE!F21 -> 0
B20: =LCOE!C22 -> OPEX escalator | C20: =LCOE!F22 -> 0
B21: =LCOE!C23 -> FUELEX/MWh produced at project start | C21: =LCOE!F23 -> 42.66
B22: =LCOE!C24 -> FUELEX escalator | C22: =LCOE!F24 -> 0
B23: =LCOE!C25 -> Efficiency loss/year | C23: =LCOE!F25 -> 0
... B41: =LCOE!C43 -> Overrides | C41: =LCOE!F43 -> 0
Z43: SUMMARY OF COSTS
A44: Year (t) | B44: CAPEXconstr | C44: CAPEXrefurb/decom | D44: Lifetime left? | E44: Operational% | F44: Capacity factor | G44: Electricity produced (MWh_e) | H44: Heat produced (MWh_h) | I44: Fixed OPEX | J44: Variable OPEX | K44: OPEX relative to startup | L44: FUELEX | M44: FUELEX relative to startup | N44: Efficiency relative to startup | O44: Total emission factor, gCO2/kWh | P44: % of emissions taxed | Q44: Total emissions, tCO2e | R44: Cost of tCO2e | S44: Cost of emissions levied, E | T44: Tax per MWh produced | U44: Taxes levied | V44: Waste fee per MWh produced | W44: Waste fee levied | X44: Heat credit per MWh_h | Y44: Heat credit total | Z44: Total capital expenditure, I | AA44: Total operation and maintenance expenditure, M | AB44: Total fuel expenditure, F | AC44: Total taxes, T | AD44: Total emission fees, E | AE44: Lifetime expended at start of year | AF44: Discount rate r (IDC when t<0) | AG44: Discount factor (1+r)^t | AH44: I discounted | AI44: M discounted | AJ44: F discounted | AK44: T discounted | AL44: E discounted | AM44: Heat credit, discounted | AN44: Production (MWh), discounted
A45: -25 | B45: =LCOE!C71+IF(A45>=((LCOE!F$17*-1)+1),LCOE!F$38/LCOE!F$17,0) -> 0 | Z45: =SUM(B45:C45) -> 0 | AA45: =SUM(I45:J45) -> 0 | AB45: =L45 -> 0 | AC45: =SUM(S45:W45) -> 0 | AD45: =S45 -> 0 | AE45: -25 | AF45: =LCOE!E71+LCOE!F$40 -> 0.05 | AG45: =(1+AF45)^A45 -> 0.29530277 | AH45: =Z45/AG45 -> 0 | AI45: =AA45/AG45 -> 0 | AJ45: =AB45/AG45 -> 0 | AK45: =AC45/AG45 -> 0 | AL45: =AD45/AG45 -> 0
A46: -24 | B46: =LCOE!C72+IF(A46>=((LCOE!F$17*-1)+1),LCOE!F$38/LCOE!F$17,0) -> 0 | Z46: =SUM(B46:C46) -> 0 | AA46: =SUM(I46:J46) -> 0 | AB46: =L46 -> 0 | AC46: =SUM(S46:W46) -> 0 | AD46: =S46 -> 0 | AE46: -24 | AF46: =LCOE!E72+LCOE!F$40 -> 0.05 | AG46: =(1+AF46)^A46 -> 0.31006791 | AH46: =Z46/AG46 -> 0 | AI46: =AA46/AG46 -> 0 | AJ46: =AB46/AG46 -> 0 | AK46: =AC46/AG46 -> 0 | AL46: =AD46/AG46 -> 0
A47: -23 | B47: =LCOE!C73+IF(A47>=((LCOE!F$17*-1)+1),LCOE!F$38/LCOE!F$17,0) -> 0 | Z47: =SUM(B47:C47) -> 0 | AA47: =SUM(I47:J47) -> 0 | AB47: =L47 -> 0 | AC47: =SUM(S47:W47) -> 0 | AD47: =S47 -> 0 | AE47: -23 | AF47: =LCOE!E73+LCOE!F$40 -> 0.05 | AG47: =(1+AF47)^A47 -> 0.32557131 | AH47: =Z47/AG47 -> 0 | AI47: =AA47/AG47 -> 0 | AJ47: =AB47/AG47 -> 0 | AK47: =AC47/AG47 -> 0 | AL47: =AD47/AG47 -> 0
A48: -22 | B48: =LCOE!C74+IF(A48>=((LCOE!F$17*-1)+1),LCOE!F$38/LCOE!F$17,0) -> 0 | Z48: =SUM(B48:C48) -> 0 | AA48: =SUM(I48:J48) -> 0 | AB48: =L48 -> 0 | AC48: =SUM(S48:W48) -> 0 | AD48: =S48 -> 0 | AE48: -22 | AF48: =LCOE!E74+LCOE!F$40 -> 0.05 | AG48: =(1+AF48)^A48 -> 0.34184987 | AH48: =Z48/AG48 -> 0 | AI48: =AA48/AG48 -> 0 | AJ48: =AB48/AG48 -> 0 | AK48: =AC48/AG48 -> 0 | AL48: =AD48/AG48 -> 0
A49: -21 | B49: =LCOE!C75+IF(A49>=((LCOE!F$17*-1)+1),LCOE!F$38/LCOE!F$17,0) -> 0 | Z49: =SUM(B49:C49) -> 0 | AA49: =SUM(I49:J49) -> 0 | AB49: =L49 -> 0 | AC49: =SUM(S49:W49) -> 0 | AD49: =S49 -> 0 | AE49: -21 | AF49: =LCOE!E75+LCOE!F$40 -> 0.05 | AG49: =(1+AF49)^A49 -> 0.35894236 | AH49: =Z49/AG49 -> 0 | AI49: =AA49/AG49 -> 0 | AJ49: =AB49/AG49 -> 0 | AK49: =AC49/AG49 -> 0 | AL49: =AD49/AG49 -> 0
A50: -20 | B50: =LCOE!C76+IF(A50>=((LCOE!F$17*-1)+1),LCOE!F$38/LCOE!F$17,0) -> 0 | Z50: =SUM(B50:C50) -> 0 | AA50: =SUM(I50:J50) -> 0 | AB50: =L50 -> 0 | AC50: =SUM(S50:W50) -> 0 | AD50: =S50 -> 0 | AE50: -20 | AF50: =LCOE!E76+LCOE!F$40 -> 0.05 | AG50: =(1+AF50)^A50 -> 0.37688948 | AH50: =Z50/AG50 -> 0 | AI50: =AA50/AG50 -> 0 | AJ50: =AB50/AG50 -> 0 | AK50: =AC50/AG50 -> 0 | AL50: =AD50/AG50 -> 0
A51: -19 | B51: =LCOE!C77+IF(A51>=((LCOE!F$17*-1)+1),LCOE!F$38/LCOE!F$17,0) -> 0 | Z51: =SUM(B51:C51) -> 0 | AA51: =SUM(I51:J51) -> 0 | AB51: =L51 -> 0 | AC51: =SUM(S51:W51) -> 0 | AD51: =S51 -> 0 | AE51: -19 | AF51: =LCOE!E77+LCOE!F$40 -> 0.05 | AG51: =(1+AF51)^A51 -> 0.39573396 | AH51: =Z51/AG51 -> 0 | AI51: =AA51/AG51 -> 0 | AJ51: =AB51/AG51 -> 0 | AK51: =AC51/AG51 -> 0 | AL51: =AD51/AG51 -> 0
A52: -18 | B52: =LCOE!C78+IF(A52>=((LCOE!F$17*-1)+1),LCOE!F$38/LCOE!F$17,0) -> 0 | Z52: =SUM(B52:C52) -> 0 | AA52: =SUM(I52:J52) -> 0 | AB52: =L52 -> 0 | AC52: =SUM(S52:W52) -> 0 | AD52: =S52 -> 0 | AE52: -18 | AF52: =LCOE!E78+LCOE!F$40 -> 0.05 | AG52: =(1+AF52)^A52 -> 0.41552065 | AH52: =Z52/AG52 -> 0 | AI52: =AA52/AG52 -> 0 | AJ52: =AB52/AG52 -> 0 | AK52: =AC52/AG52 -> 0 | AL52: =AD52/AG52 -> 0
A53: -17 | B53: =LCOE!C79+IF(A53>=((LCOE!F$17*-1)+1),LCOE!F$38/LCOE!F$17,0) -> 0 | Z53: =SUM(B53:C53) -> 0 | AA53: =SUM(I53:J53) -> 0 | AB53: =L53 -> 0 | AC53: =SUM(S53:W53) -> 0 | AD53: =S53 -> 0 | AE53: -17 | AF53: =LCOE!E79+LCOE!F$40 -> 0.05 | AG53: =(1+AF53)^A53 -> 0.43629669 | AH53: =Z53/AG53 -> 0 | AI53: =AA53/AG53 -> 0 | AJ53: =AB53/AG53 -> 0 | AK53: =AC53/AG53 -> 0 | AL53: =AD53/AG53 -> 0
A54: -16 | B54: =LCOE!C80+IF(A54>=((LCOE!F$17*-1)+1),LCOE!F$38/LCOE!F$17,0) -> 0 | Z54: =SUM(B54:C54) -> 0 | AA54: =SUM(I54:J54) -> 0 | AB54: =L54 -> 0 | AC54: =SUM(S54:W54) -> 0 | AD54: =S54 -> 0 | AE54: -16 | AF54: =LCOE!E80+LCOE!F$40 -> 0.05 | AG54: =(1+AF54)^A54 -> 0.45811152 | AH54: =Z54/AG54 -> 0 | AI54: =AA54/AG54 -> 0 | AJ54: =AB54/AG54 -> 0 | AK54: =AC54/AG54 -> 0 | AL54: =AD54/AG54 -> 0
A55: -15 | B55: =LCOE!C81+IF(A55>=((LCOE!F$17*-1)+1),LCOE!F$38/LCOE!F$17,0) -> 0 | Z55: =SUM(B55:C55) -> 0 | AA55: =SUM(I55:J55) -> 0 | AB55: =L55 -> 0 | AC55: =SUM(S55:W55) -> 0 | AD55: =S55 -> 0 | AE55: -15 | AF55: =LCOE!E81+LCOE!F$40 -> 0.05 | AG55: =(1+AF55)^A55 -> 0.4810171 | AH55: =Z55/AG55 -> 0 | AI55: =AA55/AG55 -> 0 | AJ55: =AB55/AG55 -> 0 | AK55: =AC55/AG55 -> 0 | AL55: =AD55/AG55 -> 0
A56: -14 | B56: =LCOE!C82+IF(A56>=((LCOE!F$17*-1)+1),LCOE!F$38/LCOE!F$17,0) -> 0 | Z56: =SUM(B56:C56) -> 0 | AA56: =SUM(I56:J56) -> 0 | AB56: =L56 -> 0 | AC56: =SUM(S56:W56) -> 0 | AD56: =S56 -> 0 | AE56: -14 | AF56: =LCOE!E82+LCOE!F$40 -> 0.05 | AG56: =(1+AF56)^A56 -> 0.50506795 | AH56: =Z56/AG56 -> 0 | AI56: =AA56/AG56 -> 0 | AJ56: =AB56/AG56 -> 0 | AK56: =AC56/AG56 -> 0 | AL56: =AD56/AG56 -> 0
... A69: -1 | B69: =LCOE!C95+IF(A69>=((LCOE!F$17*-1)+1),LCOE!F$38/LCOE!F$17,0) -> 1.6816667e+08 | Z69: =SUM(B69:C69) -> 1.6816667e+08 | AA69: =SUM(I69:J69) -> 0 | AB69: =L69 -> 0 | AC69: =SUM(S69:W69) -> 0 | AD69: =S69 -> 0 | AE69: -1 | AF69: =LCOE!E95+LCOE!F$40 -> 0.05 | AG69: =(1+AF69)^A69 -> 0.95238095 | AH69: =Z69/AG69 -> 176575000 | AI69: =AA69/AG69 -> 0 | AJ69: =AB69/AG69 -> 0 | AK69: =AC69/AG69 -> 0 | AL69: =AD69/AG69 -> 0
A70: 0 | B70: =LCOE!C96+IF(A70>=((LCOE!F$17*-1)+1),LCOE!F$38/LCOE!F$17,0) -> 1.6816667e+08 | C70: =LCOE!F96+IF(AND(LCOE!F$26>0,A70>=LCOE!F$26,A70<=(LCOE!F$26+LCOE!F$27-1)),LCOE!F$42/LCOE!F$27,0)+IF(AND(D70=0,AE70>=LCOE!F$16,COUNTIF(D45:D70,0)=LCOE!F$36),LCOE!F$35*LCOE!F$38,0) -> 0 | D70: =IF(AE69<LCOE!F$16,1,0) -> 1 | E70: =LCOE!G96+IF(AND(A70>=LCOE!F$26,A70<=(LCOE!F$26+LCOE!F$27-1)),0,1)*IF(A70=LCOE!F$34,0,1)*D70 -> 1 | F70: =LCOE!F$18*50%+LCOE!J96 -> 0.45 | G70: =LCOE!K96+E70*F70*N70*(LCOE!F$14+LCOE!H96)*24*365*D70 -> 1971000 | H70: =LCOE!L96+F70*(LCOE!F$15+LCOE!I96)*E70*24*365*D70*N70 -> 0 | I70: =LCOE!M96+LCOE!F$20*IF(LCOE!F$14>0,(LCOE!F$14+LCOE!H96),(LCOE!F$15+LCOE!I96))*K70*D70 -> 20000000 | J70: =LCOE!N96+LCOE!F$21*IF(LCOE!F$14>0,G70,H70)*K70*D70 -> 0 | K70: =LCOE!O96+100% -> 1 | L70: =LCOE!P96+LCOE!F$23*IF(LCOE!F$14>0,G70,H70)*M70*D70 -> 84082860 | M70: =LCOE!Q96+100% -> 1 | N70: =LCOE!R96+100% -> 1 | O70: =LCOE!S96+LCOE!F$29 -> 313.75 | P70: =LCOE!T96+IF(A70>=LCOE!F$30,100%,0%) -> 1 | Q70: =LCOE!U96+O70/1000*IF(LCOE!F$14>0,G70,H70) -> 618401.25 | R70: =LCOE!B96 -> 30 | S70: =LCOE!V96+Q70*P70*R70 -> 18552038 | T70: =LCOE!W96+LCOE!F$31 -> 0 | U70: =LCOE!X96+T70*IF(LCOE!F$14>0,G70,H70) -> 0 | V70: =LCOE!Y96+LCOE!F$32 -> 0 | W70: =LCOE!Z96+V70*IF(LCOE!F$14>0,G70,H70) -> 0 | X70: =LCOE!AA96+LCOE!F$34 -> 101 | Y70: =X70*H70 -> 0 | Z70: =SUM(B70:C70) -> 1.6816667e+08 | AA70: =SUM(I70:J70) -> 20000000 | AB70: =L70 -> 84082860 | AC70: =U70+W70 -> 0 | AD70: =S70 -> 18552038 | AE70: 0 | AF70: =LCOE!E96+LCOE!F$40 -> 0.05 | AG70: =(1+AF70)^A70 -> 1 | AH70: =Z70/AG70 -> 1.6816667e+08 | AI70: =AA70/AG70 -> 20000000 | AJ70: =AB70/AG70 -> 84082860 | AK70: =AC70/AG70 -> 0 | AL70: =AD70/AG70 -> 18552038 | AM70: =(-1)*Y70/AG70 -> 0 | AN70: =IF(LCOE!F$14>0,G70,H70)/AG70 -> 1971000
A71: 1 | C71: =LCOE!F97+IF(AND(LCOE!F$26>0,A71>=LCOE!F$26,A71<=(LCOE!F$26+LCOE!F$27-1)),LCOE!F$42/LCOE!F$27,0)+IF(AND(D71=0,AE71>=LCOE!F$16,COUNTIF(D46:D71,0)=LCOE!F$36),LCOE!F$35*LCOE!F$38,0) -> 0 | D71: =IF(AE70<LCOE!F$16,1,0) -> 1 | E71: =LCOE!G97+IF(AND(A71>=LCOE!F$26,A71<=(LCOE!F$26+LCOE!F$27-1)),0,1)*IF(A71=LCOE!F$34,0,1)*D71 -> 1 | F71: =IF(F70<LCOE!F$18,MIN(F70*(1+LCOE!F$19),LCOE!F$18),LCOE!F$18)+LCOE!J97 -> 0.72 | G71: =LCOE!K97+E71*F71*N71*(LCOE!F$14+LCOE!H97)*24*365*D71 -> 3153600 | H71: =LCOE!L97+F71*(LCOE!F$15+LCOE!I97)*E71*24*365*D71*N71 -> 0 | I71: =LCOE!M97+LCOE!F$20*IF(LCOE!F$14>0,(LCOE!F$14+LCOE!H97),(LCOE!F$15+LCOE!I97))*K71*D71 -> 20000000 | J71: =LCOE!N97+LCOE!F$21*IF(LCOE!F$14>0,G71,H71)*K71*D71 -> 0 | K71: =LCOE!O97+K70+K70*LCOE!F$22 -> 1 | L71: =LCOE!P97+LCOE!F$23*IF(LCOE!F$14>0,G71,H71)*M71*D71 -> 134532576 | M71: =LCOE!Q97+M70+M70*LCOE!F$24 -> 1 | N71: =LCOE!R97+N70-N70*LCOE!F$25 -> 1 | O71: =LCOE!S97+LCOE!F$29 -> 313.75 | P71: =LCOE!T97+IF(A71>=LCOE!F$30,100%,0%) -> 1 | Q71: =LCOE!U97+O71/1000*IF(LCOE!F$14>0,G71,H71) -> 989442 | R71: =LCOE!B97 -> 30 | S71: =LCOE!V97+Q71*P71*R71 -> 29683260 | T71: =LCOE!W97+LCOE!F$31 -> 0 | U71: =LCOE!X97+T71*IF(LCOE!F$14>0,G71,H71) -> 0 | V71: =LCOE!Y97+LCOE!F$32 -> 0 | W71: =LCOE!Z97+V71*IF(LCOE!F$14>0,G71,H71) -> 0 | X71: =LCOE!AA97+LCOE!F$34 -> 101 | Y71: =X71*H71 -> 0 | Z71: =SUM(B71:C71) -> 0 | AA71: =SUM(I71:J71) -> 20000000 | AB71: =L71 -> 134532576 | AC71: =U71+W71 -> 0 | AD71: =S71 -> 29683260 | AE71: =AE70+1*E71 -> 1 | AF71: =LCOE!E97+LCOE!F$40 -> 0.05 | AG71: =(1+AF71)^A71 -> 1.05 | AH71: =Z71/AG71 -> 0 | AI71: =AA71/AG71 -> 19047619 | AJ71: =AB71/AG71 -> 1.2812626e+08 | AK71: =AC71/AG71 -> 0 | AL71: =AD71/AG71 -> 28269771 | AM71: =(-1)*Y71/AG71 -> 0 | AN71: =IF(LCOE!F$14>0,G71,H71)/AG71 -> 3003428.6
A72: 2 | C72: =LCOE!F98+IF(AND(LCOE!F$26>0,A72>=LCOE!F$26,A72<=(LCOE!F$26+LCOE!F$27-1)),LCOE!F$42/LCOE!F$27,0)+IF(AND(D72=0,AE72>=LCOE!F$16,COUNTIF(D47:D72,0)=LCOE!F$36),LCOE!F$35*LCOE!F$38,0) -> 0 | D72: =IF(AE71<LCOE!F$16,1,0) -> 1 | E72: =LCOE!G98+IF(AND(A72>=LCOE!F$26,A72<=(LCOE!F$26+LCOE!F$27-1)),0,1)*IF(A72=LCOE!F$34,0,1)*D72 -> 1 | F72: =IF(F71<LCOE!F$18,MIN(F71*(1+LCOE!F$19),LCOE!F$18),LCOE!F$18)+LCOE!J98 -> 0.9 | G72: =LCOE!K98+E72*F72*N72*(LCOE!F$14+LCOE!H98)*24*365*D72 -> 3942000 | H72: =LCOE!L98+F72*(LCOE!F$15+LCOE!I98)*E72*24*365*D72*N72 -> 0 | I72: =LCOE!M98+LCOE!F$20*IF(LCOE!F$14>0,(LCOE!F$14+LCOE!H98),(LCOE!F$15+LCOE!I98))*K72*D72 -> 20000000 | J72: =LCOE!N98+LCOE!F$21*IF(LCOE!F$14>0,G72,H72)*K72*D72 -> 0 | K72: =LCOE!O98+K71+K71*LCOE!F$22 -> 1 | L72: =LCOE!P98+LCOE!F$23*IF(LCOE!F$14>0,G72,H72)*M72*D72 -> 168165720 | M72: =LCOE!Q98+M71+M71*LCOE!F$24 -> 1 | N72: =LCOE!R98+N71-N71*LCOE!F$25 -> 1 | O72: =LCOE!S98+LCOE!F$29 -> 313.75 | P72: =LCOE!T98+IF(A72>=LCOE!F$30,100%,0%) -> 1 | Q72: =LCOE!U98+O72/1000*IF(LCOE!F$14>0,G72,H72) -> 1236802.5 | R72: =LCOE!B98 -> 30 | S72: =LCOE!V98+Q72*P72*R72 -> 37104075 | T72: =LCOE!W98+LCOE!F$31 -> 0 | U72: =LCOE!X98+T72*IF(LCOE!F$14>0,G72,H72) -> 0 | V72: =LCOE!Y98+LCOE!F$32 -> 0 | W72: =LCOE!Z98+V72*IF(LCOE!F$14>0,G72,H72) -> 0 | X72: =LCOE!AA98+LCOE!F$34 -> 101 | Y72: =X72*H72 -> 0 | Z72: =SUM(B72:C72) -> 0 | AA72: =SUM(I72:J72) -> 20000000 | AB72: =L72 -> 168165720 | AC72: =U72+W72 -> 0 | AD72: =S72 -> 37104075 | AE72: =AE71+1*E72 -> 2 | AF72: =LCOE!E98+LCOE!F$40 -> 0.05 | AG72: =(1+AF72)^A72 -> 1.1025 | AH72: =Z72/AG72 -> 0 | AI72: =AA72/AG72 -> 18140590 | AJ72: =AB72/AG72 -> 1.5253127e+08 | AK72: =AC72/AG72 -> 0 | AL72: =AD72/AG72 -> 33654490 | AM72: =(-1)*Y72/AG72 -> 0 | AN72: =IF(LCOE!F$14>0,G72,H72)/AG72 -> 3575510.2
A73: 3 | C73: =LCOE!F99+IF(AND(LCOE!F$26>0,A73>=LCOE!F$26,A73<=(LCOE!F$26+LCOE!F$27-1)),LCOE!F$42/LCOE!F$27,0)+IF(AND(D73=0,AE73>=LCOE!F$16,COUNTIF(D48:D73,0)=LCOE!F$36),LCOE!F$35*LCOE!F$38,0) -> 0 | D73: =IF(AE72<LCOE!F$16,1,0) -> 1 | E73: =LCOE!G99+IF(AND(A73>=LCOE!F$26,A73<=(LCOE!F$26+LCOE!F$27-1)),0,1)*IF(A73=LCOE!F$34,0,1)*D73 -> 1 | F73: =IF(F72<LCOE!F$18,MIN(F72*(1+LCOE!F$19),LCOE!F$18),LCOE!F$18)+LCOE!J99 -> 0.9 | G73: =LCOE!K99+E73*F73*N73*(LCOE!F$14+LCOE!H99)*24*365*D73 -> 3942000 | H73: =LCOE!L99+F73*(LCOE!F$15+LCOE!I99)*E73*24*365*D73*N73 -> 0 | I73: =LCOE!M99+LCOE!F$20*IF(LCOE!F$14>0,(LCOE!F$14+LCOE!H99),(LCOE!F$15+LCOE!I99))*K73*D73 -> 20000000 | J73: =LCOE!N99+LCOE!F$21*IF(LCOE!F$14>0,G73,H73)*K73*D73 -> 0 | K73: =LCOE!O99+K72+K72*LCOE!F$22 -> 1 | L73: =LCOE!P99+LCOE!F$23*IF(LCOE!F$14>0,G73,H73)*M73*D73 -> 168165720 | M73: =LCOE!Q99+M72+M72*LCOE!F$24 -> 1 | N73: =LCOE!R99+N72-N72*LCOE!F$25 -> 1 | O73: =LCOE!S99+LCOE!F$29 -> 313.75 | P73: =LCOE!T99+IF(A73>=LCOE!F$30,100%,0%) -> 1 | Q73: =LCOE!U99+O73/1000*IF(LCOE!F$14>0,G73,H73) -> 1236802.5 | R73: =LCOE!B99 -> 30 | S73: =LCOE!V99+Q73*P73*R73 -> 37104075 | T73: =LCOE!W99+LCOE!F$31 -> 0 | U73: =LCOE!X99+T73*IF(LCOE!F$14>0,G73,H73) -> 0 | V73: =LCOE!Y99+LCOE!F$32 -> 0 | W73: =LCOE!Z99+V73*IF(LCOE!F$14>0,G73,H73) -> 0 | X73: =LCOE!AA99+LCOE!F$34 -> 101 | Y73: =X73*H73 -> 0 | Z73: =SUM(B73:C73) -> 0 | AA73: =SUM(I73:J73) -> 20000000 | AB73: =L73 -> 168165720 | AC73: =U73+W73 -> 0 | AD73: =S73 -> 37104075 | AE73: =AE72+1*E73 -> 3 | AF73: =LCOE!E99+LCOE!F$40 -> 0.05 | AG73: =(1+AF73)^A73 -> 1.157625 | AH73: =Z73/AG73 -> 0 | AI73: =AA73/AG73 -> 17276752 | AJ73: =AB73/AG73 -> 1.4526787e+08 | AK73: =AC73/AG73 -> 0 | AL73: =AD73/AG73 -> 32051895 | AM73: =(-1)*Y73/AG73 -> 0 | AN73: =IF(LCOE!F$14>0,G73,H73)/AG73 -> 3405247.8
A74: 4 | C74: =LCOE!F100+IF(AND(LCOE!F$26>0,A74>=LCOE!F$26,A74<=(LCOE!F$26+LCOE!F$27-1)),LCOE!F$42/LCOE!F$27,0)+IF(AND(D74=0,AE74>=LCOE!F$16,COUNTIF(D49:D74,0)=LCOE!F$36),LCOE!F$35*LCOE!F$38,0) -> 0 | D74: =IF(AE73<LCOE!F$16,1,0) -> 1 | E74: =LCOE!G100+IF(AND(A74>=LCOE!F$26,A74<=(LCOE!F$26+LCOE!F$27-1)),0,1)*IF(A74=LCOE!F$34,0,1)*D74 -> 1 | F74: =IF(F73<LCOE!F$18,MIN(F73*(1+LCOE!F$19),LCOE!F$18),LCOE!F$18)+LCOE!J100 -> 0.9 | G74: =LCOE!K100+E74*F74*N74*(LCOE!F$14+LCOE!H100)*24*365*D74 -> 3942000 | H74: =LCOE!L100+F74*(LCOE!F$15+LCOE!I100)*E74*24*365*D74*N74 -> 0 | I74: =LCOE!M100+LCOE!F$20*IF(LCOE!F$14>0,(LCOE!F$14+LCOE!H100),(LCOE!F$15+LCOE!I100))*K74*D74 -> 20000000 | J74: =LCOE!N100+LCOE!F$21*IF(LCOE!F$14>0,G74,H74)*K74*D74 -> 0 | K74: =LCOE!O100+K73+K73*LCOE!F$22 -> 1 | L74: =LCOE!P100+LCOE!F$23*IF(LCOE!F$14>0,G74,H74)*M74*D74 -> 168165720 | M74: =LCOE!Q100+M73+M73*LCOE!F$24 -> 1 | N74: =LCOE!R100+N73-N73*LCOE!F$25 -> 1 | O74: =LCOE!S100+LCOE!F$29 -> 313.75 | P74: =LCOE!T100+IF(A74>=LCOE!F$30,100%,0%) -> 1 | Q74: =LCOE!U100+O74/1000*IF(LCOE!F$14>0,G74,H74) -> 1236802.5 | R74: =LCOE!B100 -> 30 | S74: =LCOE!V100+Q74*P74*R74 -> 37104075 | T74: =LCOE!W100+LCOE!F$31 -> 0 | U74: =LCOE!X100+T74*IF(LCOE!F$14>0,G74,H74) -> 0 | V74: =LCOE!Y100+LCOE!F$32 -> 0 | W74: =LCOE!Z100+V74*IF(LCOE!F$14>0,G74,H74) -> 0 | X74: =LCOE!AA100+LCOE!F$34 -> 101 | Y74: =X74*H74 -> 0 | Z74: =SUM(B74:C74) -> 0 | AA74: =SUM(I74:J74) -> 20000000 | AB74: =L74 -> 168165720 | AC74: =U74+W74 -> 0 | AD74: =S74 -> 37104075 | AE74: =AE73+1*E74 -> 4 | AF74: =LCOE!E100+LCOE!F$40 -> 0.05 | AG74: =(1+AF74)^A74 -> 1.2155063 | AH74: =Z74/AG74 -> 0 | AI74: =AA74/AG74 -> 16454049 | AJ74: =AB74/AG74 -> 1.3835035e+08 | AK74: =AC74/AG74 -> 0 | AL74: =AD74/AG74 -> 30525614 | AM74: =(-1)*Y74/AG74 -> 0 | AN74: =IF(LCOE!F$14>0,G74,H74)/AG74 -> 3243093.2
A75: 5 | C75: =LCOE!F101+IF(AND(LCOE!F$26>0,A75>=LCOE!F$26,A75<=(LCOE!F$26+LCOE!F$27-1)),LCOE!F$42/LCOE!F$27,0)+IF(AND(D75=0,AE75>=LCOE!F$16,COUNTIF(D50:D75,0)=LCOE!F$36),LCOE!F$35*LCOE!F$38,0) -> 0 | D75: =IF(AE74<LCOE!F$16,1,0) -> 1 | E75: =LCOE!G101+IF(AND(A75>=LCOE!F$26,A75<=(LCOE!F$26+LCOE!F$27-1)),0,1)*IF(A75=LCOE!F$34,0,1)*D75 -> 1 | F75: =IF(F74<LCOE!F$18,MIN(F74*(1+LCOE!F$19),LCOE!F$18),LCOE!F$18)+LCOE!J101 -> 0.9 | G75: =LCOE!K101+E75*F75*N75*(LCOE!F$14+LCOE!H101)*24*365*D75 -> 3942000 | H75: =LCOE!L101+F75*(LCOE!F$15+LCOE!I101)*E75*24*365*D75*N75 -> 0 | I75: =LCOE!M101+LCOE!F$20*IF(LCOE!F$14>0,(LCOE!F$14+LCOE!H101),(LCOE!F$15+LCOE!I101))*K75*D75 -> 20000000 | J75: =LCOE!N101+LCOE!F$21*IF(LCOE!F$14>0,G75,H75)*K75*D75 -> 0 | K75: =LCOE!O101+K74+K74*LCOE!F$22 -> 1 | L75: =LCOE!P101+LCOE!F$23*IF(LCOE!F$14>0,G75,H75)*M75*D75 -> 168165720 | M75: =LCOE!Q101+M74+M74*LCOE!F$24 -> 1 | N75: =LCOE!R101+N74-N74*LCOE!F$25 -> 1 | O75: =LCOE!S101+LCOE!F$29 -> 313.75 | P75: =LCOE!T101+IF(A75>=LCOE!F$30,100%,0%) -> 1 | Q75: =LCOE!U101+O75/1000*IF(LCOE!F$14>0,G75,H75) -> 1236802.5 | R75: =LCOE!B101 -> 30 | S75: =LCOE!V101+Q75*P75*R75 -> 37104075 | T75: =LCOE!W101+LCOE!F$31 -> 0 | U75: =LCOE!X101+T75*IF(LCOE!F$14>0,G75,H75) -> 0 | V75: =LCOE!Y101+LCOE!F$32 -> 0 | W75: =LCOE!Z101+V75*IF(LCOE!F$14>0,G75,H75) -> 0 | X75: =LCOE!AA101+LCOE!F$34 -> 101 | Y75: =X75*H75 -> 0 | Z75: =SUM(B75:C75) -> 0 | AA75: =SUM(I75:J75) -> 20000000 | AB75: =L75 -> 168165720 | AC75: =U75+W75 -> 0 | AD75: =S75 -> 37104075 | AE75: =AE74+1*E75 -> 5 | AF75: =LCOE!E101+LCOE!F$40 -> 0.05 | AG75: =(1+AF75)^A75 -> 1.2762816 | AH75: =Z75/AG75 -> 0 | AI75: =AA75/AG75 -> 15670523 | AJ75: =AB75/AG75 -> 1.3176224e+08 | AK75: =AC75/AG75 -> 0 | AL75: =AD75/AG75 -> 29072014 | AM75: =(-1)*Y75/AG75 -> 0 | AN75: =IF(LCOE!F$14>0,G75,H75)/AG75 -> 3088660.1
A76: 6 | C76: =LCOE!F102+IF(AND(LCOE!F$26>0,A76>=LCOE!F$26,A76<=(LCOE!F$26+LCOE!F$27-1)),LCOE!F$42/LCOE!F$27,0)+IF(AND(D76=0,AE76>=LCOE!F$16,COUNTIF(D51:D76,0)=LCOE!F$36),LCOE!F$35*LCOE!F$38,0) -> 0 | D76: =IF(AE75<LCOE!F$16,1,0) -> 1 | E76: =LCOE!G102+IF(AND(A76>=LCOE!F$26,A76<=(LCOE!F$26+LCOE!F$27-1)),0,1)*IF(A76=LCOE!F$34,0,1)*D76 -> 1 | F76: =IF(F75<LCOE!F$18,MIN(F75*(1+LCOE!F$19),LCOE!F$18),LCOE!F$18)+LCOE!J102 -> 0.9 | G76: =LCOE!K102+E76*F76*N76*(LCOE!F$14+LCOE!H102)*24*365*D76 -> 3942000 | H76: =LCOE!L102+F76*(LCOE!F$15+LCOE!I102)*E76*24*365*D76*N76 -> 0 | I76: =LCOE!M102+LCOE!F$20*IF(LCOE!F$14>0,(LCOE!F$14+LCOE!H102),(LCOE!F$15+LCOE!I102))*K76*D76 -> 20000000 | J76: =LCOE!N102+LCOE!F$21*IF(LCOE!F$14>0,G76,H76)*K76*D76 -> 0 | K76: =LCOE!O102+K75+K75*LCOE!F$22 -> 1 | L76: =LCOE!P102+LCOE!F$23*IF(LCOE!F$14>0,G76,H76)*M76*D76 -> 168165720 | M76: =LCOE!Q102+M75+M75*LCOE!F$24 -> 1 | N76: =LCOE!R102+N75-N75*LCOE!F$25 -> 1 | O76: =LCOE!S102+LCOE!F$29 -> 313.75 | P76: =LCOE!T102+IF(A76>=LCOE!F$30,100%,0%) -> 1 | Q76: =LCOE!U102+O76/1000*IF(LCOE!F$14>0,G76,H76) -> 1236802.5 | R76: =LCOE!B102 -> 30 | S76: =LCOE!V102+Q76*P76*R76 -> 37104075 | T76: =LCOE!W102+LCOE!F$31 -> 0 | U76: =LCOE!X102+T76*IF(LCOE!F$14>0,G76,H76) -> 0 | V76: =LCOE!Y102+LCOE!F$32 -> 0 | W76: =LCOE!Z102+V76*IF(LCOE!F$14>0,G76,H76) -> 0 | X76: =LCOE!AA102+LCOE!F$34 -> 101 | Y76: =X76*H76 -> 0 | Z76: =SUM(B76:C76) -> 0 | AA76: =SUM(I76:J76) -> 20000000 | AB76: =L76 -> 168165720 | AC76: =U76+W76 -> 0 | AD76: =S76 -> 37104075 | AE76: =AE75+1*E76 -> 6 | AF76: =LCOE!E102+LCOE!F$40 -> 0.05 | AG76: =(1+AF76)^A76 -> 1.3400956 | AH76: =Z76/AG76 -> 0 | AI76: =AA76/AG76 -> 14924308 | AJ76: =AB76/AG76 -> 1.2548785e+08 | AK76: =AC76/AG76 -> 0 | AL76: =AD76/AG76 -> 27687632 | AM76: =(-1)*Y76/AG76 -> 0 | AN76: =IF(LCOE!F$14>0,G76,H76)/AG76 -> 2941581.1
A77: 7 | C77: =LCOE!F103+IF(AND(LCOE!F$26>0,A77>=LCOE!F$26,A77<=(LCOE!F$26+LCOE!F$27-1)),LCOE!F$42/LCOE!F$27,0)+IF(AND(D77=0,AE77>=LCOE!F$16,COUNTIF(D52:D77,0)=LCOE!F$36),LCOE!F$35*LCOE!F$38,0) -> 0 | D77: =IF(AE76<LCOE!F$16,1,0) -> 1 | E77: =LCOE!G103+IF(AND(A77>=LCOE!F$26,A77<=(LCOE!F$26+LCOE!F$27-1)),0,1)*IF(A77=LCOE!F$34,0,1)*D77 -> 1 | F77: =IF(F76<LCOE!F$18,MIN(F76*(1+LCOE!F$19),LCOE!F$18),LCOE!F$18)+LCOE!J103 -> 0.9 | G77: =LCOE!K103+E77*F77*N77*(LCOE!F$14+LCOE!H103)*24*365*D77 -> 3942000 | H77: =LCOE!L103+F77*(LCOE!F$15+LCOE!I103)*E77*24*365*D77*N77 -> 0 | I77: =LCOE!M103+LCOE!F$20*IF(LCOE!F$14>0,(LCOE!F$14+LCOE!H103),(LCOE!F$15+LCOE!I103))*K77*D77 -> 20000000 | J77: =LCOE!N103+LCOE!F$21*IF(LCOE!F$14>0,G77,H77)*K77*D77 -> 0 | K77: =LCOE!O103+K76+K76*LCOE!F$22 -> 1 | L77: =LCOE!P103+LCOE!F$23*IF(LCOE!F$14>0,G77,H77)*M77*D77 -> 168165720 | M77: =LCOE!Q103+M76+M76*LCOE!F$24 -> 1 | N77: =LCOE!R103+N76-N76*LCOE!F$25 -> 1 | O77: =LCOE!S103+LCOE!F$29 -> 313.75 | P77: =LCOE!T103+IF(A77>=LCOE!F$30,100%,0%) -> 1 | Q77: =LCOE!U103+O77/1000*IF(LCOE!F$14>0,G77,H77) -> 1236802.5 | R77: =LCOE!B103 -> 30 | S77: =LCOE!V103+Q77*P77*R77 -> 37104075 | T77: =LCOE!W103+LCOE!F$31 -> 0 | U77: =LCOE!X103+T77*IF(LCOE!F$14>0,G77,H77) -> 0 | V77: =LCOE!Y103+LCOE!F$32 -> 0 | W77: =LCOE!Z103+V77*IF(LCOE!F$14>0,G77,H77) -> 0 | X77: =LCOE!AA103+LCOE!F$34 -> 101 | Y77: =X77*H77 -> 0 | Z77: =SUM(B77:C77) -> 0 | AA77: =SUM(I77:J77) -> 20000000 | AB77: =L77 -> 168165720 | AC77: =U77+W77 -> 0 | AD77: =S77 -> 37104075 | AE77: =AE76+1*E77 -> 7 | AF77: =LCOE!E103+LCOE!F$40 -> 0.05 | AG77: =(1+AF77)^A77 -> 1.4071004 | AH77: =Z77/AG77 -> 0 | AI77: =AA77/AG77 -> 14213627 | AJ77: =AB77/AG77 -> 1.1951224e+08 | AK77: =AC77/AG77 -> 0 | AL77: =AD77/AG77 -> 26369173 | AM77: =(-1)*Y77/AG77 -> 0 | AN77: =IF(LCOE!F$14>0,G77,H77)/AG77 -> 2801505.8
A78: 8 | C78: =LCOE!F104+IF(AND(LCOE!F$26>0,A78>=LCOE!F$26,A78<=(LCOE!F$26+LCOE!F$27-1)),LCOE!F$42/LCOE!F$27,0)+IF(AND(D78=0,AE78>=LCOE!F$16,COUNTIF(D53:D78,0)=LCOE!F$36),LCOE!F$35*LCOE!F$38,0) -> 0 | D78: =IF(AE77<LCOE!F$16,1,0) -> 1 | E78: =LCOE!G104+IF(AND(A78>=LCOE!F$26,A78<=(LCOE!F$26+LCOE!F$27-1)),0,1)*IF(A78=LCOE!F$34,0,1)*D78 -> 1 | F78: =IF(F77<LCOE!F$18,MIN(F77*(1+LCOE!F$19),LCOE!F$18),LCOE!F$18)+LCOE!J104 -> 0.9 | G78: =LCOE!K104+E78*F78*N78*(LCOE!F$14+LCOE!H104)*24*365*D78 -> 3942000 | H78: =LCOE!L104+F78*(LCOE!F$15+LCOE!I104)*E78*24*365*D78*N78 -> 0 | I78: =LCOE!M104+LCOE!F$20*IF(LCOE!F$14>0,(LCOE!F$14+LCOE!H104),(LCOE!F$15+LCOE!I104))*K78*D78 -> 20000000 | J78: =LCOE!N104+LCOE!F$21*IF(LCOE!F$14>0,G78,H78)*K78*D78 -> 0 | K78: =LCOE!O104+K77+K77*LCOE!F$22 -> 1 | L78: =LCOE!P104+LCOE!F$23*IF(LCOE!F$14>0,G78,H78)*M78*D78 -> 168165720 | M78: =LCOE!Q104+M77+M77*LCOE!F$24 -> 1 | N78: =LCOE!R104+N77-N77*LCOE!F$25 -> 1 | O78: =LCOE!S104+LCOE!F$29 -> 313.75 | P78: =LCOE!T104+IF(A78>=LCOE!F$30,100%,0%) -> 1 | Q78: =LCOE!U104+O78/1000*IF(LCOE!F$14>0,G78,H78) -> 1236802.5 | R78: =LCOE!B104 -> 30 | S78: =LCOE!V104+Q78*P78*R78 -> 37104075 | T78: =LCOE!W104+LCOE!F$31 -> 0 | U78: =LCOE!X104+T78*IF(LCOE!F$14>0,G78,H78) -> 0 | V78: =LCOE!Y104+LCOE!F$32 -> 0 | W78: =LCOE!Z104+V78*IF(LCOE!F$14>0,G78,H78) -> 0 | X78: =LCOE!AA104+LCOE!F$34 -> 101 | Y78: =X78*H78 -> 0 | Z78: =SUM(B78:C78) -> 0 | AA78: =SUM(I78:J78) -> 20000000 | AB78: =L78 -> 168165720 | AC78: =U78+W78 -> 0 | AD78: =S78 -> 37104075 | AE78: =AE77+1*E78 -> 8 | AF78: =LCOE!E104+LCOE!F$40 -> 0.05 | AG78: =(1+AF78)^A78 -> 1.4774554 | AH78: =Z78/AG78 -> 0 | AI78: =AA78/AG78 -> 13536787 | AJ78: =AB78/AG78 -> 1.1382118e+08 | AK78: =AC78/AG78 -> 0 | AL78: =AD78/AG78 -> 25113498 | AM78: =(-1)*Y78/AG78 -> 0 | AN78: =IF(LCOE!F$14>0,G78,H78)/AG78 -> 2668100.8
A79: 9 | C79: =LCOE!F105+IF(AND(LCOE!F$26>0,A79>=LCOE!F$26,A79<=(LCOE!F$26+LCOE!F$27-1)),LCOE!F$42/LCOE!F$27,0)+IF(AND(D79=0,AE79>=LCOE!F$16,COUNTIF(D54:D79,0)=LCOE!F$36),LCOE!F$35*LCOE!F$38,0) -> 0 | D79: =IF(AE78<LCOE!F$16,1,0) -> 1 | E79: =LCOE!G105+IF(AND(A79>=LCOE!F$26,A79<=(LCOE!F$26+LCOE!F$27-1)),0,1)*IF(A79=LCOE!F$34,0,1)*D79 -> 1 | F79: =IF(F78<LCOE!F$18,MIN(F78*(1+LCOE!F$19),LCOE!F$18),LCOE!F$18)+LCOE!J105 -> 0.9 | G79: =LCOE!K105+E79*F79*N79*(LCOE!F$14+LCOE!H105)*24*365*D79 -> 3942000 | H79: =LCOE!L105+F79*(LCOE!F$15+LCOE!I105)*E79*24*365*D79*N79 -> 0 | I79: =LCOE!M105+LCOE!F$20*IF(LCOE!F$14>0,(LCOE!F$14+LCOE!H105),(LCOE!F$15+LCOE!I105))*K79*D79 -> 20000000 | J79: =LCOE!N105+LCOE!F$21*IF(LCOE!F$14>0,G79,H79)*K79*D79 -> 0 | K79: =LCOE!O105+K78+K78*LCOE!F$22 -> 1 | L79: =LCOE!P105+LCOE!F$23*IF(LCOE!F$14>0,G79,H79)*M79*D79 -> 168165720 | M79: =LCOE!Q105+M78+M78*LCOE!F$24 -> 1 | N79: =LCOE!R105+N78-N78*LCOE!F$25 -> 1 | O79: =LCOE!S105+LCOE!F$29 -> 313.75 | P79: =LCOE!T105+IF(A79>=LCOE!F$30,100%,0%) -> 1 | Q79: =LCOE!U105+O79/1000*IF(LCOE!F$14>0,G79,H79) -> 1236802.5 | R79: =LCOE!B105 -> 30 | S79: =LCOE!V105+Q79*P79*R79 -> 37104075 | T79: =LCOE!W105+LCOE!F$31 -> 0 | U79: =LCOE!X105+T79*IF(LCOE!F$14>0,G79,H79) -> 0 | V79: =LCOE!Y105+LCOE!F$32 -> 0 | W79: =LCOE!Z105+V79*IF(LCOE!F$14>0,G79,H79) -> 0 | X79: =LCOE!AA105+LCOE!F$34 -> 101 | Y79: =X79*H79 -> 0 | Z79: =SUM(B79:C79) -> 0 | AA79: =SUM(I79:J79) -> 20000000 | AB79: =L79 -> 168165720 | AC79: =U79+W79 -> 0 | AD79: =S79 -> 37104075 | AE79: =AE78+1*E79 -> 9 | AF79: =LCOE!E105+LCOE!F$40 -> 0.05 | AG79: =(1+AF79)^A79 -> 1.5513282 | AH79: =Z79/AG79 -> 0 | AI79: =AA79/AG79 -> 12892178 | AJ79: =AB79/AG79 -> 1.0840112e+08 | AK79: =AC79/AG79 -> 0 | AL79: =AD79/AG79 -> 23917618 | AM79: =(-1)*Y79/AG79 -> 0 | AN79: =IF(LCOE!F$14>0,G79,H79)/AG79 -> 2541048.3
A80: 10 | C80: =LCOE!F106+IF(AND(LCOE!F$26>0,A80>=LCOE!F$26,A80<=(LCOE!F$26+LCOE!F$27-1)),LCOE!F$42/LCOE!F$27,0)+IF(AND(D80=0,AE80>=LCOE!F$16,COUNTIF(D55:D80,0)=LCOE!F$36),LCOE!F$35*LCOE!F$38,0) -> 0 | D80: =IF(AE79<LCOE!F$16,1,0) -> 1 | E80: =LCOE!G106+IF(AND(A80>=LCOE!F$26,A80<=(LCOE!F$26+LCOE!F$27-1)),0,1)*IF(A80=LCOE!F$34,0,1)*D80 -> 1 | F80: =IF(F79<LCOE!F$18,MIN(F79*(1+LCOE!F$19),LCOE!F$18),LCOE!F$18)+LCOE!J106 -> 0.9 | G80: =LCOE!K106+E80*F80*N80*(LCOE!F$14+LCOE!H106)*24*365*D80 -> 3942000 | H80: =LCOE!L106+F80*(LCOE!F$15+LCOE!I106)*E80*24*365*D80*N80 -> 0 | I80: =LCOE!M106+LCOE!F$20*IF(LCOE!F$14>0,(LCOE!F$14+LCOE!H106),(LCOE!F$15+LCOE!I106))*K80*D80 -> 20000000 | J80: =LCOE!N106+LCOE!F$21*IF(LCOE!F$14>0,G80,H80)*K80*D80 -> 0 | K80: =LCOE!O106+K79+K79*LCOE!F$22 -> 1 | L80: =LCOE!P106+LCOE!F$23*IF(LCOE!F$14>0,G80,H80)*M80*D80 -> 168165720 | M80: =LCOE!Q106+M79+M79*LCOE!F$24 -> 1 | N80: =LCOE!R106+N79-N79*LCOE!F$25 -> 1 | O80: =LCOE!S106+LCOE!F$29 -> 313.75 | P80: =LCOE!T106+IF(A80>=LCOE!F$30,100%,0%) -> 1 | Q80: =LCOE!U106+O80/1000*IF(LCOE!F$14>0,G80,H80) -> 1236802.5 | R80: =LCOE!B106 -> 30 | S80: =LCOE!V106+Q80*P80*R80 -> 37104075 | T80: =LCOE!W106+LCOE!F$31 -> 0 | U80: =LCOE!X106+T80*IF(LCOE!F$14>0,G80,H80) -> 0 | V80: =LCOE!Y106+LCOE!F$32 -> 0 | W80: =LCOE!Z106+V80*IF(LCOE!F$14>0,G80,H80) -> 0 | X80: =LCOE!AA106+LCOE!F$34 -> 101 | Y80: =X80*H80 -> 0 | Z80: =SUM(B80:C80) -> 0 | AA80: =SUM(I80:J80) -> 20000000 | AB80: =L80 -> 168165720 | AC80: =U80+W80 -> 0 | AD80: =S80 -> 37104075 | AE80: =AE79+1*E80 -> 10 | AF80: =LCOE!E106+LCOE!F$40 -> 0.05 | AG80: =(1+AF80)^A80 -> 1.6288946 | AH80: =Z80/AG80 -> 0 | AI80: =AA80/AG80 -> 12278265 | AJ80: =AB80/AG80 -> 1.0323916e+08 | AK80: =AC80/AG80 -> 0 | AL80: =AD80/AG80 -> 22778683 | AM80: =(-1)*Y80/AG80 -> 0 | AN80: =IF(LCOE!F$14>0,G80,H80)/AG80 -> 2420046
A81: 11 | C81: =LCOE!F107+IF(AND(LCOE!F$26>0,A81>=LCOE!F$26,A81<=(LCOE!F$26+LCOE!F$27-1)),LCOE!F$42/LCOE!F$27,0)+IF(AND(D81=0,AE81>=LCOE!F$16,COUNTIF(D56:D81,0)=LCOE!F$36),LCOE!F$35*LCOE!F$38,0) -> 0 | D81: =IF(AE80<LCOE!F$16,1,0) -> 1 | E81: =LCOE!G107+IF(AND(A81>=LCOE!F$26,A81<=(LCOE!F$26+LCOE!F$27-1)),0,1)*IF(A81=LCOE!F$34,0,1)*D81 -> 1 | F81: =IF(F80<LCOE!F$18,MIN(F80*(1+LCOE!F$19),LCOE!F$18),LCOE!F$18)+LCOE!J107 -> 0.9 | G81: =LCOE!K107+E81*F81*N81*(LCOE!F$14+LCOE!H107)*24*365*D81 -> 3942000 | H81: =LCOE!L107+F81*(LCOE!F$15+LCOE!I107)*E81*24*365*D81*N81 -> 0 | I81: =LCOE!M107+LCOE!F$20*IF(LCOE!F$14>0,(LCOE!F$14+LCOE!H107),(LCOE!F$15+LCOE!I107))*K81*D81 -> 20000000 | J81: =LCOE!N107+LCOE!F$21*IF(LCOE!F$14>0,G81,H81)*K81*D81 -> 0 | K81: =LCOE!O107+K80+K80*LCOE!F$22 -> 1 | L81: =LCOE!P107+LCOE!F$23*IF(LCOE!F$14>0,G81,H81)*M81*D81 -> 168165720 | M81: =LCOE!Q107+M80+M80*LCOE!F$24 -> 1 | N81: =LCOE!R107+N80-N80*LCOE!F$25 -> 1 | O81: =LCOE!S107+LCOE!F$29 -> 313.75 | P81: =LCOE!T107+IF(A81>=LCOE!F$30,100%,0%) -> 1 | Q81: =LCOE!U107+O81/1000*IF(LCOE!F$14>0,G81,H81) -> 1236802.5 | R81: =LCOE!B107 -> 30 | S81: =LCOE!V107+Q81*P81*R81 -> 37104075 | T81: =LCOE!W107+LCOE!F$31 -> 0 | U81: =LCOE!X107+T81*IF(LCOE!F$14>0,G81,H81) -> 0 | V81: =LCOE!Y107+LCOE!F$32 -> 0 | W81: =LCOE!Z107+V81*IF(LCOE!F$14>0,G81,H81) -> 0 | X81: =LCOE!AA107+LCOE!F$34 -> 101 | Y81: =X81*H81 -> 0 | Z81: =SUM(B81:C81) -> 0 | AA81: =SUM(I81:J81) -> 20000000 | AB81: =L81 -> 168165720 | AC81: =U81+W81 -> 0 | AD81: =S81 -> 37104075 | AE81: =AE80+1*E81 -> 11 | AF81: =LCOE!E107+LCOE!F$40 -> 0.05 | AG81: =(1+AF81)^A81 -> 1.7103394 | AH81: =Z81/AG81 -> 0 | AI81: =AA81/AG81 -> 11693586 | AJ81: =AB81/AG81 -> 98323014 | AK81: =AC81/AG81 -> 0 | AL81: =AD81/AG81 -> 21693984 | AM81: =(-1)*Y81/AG81 -> 0 | AN81: =IF(LCOE!F$14>0,G81,H81)/AG81 -> 2304805.8
A82: 12 | C82: =LCOE!F108+IF(AND(LCOE!F$26>0,A82>=LCOE!F$26,A82<=(LCOE!F$26+LCOE!F$27-1)),LCOE!F$42/LCOE!F$27,0)+IF(AND(D82=0,AE82>=LCOE!F$16,COUNTIF(D57:D82,0)=LCOE!F$36),LCOE!F$35*LCOE!F$38,0) -> 0 | D82: =IF(AE81<LCOE!F$16,1,0) -> 1 | E82: =LCOE!G108+IF(AND(A82>=LCOE!F$26,A82<=(LCOE!F$26+LCOE!F$27-1)),0,1)*IF(A82=LCOE!F$34,0,1)*D82 -> 1 | F82: =IF(F81<LCOE!F$18,MIN(F81*(1+LCOE!F$19),LCOE!F$18),LCOE!F$18)+LCOE!J108 -> 0.9 | G82: =LCOE!K108+E82*F82*N82*(LCOE!F$14+LCOE!H108)*24*365*D82 -> 3942000 | H82: =LCOE!L108+F82*(LCOE!F$15+LCOE!I108)*E82*24*365*D82*N82 -> 0 | I82: =LCOE!M108+LCOE!F$20*IF(LCOE!F$14>0,(LCOE!F$14+LCOE!H108),(LCOE!F$15+LCOE!I108))*K82*D82 -> 20000000 | J82: =LCOE!N108+LCOE!F$21*IF(LCOE!F$14>0,G82,H82)*K82*D82 -> 0 | K82: =LCOE!O108+K81+K81*LCOE!F$22 -> 1 | L82: =LCOE!P108+LCOE!F$23*IF(LCOE!F$14>0,G82,H82)*M82*D82 -> 168165720 | M82: =LCOE!Q108+M81+M81*LCOE!F$24 -> 1 | N82: =LCOE!R108+N81-N81*LCOE!F$25 -> 1 | O82: =LCOE!S108+LCOE!F$29 -> 313.75 | P82: =LCOE!T108+IF(A82>=LCOE!F$30,100%,0%) -> 1 | Q82: =LCOE!U108+O82/1000*IF(LCOE!F$14>0,G82,H82) -> 1236802.5 | R82: =LCOE!B108 -> 30 | S82: =LCOE!V108+Q82*P82*R82 -> 37104075 | T82: =LCOE!W108+LCOE!F$31 -> 0 | U82: =LCOE!X108+T82*IF(LCOE!F$14>0,G82,H82) -> 0 | V82: =LCOE!Y108+LCOE!F$32 -> 0 | W82: =LCOE!Z108+V82*IF(LCOE!F$14>0,G82,H82) -> 0 | X82: =LCOE!AA108+LCOE!F$34 -> 101 | Y82: =X82*H82 -> 0 | Z82: =SUM(B82:C82) -> 0 | AA82: =SUM(I82:J82) -> 20000000 | AB82: =L82 -> 168165720 | AC82: =U82+W82 -> 0 | AD82: =S82 -> 37104075 | AE82: =AE81+1*E82 -> 12 | AF82: =LCOE!E108+LCOE!F$40 -> 0.05 | AG82: =(1+AF82)^A82 -> 1.7958563 | AH82: =Z82/AG82 -> 0 | AI82: =AA82/AG82 -> 11136748 | AJ82: =AB82/AG82 -> 93640965 | AK82: =AC82/AG82 -> 0 | AL82: =AD82/AG82 -> 20660937 | AM82: =(-1)*Y82/AG82 -> 0 | AN82: =IF(LCOE!F$14>0,G82,H82)/AG82 -> 2195053.1
... A170: 100 | C170: =LCOE!F196+IF(AND(LCOE!F$26>0,A170>=LCOE!F$26,A170<=(LCOE!F$26+LCOE!F$27-1)),LCOE!F$42/LCOE!F$27,0)+IF(AND(D170=0,AE170>=LCOE!F$16,COUNTIF(D145:D170,0)=LCOE!F$36),LCOE!F$35*LCOE!F$38,0) -> 0 | D170: =IF(AE169<LCOE!F$16,1,0) -> 0 | E170: =LCOE!G196+IF(AND(A170>=LCOE!F$26,A170<=(LCOE!F$26+LCOE!F$27-1)),0,1)*IF(A170=LCOE!F$34,0,1)*D170 -> 0 | F170: =IF(F169<LCOE!F$18,MIN(F169*(1+LCOE!F$19),LCOE!F$18),LCOE!F$18)+LCOE!J196 -> 0.9 | G170: =LCOE!K196+E170*F170*N170*(LCOE!F$14+LCOE!H196)*24*365*D170 -> 0 | H170: =LCOE!L196+F170*(LCOE!F$15+LCOE!I196)*E170*24*365*D170*N170 -> 0 | I170: =LCOE!M196+LCOE!F$20*IF(LCOE!F$14>0,(LCOE!F$14+LCOE!H196),(LCOE!F$15+LCOE!I196))*K170*D170 -> 0 | J170: =LCOE!N196+LCOE!F$21*IF(LCOE!F$14>0,G170,H170)*K170*D170 -> 0 | K170: =LCOE!O196+K169+K169*LCOE!F$22 -> 1 | L170: =LCOE!P196+LCOE!F$23*IF(LCOE!F$14>0,G170,H170)*M170*D170 -> 0 | M170: =LCOE!Q196+M169+M169*LCOE!F$24 -> 1 | N170: =LCOE!R196+N169-N169*LCOE!F$25 -> 1 | O170: =LCOE!S196+LCOE!F$29 -> 313.75 | P170: =LCOE!T196+IF(A170>=LCOE!F$30,100%,0%) -> 1 | Q170: =LCOE!U196+O170/1000*IF(LCOE!F$14>0,G170,H170) -> 0 | R170: =LCOE!B196 -> 30 | S170: =LCOE!V196+Q170*P170*R170 -> 0 | T170: =LCOE!W196+LCOE!F$31 -> 0 | U170: =LCOE!X196+T170*IF(LCOE!F$14>0,G170,H170) -> 0 | V170: =LCOE!Y196+LCOE!F$32 -> 0 | W170: =LCOE!Z196+V170*IF(LCOE!F$14>0,G170,H170) -> 0 | X170: =LCOE!AA196+LCOE!F$34 -> 101 | Y170: =X170*H170 -> 0 | Z170: =SUM(B170:C170) -> 0 | AA170: =SUM(I170:J170) -> 0 | AB170: =L170 -> 0 | AC170: =U170+W170 -> 0 | AD170: =S170 -> 0 | AE170: =AE169+1*E170 -> 30 | AF170: =LCOE!E196+LCOE!F$40 -> 0.05 | AG170: =(1+AF170)^A170 -> 131.50126 | AH170: =Z170/AG170 -> 0 | AI170: =AA170/AG170 -> 0 | AJ170: =AB170/AG170 -> 0 | AK170: =AC170/AG170 -> 0 | AL170: =AD170/AG170 -> 0 | AM170: =(-1)*Y170/AG170 -> 0 | AN170: =IF(LCOE!F$14>0,G170,H170)/AG170 -> 0

Sheet LCOE 4
B2: Parameter recap (not used in calcs) | C2: =LCOE!G3 -> LCOE 4 | F2: RESULTS | G2: =C4 -> USD | I2: =C6 -> USD
B3: =LCOE!C5 -> Name | C3: =LCOE!G5 -> CCGT in Belgium (2020) | F3: =LCOE!C46 -> LCOE (LCOHeat for pure heat plants) | G3: =SUM(AH45:AM170)/SUM(AN45:AN170) -> 68.258027 | H3: =_xlfn.CONCAT(C$4,"/MWh") -> USD/MWh | I3: =G3*C$7 -> 68.258027 | J3: =_xlfn.CONCAT(C$6,"/MWh") -> USD/MWh
B4: =LCOE!C6 -> Currency used for LCOE calculations | C4: =LCOE!G6 -> USD | F4: =LCOE!C47 -> Of which: Capital costs | G4: =SUM(AH45:AH170)/SUM(AN45:AN170) -> 10.838019 | H4: =_xlfn.CONCAT(C$4,"/MWh") -> USD/MWh | I4: =G4*C$7 -> 10.838019 | J4: =_xlfn.CONCAT(C$6,"/MWh") -> USD/MWh
B5: =LCOE!C7 -> Price reference year | C5: =LCOE!G7 -> 0 | F5: =LCOE!C48 -> O&M | G5: =SUM(AI45:AI170)/SUM(AN45:AN170) -> 5.3475079 | H5: =_xlfn.CONCAT(C$4,"/MWh") -> USD/MWh | I5: =G5*C$7 -> 5.3475079 | J5: =_xlfn.CONCAT(C$6,"/MWh") -> USD/MWh
B6: =LCOE!C8 -> Currency used | C6: =LCOE!G8 -> USD | F6: =LCOE!C49 -> Fuel | G6: =SUM(AJ45:AJ170)/SUM(AN45:AN170) -> 42.66 | H6: =_xlfn.CONCAT(C$4,"/MWh") -> USD/MWh | I6: =G6*C$7 -> 42.66 | J6: =_xlfn.CONCAT(C$6,"/MWh") -> USD/MWh
B7: =LCOE!C9 -> Conversion rate at reference year | C7: =LCOE!G9 -> 1 | F7: =LCOE!C50 -> Taxes and fees | G7: =SUM(AK45:AK170)/SUM(AN45:AN170) -> 0 | H7: =_xlfn.CONCAT(C$4,"/MWh") -> USD/MWh | I7: =G7*C$7 -> 0 | J7: =_xlfn.CONCAT(C$6,"/MWh") -> USD/MWh
B8: =LCOE!C10 -> Debt % | C8: =LCOE!G10 -> 0.9 | F8: =LCOE!C51 -> Emission costs | G8: =SUM(AL45:AL170)/SUM(AN45:AN170) -> 9.4125 | H8: =_xlfn.CONCAT(C$4,"/MWh") -> USD/MWh | I8: =G8*C$7 -> 9.4125 | J8: =_xlfn.CONCAT(C$6,"/MWh") -> USD/MWh
B9: =LCOE!C11 -> Cost of debt (private discount rate) | C9: =LCOE!G11 -> 0.07 | F9: =LCOE!C52 -> Heat credit (for CHP plants) | G9: =IF(C15>0,SUM(AM45:AM170)/SUM(AN45:AN170),0) -> 0 | H9: =_xlfn.CONCAT(C$4,"/MWh") -> USD/MWh | I9: =G9*C$7 -> 0 | J9: =_xlfn.CONCAT(C$6,"/MWh") -> USD/MWh
B10: =LCOE!C12 -> Cost of equity (discount rate) | C10: =LCOE!G12 -> 0.07 | F10: =LCOE!C53 -> WACC average over lifetime | G10: =AVERAGE(AF70:AF170) -> 0.07 | I10: =G10 -> 0.07
B11: =LCOE!C13 -> Construction cost per kW | C11: =LCOE!G13 -> 1009 | F11: =LCOE!C54 -> Plant type | G11: =IF(AND(LCOE!G$14>0,LCOE!G$15=0),"Electric only",IF(AND(LCOE!G$14>0,LCOE!G$15>0),"CHP",IF(AND(LCOE!G$14=0,LCOE!G$15>0),"Heat only","Error: no generation"))) -> Electric only | I11: =G11 -> Electric only
B12: =LCOE!C14 -> Maximum electric power, in MW_e | C12: =LCOE!G14 -> 500
B13: =LCOE!C15 -> Maximum heat power, in MW_h | C13: =LCOE!G15 -> 0
B14: =LCOE!C16 -> Plant lifetime | C14: =LCOE!G16 -> 30
B15: =LCOE!C17 -> Construction period, years | C15: =LCOE!G17 -> 3
B16: =LCOE!C18 -> Capacity factor (settled down) | C16: =LCOE!G18 -> 0.9
B17: =LCOE!C19 -> Capacity factor ramp-up on startup, per year | C17: =LCOE!G19 -> 0.6
B18: =LCOE!C20 -> Fixed OPEX/MW capacity at project start | C18: =LCOE!G20 -> 40000
B19: =LCOE!C21 -> Variable OPEX/MWh produced at project start | C19: =LCOE!G21 -> 0
B20: =LCOE!C22 -> OPEX escalator | C20: =LCOE!G22 -> 0
B21: =LCOE!C23 -> FUELEX/MWh produced at project start | C21: =LCOE!G23 -> 42.66
B22: =LCOE!C24 -> FUELEX escalator | C22: =LCOE!G24 -> 0
B23: =LCOE!C25 -> Efficiency loss/year | C23: =LCOE!G25 -> 0
... B41: =LCOE!C43 -> Overrides | C41: =LCOE!G43 -> 0
Z43: SUMMARY OF COSTS
A44: Year (t) | B44: CAPEXconstr | C44: CAPEXrefurb/decom | D44: Lifetime left? | E44: Operational% | F44: Capacity factor | G44: Electricity produced (MWh_e) | H44: Heat produced (MWh_h) | I44: Fixed OPEX | J44: Variable OPEX | K44: OPEX relative to startup | L44: FUELEX | M44: FUELEX relative to startup | N44: Efficiency relative to startup | O44: Total emission factor, gCO2/kWh | P44: % of emissions taxed | Q44: Total emissions, tCO2e | R44: Cost of tCO2e | S44: Cost of emissions levied, E | T44: Tax per MWh produced | U44: Taxes levied | V44: Waste fee per MWh produced | W44: Waste fee levied | X44: Heat credit per MWh_h | Y44: Heat credit total | Z44: Total capital expenditure, I | AA44: Total operation and maintenance expenditure, M | AB44: Total fuel expenditure, F | AC44: Total taxes, T | AD44: Total emission fees, E | AE44: Lifetime expended at start of year | AF44: Discount rate r (IDC when t<0) | AG44: Discount factor (1+r)^t | AH44: I discounted | AI44: M discounted | AJ44: F discounted | AK44: T discounted | AL44: E discounted | AM44: Heat credit, discounted | AN44: Production (MWh), discounted
A45: -25 | B45: =LCOE!C71+IF(A45>=((LCOE!G$17*-1)+1),LCOE!G$38/LCOE!G$17,0) -> 0 | Z45: =SUM(B45:C45) -> 0 | AA45: =SUM(I45:J45) -> 0 | AB45: =L45 -> 0 | AC45: =SUM(S45:W45) -> 0 | AD45: =S45 -> 0 | AE45: -25 | AF45: =LCOE!E71+LCOE!G$40 -> 0.07 | AG45: =(1+AF45)^A45 -> 0.18424918 | AH45: =Z45/AG45 -> 0 | AI45: =AA45/AG45 -> 0 | AJ45: =AB45/AG45 -> 0 | AK45: =AC45/AG45 -> 0 | AL45: =AD45/AG45 -> 0
A46: -24 | B46: =LCOE!C72+IF(A46>=((LCOE!G$17*-1)+1),LCOE!G$38/LCOE!G$17,0) -> 0 | Z46: =SUM(B46:C46) -> 0 | AA46: =SUM(I46:J46) -> 0 | AB46: =L46 -> 0 | AC46: =SUM(S46:W46) -> 0 | AD46: =S46 -> 0 | AE46: -24 | AF46: =LCOE!E72+LCOE!G$40 -> 0.07 | AG46: =(1+AF46)^A46 -> 0.19714662 | AH46: =Z46/AG46 -> 0 | AI46: =AA46/AG46 -> 0 | AJ46: =AB46/AG46 -> 0 | AK46: =AC46/AG46 -> 0 | AL46: =AD46/AG46 -> 0
A47: -23 | B47: =LCOE!C73+IF(A47>=((LCOE!G$17*-1)+1),LCOE!G$38/LCOE!G$17,0) -> 0 | Z47: =SUM(B47:C47) -> 0 | AA47: =SUM(I47:J47) -> 0 | AB47: =L47 -> 0 | AC47: =SUM(S47:W47) -> 0 | AD47: =S47 -> 0 | AE47: -23 | AF47: =LCOE!E73+LCOE!G$40 -> 0.07 | AG47: =(1+AF47)^A47 -> 0.21094688 | AH47: =Z47/AG47 -> 0 | AI47: =AA47/AG47 -> 0 | AJ47: =AB47/AG47 -> 0 | AK47: =AC47/AG47 -> 0 | AL47: =AD47/AG47 -> 0
A48: -22 | B48: =LCOE!C74+IF(A48>=((LCOE!G$17*-1)+1),LCOE!G$38/LCOE!G$17,0) -> 0 | Z48: =SUM(B48:C48) -> 0 | AA48: =SUM(I48:J48) -> 0 | AB48: =L48 -> 0 | AC48: =SUM(S48:W48) -> 0 | AD48: =S48 -> 0 | AE48: -22 | AF48: =LCOE!E74+LCOE!G$40 -> 0.07 | AG48: =(1+AF48)^A48 -> 0.22571317 | AH48: =Z48/AG48 -> 0 | AI48: =AA48/AG48 -> 0 | AJ48: =AB48/AG48 -> 0 | AK48: =AC48/AG48 -> 0 | AL48: =AD48/AG48 -> 0
A49: -21 | B49: =LCOE!C75+IF(A49>=((LCOE!G$17*-1)+1),LCOE!G$38/LCOE!G$17,0) -> 0 | Z49: =SUM(B49:C49) -> 0 | AA49: =SUM(I49:J49) -> 0 | AB49: =L49 -> 0 | AC49: =SUM(S49:W49) -> 0 | AD49: =S49 -> 0 | AE49: -21 | AF49: =LCOE!E75+LCOE!G$40 -> 0.07 | AG49: =(1+AF49)^A49 -> 0.24151309 | AH49: =Z49/AG49 -> 0 | AI49: =AA49/AG49 -> 0 | AJ49: =AB49/AG49 -> 0 | AK49: =AC49/AG49 -> 0 | AL49: =AD49/AG49 -> 0
A50: -20 | B50: =LCOE!C76+IF(A50>=((LCOE!G$17*-1)+1),LCOE!G$38/LCOE!G$17,0) -> 0 | Z50: =SUM(B50:C50) -> 0 | AA50: =SUM(I50:J50) -> 0 | AB50: =L50 -> 0 | AC50: =SUM(S50:W50) -> 0 | AD50: =S50 -> 0 | AE50: -20 | AF50: =LCOE!E76+LCOE!G$40 -> 0.07 | AG50: =(1+AF50)^A50 -> 0.258419 | AH50: =Z50/AG50 -> 0 | AI50: =AA50/AG50 -> 0 | AJ50: =AB50/AG50 -> 0 | AK50: =AC50/AG50 -> 0 | AL50: =AD50/AG50 -> 0
A51: -19 | B51: =LCOE!C77+IF(A51>=((LCOE!G$17*-1)+1),LCOE!G$38/LCOE!G$17,0) -> 0 | Z51: =SUM(B51:C51) -> 0 | AA51: =SUM(I51:J51) -> 0 | AB51: =L51 -> 0 | AC51: =SUM(S51:W51) -> 0 | AD51: =S51 -> 0 | AE51: -19 | AF51: =LCOE!E77+LCOE!G$40 -> 0.07 | AG51: =(1+AF51)^A51 -> 0.27650833 | AH51: =Z51/AG51 -> 0 | AI51: =AA51/AG51 -> 0 | AJ51: =AB51/AG51 -> 0 | AK51: =AC51/AG51 -> 0 | AL51: =AD51/AG51 -> 0
A52: -18 | B52: =LCOE!C78+IF(A52>=((LCOE!G$17*-1)+1),LCOE!G$38/LCOE!G$17,0) -> 0 | Z52: =SUM(B52:C52) -> 0 | AA52: =SUM(I52:J52) -> 0 | AB52: =L52 -> 0 | AC52: =SUM(S52:W52) -> 0 | AD52: =S52 -> 0 | AE52: -18 | AF52: =LCOE!E78+LCOE!G$40 -> 0.07 | AG52: =(1+AF52)^A52 -> 0.29586392 | AH52: =Z52/AG52 -> 0 | AI52: =AA52/AG52 -> 0 | AJ52: =AB52/AG52 -> 0 | AK52: =AC52/AG52 -> 0 | AL52: =AD52/AG52 -> 0
A53: -17 | B53: =LCOE!C79+IF(A53>=((LCOE!G$17*-1)+1),LCOE!G$38/LCOE!G$17,0) -> 0 | Z53: =SUM(B53:C53) -> 0 | AA53: =SUM(I53:J53) -> 0 | AB53: =L53 -> 0 | AC53: =SUM(S53:W53) -> 0 | AD53: =S53 -> 0 | AE53: -17 | AF53: =LCOE!E79+LCOE!G$40 -> 0.07 | AG53: =(1+AF53)^A53 -> 0.31657439 | AH53: =Z53/AG53 -> 0 | AI53: =AA53/AG53 -> 0 | AJ53: =AB53/AG53 -> 0 | AK53: =AC53/AG53 -> 0 | AL53: =AD53/AG53 -> 0
A54: -16 | B54: =LCOE!C80+IF(A54>=((LCOE!G$17*-1)+1),LCOE!G$38/LCOE!G$17,0) -> 0 | Z54: =SUM(B54:C54) -> 0 | AA54: =SUM(I54:J54) -> 0 | AB54: =L54 -> 0 | AC54: =SUM(S54:W54) -> 0 | AD54: =S54 -> 0 | AE54: -16 | AF54: =LCOE!E80+LCOE!G$40 -> 0.07 | AG54: =(1+AF54)^A54 -> 0.3387346 | AH54: =Z54/AG54 -> 0 | AI54: =AA54/AG54 -> 0 | AJ54: =AB54/AG54 -> 0 | AK54: =AC54/AG54 -> 0 | AL54: =AD54/AG54 -> 0
A55: -15 | B55: =LCOE!C81+IF(A55>=((LCOE!G$17*-1)+1),LCOE!G$38/LCOE!G$17,0) -> 0 | Z55: =SUM(B55:C55) -> 0 | AA55: =SUM(I55:J55) -> 0 | AB55: =L55 -> 0 | AC55: =SUM(S55:W55) -> 0 | AD55: =S55 -> 0 | AE55: -15 | AF55: =LCOE!E81+LCOE!G$40 -> 0.07 | AG55: =(1+AF55)^A55 -> 0.36244602 | AH55: =Z55/AG55 -> 0 | AI55: =AA55/AG55 -> 0 | AJ55: =AB55/AG55 -> 0 | AK55: =AC55/AG55 -> 0 | AL55: =AD55/AG55 -> 0
A56: -14 | B56: =LCOE!C82+IF(A56>=((LCOE!G$17*-1)+1),LCOE!G$38/LCOE!G$17,0) -> 0 | Z56: =SUM(B56:C56) -> 0 | AA56: =SUM(I56:J56) -> 0 | AB56: =L56 -> 0 | AC56: =SUM(S56:W56) -> 0 | AD56: =S56 -> 0 | AE56: -14 | AF56: =LCOE!E82+LCOE!G$40 -> 0.07 | AG56: =(1+AF56)^A56 -> 0.38781724 | AH56: =Z56/AG56 -> 0 | AI56: =AA56/AG56 -> 0 | AJ56: =AB56/AG56 -> 0 | AK56: =AC56/AG56 -> 0 | AL56: =AD56/AG56 -> 0
... A69: -1 | B69: =LCOE!C95+IF(A69>=((LCOE!G$17*-1)+1),LCOE!G$38/LCOE!G$17,0) -> 1.6816667e+08 | Z69: =SUM(B69:C69) -> 1.6816667e+08 | AA69: =SUM(I69:J69) -> 0 | AB69: =L69 -> 0 | AC69: =SUM(S69:W69) -> 0 | AD69: =S69 -> 0 | AE69: -1 | AF69: =LCOE!E95+LCOE!G$40 -> 0.07 | AG69: =(1+AF69)^A69 -> 0.93457944 | AH69: =Z69/AG69 -> 1.7993833e+08 | AI69: =AA69/AG69 -> 0 | AJ69: =AB69/AG69 -> 0 | AK69: =AC69/AG69 -> 0 | AL69: =AD69/AG69 -> 0
A70: 0 | B70: =LCOE!C96+IF(A70>=((LCOE!G$17*-1)+1),LCOE!G$38/LCOE!G$17,0) -> 1.6816667e+08 | C70: =LCOE!G96+IF(AND(LCOE!G$26>0,A70>=LCOE!G$26,A70<=(LCOE!G$26+LCOE!G$27-1)),LCOE!G$42/LCOE!G$27,0)+IF(AND(D70=0,AE70>=LCOE!G$16,COUNTIF(D45:D70,0)=LCOE!G$36),LCOE!G$35*LCOE!G$38,0) -> 0 | D70: =IF(AE69<LCOE!G$16,1,0) -> 1 | E70: =LCOE!G96+IF(AND(A70>=LCOE!G$26,A70<=(LCOE!G$26+LCOE!G$27-1)),0,1)*IF(A70=LCOE!G$34,0,1)*D70 -> 1 | F70: =LCOE!G$18*50%+LCOE!J96 -> 0.45 | G70: =LCOE!K96+E70*F70*N70*(LCOE!G$14+LCOE!H96)*24*365*D70 -> 1971000 | H70: =LCOE!L96+F70*(LCOE!G$15+LCOE!I96)*E70*24*365*D70*N70 -> 0 | I70: =LCOE!M96+LCOE!G$20*IF(LCOE!G$14>0,(LCOE!G$14+LCOE!H96),(LCOE!G$15+LCOE!I96))*K70*D70 -> 20000000 | J70: =LCOE!N96+LCOE!G$21*IF(LCOE!G$14>0,G70,H70)*K70*D70 -> 0 | K70: =LCOE!O96+100% -> 1 | L70: =LCOE!P96+LCOE!G$23*IF(LCOE!G$14>0,G70,H70)*M70*D70 -> 84082860 | M70: =LCOE!Q96+100% -> 1 | N70: =LCOE!R96+100% -> 1 | O70: =LCOE!S96+LCOE!G$29 -> 313.75 | P70: =LCOE!T96+IF(A70>=LCOE!G$30,100%,0%) -> 1 | Q70: =LCOE!U96+O70/1000*IF(LCOE!G$14>0,G70,H70) -> 618401.25 | R70: =LCOE!B96 -> 30 | S70: =LCOE!V96+Q70*P70*R70 -> 18552038 | T70: =LCOE!W96+LCOE!G$31 -> 0 | U70: =LCOE!X96+T70*IF(LCOE!G$14>0,G70,H70) -> 0 | V70: =LCOE!Y96+LCOE!G$32 -> 0 | W70: =LCOE!Z96+V70*IF(LCOE!G$14>0,G70,H70) -> 0 | X70: =LCOE!AA96+LCOE!G$34 -> 101 | Y70: =X70*H70 -> 0 | Z70: =SUM(B70:C70) -> 1.6816667e+08 | AA70: =SUM(I70:J70) -> 20000000 | AB70: =L70 -> 84082860 | AC70: =U70+W70 -> 0 | AD70: =S70 -> 18552038 | AE70: 0 | AF70: =LCOE!E96+LCOE!G$40 -> 0.07 | AG70: =(1+AF70)^A70 -> 1 | AH70: =Z70/AG70 -> 1.6816667e+08 | AI70: =AA70/AG70 -> 20000000 | AJ70: =AB70/AG70 -> 84082860 | AK70: =AC70/AG70 -> 0 | AL70: =AD70/AG70 -> 18552038 | AM70: =(-1)*Y70/AG70 -> 0 | AN70: =IF(LCOE!G$14>0,G70,H70)/AG70 -> 1971000
A71: 1 | C71: =LCOE!G97+IF(AND(LCOE!G$26>0,A71>=LCOE!G$26,A71<=(LCOE!G$26+LCOE!G$27-1)),LCOE!G$42/LCOE!G$27,0)+IF(AND(D71=0,AE71>=LCOE!G$16,COUNTIF(D46:D71,0)=LCOE!G$36),LCOE!G$35*LCOE!G$38,0) -> 0 | D71: =IF(AE70<LCOE!G$16,1,0) -> 1 | E71: =LCOE!G97+IF(AND(A71>=LCOE!G$26,A71<=(LCOE!G$26+LCOE!G$27-1)),0,1)*IF(A71=LCOE!G$34,0,1)*D71 -> 1 | F71: =IF(F70<LCOE!G$18,MIN(F70*(1+LCOE!G$19),LCOE!G$18),LCOE!G$18)+LCOE!J97 -> 0.72 | G71: =LCOE!K97+E71*F71*N71*(LCOE!G$14+LCOE!H97)*24*365*D71 -> 3153600 | H71: =LCOE!L97+F71*(LCOE!G$15+LCOE!I97)*E71*24*365*D71*N71 -> 0 | I71: =LCOE!M97+LCOE!G$20*IF(LCOE!G$14>0,(LCOE!G$14+LCOE!H97),(LCOE!G$15+LCOE!I97))*K71*D71 -> 20000000 | J71: =LCOE!N97+LCOE!G$21*IF(LCOE!G$14>0,G71,H71)*K71*D71 -> 0 | K71: =LCOE!O97+K70+K70*LCOE!G$22 -> 1 | L71: =LCOE!P97+LCOE!G$23*IF(LCOE!G$14>0,G71,H71)*M71*D71 -> 134532576 | M71: =LCOE!Q97+M70+M70*LCOE!G$24 -> 1 | N71: =LCOE!R97+N70-N70*LCOE!G$25 -> 1 | O71: =LCOE!S97+LCOE!G$29 -> 313.75 | P71: =LCOE!T97+IF(A71>=LCOE!G$30,100%,0%) -> 1 | Q71: =LCOE!U97+O71/1000*IF(LCOE!G$14>0,G71,H71) -> 989442 | R71: =LCOE!B97 -> 30 | S71: =LCOE!V97+Q71*P71*R71 -> 29683260 | T71: =LCOE!W97+LCOE!G$31 -> 0 | U71: =LCOE!X97+T71*IF(LCOE!G$14>0,G71,H71) -> 0 | V71: =LCOE!Y97+LCOE!G$32 -> 0 | W71: =LCOE!Z97+V71*IF(LCOE!G$14>0,G71,H71) -> 0 | X71: =LCOE!AA97+LCOE!G$34 -> 101 | Y71: =X71*H71 -> 0 | Z71: =SUM(B71:C71) -> 0 | AA71: =SUM(I71:J71) -> 20000000 | AB71: =L71 -> 134532576 | AC71: =U71+W71 -> 0 | AD71: =S71 -> 29683260 | AE71: =AE70+1*E71 -> 1 | AF71: =LCOE!E97+LCOE!G$40 -> 0.07 | AG71: =(1+AF71)^A71 -> 1.07 | AH71: =Z71/AG71 -> 0 | AI71: =AA71/AG71 -> 18691589 | AJ71: =AB71/AG71 -> 1.2573138e+08 | AK71: =AC71/AG71 -> 0 | AL71: =AD71/AG71 -> 27741364 | AM71: =(-1)*Y71/AG71 -> 0 | AN71: =IF(LCOE!G$14>0,G71,H71)/AG71 -> 2947289.7
A72: 2 | C72: =LCOE!G98+IF(AND(LCOE!G$26>0,A72>=LCOE!G$26,A72<=(LCOE!G$26+LCOE!G$27-1)),LCOE!G$42/LCOE!G$27,0)+IF(AND(D72=0,AE72>=LCOE!G$16,COUNTIF(D47:D72,0)=LCOE!G$36),LCOE!G$35*LCOE!G$38,0) -> 0 | D72: =IF(AE71<LCOE!G$16,1,0) -> 1 | E72: =LCOE!G98+IF(AND(A72>=LCOE!G$26,A72<=(LCOE!G$26+LCOE!G$27-1)),0,1)*IF(A72=LCOE!G$34,0,1)*D72 -> 1 | F72: =IF(F71<LCOE!G$18,MIN(F71*(1+LCOE!G$19),LCOE!G$18),LCOE!G$18)+LCOE!J98 -> 0.9 | G72: =LCOE!K98+E72*F72*N72*(LCOE!G$14+LCOE!H98)*24*365*D72 -> 3942000 | H72: =LCOE!L98+F72*(LCOE!G$15+LCOE!I98)*E72*24*365*D72*N72 -> 0 | I72: =LCOE!M98+LCOE!G$20*IF(LCOE!G$14>0,(LCOE!G$14+LCOE!H98),(LCOE!G$15+LCOE!I98))*K72*D72 -> 20000000 | J72: =LCOE!N98+LCOE!G$21*IF(LCOE!G$14>0,G72,H72)*K72*D72 -> 0 | K72: =LCOE!O98+K71+K71*LCOE!G$22 -> 1 | L72: =LCOE!P98+LCOE!G$23*IF(LCOE!G$14>0,G72,H72)*M72*D72 -> 168165720 | M72: =LCOE!Q98+M71+M71*LCOE!G$24 -> 1 | N72: =LCOE!R98+N71-N71*LCOE!G$25 -> 1 | O72: =LCOE!S98+LCOE!G$29 -> 313.75 | P72: =LCOE!T98+IF(A72>=LCOE!G$30,100%,0%) -> 1 | Q72: =LCOE!U98+O72/1000*IF(LCOE!G$14>0,G72,H72) -> 1236802.5 | R72: =LCOE!B98 -> 30 | S72: =LCOE!V98+Q72*P72*R72 -> 37104075 | T72: =LCOE!W98+LCOE!G$31 -> 0 | U72: =LCOE!X98+T72*IF(LCOE!G$14>0,G72,H72) -> 0 | V72: =LCOE!Y98+LCOE!G$32 -> 0 | W72: =LCOE!Z98+V72*IF(LCOE!G$14>0,G72,H72) -> 0 | X72: =LCOE!AA98+LCOE!G$34 -> 101 | Y72: =X72*H72 -> 0 | Z72: =SUM(B72:C72) -> 0 | AA72: =SUM(I72:J72) -> 20000000 | AB72: =L72 -> 168165720 | AC72: =U72+W72 -> 0 | AD72: =S72 -> 37104075 | AE72: =AE71+1*E72 -> 2 | AF72: =LCOE!E98+LCOE!G$40 -> 0.07 | AG72: =(1+AF72)^A72 -> 1.1449 | AH72: =Z72/AG72 -> 0 | AI72: =AA72/AG72 -> 17468775 | AJ72: =AB72/AG72 -> 1.4688245e+08 | AK72: =AC72/AG72 -> 0 | AL72: =AD72/AG72 -> 32408136 | AM72: =(-1)*Y72/AG72 -> 0 | AN72: =IF(LCOE!G$14>0,G72,H72)/AG72 -> 3443095.5
A73: 3 | C73: =LCOE!G99+IF(AND(LCOE!G$26>0,A73>=LCOE!G$26,A73<=(LCOE!G$26+LCOE!G$27-1)),LCOE!G$42/LCOE!G$27,0)+IF(AND(D73=0,AE73>=LCOE!G$16,COUNTIF(D48:D73,0)=LCOE!G$36),LCOE!G$35*LCOE!G$38,0) -> 0 | D73: =IF(AE72<LCOE!G$16,1,0) -> 1 | E73: =LCOE!G99+IF(AND(A73>=LCOE!G$26,A73<=(LCOE!G$26+LCOE!G$27-1)),0,1)*IF(A73=LCOE!G$34,0,1)*D73 -> 1 | F73: =IF(F72<LCOE!G$18,MIN(F72*(1+LCOE!G$19),LCOE!G$18),LCOE!G$18)+LCOE!J99 -> 0.9 | G73: =LCOE!K99+E73*F73*N73*(LCOE!G$14+LCOE!H99)*24*365*D73 -> 3942000 | H73: =LCOE!L99+F73*(LCOE!G$15+LCOE!I99)*E73*24*365*D73*N73 -> 0 | I73: =LCOE!M99+LCOE!G$20*IF(LCOE!G$14>0,(LCOE!G$14+LCOE!H99),(LCOE!G$15+LCOE!I99))*K73*D73 -> 20000000 | J73: =LCOE!N99+LCOE!G$21*IF(LCOE!G$14>0,G73,H73)*K73*D73 -> 0 | K73: =LCOE!O99+K72+K72*LCOE!G$22 -> 1 | L73: =LCOE!P99+LCOE!G$23*IF(LCOE!G$14>0,G73,H73)*M73*D73 -> 168165720 | M73: =LCOE!Q99+M72+M72*LCOE!G$24 -> 1 | N73: =LCOE!R99+N72-N72*LCOE!G$25 -> 1 | O73: =LCOE!S99+LCOE!G$29 -> 313.75 | P73: =LCOE!T99+IF(A73>=LCOE!G$30,100%,0%) -> 1 | Q73: =LCOE!U99+O73/1000*IF(LCOE!G$14>0,G73,H73) -> 1236802.5 | R73: =LCOE!B99 -> 30 | S73: =LCOE!V99+Q73*P73*R73 -> 37104075 | T73: =LCOE!W99+LCOE!G$31 -> 0 | U73: =LCOE!X99+T73*IF(LCOE!G$14>0,G73,H73) -> 0 | V73: =LCOE!Y99+LCOE!G$32 -> 0 | W73: =LCOE!Z99+V73*IF(LCOE!G$14>0,G73,H73) -> 0 | X73: =LCOE!AA99+LCOE!G$34 -> 101 | Y73: =X73*H73 -> 0 | Z73: =SUM(B73:C73) -> 0 | AA73: =SUM(I73:J73) -> 20000000 | AB73: =L73 -> 168165720 | AC73: =U73+W73 -> 0 | AD73: =S73 -> 37104075 | AE73: =AE72+1*E73 -> 3 | AF73: =LCOE!E99+LCOE!G$40 -> 0.07 | AG73: =(1+AF73)^A73 -> 1.225043 | AH73: =Z73/AG73 -> 0 | AI73: =AA73/AG73 -> 16325958 | AJ73: =AB73/AG73 -> 1.3727332e+08 | AK73: =AC73/AG73 -> 0 | AL73: =AD73/AG73 -> 30287978 | AM73: =(-1)*Y73/AG73 -> 0 | AN73: =IF(LCOE!G$14>0,G73,H73)/AG73 -> 3217846.2
A74: 4 | C74: =LCOE!G100+IF(AND(LCOE!G$26>0,A74>=LCOE!G$26,A74<=(LCOE!G$26+LCOE!G$27-1)),LCOE!G$42/LCOE!G$27,0)+IF(AND(D74=0,AE74>=LCOE!G$16,COUNTIF(D49:D74,0)=LCOE!G$36),LCOE!G$35*LCOE!G$38,0) -> 0 | D74: =IF(AE73<LCOE!G$16,1,0) -> 1 | E74: =LCOE!G100+IF(AND(A74>=LCOE!G$26,A74<=(LCOE!G$26+LCOE!G$27-1)),0,1)*IF(A74=LCOE!G$34,0,1)*D74 -> 1 | F74: =IF(F73<LCOE!G$18,MIN(F73*(1+LCOE!G$19),LCOE!G$18),LCOE!G$18)+LCOE!J100 -> 0.9 | G74: =LCOE!K100+E74*F74*N74*(LCOE!G$14+LCOE!H100)*24*365*D74 -> 3942000 | H74: =LCOE!L100+F74*(LCOE!G$15+LCOE!I100)*E74*24*365*D74*N74 -> 0 | I74: =LCOE!M100+LCOE!G$20*IF(LCOE!G$14>0,(LCOE!G$14+LCOE!H100),(LCOE!G$15+LCOE!I100))*K74*D74 -> 20000000 | J74: =LCOE!N100+LCOE!G$21*IF(LCOE!G$14>0,G74,H74)*K74*D74 -> 0 | K74: =LCOE!O100+K73+K73*LCOE!G$22 -> 1 | L74: =LCOE!P100+LCOE!G$23*IF(LCOE!G$14>0,G74,H74)*M74*D74 -> 168165720 | M74: =LCOE!Q100+M73+M73*LCOE!G$24 -> 1 | N74: =LCOE!R100+N73-N73*LCOE!G$25 -> 1 | O74: =LCOE!S100+LCOE!G$29 -> 313.75 | P74: =LCOE!T100+IF(A74>=LCOE!G$30,100%,0%) -> 1 | Q74: =LCOE!U100+O74/1000*IF(LCOE!G$14>0,G74,H74) -> 1236802.5 | R74: =LCOE!B100 -> 30 | S74: =LCOE!V100+Q74*P74*R74 -> 37104075 | T74: =LCOE!W100+LCOE!G$31 -> 0 | U74: =LCOE!X100+T74*IF(LCOE!G$14>0,G74,H74) -> 0 | V74: =LCOE!Y100+LCOE!G$32 -> 0 | W74: =LCOE!Z100+V74*IF(LCOE!G$14>0,G74,H74) -> 0 | X74: =LCOE!AA100+LCOE!G$34 -> 101 | Y74: =X74*H74 -> 0 | Z74: =SUM(B74:C74) -> 0 | AA74: =SUM(I74:J74) -> 20000000 | AB74: =L74 -> 168165720 | AC74: =U74+W74 -> 0 | AD74: =S74 -> 37104075 | AE74: =AE73+1*E74 -> 4 | AF74: =LCOE!E100+LCOE!G$40 -> 0.07 | AG74: =(1+AF74)^A74 -> 1.310796 | AH74: =Z74/AG74 -> 0 | AI74: =AA74/AG74 -> 15257904 | AJ74: =AB74/AG74 -> 1.2829282e+08 | AK74: =AC74/AG74 -> 0 | AL74: =AD74/AG74 -> 28306521 | AM74: =(-1)*Y74/AG74 -> 0 | AN74: =IF(LCOE!G$14>0,G74,H74)/AG74 -> 3007332.9
A75: 5 | C75: =LCOE!G101+IF(AND(LCOE!G$26>0,A75>=LCOE!G$26,A75<=(LCOE!G$26+LCOE!G$27-1)),LCOE!G$42/LCOE!G$27,0)+IF(AND(D75=0,AE75>=LCOE!G$16,COUNTIF(D50:D75,0)=LCOE!G$36),LCOE!G$35*LCOE!G$38,0) -> 0 | D75: =IF(AE74<LCOE!G$16,1,0) -> 1 | E75: =LCOE!G101+IF(AND(A75>=LCOE!G$26,A75<=(LCOE!G$26+LCOE!G$27-1)),0,1)*IF(A75=LCOE!G$34,0,1)*D75 -> 1 | F75: =IF(F74<LCOE!G$18,MIN(F74*(1+LCOE!G$19),LCOE!G$18),LCOE!G$18)+LCOE!J101 -> 0.9 | G75: =LCOE!K101+E75*F75*N75*(LCOE!G$14+LCOE!H101)*24*365*D75 -> 3942000 | H75: =LCOE!L101+F75*(LCOE!G$15+LCOE!I101)*E75*24*365*D75*N75 -> 0 | I75: =LCOE!M101+LCOE!G$20*IF(LCOE!G$14>0,(LCOE!G$14+LCOE!H101),(LCOE!G$15+LCOE!I101))*K75*D75 -> 20000000 | J75: =LCOE!N101+LCOE!G$21*IF(LCOE!G$14>0,G75,H75)*K75*D75 -> 0 | K75: =LCOE!O101+K74+K74*LCOE!G$22 -> 1 | L75: =LCOE!P101+LCOE!G$23*IF(LCOE!G$14>0,G75,H75)*M75*D75 -> 168165720 | M75: =LCOE!Q101+M74+M74*LCOE!G$24 -> 1 | N75: =LCOE!R101+N74-N74*LCOE!G$25 -> 1 | O75: =LCOE!S101+LCOE!G$29 -> 313.75 | P75: =LCOE!T101+IF(A75>=LCOE!G$30,100%,0%) -> 1 | Q75: =LCOE!U101+O75/1000*IF(LCOE!G$14>0,G75,H75) -> 1236802.5 | R75: =LCOE!B101 -> 30 | S75: =LCOE!V101+Q75*P75*R75 -> 37104075 | T75: =LCOE!W101+LCOE!G$31 -> 0 | U75: =LCOE!X101+T75*IF(LCOE!G$14>0,G75,H75) -> 0 | V75: =LCOE!Y101+LCOE!G$32 -> 0 | W75: =LCOE!Z101+V75*IF(LCOE!G$14>0,G75,H75) -> 0 | X75: =LCOE!AA101+LCOE!G$34 -> 101 | Y75: =X75*H75 -> 0 | Z75: =SUM(B75:C75) -> 0 | AA75: =SUM(I75:J75) -> 20000000 | AB75: =L75 -> 168165720 | AC75: =U75+W75 -> 0 | AD75: =S75 -> 37104075 | AE75: =AE74+1*E75 -> 5 | AF75: =LCOE!E101+LCOE!G$40 -> 0.07 | AG75: =(1+AF75)^A75 -> 1.4025517 | AH75: =Z75/AG75 -> 0 | AI75: =AA75/AG75 -> 14259724 | AJ75: =AB75/AG75 -> 1.1989983e+08 | AK75: =AC75/AG75 -> 0 | AL75: =AD75/AG75 -> 26454693 | AM75: =(-1)*Y75/AG75 -> 0 | AN75: =IF(LCOE!G$14>0,G75,H75)/AG75 -> 2810591.5
A76: 6 | C76: =LCOE!G102+IF(AND(LCOE!G$26>0,A76>=LCOE!G$26,A76<=(LCOE!G$26+LCOE!G$27-1)),LCOE!G$42/LCOE!G$27,0)+IF(AND(D76=0,AE76>=LCOE!G$16,COUNTIF(D51:D76,0)=LCOE!G$36),LCOE!G$35*LCOE!G$38,0) -> 0 | D76: =IF(AE75<LCOE!G$16,1,0) -> 1 | E76: =LCOE!G102+IF(AND(A76>=LCOE!G$26,A76<=(LCOE!G$26+LCOE!G$27-1)),0,1)*IF(A76=LCOE!G$34,0,1)*D76 -> 1 | F76: =IF(F75<LCOE!G$18,MIN(F75*(1+LCOE!G$19),LCOE!G$18),LCOE!G$18)+LCOE!J102 -> 0.9 | G76: =LCOE!K102+E76*F76*N76*(LCOE!G$14+LCOE!H102)*24*365*D76 -> 3942000 | H76: =LCOE!L102+F76*(LCOE!G$15+LCOE!I102)*E76*24*365*D76*N76 -> 0 | I76: =LCOE!M102+LCOE!G$20*IF(LCOE!G$14>0,(LCOE!G$14+LCOE!H102),(LCOE!G$15+LCOE!I102))*K76*D76 -> 20000000 | J76: =LCOE!N102+LCOE!G$21*IF(LCOE!G$14>0,G76,H76)*K76*D76 -> 0 | K76: =LCOE!O102+K75+K75*LCOE!G$22 -> 1 | L76: =LCOE!P102+LCOE!G$23*IF(LCOE!G$14>0,G76,H76)*M76*D76 -> 168165720 | M76: =LCOE!Q102+M75+M75*LCOE!G$24 -> 1 | N76: =LCOE!R102+N75-N75*LCOE!G$25 -> 1 | O76: =LCOE!S102+LCOE!G$29 -> 313.75 | P76: =LCOE!T102+IF(A76>=LCOE!G$30,100%,0%) -> 1 | Q76: =LCOE!U102+O76/1000*IF(LCOE!G$14>0,G76,H76) -> 1236802.5 | R76: =LCOE!B102 -> 30 | S76: =LCOE!V102+Q76*P76*R76 -> 37104075 | T76: =LCOE!W102+LCOE!G$31 -> 0 | U76: =LCOE!X102+T76*IF(LCOE!G$14>0,G76,H76) -> 0 | V76: =LCOE!Y102+LCOE!G$32 -> 0 | W76: =LCOE!Z102+V76*IF(LCOE!G$14>0,G76,H76) -> 0 | X76: =LCOE!AA102+LCOE!G$34 -> 101 | Y76: =X76*H76 -> 0 | Z76: =SUM(B76:C76) -> 0 | AA76: =SUM(I76:J76) -> 20000000 | AB76: =L76 -> 168165720 | AC76: =U76+W76 -> 0 | AD76: =S76 -> 37104075 | AE76: =AE75+1*E76 -> 6 | AF76: =LCOE!E102+LCOE!G$40 -> 0.07 | AG76: =(1+AF76)^A76 -> 1.5007304 | AH76: =Z76/AG76 -> 0 | AI76: =AA76/AG76 -> 13326844 | AJ76: =AB76/AG76 -> 1.1205592e+08 | AK76: =AC76/AG76 -> 0 | AL76: =AD76/AG76 -> 24724012 | AM76: =(-1)*Y76/AG76 -> 0 | AN76: =IF(LCOE!G$14>0,G76,H76)/AG76 -> 2626721
A77: 7 | C77: =LCOE!G103+IF(AND(LCOE!G$26>0,A77>=LCOE!G$26,A77<=(LCOE!G$26+LCOE!G$27-1)),LCOE!G$42/LCOE!G$27,0)+IF(AND(D77=0,AE77>=LCOE!G$16,COUNTIF(D52:D77,0)=LCOE!G$36),LCOE!G$35*LCOE!G$38,0) -> 0 | D77: =IF(AE76<LCOE!G$16,1,0) -> 1 | E77: =LCOE!G103+IF(AND(A77>=LCOE!G$26,A77<=(LCOE!G$26+LCOE!G$27-1)),0,1)*IF(A77=LCOE!G$34,0,1)*D77 -> 1 | F77: =IF(F76<LCOE!G$18,MIN(F76*(1+LCOE!G$19),LCOE!G$18),LCOE!G$18)+LCOE!J103 -> 0.9 | G77: =LCOE!K103+E77*F77*N77*(LCOE!G$14+LCOE!H103)*24*365*D77 -> 3942000 | H77: =LCOE!L103+F77*(LCOE!G$15+LCOE!I103)*E77*24*365*D77*N77 -> 0 | I77: =LCOE!M103+LCOE!G$20*IF(LCOE!G$14>0,(LCOE!G$14+LCOE!H103),(LCOE!G$15+LCOE!I103))*K77*D77 -> 20000000 | J77: =LCOE!N103+LCOE!G$21*IF(LCOE!G$14>0,G77,H77)*K77*D77 -> 0 | K77: =LCOE!O103+K76+K76*LCOE!G$22 -> 1 | L77: =LCOE!P103+LCOE!G$23*IF(LCOE!G$14>0,G77,H77)*M77*D77 -> 168165720 | M77: =LCOE!Q103+M76+M76*LCOE!G$24 -> 1 | N77: =LCOE!R103+N76-N76*LCOE!G$25 -> 1 | O77: =LCOE!S103+LCOE!G$29 -> 313.75 | P77: =LCOE!T103+IF(A77>=LCOE!G$30,100%,0%) -> 1 | Q77: =LCOE!U103+O77/1000*IF(LCOE!G$14>0,G77,H77) -> 1236802.5 | R77: =LCOE!B103 -> 30 | S77: =LCOE!V103+Q77*P77*R77 -> 37104075 | T77: =LCOE!W103+LCOE!G$31 -> 0 | U77: =LCOE!X103+T77*IF(LCOE!G$14>0,G77,H77) -> 0 | V77: =LCOE!Y103+LCOE!G$32 -> 0 | W77: =LCOE!Z103+V77*IF(LCOE!G$14>0,G77,H77) -> 0 | X77: =LCOE!AA103+LCOE!G$34 -> 101 | Y77: =X77*H77 -> 0 | Z77: =SUM(B77:C77) -> 0 | AA77: =SUM(I77:J77) -> 20000000 | AB77: =L77 -> 168165720 | AC77: =U77+W77 -> 0 | AD77: =S77 -> 37104075 | AE77: =AE76+1*E77 -> 7 | AF77: =LCOE!E103+LCOE!G$40 -> 0.07 | AG77: =(1+AF77)^A77 -> 1.6057815 | AH77: =Z77/AG77 -> 0 | AI77: =AA77/AG77 -> 12454995 | AJ77: =AB77/AG77 -> 1.0472516e+08 | AK77: =AC77/AG77 -> 0 | AL77: =AD77/AG77 -> 23106553 | AM77: =(-1)*Y77/AG77 -> 0 | AN77: =IF(LCOE!G$14>0,G77,H77)/AG77 -> 2454879.5
A78: 8 | C78: =LCOE!G104+IF(AND(LCOE!G$26>0,A78>=LCOE!G$26,A78<=(LCOE!G$26+LCOE!G$27-1)),LCOE!G$42/LCOE!G$27,0)+IF(AND(D78=0,AE78>=LCOE!G$16,COUNTIF(D53:D78,0)=LCOE!G$36),LCOE!G$35*LCOE!G$38,0) -> 0 | D78: =IF(AE77<LCOE!G$16,1,0) -> 1 | E78: =LCOE!G104+IF(AND(A78>=LCOE!G$26,A78<=(LCOE!G$26+LCOE!G$27-1)),0,1)*IF(A78=LCOE!G$34,0,1)*D78 -> 1 | F78: =IF(F77<LCOE!G$18,MIN(F77*(1+LCOE!G$19),LCOE!G$18),LCOE!G$18)+LCOE!J104 -> 0.9 | G78: =LCOE!K104+E78*F78*N78*(LCOE!G$14+LCOE!H104)*24*365*D78 -> 3942000 | H78: =LCOE!L104+F78*(LCOE!G$15+LCOE!I104)*E78*24*365*D78*N78 -> 0 | I78: =LCOE!M104+LCOE!G$20*IF(LCOE!G$14>0,(LCOE!G$14+LCOE!H104),(LCOE!G$15+LCOE!I104))*K78*D78 -> 20000000 | J78: =LCOE!N104+LCOE!G$21*IF(LCOE!G$14>0,G78,H78)*K78*D78 -> 0 | K78: =LCOE!O104+K77+K77*LCOE!G$22 -> 1 | L78: =LCOE!P104+LCOE!G$23*IF(LCOE!G$14>0,G78,H78)*M78*D78 -> 168165720 | M78: =LCOE!Q104+M77+M77*LCOE!G$24 -> 1 | N78: =LCOE!R104+N77-N77*LCOE!G$25 -> 1 | O78: =LCOE!S104+LCOE!G$29 -> 313.75 | P78: =LCOE!T104+IF(A78>=LCOE!G$30,100%,0%) -> 1 | Q78: =LCOE!U104+O78/1000*IF(LCOE!G$14>0,G78,H78) -> 1236802.5 | R78: =LCOE!B104 -> 30 | S78: =LCOE!V104+Q78*P78*R78 -> 37104075 | T78: =LCOE!W104+LCOE!G$31 -> 0 | U78: =LCOE!X104+T78*IF(LCOE!G$14>0,G78,H78) -> 0 | V78: =LCOE!Y104+LCOE!G$32 -> 0 | W78: =LCOE!Z104+V78*IF(LCOE!G$14>0,G78,H78) -> 0 | X78: =LCOE!AA104+LCOE!G$34 -> 101 | Y78: =X78*H78 -> 0 | Z78: =SUM(B78:C78) -> 0 | AA78: =SUM(I78:J78) -> 20000000 | AB78: =L78 -> 168165720 | AC78: =U78+W78 -> 0 | AD78: =S78 -> 37104075 | AE78: =AE77+1*E78 -> 8 | AF78: =LCOE!E104+LCOE!G$40 -> 0.07 | AG78: =(1+AF78)^A78 -> 1.7181862 | AH78: =Z78/AG78 -> 0 | AI78: =AA78/AG78 -> 11640182 | AJ78: =AB78/AG78 -> 97873980 | AK78: =AC78/AG78 -> 0 | AL78: =AD78/AG78 -> 21594909 | AM78: =(-1)*Y78/AG78 -> 0 | AN78: =IF(LCOE!G$14>0,G78,H78)/AG78 -> 2294279.9
A79: 9 | C79: =LCOE!G105+IF(AND(LCOE!G$26>0,A79>=LCOE!G$26,A79<=(LCOE!G$26+LCOE!G$27-1)),LCOE!G$42/LCOE!G$27,0)+IF(AND(D79=0,AE79>=LCOE!G$16,COUNTIF(D54:D79,0)=LCOE!G$36),LCOE!G$35*LCOE!G$38,0) -> 0 | D79: =IF(AE78<LCOE!G$16,1,0) -> 1 | E79: =LCOE!G105+IF(AND(A79>=LCOE!G$26,A79<=(LCOE!G$26+LCOE!G$27-1)),0,1)*IF(A79=LCOE!G$34,0,1)*D79 -> 1 | F79: =IF(F78<LCOE!G$18,MIN(F78*(1+LCOE!G$19),LCOE!G$18),LCOE!G$18)+LCOE!J105 -> 0.9 | G79: =LCOE!K105+E79*F79*N79*(LCOE!G$14+LCOE!H105)*24*365*D79 -> 3942000 | H79: =LCOE!L105+F79*(LCOE!G$15+LCOE!I105)*E79*24*365*D79*N79 -> 0 | I79: =LCOE!M105+LCOE!G$20*IF(LCOE!G$14>0,(LCOE!G$14+LCOE!H105),(LCOE!G$15+LCOE!I105))*K79*D79 -> 20000000 | J79: =LCOE!N105+LCOE!G$21*IF(LCOE!G$14>0,G79,H79)*K79*D79 -> 0 | K79: =LCOE!O105+K78+K78*LCOE!G$22 -> 1 | L79: =LCOE!P105+LCOE!G$23*IF(LCOE!G$14>0,G79,H79)*M79*D79 -> 168165720 | M79: =LCOE!Q105+M78+M78*LCOE!G$24 -> 1 | N79: =LCOE!R105+N78-N78*LCOE!G$25 -> 1 | O79: =LCOE!S105+LCOE!G$29 -> 313.75 | P79: =LCOE!T105+IF(A79>=LCOE!G$30,100%,0%) -> 1 | Q79: =LCOE!U105+O79/1000*IF(LCOE!G$14>0,G79,H79) -> 1236802.5 | R79: =LCOE!B105 -> 30 | S79: =LCOE!V105+Q79*P79*R79 -> 37104075 | T79: =LCOE!W105+LCOE!G$31 -> 0 | U79: =LCOE!X105+T79*IF(LCOE!G$14>0,G79,H79) -> 0 | V79: =LCOE!Y105+LCOE!G$32 -> 0 | W79: =LCOE!Z105+V79*IF(LCOE!G$14>0,G79,H79) -> 0 | X79: =LCOE!AA105+LCOE!G$34 -> 101 | Y79: =X79*H79 -> 0 | Z79: =SUM(B79:C79) -> 0 | AA79: =SUM(I79:J79) -> 20000000 | AB79: =L79 -> 168165720 | AC79: =U79+W79 -> 0 | AD79: =S79 -> 37104075 | AE79: =AE78+1*E79 -> 9 | AF79: =LCOE!E105+LCOE!G$40 -> 0.07 | AG79: =(1+AF79)^A79 -> 1.8384592 | AH79: =Z79/AG79 -> 0 | AI79: =AA79/AG79 -> 10878675 | AJ79: =AB79/AG79 -> 91471009 | AK79: =AC79/AG79 -> 0 | AL79: =AD79/AG79 -> 20182158 | AM79: =(-1)*Y79/AG79 -> 0 | AN79: =IF(LCOE!G$14>0,G79,H79)/AG79 -> 2144186.8
A80: 10 | C80: =LCOE!G106+IF(AND(LCOE!G$26>0,A80>=LCOE!G$26,A80<=(LCOE!G$26+LCOE!G$27-1)),LCOE!G$42/LCOE!G$27,0)+IF(AND(D80=0,AE80>=LCOE!G$16,COUNTIF(D55:D80,0)=LCOE!G$36),LCOE!G$35*LCOE!G$38,0) -> 0 | D80: =IF(AE79<LCOE!G$16,1,0) -> 1 | E80: =LCOE!G106+IF(AND(A80>=LCOE!G$26,A80<=(LCOE!G$26+LCOE!G$27-1)),0,1)*IF(A80=LCOE!G$34,0,1)*D80 -> 1 | F80: =IF(F79<LCOE!G$18,MIN(F79*(1+LCOE!G$19),LCOE!G$18),LCOE!G$18)+LCOE!J106 -> 0.9 | G80: =LCOE!K106+E80*F80*N80*(LCOE!G$14+LCOE!H106)*24*365*D80 -> 3942000 | H80: =LCOE!L106+F80*(LCOE!G$15+LCOE!I106)*E80*24*365*D80*N80 -> 0 | I80: =LCOE!M106+LCOE!G$20*IF(LCOE!G$14>0,(LCOE!G$14+LCOE!H106),(LCOE!G$15+LCOE!I106))*K80*D80 -> 20000000 | J80: =LCOE!N106+LCOE!G$21*IF(LCOE!G$14>0,G80,H80)*K80*D80 -> 0 | K80: =LCOE!O106+K79+K79*LCOE!G$22 -> 1 | L80: =LCOE!P106+LCOE!G$23*IF(LCOE!G$14>0,G80,H80)*M80*D80 -> 168165720 | M80: =LCOE!Q106+M79+M79*LCOE!G$24 -> 1 | N80: =LCOE!R106+N79-N79*LCOE!G$25 -> 1 | O80: =LCOE!S106+LCOE!G$29 -> 313.75 | P80: =LCOE!T106+IF(A80>=LCOE!G$30,100%,0%) -> 1 | Q80: =LCOE!U106+O80/1000*IF(LCOE!G$14>0,G80,H80) -> 1236802.5 | R80: =LCOE!B106 -> 30 | S80: =LCOE!V106+Q80*P80*R80 -> 37104075 | T80: =LCOE!W106+LCOE!G$31 -> 0 | U80: =LCOE!X106+T80*IF(LCOE!G$14>0,G80,H80) -> 0 | V80: =LCOE!Y106+LCOE!G$32 -> 0 | W80: =LCOE!Z106+V80*IF(LCOE!G$14>0,G80,H80) -> 0 | X80: =LCOE!AA106+LCOE!G$34 -> 101 | Y80: =X80*H80 -> 0 | Z80: =SUM(B80:C80) -> 0 | AA80: =SUM(I80:J80) -> 20000000 | AB80: =L80 -> 168165720 | AC80: =U80+W80 -> 0 | AD80: =S80 -> 37104075 | AE80: =AE79+1*E80 -> 10 | AF80: =LCOE!E106+LCOE!G$40 -> 0.07 | AG80: =(1+AF80)^A80 -> 1.9671514 | AH80: =Z80/AG80 -> 0 | AI80: =AA80/AG80 -> 10166986 | AJ80: =AB80/AG80 -> 85486925 | AK80: =AC80/AG80 -> 0 | AL80: =AD80/AG80 -> 18861830 | AM80: =(-1)*Y80/AG80 -> 0 | AN80: =IF(LCOE!G$14>0,G80,H80)/AG80 -> 2003912.9
A81: 11 | C81: =LCOE!G107+IF(AND(LCOE!G$26>0,A81>=LCOE!G$26,A81<=(LCOE!G$26+LCOE!G$27-1)),LCOE!G$42/LCOE!G$27,0)+IF(AND(D81=0,AE81>=LCOE!G$16,COUNTIF(D56:D81,0)=LCOE!G$36),LCOE!G$35*LCOE!G$38,0) -> 0 | D81: =IF(AE80<LCOE!G$16,1,0) -> 1 | E81: =LCOE!G107+IF(AND(A81>=LCOE!G$26,A81<=(LCOE!G$26+LCOE!G$27-1)),0,1)*IF(A81=LCOE!G$34,0,1)*D81 -> 1 | F81: =IF(F80<LCOE!G$18,MIN(F80*(1+LCOE!G$19),LCOE!G$18),LCOE!G$18)+LCOE!J107 -> 0.9 | G81: =LCOE!K107+E81*F81*N81*(LCOE!G$14+LCOE!H107)*24*365*D81 -> 3942000 | H81: =LCOE!L107+F81*(LCOE!G$15+LCOE!I107)*E81*24*365*D81*N81 -> 0 | I81: =LCOE!M107+LCOE!G$20*IF(LCOE!G$14>0,(LCOE!G$14+LCOE!H107),(LCOE!G$15+LCOE!I107))*K81*D81 -> 20000000 | J81: =LCOE!N107+LCOE!G$21*IF(LCOE!G$14>0,G81,H81)*K81*D81 -> 0 | K81: =LCOE!O107+K80+K80*LCOE!G$22 -> 1 | L81: =LCOE!P107+LCOE!G$23*IF(LCOE!G$14>0,G81,H81)*M81*D81 -> 168165720 | M81: =LCOE!Q107+M80+M80*LCOE!G$24 -> 1 | N81: =LCOE!R107+N80-N80*LCOE!G$25 -> 1 | O81: =LCOE!S107+LCOE!G$29 -> 313.75 | P81: =LCOE!T107+IF(A81>=LCOE!G$30,100%,0%) -> 1 | Q81: =LCOE!U107+O81/1000*IF(LCOE!G$14>0,G81,H81) -> 1236802.5 | R81: =LCOE!B107 -> 30 | S81: =LCOE!V107+Q81*P81*R81 -> 37104075 | T81: =LCOE!W107+LCOE!G$31 -> 0 | U81: =LCOE!X107+T81*IF(LCOE!G$14>0,G81,H81) -> 0 | V81: =LCOE!Y107+LCOE!G$32 -> 0 | W81: =LCOE!Z107+V81*IF(LCOE!G$14>0,G81,H81) -> 0 | X81: =LCOE!AA107+LCOE!G$34 -> 101 | Y81: =X81*H81 -> 0 | Z81: =SUM(B81:C81) -> 0 | AA81: =SUM(I81:J81) -> 20000000 | AB81: =L81 -> 168165720 | AC81: =U81+W81 -> 0 | AD81: =S81 -> 37104075 | AE81: =AE80+1*E81 -> 11 | AF81: =LCOE!E107+LCOE!G$40 -> 0.07 | AG81: =(1+AF81)^A81 -> 2.104852 | AH81: =Z81/AG81 -> 0 | AI81: =AA81/AG81 -> 9501855.9 | AJ81: =AB81/AG81 -> 79894322 | AK81: =AC81/AG81 -> 0 | AL81: =AD81/AG81 -> 17627879 | AM81: =(-1)*Y81/AG81 -> 0 | AN81: =IF(LCOE!G$14>0,G81,H81)/AG81 -> 1872815.8
A82: 12 | C82: =LCOE!G108+IF(AND(LCOE!G$26>0,A82>=LCOE!G$26,A82<=(LCOE!G$26+LCOE!G$27-1)),LCOE!G$42/LCOE!G$27,0)+IF(AND(D82=0,AE82>=LCOE!G$16,COUNTIF(D57:D82,0)=LCOE!G$36),LCOE!G$35*LCOE!G$38,0) -> 0 | D82: =IF(AE81<LCOE!G$16,1,0) -> 1 | E82: =LCOE!G108+IF(AND(A82>=LCOE!G$26,A82<=(LCOE!G$26+LCOE!G$27-1)),0,1)*IF(A82=LCOE!G$34,0,1)*D82 -> 1 | F82: =IF(F81<LCOE!G$18,MIN(F81*(1+LCOE!G$19),LCOE!G$18),LCOE!G$18)+LCOE!J108 -> 0.9 | G82: =LCOE!K108+E82*F82*N82*(LCOE!G$14+LCOE!H108)*24*365*D82 -> 3942000 | H82: =LCOE!L108+F82*(LCOE!G$15+LCOE!I108)*E82*24*365*D82*N82 -> 0 | I82: =LCOE!M108+LCOE!G$20*IF(LCOE!G$14>0,(LCOE!G$14+LCOE!H108),(LCOE!G$15+LCOE!I108))*K82*D82 -> 20000000 | J82: =LCOE!N108+LCOE!G$21*IF(LCOE!G$14>0,G82,H82)*K82*D82 -> 0 | K82: =LCOE!O108+K81+K81*LCOE!G$22 -> 1 | L82: =LCOE!P108+LCOE!G$23*IF(LCOE!G$14>0,G82,H82)*M82*D82 -> 168165720 | M82: =LCOE!Q108+M81+M81*LCOE!G$24 -> 1 | N82: =LCOE!R108+N81-N81*LCOE!G$25 -> 1 | O82: =LCOE!S108+LCOE!G$29 -> 313.75 | P82: =LCOE!T108+IF(A82>=LCOE!G$30,100%,0%) -> 1 | Q82: =LCOE!U108+O82/1000*IF(LCOE!G$14>0,G82,H82) -> 1236802.5 | R82: =LCOE!B108 -> 30 | S82: =LCOE!V108+Q82*P82*R82 -> 37104075 | T82: =LCOE!W108+LCOE!G$31 -> 0 | U82: =LCOE!X108+T82*IF(LCOE!G$14>0,G82,H82) -> 0 | V82: =LCOE!Y108+LCOE!G$32 -> 0 | W82: =LCOE!Z108+V82*IF(LCOE!G$14>0,G82,H82) -> 0 | X82: =LCOE!AA108+LCOE!G$34 -> 101 | Y82: =X82*H82 -> 0 | Z82: =SUM(B82:C82) -> 0 | AA82: =SUM(I82:J82) -> 20000000 | AB82: =L82 -> 168165720 | AC82: =U82+W82 -> 0 | AD82: =S82 -> 37104075 | AE82: =AE81+1*E82 -> 12 | AF82: =LCOE!E108+LCOE!G$40 -> 0.07 | AG82: =(1+AF82)^A82 -> 2.2521916 | AH82: =Z82/AG82 -> 0 | AI82: =AA82/AG82 -> 8880239.2 | AJ82: =AB82/AG82 -> 74667591 | AK82: =AC82/AG82 -> 0 | AL82: =AD82/AG82 -> 16474653 | AM82: =(-1)*Y82/AG82 -> 0 | AN82: =IF(LCOE!G$14>0,G82,H82)/AG82 -> 1750295.1
... A170: 100 | C170: =LCOE!G196+IF(AND(LCOE!G$26>0,A170>=LCOE!G$26,A170<=(LCOE!G$26+LCOE!G$27-1)),LCOE!G$42/LCOE!G$27,0)+IF(AND(D170=0,AE170>=LCOE!G$16,COUNTIF(D145:D170,0)=LCOE!G$36),LCOE!G$35*LCOE!G$38,0) -> 0 | D170: =IF(AE169<LCOE!G$16,1,0) -> 0 | E170: =LCOE!G196+IF(AND(A170>=LCOE!G$26,A170<=(LCOE!G$26+LCOE!G$27-1)),0,1)*IF(A170=LCOE!G$34,0,1)*D170 -> 0 | F170: =IF(F169<LCOE!G$18,MIN(F169*(1+LCOE!G$19),LCOE!G$18),LCOE!G$18)+LCOE!J196 -> 0.9 | G170: =LCOE!K196+E170*F170*N170*(LCOE!G$14+LCOE!H196)*24*365*D170 -> 0 | H170: =LCOE!L196+F170*(LCOE!G$15+LCOE!I196)*E170*24*365*D170*N170 -> 0 | I170: =LCOE!M196+LCOE!G$20*IF(LCOE!G$14>0,(LCOE!G$14+LCOE!H196),(LCOE!G$15+LCOE!I196))*K170*D170 -> 0 | J170: =LCOE!N196+LCOE!G$21*IF(LCOE!G$14>0,G170,H170)*K170*D170 -> 0 | K170: =LCOE!O196+K169+K169*LCOE!G$22 -> 1 | L170: =LCOE!P196+LCOE!G$23*IF(LCOE!G$14>0,G170,H170)*M170*D170 -> 0 | M170: =LCOE!Q196+M169+M169*LCOE!G$24 -> 1 | N170: =LCOE!R196+N169-N169*LCOE!G$25 -> 1 | O170: =LCOE!S196+LCOE!G$29 -> 313.75 | P170: =LCOE!T196+IF(A170>=LCOE!G$30,100%,0%) -> 1 | Q170: =LCOE!U196+O170/1000*IF(LCOE!G$14>0,G170,H170) -> 0 | R170: =LCOE!B196 -> 30 | S170: =LCOE!V196+Q170*P170*R170 -> 0 | T170: =LCOE!W196+LCOE!G$31 -> 0 | U170: =LCOE!X196+T170*IF(LCOE!G$14>0,G170,H170) -> 0 | V170: =LCOE!Y196+LCOE!G$32 -> 0 | W170: =LCOE!Z196+V170*IF(LCOE!G$14>0,G170,H170) -> 0 | X170: =LCOE!AA196+LCOE!G$34 -> 101 | Y170: =X170*H170 -> 0 | Z170: =SUM(B170:C170) -> 0 | AA170: =SUM(I170:J170) -> 0 | AB170: =L170 -> 0 | AC170: =U170+W170 -> 0 | AD170: =S170 -> 0 | AE170: =AE169+1*E170 -> 30 | AF170: =LCOE!E196+LCOE!G$40 -> 0.07 | AG170: =(1+AF170)^A170 -> 867.71633 | AH170: =Z170/AG170 -> 0 | AI170: =AA170/AG170 -> 0 | AJ170: =AB170/AG170 -> 0 | AK170: =AC170/AG170 -> 0 | AL170: =AD170/AG170 -> 0 | AM170: =(-1)*Y170/AG170 -> 0 | AN170: =IF(LCOE!G$14>0,G170,H170)/AG170 -> 0

Sheet LCOE 5
B2: Parameter recap (not used in calcs) | C2: =LCOE!H3 -> LCOE 5 | F2: RESULTS | G2: =C4 -> USD | I2: =C6 -> USD
B3: =LCOE!C5 -> Name | C3: =LCOE!H5 -> CCGT in Belgium (2020) | F3: =LCOE!C46 -> LCOE (LCOHeat for pure heat plants) | G3: =SUM(AH45:AM170)/SUM(AN45:AN170) -> 69.460824 | H3: =_xlfn.CONCAT(C$4,"/MWh") -> USD/MWh | I3: =G3*C$7 -> 69.460824 | J3: =_xlfn.CONCAT(C$6,"/MWh") -> USD/MWh
B4: =LCOE!C6 -> Currency used for LCOE calculations | C4: =LCOE!H6 -> USD | F4: =LCOE!C47 -> Of which: Capital costs | G4: =SUM(AH45:AH170)/SUM(AN45:AN170) -> 12.014364 | H4: =_xlfn.CONCAT(C$4,"/MWh") -> USD/MWh | I4: =G4*C$7 -> 12.014364 | J4: =_xlfn.CONCAT(C$6,"/MWh") -> USD/MWh
B5: =LCOE!C7 -> Price reference year | C5: =LCOE!H7 -> 0 | F5: =LCOE!C48 -> O&M | G5: =SUM(AI45:AI170)/SUM(AN45:AN170) -> 5.3739602 | H5: =_xlfn.CONCAT(C$4,"/MWh") -> USD/MWh | I5: =G5*C$7 -> 5.3739602 | J5: =_xlfn.CONCAT(C$6,"/MWh") -> USD/MWh
B6: =LCOE!C8 -> Currency used | C6: =LCOE!H8 -> USD | F6: =LCOE!C49 -> Fuel | G6: =SUM(AJ45:AJ170)/SUM(AN45:AN170) -> 42.66 | H6: =_xlfn.CONCAT(C$4,"/MWh") -> USD/MWh | I6: =G6*C$7 -> 42.66 | J6: =_xlfn.CONCAT(C$6,"/MWh") -> USD/MWh
B7: =LCOE!C9 -> Conversion rate at reference year | C7: =LCOE!H9 -> 1 | F7: =LCOE!C50 -> Taxes and fees | G7: =SUM(AK45:AK170)/SUM(AN45:AN170) -> 0 | H7: =_xlfn.CONCAT(C$4,"/MWh") -> USD/MWh | I7: =G7*C$7 -> 0 | J7: =_xlfn.CONCAT(C$6,"/MWh") -> USD/MWh
B8: =LCOE!C10 -> Debt % | C8: =LCOE!H10 -> 0.9 | F8: =LCOE!C51 -> Emission costs | G8: =SUM(AL45:AL170)/SUM(AN45:AN170) -> 9.4125 | H8: =_xlfn.CONCAT(C$4,"/MWh") -> USD/MWh | I8: =G8*C$7 -> 9.4125 | J8: =_xlfn.CONCAT(C$6,"/MWh") -> USD/MWh
B9: =LCOE!C11 -> Cost of debt (private discount rate) | C9: =LCOE!H11 -> 0.08 | F9: =LCOE!C52 -> Heat credit (for CHP plants) | G9: =IF(C15>0,SUM(AM45:AM170)/SUM(AN45:AN170),0) -> 0 | H9: =_xlfn.CONCAT(C$4,"/MWh") -> USD/MWh | I9: =G9*C$7 -> 0 | J9: =_xlfn.CONCAT(C$6,"/MWh") -> USD/MWh
B10: =LCOE!C12 -> Cost of equity (discount rate) | C10: =LCOE!H12 -> 0.08 | F10: =LCOE!C53 -> WACC average over lifetime | G10: =AVERAGE(AF70:AF170) -> 0.08 | I10: =G10 -> 0.08
B11: =LCOE!C13 -> Construction cost per kW | C11: =LCOE!H13 -> 1009 | F11: =LCOE!C54 -> Plant type | G11: =IF(AND(LCOE!H$14>0,LCOE!H$15=0),"Electric only",IF(AND(LCOE!H$14>0,LCOE!H$15>0),"CHP",IF(AND(LCOE!H$14=0,LCOE!H$15>0),"Heat only","Error: no generation"))) -> Electric only | I11: =G11 -> Electric only
B12: =LCOE!C14 -> Maximum electric power, in MW_e | C12: =LCOE!H14 -> 500
B13: =LCOE!C15 -> Maximum heat power, in MW_h | C13: =LCOE!H15 -> 0
B14: =LCOE!C16 -> Plant lifetime | C14: =LCOE!H16 -> 30
B15: =LCOE!C17 -> Construction period, years | C15: =LCOE!H17 -> 3
B16: =LCOE!C18 -> Capacity factor (settled down) | C16: =LCOE!H18 -> 0.9
B17: =LCOE!C19 -> Capacity factor ramp-up on startup, per year | C17: =LCOE!H19 -> 0.6
B18: =LCOE!C20 -> Fixed OPEX/MW capacity at project start | C18: =LCOE!H20 -> 40000
B19: =LCOE!C21 -> Variable OPEX/MWh produced at project start | C19: =LCOE!H21 -> 0
B20: =LCOE!C22 -> OPEX escalator | C20: =LCOE!H22 -> 0
B21: =LCOE!C23 -> FUELEX/MWh produced at project start | C21: =LCOE!H23 -> 42.66
B22: =LCOE!C24 -> FUELEX escalator | C22: =LCOE!H24 -> 0
B23: =LCOE!C25 -> Efficiency loss/year | C23: =LCOE!H25 -> 0
... B41: =LCOE!C43 -> Overrides | C41: =LCOE!H43 -> 0
Z43: SUMMARY OF COSTS
A44: Year (t) | B44: CAPEXconstr | C44: CAPEXrefurb/decom | D44: Lifetime left? | E44: Operational% | F44: Capacity factor | G44: Electricity produced (MWh_e) | H44: Heat produced (MWh_h) | I44: Fixed OPEX | J44: Variable OPEX | K44: OPEX relative to startup | L44: FUELEX | M44: FUELEX relative to startup | N44: Efficiency relative to startup | O44: Total emission factor, gCO2/kWh | P44: % of emissions taxed | Q44: Total emissions, tCO2e | R44: Cost of tCO2e | S44: Cost of emissions levied, E | T44: Tax per MWh produced | U44: Taxes levied | V44: Waste fee per MWh produced | W44: Waste fee levied | X44: Heat credit per MWh_h | Y44: Heat credit total | Z44: Total capital expenditure, I | AA44: Total operation and maintenance expenditure, M | AB44: Total fuel expenditure, F | AC44: Total taxes, T | AD44: Total emission fees, E | AE44: Lifetime expended at start of year | AF44: Discount rate r (IDC when t<0) | AG44: Discount factor (1+r)^t | AH44: I discounted | AI44: M discounted | AJ44: F discounted | AK44: T discounted | AL44: E discounted | AM44: Heat credit, discounted | AN44: Production (MWh), discounted
A45: -25 | B45: =LCOE!C71+IF(A45>=((LCOE!H$17*-1)+1),LCOE!H$38/LCOE!H$17,0) -> 0 | Z45: =SUM(B45:C45) -> 0 | AA45: =SUM(I45:J45) -> 0 | AB45: =L45 -> 0 | AC45: =SUM(S45:W45) -> 0 | AD45: =S45 -> 0 | AE45: -25 | AF45: =LCOE!E71+LCOE!H$40 -> 0.08 | AG45: =(1+AF45)^A45 -> 0.1460179 | AH45: =Z45/AG45 -> 0 | AI45: =AA45/AG45 -> 0 | AJ45: =AB45/AG45 -> 0 | AK45: =AC45/AG45 -> 0 | AL45: =AD45/AG45 -> 0
A46: -24 | B46: =LCOE!C72+IF(A46>=((LCOE!H$17*-1)+1),LCOE!H$38/LCOE!H$17,0) -> 0 | Z46: =SUM(B46:C46) -> 0 | AA46: =SUM(I46:J46) -> 0 | AB46: =L46 -> 0 | AC46: =SUM(S46:W46) -> 0 | AD46: =S46 -> 0 | AE46: -24 | AF46: =LCOE!E72+LCOE!H$40 -> 0.08 | AG46: =(1+AF46)^A46 -> 0.15769934 | AH46: =Z46/AG46 -> 0 | AI46: =AA46/AG46 -> 0 | AJ46: =AB46/AG46 -> 0 | AK46: =AC46/AG46 -> 0 | AL46: =AD46/AG46 -> 0
A47: -23 | B47: =LCOE!C73+IF(A47>=((LCOE!H$17*-1)+1),LCOE!H$38/LCOE!H$17,0) -> 0 | Z47: =SUM(B47:C47) -> 0 | AA47: =SUM(I47:J47) -> 0 | AB47: =L47 -> 0 | AC47: =SUM(S47:W47) -> 0 | AD47: =S47 -> 0 | AE47: -23 | AF47: =LCOE!E73+LCOE!H$40 -> 0.08 | AG47: =(1+AF47)^A47 -> 0.17031528 | AH47: =Z47/AG47 -> 0 | AI47: =AA47/AG47 -> 0 | AJ47: =AB47/AG47 -> 0 | AK47: =AC47/AG47 -> 0 | AL47: =AD47/AG47 -> 0
A48: -22 | B48: =LCOE!C74+IF(A48>=((LCOE!H$17*-1)+1),LCOE!H$38/LCOE!H$17,0) -> 0 | Z48: =SUM(B48:C48) -> 0 | AA48: =SUM(I48:J48) -> 0 | AB48: =L48 -> 0 | AC48: =SUM(S48:W48) -> 0 | AD48: =S48 -> 0 | AE48: -22 | AF48: =LCOE!E74+LCOE!H$40 -> 0.08 | AG48: =(1+AF48)^A48 -> 0.18394051 | AH48: =Z48/AG48 -> 0 | AI48: =AA48/AG48 -> 0 | AJ48: =AB48/AG48 -> 0 | AK48: =AC48/AG48 -> 0 | AL48: =AD48/AG48 -> 0
A49: -21 | B49: =LCOE!C75+IF(A49>=((LCOE!H$17*-1)+1),LCOE!H$38/LCOE!H$17,0) -> 0 | Z49: =SUM(B49:C49) -> 0 | AA49: =SUM(I49:J49) -> 0 | AB49: =L49 -> 0 | AC49: =SUM(S49:W49) -> 0 | AD49: =S49 -> 0 | AE49: -21 | AF49: =LCOE!E75+LCOE!H$40 -> 0.08 | AG49: =(1+AF49)^A49 -> 0.19865575 | AH49: =Z49/AG49 -> 0 | AI49: =AA49/AG49 -> 0 | AJ49: =AB49/AG49 -> 0 | AK49: =AC49/AG49 -> 0 | AL49: =AD49/AG49 -> 0
A50: -20 | B50: =LCOE!C76+IF(A50>=((LCOE!H$17*-1)+1),LCOE!H$38/LCOE!H$17,0) -> 0 | Z50: =SUM(B50:C50) -> 0 | AA50: =SUM(I50:J50) -> 0 | AB50: =L50 -> 0 | AC50: =SUM(S50:W50) -> 0 | AD50: =S50 -> 0 | AE50: -20 | AF50: =LCOE!E76+LCOE!H$40 -> 0.08 | AG50: =(1+AF50)^A50 -> 0.21454821 | AH50: =Z50/AG50 -> 0 | AI50: =AA50/AG50 -> 0 | AJ50: =AB50/AG50 -> 0 | AK50: =AC50/AG50 -> 0 | AL50: =AD50/AG50 -> 0
A51: -19 | B51: =LCOE!C77+IF(A51>=((LCOE!H$17*-1)+1),LCOE!H$38/LCOE!H$17,0) -> 0 | Z51: =SUM(B51:C51) -> 0 | AA51: =SUM(I51:J51) -> 0 | AB51: =L51 -> 0 | AC51: =SUM(S51:W51) -> 0 | AD51: =S51 -> 0 | AE51: -19 | AF51: =LCOE!E77+LCOE!H$40 -> 0.08 | AG51: =(1+AF51)^A51 -> 0.23171206 | AH51: =Z51/AG51 -> 0 | AI51: =AA51/AG51 -> 0 | AJ51: =AB51/AG51 -> 0 | AK51: =AC51/AG51 -> 0 | AL51: =AD51/AG51 -> 0
A52: -18 | B52: =LCOE!C78+IF(A52>=((LCOE!H$17*-1)+1),LCOE!H$38/LCOE!H$17,0) -> 0 | Z52: =SUM(B52:C52) -> 0 | AA52: =SUM(I52:J52) -> 0 | AB52: =L52 -> 0 | AC52: =SUM(S52:W52) -> 0 | AD52: =S52 -> 0 | AE52: -18 | AF52: =LCOE!E78+LCOE!H$40 -> 0.08 | AG52: =(1+AF52)^A52 -> 0.25024903 | AH52: =Z52/AG52 -> 0 | AI52: =AA52/AG52 -> 0 | AJ52: =AB52/AG52 -> 0 | AK52: =AC52/AG52 -> 0 | AL52: =AD52/AG52 -> 0
A53: -17 | B53: =LCOE!C79+IF(A53>=((LCOE!H$17*-1)+1),LCOE!H$38/LCOE!H$17,0) -> 0 | Z53: =SUM(B53:C53) -> 0 | AA53: =SUM(I53:J53) -> 0 | AB53: =L53 -> 0 | AC53: =SUM(S53:W53) -> 0 | AD53: =S53 -> 0 | AE53: -17 | AF53: =LCOE!E79+LCOE!H$40 -> 0.08 | AG53: =(1+AF53)^A53 -> 0.27026895 | AH53: =Z53/AG53 -> 0 | AI53: =AA53/AG53 -> 0 | AJ53: =AB53/AG53 -> 0 | AK53: =AC53/AG53 -> 0 | AL53: =AD53/AG53 -> 0
A54: -16 | B54: =LCOE!C80+IF(A54>=((LCOE!H$17*-1)+1),LCOE!H$38/LCOE!H$17,0) -> 0 | Z54: =SUM(B54:C54) -> 0 | AA54: =SUM(I54:J54) -> 0 | AB54: =L54 -> 0 | AC54: =SUM(S54:W54) -> 0 | AD54: =S54 -> 0 | AE54: -16 | AF54: =LCOE!E80+LCOE!H$40 -> 0.08 | AG54: =(1+AF54)^A54 -> 0.29189047 | AH54: =Z54/AG54 -> 0 | AI54: =AA54/AG54 -> 0 | AJ54: =AB54/AG54 -> 0 | AK54: =AC54/AG54 -> 0 | AL54: =AD54/AG54 -> 0
A55: -15 | B55: =LCOE!C81+IF(A55>=((LCOE!H$17*-1)+1),LCOE!H$38/LCOE!H$17,0) -> 0 | Z55: =SUM(B55:C55) -> 0 | AA55: =SUM(I55:J55) -> 0 | AB55: =L55 -> 0 | AC55: =SUM(S55:W55) -> 0 | AD55: =S55 -> 0 | AE55: -15 | AF55: =LCOE!E81+LCOE!H$40 -> 0.08 | AG55: =(1+AF55)^A55 -> 0.3152417 | AH55: =Z55/AG55 -> 0 | AI55: =AA55/AG55 -> 0 | AJ55: =AB55/AG55 -> 0 | AK55: =AC55/AG55 -> 0 | AL55: =AD55/AG55 -> 0
A56: -14 | B56: =LCOE!C82+IF(A56>=((LCOE!H$17*-1)+1),LCOE!H$38/LCOE!H$17,0) -> 0 | Z56: =SUM(B56:C56) -> 0 | AA56: =SUM(I56:J56) -> 0 | AB56: =L56 -> 0 | AC56: =SUM(S56:W56) -> 0 | AD56: =S56 -> 0 | AE56: -14 | AF56: =LCOE!E82+LCOE!H$40 -> 0.08 | AG56: =(1+AF56)^A56 -> 0.34046104 | AH56: =Z56/AG56 -> 0 | AI56: =AA56/AG56 -> 0 | AJ56: =AB56/AG56 -> 0 | AK56: =AC56/AG56 -> 0 | AL56: =AD56/AG56 -> 0
... A69: -1 | B69: =LCOE!C95+IF(A69>=((LCOE!H$17*-1)+1),LCOE!H$38/LCOE!H$17,0) -> 1.6816667e+08 | Z69: =SUM(B69:C69) -> 1.6816667e+08 | AA69: =SUM(I69:J69) -> 0 | AB69: =L69 -> 0 | AC69: =SUM(S69:W69) -> 0 | AD69: =S69 -> 0 | AE69: -1 | AF69: =LCOE!E95+LCOE!H$40 -> 0.08 | AG69: =(1+AF69)^A69 -> 0.92592593 | AH69: =Z69/AG69 -> 181620000 | AI69: =AA69/AG69 -> 0 | AJ69: =AB69/AG69 -> 0 | AK69: =AC69/AG69 -> 0 | AL69: =AD69/AG69 -> 0
A70: 0 | B70: =LCOE!C96+IF(A70>=((LCOE!H$17*-1)+1),LCOE!H$38/LCOE!H$17,0) -> 1.6816667e+08 | C70: =LCOE!H96+IF(AND(LCOE!H$26>0,A70>=LCOE!H$26,A70<=(LCOE!H$26+LCOE!H$27-1)),LCOE!H$42/LCOE!H$27,0)+IF(AND(D70=0,AE70>=LCOE!H$16,COUNTIF(D45:D70,0)=LCOE!H$36),LCOE!H$35*LCOE!H$38,0) -> 0 | D70: =IF(AE69<LCOE!H$16,1,0) -> 1 | E70: =LCOE!G96+IF(AND(A70>=LCOE!H$26,A70<=(LCOE!H$26+LCOE!H$27-1)),0,1)*IF(A70=LCOE!H$34,0,1)*D70 -> 1 | F70: =LCOE!H$18*50%+LCOE!J96 -> 0.45 | G70: =LCOE!K96+E70*F70*N70*(LCOE!H$14+LCOE!H96)*24*365*D70 -> 1971000 | H70: =LCOE!L96+F70*(LCOE!H$15+LCOE!I96)*E70*24*365*D70*N70 -> 0 | I70: =LCOE!M96+LCOE!H$20*IF(LCOE!H$14>0,(LCOE!H$14+LCOE!H96),(LCOE!H$15+LCOE!I96))*K70*D70 -> 20000000 | J70: =LCOE!N96+LCOE!H$21*IF(LCOE!H$14>0,G70,H70)*K70*D70 -> 0 | K70: =LCOE!O96+100% -> 1 | L70: =LCOE!P96+LCOE!H$23*IF(LCOE!H$14>0,G70,H70)*M70*D70 -> 84082860 | M70: =LCOE!Q96+100% -> 1 | N70: =LCOE!R96+100% -> 1 | O70: =LCOE!S96+LCOE!H$29 -> 313.75 | P70: =LCOE!T96+IF(A70>=LCOE!H$30,100%,0%) -> 1 | Q70: =LCOE!U96+O70/1000*IF(LCOE!H$14>0,G70,H70) -> 618401.25 | R70: =LCOE!B96 -> 30 | S70: =LCOE!V96+Q70*P70*R70 -> 18552038 | T70: =LCOE!W96+LCOE!H$31 -> 0 | U70: =LCOE!X96+T70*IF(LCOE!H$14>0,G70,H70) -> 0 | V70: =LCOE!Y96+LCOE!H$32 -> 0 | W70: =LCOE!Z96+V70*IF(LCOE!H$14>0,G70,H70) -> 0 | X70: =LCOE!AA96+LCOE!H$34 -> 101 | Y70: =X70*H70 -> 0 | Z70: =SUM(B70:C70) -> 1.6816667e+08 | AA70: =SUM(I70:J70) -> 20000000 | AB70: =L70 -> 84082860 | AC70: =U70+W70 -> 0 | AD70: =S70 -> 18552038 | AE70: 0 | AF70: =LCOE!E96+LCOE!H$40 -> 0.08 | AG70: =(1+AF70)^A70 -> 1 | AH70: =Z70/AG70 -> 1.6816667e+08 | AI70: =AA70/AG70 -> 20000000 | AJ70: =AB70/AG70 -> 84082860 | AK70: =AC70/AG70 -> 0 | AL70: =AD70/AG70 -> 18552038 | AM70: =(-1)*Y70/AG70 -> 0 | AN70: =IF(LCOE!H$14>0,G70,H70)/AG70 -> 1971000
A71: 1 | C71: =LCOE!H97+IF(AND(LCOE!H$26>0,A71>=LCOE!H$26,A71<=(LCOE!H$26+LCOE!H$27-1)),LCOE!H$42/LCOE!H$27,0)+IF(AND(D71=0,AE71>=LCOE!H$16,COUNTIF(D46:D71,0)=LCOE!H$36),LCOE!H$35*LCOE!H$38,0) -> 0 | D71: =IF(AE70<LCOE!H$16,1,0) -> 1 | E71: =LCOE!G97+IF(AND(A71>=LCOE!H$26,A71<=(LCOE!H$26+LCOE!H$27-1)),0,1)*IF(A71=LCOE!H$34,0,1)*D71 -> 1 | F71: =IF(F70<LCOE!H$18,MIN(F70*(1+LCOE!H$19),LCOE!H$18),LCOE!H$18)+LCOE!J97 -> 0.72 | G71: =LCOE!K97+E71*F71*N71*(LCOE!H$14+LCOE!H97)*24*365*D71 -> 3153600 | H71: =LCOE!L97+F71*(LCOE!H$15+LCOE!I97)*E71*24*365*D71*N71 -> 0 | I71: =LCOE!M97+LCOE!H$20*IF(LCOE!H$14>0,(LCOE!H$14+LCOE!H97),(LCOE!H$15+LCOE!I97))*K71*D71 -> 20000000 | J71: =LCOE!N97+LCOE!H$21*IF(LCOE!H$14>0,G71,H71)*K71*D71 -> 0 | K71: =LCOE!O97+K70+K70*LCOE!H$22 -> 1 | L71: =LCOE!P97+LCOE!H$23*IF(LCOE!H$14>0,G71,H71)*M71*D71 -> 134532576 | M71: =LCOE!Q97+M70+M70*LCOE!H$24 -> 1 | N71: =LCOE!R97+N70-N70*LCOE!H$25 -> 1 | O71: =LCOE!S97+LCOE!H$29 -> 313.75 | P71: =LCOE!T97+IF(A71>=LCOE!H$30,100%,0%) -> 1 | Q71: =LCOE!U97+O71/1000*IF(LCOE!H$14>0,G71,H71) -> 989442 | R71: =LCOE!B97 -> 30 | S71: =LCOE!V97+Q71*P71*R71 -> 29683260 | T71: =LCOE!W97+LCOE!H$31 -> 0 | U71: =LCOE!X97+T71*IF(LCOE!H$14>0,G71,H71) -> 0 | V71: =LCOE!Y97+LCOE!H$32 -> 0 | W71: =LCOE!Z97+V71*IF(LCOE!H$14>0,G71,H71) -> 0 | X71: =LCOE!AA97+LCOE!H$34 -> 101 | Y71: =X71*H71 -> 0 | Z71: =SUM(B71:C71) -> 0 | AA71: =SUM(I71:J71) -> 20000000 | AB71: =L71 -> 134532576 | AC71: =U71+W71 -> 0 | AD71: =S71 -> 29683260 | AE71: =AE70+1*E71 -> 1 | AF71: =LCOE!E97+LCOE!H$40 -> 0.08 | AG71: =(1+AF71)^A71 -> 1.08 | AH71: =Z71/AG71 -> 0 | AI71: =AA71/AG71 -> 18518519 | AJ71: =AB71/AG71 -> 1.245672e+08 | AK71: =AC71/AG71 -> 0 | AL71: =AD71/AG71 -> 27484500 | AM71: =(-1)*Y71/AG71 -> 0 | AN71: =IF(LCOE!H$14>0,G71,H71)/AG71 -> 2920000
A72: 2 | C72: =LCOE!H98+IF(AND(LCOE!H$26>0,A72>=LCOE!H$26,A72<=(LCOE!H$26+LCOE!H$27-1)),LCOE!H$42/LCOE!H$27,0)+IF(AND(D72=0,AE72>=LCOE!H$16,COUNTIF(D47:D72,0)=LCOE!H$36),LCOE!H$35*LCOE!H$38,0) -> 0 | D72: =IF(AE71<LCOE!H$16,1,0) -> 1 | E72: =LCOE!G98+IF(AND(A72>=LCOE!H$26,A72<=(LCOE!H$26+LCOE!H$27-1)),0,1)*IF(A72=LCOE!H$34,0,1)*D72 -> 1 | F72: =IF(F71<LCOE!H$18,MIN(F71*(1+LCOE!H$19),LCOE!H$18),LCOE!H$18)+LCOE!J98 -> 0.9 | G72: =LCOE!K98+E72*F72*N72*(LCOE!H$14+LCOE!H98)*24*365*D72 -> 3942000 | H72: =LCOE!L98+F72*(LCOE!H$15+LCOE!I98)*E72*24*365*D72*N72 -> 0 | I72: =LCOE!M98+LCOE!H$20*IF(LCOE!H$14>0,(LCOE!H$14+LCOE!H98),(LCOE!H$15+LCOE!I98))*K72*D72 -> 20000000 | J72: =LCOE!N98+LCOE!H$21*IF(LCOE!H$14>0,G72,H72)*K72*D72 -> 0 | K72: =LCOE!O98+K71+K71*LCOE!H$22 -> 1 | L72: =LCOE!P98+LCOE!H$23*IF(LCOE!H$14>0,G72,H72)*M72*D72 -> 168165720 | M72: =LCOE!Q98+M71+M71*LCOE!H$24 -> 1 | N72: =LCOE!R98+N71-N71*LCOE!H$25 -> 1 | O72: =LCOE!S98+LCOE!H$29 -> 313.75 | P72: =LCOE!T98+IF(A72>=LCOE!H$30,100%,0%) -> 1 | Q72: =LCOE!U98+O72/1000*IF(LCOE!H$14>0,G72,H72) -> 1236802.5 | R72: =LCOE!B98 -> 30 | S72: =LCOE!V98+Q72*P72*R72 -> 37104075 | T72: =LCOE!W98+LCOE!H$31 -> 0 | U72: =LCOE!X98+T72*IF(LCOE!H$14>0,G72,H72) -> 0 | V72: =LCOE!Y98+LCOE!H$32 -> 0 | W72: =LCOE!Z98+V72*IF(LCOE!H$14>0,G72,H72) -> 0 | X72: =LCOE!AA98+LCOE!H$34 -> 101 | Y72: =X72*H72 -> 0 | Z72: =SUM(B72:C72) -> 0 | AA72: =SUM(I72:J72) -> 20000000 | AB72: =L72 -> 168165720 | AC72: =U72+W72 -> 0 | AD72: =S72 -> 37104075 | AE72: =AE71+1*E72 -> 2 | AF72: =LCOE!E98+LCOE!H$40 -> 0.08 | AG72: =(1+AF72)^A72 -> 1.1664 | AH72: =Z72/AG72 -> 0 | AI72: =AA72/AG72 -> 17146776 | AJ72: =AB72/AG72 -> 144175000 | AK72: =AC72/AG72 -> 0 | AL72: =AD72/AG72 -> 31810764 | AM72: =(-1)*Y72/AG72 -> 0 | AN72: =IF(LCOE!H$14>0,G72,H72)/AG72 -> 3379629.6
A73: 3 | C73: =LCOE!H99+IF(AND(LCOE!H$26>0,A73>=LCOE!H$26,A73<=(LCOE!H$26+LCOE!H$27-1)),LCOE!H$42/LCOE!H$27,0)+IF(AND(D73=0,AE73>=LCOE!H$16,COUNTIF(D48:D73,0)=LCOE!H$36),LCOE!H$35*LCOE!H$38,0) -> 0 | D73: =IF(AE72<LCOE!H$16,1,0) -> 1 | E73: =LCOE!G99+IF(AND(A73>=LCOE!H$26,A73<=(LCOE!H$26+LCOE!H$27-1)),0,1)*IF(A73=LCOE!H$34,0,1)*D73 -> 1 | F73: =IF(F72<LCOE!H$18,MIN(F72*(1+LCOE!H$19),LCOE!H$18),LCOE!H$18)+LCOE!J99 -> 0.9 | G73: =LCOE!K99+E73*F73*N73*(LCOE!H$14+LCOE!H99)*24*365*D73 -> 3942000 | H73: =LCOE!L99+F73*(LCOE!H$15+LCOE!I99)*E73*24*365*D73*N73 -> 0 | I73: =LCOE!M99+LCOE!H$20*IF(LCOE!H$14>0,(LCOE!H$14+LCOE!H99),(LCOE!H$15+LCOE!I99))*K73*D73 -> 20000000 | J73: =LCOE!N99+LCOE!H$21*IF(LCOE!H$14>0,G73,H73)*K73*D73 -> 0 | K73: =LCOE!O99+K72+K72*LCOE!H$22 -> 1 | L73: =LCOE!P99+LCOE!H$23*IF(LCOE!H$14>0,G73,H73)*M73*D73 -> 168165720 | M73: =LCOE!Q99+M72+M72*LCOE!H$24 -> 1 | N73: =LCOE!R99+N72-N72*LCOE!H$25 -> 1 | O73: =LCOE!S99+LCOE!H$29 -> 313.75 | P73: =LCOE!T99+IF(A73>=LCOE!H$30,100%,0%) -> 1 | Q73: =LCOE!U99+O73/1000*IF(LCOE!H$14>0,G73,H73) -> 1236802.5 | R73: =LCOE!B99 -> 30 | S73: =LCOE!V99+Q73*P73*R73 -> 37104075 | T73: =LCOE!W99+LCOE!H$31 -> 0 | U73: =LCOE!X99+T73*IF(LCOE!H$14>0,G73,H73) -> 0 | V73: =LCOE!Y99+LCOE!H$32 -> 0 | W73: =LCOE!Z99+V73*IF(LCOE!H$14>0,G73,H73) -> 0 | X73: =LCOE!AA99+LCOE!H$34 -> 101 | Y73: =X73*H73 -> 0 | Z73: =SUM(B73:C73) -> 0 | AA73: =SUM(I73:J73) -> 20000000 | AB73: =L73 -> 168165720 | AC73: =U73+W73 -> 0 | AD73: =S73 -> 37104075 | AE73: =AE72+1*E73 -> 3 | AF73: =LCOE!E99+LCOE!H$40 -> 0.08 | AG73: =(1+AF73)^A73 -> 1.259712 | AH73: =Z73/AG73 -> 0 | AI73: =AA73/AG73 -> 15876645 | AJ73: =AB73/AG73 -> 1.3349537e+08 | AK73: =AC73/AG73 -> 0 | AL73: =AD73/AG73 -> 29454411 | AM73: =(-1)*Y73/AG73 -> 0 | AN73: =IF(LCOE!H$14>0,G73,H73)/AG73 -> 3129286.7
A74: 4 | C74: =LCOE!H100+IF(AND(LCOE!H$26>0,A74>=LCOE!H$26,A74<=(LCOE!H$26+LCOE!H$27-1)),LCOE!H$42/LCOE!H$27,0)+IF(AND(D74=0,AE74>=LCOE!H$16,COUNTIF(D49:D74,0)=LCOE!H$36),LCOE!H$35*LCOE!H$38,0) -> 0 | D74: =IF(AE73<LCOE!H$16,1,0) -> 1 | E74: =LCOE!G100+IF(AND(A74>=LCOE!H$26,A74<=(LCOE!H$26+LCOE!H$27-1)),0,1)*IF(A74=LCOE!H$34,0,1)*D74 -> 1 | F74: =IF(F73<LCOE!H$18,MIN(F73*(1+LCOE!H$19),LCOE!H$18),LCOE!H$18)+LCOE!J100 -> 0.9 | G74: =LCOE!K100+E74*F74*N74*(LCOE!H$14+LCOE!H100)*24*365*D74 -> 3942000 | H74: =LCOE!L100+F74*(LCOE!H$15+LCOE!I100)*E74*24*365*D74*N74 -> 0 | I74: =LCOE!M100+LCOE!H$20*IF(LCOE!H$14>0,(LCOE!H$14+LCOE!H100),(LCOE!H$15+LCOE!I100))*K74*D74 -> 20000000 | J74: =LCOE!N100+LCOE!H$21*IF(LCOE!H$14>0,G74,H74)*K74*D74 -> 0 | K74: =LCOE!O100+K73+K73*LCOE!H$22 -> 1 | L74: =LCOE!P100+LCOE!H$23*IF(LCOE!H$14>0,G74,H74)*M74*D74 -> 168165720 | M74: =LCOE!Q100+M73+M73*LCOE!H$24 -> 1 | N74: =LCOE!R100+N73-N73*LCOE!H$25 -> 1 | O74: =LCOE!S100+LCOE!H$29 -> 313.75 | P74: =LCOE!T100+IF(A74>=LCOE!H$30,100%,0%) -> 1 | Q74: =LCOE!U100+O74/1000*IF(LCOE!H$14>0,G74,H74) -> 1236802.5 | R74: =LCOE!B100 -> 30 | S74: =LCOE!V100+Q74*P74*R74 -> 37104075 | T74: =LCOE!W100+LCOE!H$31 -> 0 | U74: =LCOE!X100+T74*IF(LCOE!H$14>0,G74,H74) -> 0 | V74: =LCOE!Y100+LCOE!H$32 -> 0 | W74: =LCOE!Z100+V74*IF(LCOE!H$14>0,G74,H74) -> 0 | X74: =LCOE!AA100+LCOE!H$34 -> 101 | Y74: =X74*H74 -> 0 | Z74: =SUM(B74:C74) -> 0 | AA74: =SUM(I74:J74) -> 20000000 | AB74: =L74 -> 168165720 | AC74: =U74+W74 -> 0 | AD74: =S74 -> 37104075 | AE74: =AE73+1*E74 -> 4 | AF74: =LCOE!E100+LCOE!H$40 -> 0.08 | AG74: =(1+AF74)^A74 -> 1.360489 | AH74: =Z74/AG74 -> 0 | AI74: =AA74/AG74 -> 14700597 | AJ74: =AB74/AG74 -> 1.2360682e+08 | AK74: =AC74/AG74 -> 0 | AL74: =AD74/AG74 -> 27272603 | AM74: =(-1)*Y74/AG74 -> 0 | AN74: =IF(LCOE!H$14>0,G74,H74)/AG74 -> 2897487.7
A75: 5 | C75: =LCOE!H101+IF(AND(LCOE!H$26>0,A75>=LCOE!H$26,A75<=(LCOE!H$26+LCOE!H$27-1)),LCOE!H$42/LCOE!H$27,0)+IF(AND(D75=0,AE75>=LCOE!H$16,COUNTIF(D50:D75,0)=LCOE!H$36),LCOE!H$35*LCOE!H$38,0) -> 0 | D75: =IF(AE74<LCOE!H$16,1,0) -> 1 | E75: =LCOE!G101+IF(AND(A75>=LCOE!H$26,A75<=(LCOE!H$26+LCOE!H$27-1)),0,1)*IF(A75=LCOE!H$34,0,1)*D75 -> 1 | F75: =IF(F74<LCOE!H$18,MIN(F74*(1+LCOE!H$19),LCOE!H$18),LCOE!H$18)+LCOE!J101 -> 0.9 | G75: =LCOE!K101+E75*F75*N75*(LCOE!H$14+LCOE!H101)*24*365*D75 -> 3942000 | H75: =LCOE!L101+F75*(LCOE!H$15+LCOE!I101)*E75*24*365*D75*N75 -> 0 | I75: =LCOE!M101+LCOE!H$20*IF(LCOE!H$14>0,(LCOE!H$14+LCOE!H101),(LCOE!H$15+LCOE!I101))*K75*D75 -> 20000000 | J75: =LCOE!N101+LCOE!H$21*IF(LCOE!H$14>0,G75,H75)*K75*D75 -> 0 | K75: =LCOE!O101+K74+K74*LCOE!H$22 -> 1 | L75: =LCOE!P101+LCOE!H$23*IF(LCOE!H$14>0,G75,H75)*M75*D75 -> 168165720 | M75: =LCOE!Q101+M74+M74*LCOE!H$24 -> 1 | N75: =LCOE!R101+N74-N74*LCOE!H$25 -> 1 | O75: =LCOE!S101+LCOE!H$29 -> 313.75 | P75: =LCOE!T101+IF(A75>=LCOE!H$30,100%,0%) -> 1 | Q75: =LCOE!U101+O75/1000*IF(LCOE!H$14>0,G75,H75) -> 1236802.5 | R75: =LCOE!B101 -> 30 | S75: =LCOE!V101+Q75*P75*R75 -> 37104075 | T75: =LCOE!W101+LCOE!H$31 -> 0 | U75: =LCOE!X101+T75*IF(LCOE!H$14>0,G75,H75) -> 0 | V75: =LCOE!Y101+LCOE!H$32 -> 0 | W75: =LCOE!Z101+V75*IF(LCOE!H$14>0,G75,H75) -> 0 | X75: =LCOE!AA101+LCOE!H$34 -> 101 | Y75: =X75*H75 -> 0 | Z75: =SUM(B75:C75) -> 0 | AA75: =SUM(I75:J75) -> 20000000 | AB75: =L75 -> 168165720 | AC75: =U75+W75 -> 0 | AD75: =S75 -> 37104075 | AE75: =AE74+1*E75 -> 5 | AF75: =LCOE!E101+LCOE!H$40 -> 0.08 | AG75: =(1+AF75)^A75 -> 1.4693281 | AH75: =Z75/AG75 -> 0 | AI75: =AA75/AG75 -> 13611664 | AJ75: =AB75/AG75 -> 1.1445076e+08 | AK75: =AC75/AG75 -> 0 | AL75: =AD75/AG75 -> 25252410 | AM75: =(-1)*Y75/AG75 -> 0 | AN75: =IF(LCOE!H$14>0,G75,H75)/AG75 -> 2682859
A76: 6 | C76: =LCOE!H102+IF(AND(LCOE!H$26>0,A76>=LCOE!H$26,A76<=(LCOE!H$26+LCOE!H$27-1)),LCOE!H$42/LCOE!H$27,0)+IF(AND(D76=0,AE76>=LCOE!H$16,COUNTIF(D51:D76,0)=LCOE!H$36),LCOE!H$35*LCOE!H$38,0) -> 0 | D76: =IF(AE75<LCOE!H$16,1,0) -> 1 | E76: =LCOE!G102+IF(AND(A76>=LCOE!H$26,A76<=(LCOE!H$26+LCOE!H$27-1)),0,1)*IF(A76=LCOE!H$34,0,1)*D76 -> 1 | F76: =IF(F75<LCOE!H$18,MIN(F75*(1+LCOE!H$19),LCOE!H$18),LCOE!H$18)+LCOE!J102 -> 0.9 | G76: =LCOE!K102+E76*F76*N76*(LCOE!H$14+LCOE!H102)*24*365*D76 -> 3942000 | H76: =LCOE!L102+F76*(LCOE!H$15+LCOE!I102)*E76*24*365*D76*N76 -> 0 | I76: =LCOE!M102+LCOE!H$20*IF(LCOE!H$14>0,(LCOE!H$14+LCOE!H102),(LCOE!H$15+LCOE!I102))*K76*D76 -> 20000000 | J76: =LCOE!N102+LCOE!H$21*IF(LCOE!H$14>0,G76,H76)*K76*D76 -> 0 | K76: =LCOE!O102+K75+K75*LCOE!H$22 -> 1 | L76: =LCOE!P102+LCOE!H$23*IF(LCOE!H$14>0,G76,H76)*M76*D76 -> 168165720 | M76: =LCOE!Q102+M75+M75*LCOE!H$24 -> 1 | N76: =LCOE!R102+N75-N75*LCOE!H$25 -> 1 | O76: =LCOE!S102+LCOE!H$29 -> 313.75 | P76: =LCOE!T102+IF(A76>=LCOE!H$30,100%,0%) -> 1 | Q76: =LCOE!U102+O76/1000*IF(LCOE!H$14>0,G76,H76) -> 1236802.5 | R76: =LCOE!B102 -> 30 | S76: =LCOE!V102+Q76*P76*R76 -> 37104075 | T76: =LCOE!W102+LCOE!H$31 -> 0 | U76: =LCOE!X102+T76*IF(LCOE!H$14>0,G76,H76) -> 0 | V76: =LCOE!Y102+LCOE!H$32 -> 0 | W76: =LCOE!Z102+V76*IF(LCOE!H$14>0,G76,H76) -> 0 | X76: =LCOE!AA102+LCOE!H$34 -> 101 | Y76: =X76*H76 -> 0 | Z76: =SUM(B76:C76) -> 0 | AA76: =SUM(I76:J76) -> 20000000 | AB76: =L76 -> 168165720 | AC76: =U76+W76 -> 0 | AD76: =S76 -> 37104075 | AE76: =AE75+1*E76 -> 6 | AF76: =LCOE!E102+LCOE!H$40 -> 0.08 | AG76: =(1+AF76)^A76 -> 1.5868743 | AH76: =Z76/AG76 -> 0 | AI76: =AA76/AG76 -> 12603393 | AJ76: =AB76/AG76 -> 1.0597293e+08 | AK76: =AC76/AG76 -> 0 | AL76: =AD76/AG76 -> 23381861 | AM76: =(-1)*Y76/AG76 -> 0 | AN76: =IF(LCOE!H$14>0,G76,H76)/AG76 -> 2484128.7
