Workbook
Name Deflator_2010: #REF!
Name Deflator_2011: #REF!
Name Deflator_2012: #REF!
Name Deflator_2013: #REF!
Name Deflator_2014: #REF!
Name Deflator_2015: #REF!
Name Deflator_2016: #REF!
Name Deflator_2017: #REF!
Name Deflator_2018: #REF!

Sheet Kuvaus ja ohje
A1: Kuvaus ja ohje: LCOE-laskin, päivitetty 26.9.2023
B3: Tällä laskurilla voidaan laskea erilaisten sähköä ja lämpöä tuottavien voimaloiden niin sanottu tasoitettu tuotantokustannus LCOE (Levelized Cost Of Electricity).
B4: LCOE tarkoittaa hintaa, jonka laitoksen on keskimäärin saatava myymästään sähköstä, jotta se olisi kannattava, kun kaikki kustannukset huomioidaan.
B5: Laskuri huomioi rakentamis- ja käyttökustannusten lisäksi myös päästömaksut ja mahdolliset erityisesti laitokseen kohdistuvat verot ja maksut.
B7: Laskuri perustuu Ison-Britannian energiaministeriön (Department of Energy Security and Net Zero) 2023 julkaisemaan LCOE-laskuriin (https://www.gov.uk/government/publications/electricity-generation-costs-2023).
B8: Alkuperäinen laskuri on julkaistu Open Government v3.0-lisenssillä (http://nationalarchives.gov.uk/doc/open-government-licence/version/3/).
B9: Laskuri on lokalisoitu Suomeen muuttamalla rahayksiköt vuosien 2022 tai 2023 euroiksi (riippuen datan saatavuudesta). Siihen on myös lisätty uusia laitoksia ja toiminnallisuuksia.
B10: Lokalisoinnin ja lisäykset on toteuttanut Janne M. Korhonen, Kalevi Sorsa-säätiö (janne.korhonen@sorsafoundation.fi).
B11: Huomaa, että laskuri on vielä osin kesken, ja esimerkiksi kaikkia polttoaine- tai päästöskenaarioita ei ole vielä sisällytetty.
B12: Laskurilla voi kuitenkin laskea Sorsa-säätiön raportissa Muuttuva energiapalapeli: onko edessä vihreä humahdus?-käsiteltyjen voimaloiden LCOE:n.
B14: Miten laskuri toimii?
B15: Varsinainen laskuri löytyy välilehdeltä "LCOE EUR". Välilehdellä "Muuttujien kuvaus" on tarkempaa tietoa muuttujista.
A16: . | B16: Vaaleanpunainen väri kertoo käyttäjältä vaaditusta syötteestä:
B18: Muuttele näitä soluja!
B20: Useimmissa muutettavissa soluissa on alasvetovalikko, josta voi valita esimerkiksi eri laitoksen tai skenaariovaihtoehdon. Sen saa esiin klikkaamalla ensin solua, ja sitten alaspäin osoittavaa kolmiota.
B21: (Muutos ei välttämättä päivity automaattisesti; päivitä taulukko käsin tai tallenna se, jolloin se päivittyy.)
B23: Kohdassa "Muutokset" oleviin soluihin voi kokeilla skenaarioiden variaatioita. Kyseisiin soluihin syötetyt luvut lisätään (tai negatiivisten lukujen tapauksessa vähennetään) vastaavasta muuttujasta.
B25: Laskurin käyttämä data haetaan välilehdiltä "Laitokset," "Polttoainekustannukset," "Päästötase" ja "Päästömaksut."

Sheet Muuttujien kuvaus
A1: Muuttujien kuvaus
B3: Muuttuja | C3: Kuvaus
B4: Suunnittelukustannukset | C4: Suunnittelun, luvituksen ynnä muut kulut, jotka aiheutuvat ennen kuin laitosta ryhdytään rakentamaan. Ilmoitettu euroina nimellistehon kilowattia kohden. Kolme skenaariota: matala, keski, korkea.
B5: Suunnittelun kesto | C5: Suunnitteluvaiheen kesto vuosina. Kolme skenaariota: matala, keski, korkea.
B6: Rakentamiskustannukset | C6: Laitoksen rakentamiskustannukset. Ilmoitettu euroina nimellistehon kilowattia kohden. Kolme skenaariota: matala, keski, korkea.
B7: Rakentamisaikataulu | C7: Rakennusvaiheen kesto vuosina. Kolme skenaariota: matala, keski, korkea.
B8: Polttoaineen hintaskenaario | C8: Laskelmassa käytettävä polttoaineen hintaskenaario (välilehti Polttoainekustannukset). Useita skenaarioita.
B9: Polttoaineen päästötase | C9: Laskelmassa käytettävä arvio laitoksen käytön päästötaseesta (välilehti Päästötase). Useita skenaarioita.
B10: Päästöoikeuden hintaskenaario | C10: Laskelmassa käytettävä skenaario päästöoikeuden hinnan kehittymisestä (välilehti Päästömaksut). Useita skenaarioita.
B11: Projektin aloitusvuosi | C11: Vuosi, jolloin projektin suunnittelu aloitetaan; minimi 2020. Vaikuttaa polttoaineen ja päästöoikeuden hintaan valitun skenaarion mukaisesti.
B12: Tekniikka vuodelta | C12: Vuosi, jolloin laitoksen tekniikan uskotaan olevan valmiina kaupalliseen käyttöön, tai vuosi, jolta tiedot ovat peräisin.
B13: Rakentamisen aloitusvuosi | C13: Vuosi, jolloin laitoksen rakentaminen päästään aloittamaan. Määräytyy projektin aloitusvuoden ja suunnittelun keston perusteella.
B14: Käyttöönottovuosi | C14: Vuosi, jolloin laitos otetaan käyttöön. Määräytyy rakentamisen aloitusvuoden ja rakentamisaikataulun perusteella.
... B25: Sähkön tasoitettu tuotantokustannus (LCOE) | C25: Hinta, jonka laitoksen on saatava keskimäärin myymästään sähköstä, jotta se olisi kannattava sijoitus, kun kaikki kulut ja pääoman kustannus huomioidaan.

Sheet LCOE EUR
B1: LCOE-laskin, päivitetty 19.8.2024
B2: Pohjautuu Annex B LCOE-laskuriin | C2: Muutokset: Janne M. Korhonen, Kalevi Sorsa-säätiö
B3: (Energiaministeriö, Iso-Britannia, 2023)
B4: Jaettu Open Government v3.0-lisenssillä | D4: <- Syötteet
B6: Skenaario | E6: Huom: | H6: Skenaarion tiedot (haettu välilehdeltä Laitokset)
B7: Laitos | C7: Ydinreaktori, 1 250 MW, Ruotsi 2024 referenssilaskelma | E7: =_xlfn.XLOOKUP(C7,Laitokset!7:7,Laitokset!11:11) -> Ruotsin hallituksen selvityksestä | H7: Tiedot vuodelta | J7: =_xlfn.XLOOKUP(C7,Laitokset!7:7,Laitokset!3:3) -> 2024 | L7: =Laitokset!A61 -> Kiinteä OPEX | O7: =_xlfn.XLOOKUP(C$7,Laitokset!$7:$7,Laitokset!61:61) -> 0 | P7: =Laitokset!C61 -> EUR/MW/vuosi | R7: =Laitokset!A27 -> Suunnittelun aikataulu | T7: 1 | U7: =_xlfn.XLOOKUP($C$7,Laitokset!$7:$7,Laitokset!27:27) -> 0 | V7: =Laitokset!A43 -> Rakentamisaikataulutus | W7: 1 | X7: =_xlfn.XLOOKUP($C$7,Laitokset!$7:$7,Laitokset!43:43) -> 0.14285714
B8: Polttoaine | C8: =J11 -> Uraani | H8: Sijainti | J8: =_xlfn.XLOOKUP(C7,Laitokset!7:7,Laitokset!4:4) -> Ruotsi | L8: =Laitokset!A62 -> Muuttuva OPEX | O8: =_xlfn.XLOOKUP(C$7,Laitokset!$7:$7,Laitokset!62:62) -> 16.52 | P8: =Laitokset!C62 -> EUR/MWh | Q8: =IF(J12="Kyllä","Sis. pa-kustannukset!","") -> Sis. pa-kustannukset! | R8: =Laitokset!A28 -> (% käytetty vuodessa) | T8: 2 | U8: =_xlfn.XLOOKUP($C$7,Laitokset!$7:$7,Laitokset!28:28) -> 0 | V8: =Laitokset!A44 -> (% käytetty vuodessa) | W8: 2 | X8: =_xlfn.XLOOKUP($C$7,Laitokset!$7:$7,Laitokset!44:44) -> 0.14285714
B9: =H22 -> Suunnittelukustannukset | C9: Keski | H9: Rahayksikkö | J9: =_xlfn.XLOOKUP(C7,Laitokset!7:7,Laitokset!12:12) -> 2022 real EUR | L9: =Laitokset!A63 -> Vakuutus | O9: =_xlfn.XLOOKUP(C$7,Laitokset!$7:$7,Laitokset!63:63) -> 0 | P9: =Laitokset!C63 -> EUR/MW/vuosi | T9: 3 | U9: =_xlfn.XLOOKUP($C$7,Laitokset!$7:$7,Laitokset!29:29) -> 0 | W9: 3 | X9: =_xlfn.XLOOKUP($C$7,Laitokset!$7:$7,Laitokset!45:45) -> 0.14285714
B10: =H25 -> Suunnittelun kesto | C10: Keski | H10: =Laitokset!A5 -> Tekniikka | J10: =_xlfn.XLOOKUP(C7,Laitokset!7:7,Laitokset!5:5) -> Ydinreaktori, 1 250 MW | L10: =Laitokset!A64 -> Liittymis- ja muut kustannukset | O10: =_xlfn.XLOOKUP(C$7,Laitokset!$7:$7,Laitokset!64:64) -> 0 | P10: =Laitokset!C64 -> EUR/MW/vuosi | T10: 4 | U10: =_xlfn.XLOOKUP($C$7,Laitokset!$7:$7,Laitokset!30:30) -> 0 | W10: 4 | X10: =_xlfn.XLOOKUP($C$7,Laitokset!$7:$7,Laitokset!46:46) -> 0.14285714
B11: =H28 -> Rakentamiskustannukset | C11: Keski | H11: Polttoaine | J11: =_xlfn.XLOOKUP(C7,Laitokset!7:7,Laitokset!9:9) -> Uraani | L11: =Laitokset!A65 -> Lämmönmyyntisopimuksen kesto | O11: =_xlfn.XLOOKUP(C$7,Laitokset!$7:$7,Laitokset!65:65) -> 0 | P11: =Laitokset!C65 -> vuotta | T11: 5 | U11: =_xlfn.XLOOKUP($C$7,Laitokset!$7:$7,Laitokset!31:31) -> 0 | W11: 5 | X11: =_xlfn.XLOOKUP($C$7,Laitokset!$7:$7,Laitokset!47:47) -> 0.14285714
B12: =H31 -> Rakentamisaikataulu | C12: Pitkä | H12: Sisältyvätkö polttoainekustannukset OPEXiin? | J12: =_xlfn.XLOOKUP(C7,Laitokset!7:7,Laitokset!10:10,"") -> Kyllä | L12: =Laitokset!A66 -> Pääoman kustannus (WACC) | O12: =_xlfn.XLOOKUP(C$7,Laitokset!$7:$7,Laitokset!66:66)*100 -> 4 | P12: =Laitokset!C66 -> % | T12: 6 | U12: =_xlfn.XLOOKUP($C$7,Laitokset!$7:$7,Laitokset!32:32) -> 0 | W12: 6 | X12: =_xlfn.XLOOKUP($C$7,Laitokset!$7:$7,Laitokset!48:48) -> 0.14285714
B13: =H34 -> Infrastruktuurin hinta | C13: Keski | H13: Tekniikka vuodelta | J13: =_xlfn.XLOOKUP(C7,Laitokset!7:7,Laitokset!6:6) -> 2035 | L13: =Laitokset!A67 -> Jätemaksu | O13: =_xlfn.XLOOKUP(C$7,Laitokset!$7:$7,Laitokset!67:67)*100 -> 0 | P13: =Laitokset!C67 -> EUR/MWh | T13: 7 | U13: =_xlfn.XLOOKUP($C$7,Laitokset!$7:$7,Laitokset!33:33) -> 0 | W13: 7 | X13: =_xlfn.XLOOKUP($C$7,Laitokset!$7:$7,Laitokset!49:49) -> 0.14285714
B14: =L16 -> Purkukustannukset | C14: Keski | H14: =Laitokset!A13 -> Sähköntuotannon nimellisteho | J14: =_xlfn.XLOOKUP(C7,Laitokset!7:7,Laitokset!13:13) -> 1250 | K14: =Laitokset!C13 -> MWe | L14: =Laitokset!A68 -> Hiilen talteenotto | O14: =_xlfn.XLOOKUP(C$7,Laitokset!$7:$7,Laitokset!68:68)*100 -> 0 | P14: =Laitokset!C68 -> % | T14: 8 | U14: =_xlfn.XLOOKUP($C$7,Laitokset!$7:$7,Laitokset!34:34) -> 0 | W14: 8 | X14: =_xlfn.XLOOKUP($C$7,Laitokset!$7:$7,Laitokset!50:50) -> 0
B15: Polttoaineen hintaskenaario | C15: Keski | H15: =Laitokset!A14 -> Sähköntuotannon kapasiteettikerroin | J15: =_xlfn.XLOOKUP(C7,Laitokset!7:7,Laitokset!14:14)*100 -> 89 | K15: =Laitokset!C14 -> % | L15: =Laitokset!A69 -> Talteenoton hinta | O15: =_xlfn.XLOOKUP(C$7,Laitokset!$7:$7,Laitokset!69:69) -> 0 | P15: =Laitokset!C69 -> EUR/tCO2 | T15: 9 | U15: =_xlfn.XLOOKUP($C$7,Laitokset!$7:$7,Laitokset!35:35) -> 0 | W15: 9 | X15: =_xlfn.XLOOKUP($C$7,Laitokset!$7:$7,Laitokset!51:51) -> 0
B16: Polttoaineen päästötase | C16: Keski (IPCC) | H16: =Laitokset!A15 -> Sähköntuotannon hyötysuhde | J16: =_xlfn.XLOOKUP(C7,Laitokset!7:7,Laitokset!15:15)*100 -> 37 | K16: =Laitokset!C15 -> % | L16: =Laitokset!A70 -> Purkukustannukset | N16: =Laitokset!B70 -> Matala | O16: =_xlfn.XLOOKUP(C$7,Laitokset!$7:$7,Laitokset!70:70)*100 -> 0 | P16: =Laitokset!C70 -> % | T16: 10 | U16: =_xlfn.XLOOKUP($C$7,Laitokset!$7:$7,Laitokset!36:36) -> 0 | W16: 10 | X16: =_xlfn.XLOOKUP($C$7,Laitokset!$7:$7,Laitokset!52:52) -> 0
B17: Päästöoikeuden hintaskenaario | C17: Suomi, Ilmasto- ja energiastrategia (2021) | H17: =Laitokset!A16 -> Nimellistehon muutos | J17: =_xlfn.XLOOKUP(C7,Laitokset!7:7,Laitokset!16:16)*100 -> 0 | K17: =Laitokset!C16 -> %/vvuosi | N17: =Laitokset!B71 -> Keski | O17: =_xlfn.XLOOKUP(C$7,Laitokset!$7:$7,Laitokset!71:71)*100 -> 0 | P17: =Laitokset!C71 -> % | W17: 11 | X17: =_xlfn.XLOOKUP($C$7,Laitokset!$7:$7,Laitokset!53:53) -> 0
H18: =Laitokset!A17 -> Lämmöntuotannon kapasiteettikerroin | J18: =_xlfn.XLOOKUP(C7,Laitokset!7:7,Laitokset!17:17)*100 -> 0 | K18: =Laitokset!C17 -> % | N18: =Laitokset!B72 -> Korkea | O18: =_xlfn.XLOOKUP(C$7,Laitokset!$7:$7,Laitokset!72:72)*100 -> 0 | P18: =Laitokset!C72 -> % | W18: 12 | X18: =_xlfn.XLOOKUP($C$7,Laitokset!$7:$7,Laitokset!54:54) -> 0
B19: Projektin aloitusvuosi | C19: 2028 | H19: =Laitokset!A18 -> Yhteistuotannon hyötysuhde | J19: =_xlfn.XLOOKUP(C7,Laitokset!7:7,Laitokset!18:18)*100 -> 0 | K19: =Laitokset!C18 -> % | L19: =Laitokset!A73 -> Purkamisen viive | O19: =_xlfn.XLOOKUP(C$7,Laitokset!$7:$7,Laitokset!73:73) -> 0 | P19: =Laitokset!C73 -> vuotta | W19: 13 | X19: =_xlfn.XLOOKUP($C$7,Laitokset!$7:$7,Laitokset!55:55) -> 0
B20: =H13 -> Tekniikka vuodelta | C20: =J13 -> 2035 | H20: =Laitokset!A19 -> Käyttöikä | J20: =_xlfn.XLOOKUP(C7,Laitokset!7:7,Laitokset!19:19) -> 60 | K20: =Laitokset!C19 -> vuotta | W20: 14 | X20: =_xlfn.XLOOKUP($C$7,Laitokset!$7:$7,Laitokset!56:56) -> 0
B21: Rakentamisen aloitusvuosi | C21: =C19+_xlfn.XLOOKUP(C10,I25:I27,J25:J27) -> 2028 | H21: =Laitokset!A20 -> Regulaatio, luvitus, julkiset kuulemiset | J21: =_xlfn.XLOOKUP(C7,Laitokset!7:7,Laitokset!20:20) -> 0 | K21: =Laitokset!C20 -> EUR/kW | W21: 15 | X21: =_xlfn.XLOOKUP($C$7,Laitokset!$7:$7,Laitokset!57:57) -> 0
B22: Käyttöönottovuosi | C22: =C21+_xlfn.XLOOKUP(C12,I31:I33,J31:J33) -> 2036 | H22: =Laitokset!A21 -> Suunnittelukustannukset | I22: =Laitokset!B21 -> Matala | J22: =_xlfn.XLOOKUP(C$7,Laitokset!$7:$7,Laitokset!21:21) -> 0 | K22: =Laitokset!C21 -> EUR/kW
B23: Käytöstä poistovuosi | C23: =C22+J20 -> 2096 | I23: =Laitokset!B22 -> Keski | J23: =_xlfn.XLOOKUP(C$7,Laitokset!$7:$7,Laitokset!22:22) -> 0 | K23: =Laitokset!C22 -> EUR/kW
B24: Lämmön myyntisopimus päättyy | C24: =C22+O11 -> 2036 | I24: =Laitokset!B23 -> Korkea | J24: =_xlfn.XLOOKUP(C$7,Laitokset!$7:$7,Laitokset!23:23) -> 0 | K24: =Laitokset!C23 -> EUR/kW
E25: Muutokset | H25: =Laitokset!A24 -> Suunnittelun kesto | I25: =Laitokset!B24 -> Lyhyt | J25: =_xlfn.XLOOKUP(C$7,Laitokset!$7:$7,Laitokset!24:24) -> 0 | K25: =Laitokset!C24 -> vuotta
B26: =H14 -> Sähköntuotannon nimellisteho | C26: =_xlfn.XLOOKUP(C$7,Laitokset!$7:$7,Laitokset!13:13)+E26 -> 1250 | D26: =K14 -> MWe | E26: 0 | F26: Lisätään nimellistehoon | I26: =Laitokset!B25 -> Keski | J26: =_xlfn.XLOOKUP(C$7,Laitokset!$7:$7,Laitokset!25:25) -> 0 | K26: =Laitokset!C25 -> vuotta | U26: =IF(T46=$C$19,$B$19,IF(T46=$C$21,$B$21,IF(T46=$C$22,$B$22,IF(T46=$C$23,$B$23,IF(T46=$C$24,$B$24,""))))) | V26: =IF(U46=$C$19,$B$19,IF(U46=$C$21,$B$21,IF(U46=$C$22,$B$22,IF(U46=$C$23,$B$23,IF(U46=$C$24,$B$24,""))))) | W26: =IF(V46=$C$19,$B$19,IF(V46=$C$21,$B$21,IF(V46=$C$22,$B$22,IF(V46=$C$23,$B$23,IF(V46=$C$24,$B$24,""))))) | X26: =IF(W46=$C$19,$B$19,IF(W46=$C$21,$B$21,IF(W46=$C$22,$B$22,IF(W46=$C$23,$B$23,IF(W46=$C$24,$B$24,"")))))
B27: =H16 -> Sähköntuotannon hyötysuhde | C27: =_xlfn.XLOOKUP(C$7,Laitokset!$7:$7,Laitokset!15:15)+E27 -> 0.37 | E27: 0 | F27: Lisätään hyötysuhteeseen | I27: =Laitokset!B26 -> Pitkä | J27: =_xlfn.XLOOKUP(C$7,Laitokset!$7:$7,Laitokset!26:26) -> 0 | K27: =Laitokset!C26 -> vuotta | Q27: =IF(R46=$C$19,$B$19,IF(R46=$C$21,$B$21,IF(R46=$C$22,$B$22,IF(R46=$C$23,$B$23,IF(R46=$C$24,$B$24,""))))) -> Käyttöönottovuosi | R27: =IF(S46=$C$19,$B$19,IF(S46=$C$21,$B$21,IF(S46=$C$22,$B$22,IF(S46=$C$23,$B$23,IF(S46=$C$24,$B$24,""))))) | Z27: =IF(X46=$C$19,$B$19,IF(X46=$C$21,$B$21,IF(X46=$C$22,$B$22,IF(X46=$C$23,$B$23,IF(X46=$C$24,$B$24,""))))) | AA27: =IF(Y46=$C$19,$B$19,IF(Y46=$C$21,$B$21,IF(Y46=$C$22,$B$22,IF(Y46=$C$23,$B$23,IF(Y46=$C$24,$B$24,""))))) | AB27: =IF(Z46=$C$19,$B$19,IF(Z46=$C$21,$B$21,IF(Z46=$C$22,$B$22,IF(Z46=$C$23,$B$23,IF(Z46=$C$24,$B$24,""))))) | AC27: =IF(AA46=$C$19,$B$19,IF(AA46=$C$21,$B$21,IF(AA46=$C$22,$B$22,IF(AA46=$C$23,$B$23,IF(AA46=$C$24,$B$24,""))))) | AD27: =IF(AB46=$C$19,$B$19,IF(AB46=$C$21,$B$21,IF(AB46=$C$22,$B$22,IF(AB46=$C$23,$B$23,IF(AB46=$C$24,$B$24,""))))) | AE27: =IF(AC46=$C$19,$B$19,IF(AC46=$C$21,$B$21,IF(AC46=$C$22,$B$22,IF(AC46=$C$23,$B$23,IF(AC46=$C$24,$B$24,""))))) | AF27: =IF(AD46=$C$19,$B$19,IF(AD46=$C$21,$B$21,IF(AD46=$C$22,$B$22,IF(AD46=$C$23,$B$23,IF(AD46=$C$24,$B$24,""))))) | AG27: =IF(AE46=$C$19,$B$19,IF(AE46=$C$21,$B$21,IF(AE46=$C$22,$B$22,IF(AE46=$C$23,$B$23,IF(AE46=$C$24,$B$24,""))))) | ... AJ27: =IF(AH46=$C$19,$B$19,IF(AH46=$C$21,$B$21,IF(AH46=$C$22,$B$22,IF(AH46=$C$23,$B$23,IF(AH46=$C$24,$B$24,""))))) | AL27: =IF(AJ46=$C$19,$B$19,IF(AJ46=$C$21,$B$21,IF(AJ46=$C$22,$B$22,IF(AJ46=$C$23,$B$23,IF(AJ46=$C$24,$B$24,""))))) | AM27: =IF(AK46=$C$19,$B$19,IF(AK46=$C$21,$B$21,IF(AK46=$C$22,$B$22,IF(AK46=$C$23,$B$23,IF(AK46=$C$24,$B$24,""))))) | AN27: =IF(AL46=$C$19,$B$19,IF(AL46=$C$21,$B$21,IF(AL46=$C$22,$B$22,IF(AL46=$C$23,$B$23,IF(AL46=$C$24,$B$24,""))))) | AP27: =IF(AN46=$C$19,$B$19,IF(AN46=$C$21,$B$21,IF(AN46=$C$22,$B$22,IF(AN46=$C$23,$B$23,IF(AN46=$C$24,$B$24,""))))) | AQ27: =IF(AO46=$C$19,$B$19,IF(AO46=$C$21,$B$21,IF(AO46=$C$22,$B$22,IF(AO46=$C$23,$B$23,IF(AO46=$C$24,$B$24,""))))) | AR27: =IF(AP46=$C$19,$B$19,IF(AP46=$C$21,$B$21,IF(AP46=$C$22,$B$22,IF(AP46=$C$23,$B$23,IF(AP46=$C$24,$B$24,""))))) | AS27: =IF(AQ46=$C$19,$B$19,IF(AQ46=$C$21,$B$21,IF(AQ46=$C$22,$B$22,IF(AQ46=$C$23,$B$23,IF(AQ46=$C$24,$B$24,""))))) | AT27: =IF(AR46=$C$19,$B$19,IF(AR46=$C$21,$B$21,IF(AR46=$C$22,$B$22,IF(AR46=$C$23,$B$23,IF(AR46=$C$24,$B$24,""))))) | AV27: =IF(AT46=$C$19,$B$19,IF(AT46=$C$21,$B$21,IF(AT46=$C$22,$B$22,IF(AT46=$C$23,$B$23,IF(AT46=$C$24,$B$24,""))))) | AW27: =IF(AU46=$C$19,$B$19,IF(AU46=$C$21,$B$21,IF(AU46=$C$22,$B$22,IF(AU46=$C$23,$B$23,IF(AU46=$C$24,$B$24,""))))) | AX27: =IF(AV46=$C$19,$B$19,IF(AV46=$C$21,$B$21,IF(AV46=$C$22,$B$22,IF(AV46=$C$23,$B$23,IF(AV46=$C$24,$B$24,""))))) | AY27: =IF(AW46=$C$19,$B$19,IF(AW46=$C$21,$B$21,IF(AW46=$C$22,$B$22,IF(AW46=$C$23,$B$23,IF(AW46=$C$24,$B$24,""))))) | AZ27: =IF(AX46=$C$19,$B$19,IF(AX46=$C$21,$B$21,IF(AX46=$C$22,$B$22,IF(AX46=$C$23,$B$23,IF(AX46=$C$24,$B$24,""))))) | BA27: =IF(AY46=$C$19,$B$19,IF(AY46=$C$21,$B$21,IF(AY46=$C$22,$B$22,IF(AY46=$C$23,$B$23,IF(AY46=$C$24,$B$24,""))))) | BB27: =IF(AZ46=$C$19,$B$19,IF(AZ46=$C$21,$B$21,IF(AZ46=$C$22,$B$22,IF(AZ46=$C$23,$B$23,IF(AZ46=$C$24,$B$24,""))))) | BC27: =IF(BA46=$C$19,$B$19,IF(BA46=$C$21,$B$21,IF(BA46=$C$22,$B$22,IF(BA46=$C$23,$B$23,IF(BA46=$C$24,$B$24,""))))) | ... BU27: =IF(BS46=$C$19,$B$19,IF(BS46=$C$21,$B$21,IF(BS46=$C$22,$B$22,IF(BS46=$C$23,$B$23,IF(BS46=$C$24,$B$24,"")))))
B28: =H17 -> Nimellistehon muutos | C28: =J17/100+E28 -> 0 | D28: /vuosi | E28: 0 | F28: Lisätään muutosnopeuteen | H28: =Laitokset!A37 -> Rakentamiskustannukset | I28: =Laitokset!B37 -> Matala | J28: =_xlfn.XLOOKUP(C$7,Laitokset!$7:$7,Laitokset!37:37) -> 3272 | K28: =Laitokset!C37 -> EUR/kW
B29: =H15 -> Sähköntuotannon kapasiteettikerroin | C29: =J15/100+E29 -> 0.89 | E29: 0 | F29: Lisätään käyttöasteeseen | I29: =Laitokset!B38 -> Keski | J29: =_xlfn.XLOOKUP(C$7,Laitokset!$7:$7,Laitokset!38:38) -> 6544 | K29: =Laitokset!C38 -> EUR/kW
B30: Sähköntuotantoa vuodessa | C30: =8760*C29 -> 7796.4 | D30: h | I30: =Laitokset!B39 -> Korkea | J30: =_xlfn.XLOOKUP(C$7,Laitokset!$7:$7,Laitokset!39:39) -> 9816 | K30: =Laitokset!C39 -> EUR/kW
B31: =H18 -> Lämmöntuotannon kapasiteettikerroin | C31: =_xlfn.XLOOKUP(C$7,Laitokset!$7:$7,Laitokset!17:17)+E31 -> 0 | E31: 0 | F31: Lisätään käyttöasteeseen | H31: =Laitokset!A40 -> Rakentamisaikataulu | I31: =Laitokset!B40 -> Lyhyt | J31: =_xlfn.XLOOKUP(C$7,Laitokset!$7:$7,Laitokset!40:40) -> 5 | K31: =Laitokset!C40 -> vuotta
B32: Lämmöntuotantoa vuodessa | C32: =8760*C31 -> 0 | D32: h | I32: =Laitokset!B41 -> Keski | J32: =_xlfn.XLOOKUP(C$7,Laitokset!$7:$7,Laitokset!41:41) -> 7 | K32: =Laitokset!C41 -> vuotta
B33: =L12 -> Pääoman kustannus (WACC) | C33: =_xlfn.XLOOKUP(C$7,Laitokset!$7:$7,Laitokset!66:66)+E33 -> 0.05 | E33: 0.01 | F33: Lisätään pääoman kustannukseen | I33: =Laitokset!B42 -> Pitkä | J33: =_xlfn.XLOOKUP(C$7,Laitokset!$7:$7,Laitokset!42:42) -> 8 | K33: =Laitokset!C42 -> vuotta
H34: =Laitokset!A58 -> Infrastruktuurin hinta | I34: =Laitokset!B58 -> Matala | J34: =_xlfn.XLOOKUP(C$7,Laitokset!$7:$7,Laitokset!58:58) -> 0 | K34: =Laitokset!C58 -> EUR
I35: =Laitokset!B59 -> Keski | J35: =_xlfn.XLOOKUP(C$7,Laitokset!$7:$7,Laitokset!59:59) -> 0 | K35: =Laitokset!C59 -> EUR
I36: =Laitokset!B60 -> Korkea | J36: =_xlfn.XLOOKUP(C$7,Laitokset!$7:$7,Laitokset!60:60) -> 0 | K36: =Laitokset!C60 -> EUR
B37: Tulokset: LCOE | C37: =_xlfn.CONCAT(LEFT(J9,4)," EUR") -> 2022 EUR | E37: 2023 EUR
B38: Sähkön tasoitettu tuotantokustannus | C38: =SUM(C40:C48) -> 71.737104 | D38: /MWhe | E38: =C38*1.062 -> 76.184805 | H38: Polttoaine- ja päästömaksut
B39: josta | J39: =C19 -> 2028 | K39: =J39+1 -> 2029 | L39: =K39+1 -> 2030 | M39: =L39+1 -> 2031 | N39: =M39+1 -> 2032 | O39: =N39+1 -> 2033 | P39: =O39+1 -> 2034 | Q39: =P39+1 -> 2035 | R39: =Q39+1 -> 2036 | ... BS39: =BR39+1 -> 2089
B40: Suunnittelukustannukset | C40: =H56 -> 0 | D40: /MWhe | E40: =C40*1.062 -> 0 | H40: =_xlfn.CONCAT("Polttoaine: ",J11) -> Polttoaine: Uraani | I40: =IF(J12="Kyllä","Kustannukset sis. OPEXiin",I129) -> Kustannukset sis. OPEXiin | J40: =_xlfn.XLOOKUP(J$39,$J$128:$DF$128,$J129:$DF129)*IF($J$12="Kyllä",0,1) -> 0 | K40: =_xlfn.XLOOKUP(K$39,$J$128:$DF$128,$J129:$DF129)*IF($J$12="Kyllä",0,1) -> 0 | L40: =_xlfn.XLOOKUP(L$39,$J$128:$DF$128,$J129:$DF129)*IF($J$12="Kyllä",0,1) -> 0 | M40: =_xlfn.XLOOKUP(M$39,$J$128:$DF$128,$J129:$DF129)*IF($J$12="Kyllä",0,1) -> 0 | N40: =_xlfn.XLOOKUP(N$39,$J$128:$DF$128,$J129:$DF129)*IF($J$12="Kyllä",0,1) -> 0 | O40: =_xlfn.XLOOKUP(O$39,$J$128:$DF$128,$J129:$DF129)*IF($J$12="Kyllä",0,1) -> 0 | P40: =_xlfn.XLOOKUP(P$39,$J$128:$DF$128,$J129:$DF129)*IF($J$12="Kyllä",0,1) -> 0 | Q40: =_xlfn.XLOOKUP(Q$39,$J$128:$DF$128,$J129:$DF129)*IF($J$12="Kyllä",0,1) -> 0 | ... BS40: =_xlfn.XLOOKUP(BS$39,$J$128:$DF$128,$J129:$DF129)*IF($J$12="Kyllä",0,1) -> 0
B41: Pääomakustannukset (rakennuskustannukset) | C41: =H65 -> 55.217104 | D41: /MWhe | E41: =C41*1.062 -> 58.640565 | H41: Polttoaineen päästötase | I41: kgCO2e/MWh | J41: =_xlfn.XLOOKUP(J$39,$J$128:$DF$128,$J130:$DF130) -> 0 | K41: =_xlfn.XLOOKUP(K$39,$J$128:$DF$128,$J130:$DF130) -> 0 | L41: =_xlfn.XLOOKUP(L$39,$J$128:$DF$128,$J130:$DF130) -> 0 | M41: =_xlfn.XLOOKUP(M$39,$J$128:$DF$128,$J130:$DF130) -> 0 | N41: =_xlfn.XLOOKUP(N$39,$J$128:$DF$128,$J130:$DF130) -> 0 | O41: =_xlfn.XLOOKUP(O$39,$J$128:$DF$128,$J130:$DF130) -> 0 | P41: =_xlfn.XLOOKUP(P$39,$J$128:$DF$128,$J130:$DF130) -> 0 | Q41: =_xlfn.XLOOKUP(Q$39,$J$128:$DF$128,$J130:$DF130) -> 0 | ... BS41: =_xlfn.XLOOKUP(BS$39,$J$128:$DF$128,$J130:$DF130) -> 0
B42: Kiinteät käyttö- ja huoltokustannukset | C42: =H73 -> 0 | D42: /MWhe | E42: =C42*1.062 -> 0 | H42: Päästömaksu | I42: =I131 -> 2022 EUR/tCO2e | J42: =_xlfn.XLOOKUP(J$39,$J$128:$DF$128,$J131:$DF131) -> 34.872684 | K42: =_xlfn.XLOOKUP(K$39,$J$128:$DF$128,$J131:$DF131) -> 35.350392 | L42: =_xlfn.XLOOKUP(L$39,$J$128:$DF$128,$J131:$DF131) -> 35.8281 | M42: =_xlfn.XLOOKUP(M$39,$J$128:$DF$128,$J131:$DF131) -> 38.21664 | N42: =_xlfn.XLOOKUP(N$39,$J$128:$DF$128,$J131:$DF131) -> 40.60518 | O42: =_xlfn.XLOOKUP(O$39,$J$128:$DF$128,$J131:$DF131) -> 42.99372 | P42: =_xlfn.XLOOKUP(P$39,$J$128:$DF$128,$J131:$DF131) -> 45.38226 | Q42: =_xlfn.XLOOKUP(Q$39,$J$128:$DF$128,$J131:$DF131) -> 47.7708 | ... BS42: =_xlfn.XLOOKUP(BS$39,$J$128:$DF$128,$J131:$DF131) -> 63.23944
B43: Muuttuvat käyttö- ja huoltokustannukset | C43: =H83 -> 16.52 | D43: /MWhe | E43: =C43*1.062 -> 17.54424 | H43: Keskimääräinen päästötase | I43: =(H107*1000*1000)/(H53*1000) -> 0 | J43: gCO2e/kWh
B44: Polttoainekustannukset | C44: =H88 -> 0 | D44: /MWhe | E44: =C44*1.062 -> 0
B45: Jäte- ja purkukustannukset | C45: =H95 -> 0 | D45: /MWhe | E45: =C45*1.062 -> 0 | J45: =IF(J46=$C$19,$B$19,IF(J46=$C$21,$B$21,IF(J46=$C$22,$B$22,IF(J46=$C$23,$B$23,IF(J46=$C$24,$B$24,""))))) -> Projektin aloitusvuosi | K45: =IF(K46=$C$19,$B$19,IF(K46=$C$21,$B$21,IF(K46=$C$22,$B$22,IF(K46=$C$23,$B$23,IF(K46=$C$24,$B$24,""))))) | L45: =IF(L46=$C$19,$B$19,IF(L46=$C$21,$B$21,IF(L46=$C$22,$B$22,IF(L46=$C$23,$B$23,IF(L46=$C$24,$B$24,""))))) | M45: =IF(M46=$C$19,$B$19,IF(M46=$C$21,$B$21,IF(M46=$C$22,$B$22,IF(M46=$C$23,$B$23,IF(M46=$C$24,$B$24,""))))) | N45: =IF(N46=$C$19,$B$19,IF(N46=$C$21,$B$21,IF(N46=$C$22,$B$22,IF(N46=$C$23,$B$23,IF(N46=$C$24,$B$24,""))))) | O45: =IF(O46=$C$19,$B$19,IF(O46=$C$21,$B$21,IF(O46=$C$22,$B$22,IF(O46=$C$23,$B$23,IF(O46=$C$24,$B$24,""))))) | P45: =IF(P46=$C$19,$B$19,IF(P46=$C$21,$B$21,IF(P46=$C$22,$B$22,IF(P46=$C$23,$B$23,IF(P46=$C$24,$B$24,""))))) | Q45: =IF(Q46=$C$19,$B$19,IF(Q46=$C$21,$B$21,IF(Q46=$C$22,$B$22,IF(Q46=$C$23,$B$23,IF(Q46=$C$24,$B$24,""))))) | ... BS45: =IF(BS46=$C$19,$B$19,IF(BS46=$C$21,$B$21,IF(BS46=$C$22,$B$22,IF(BS46=$C$23,$B$23,IF(BS46=$C$24,$B$24,"")))))
B46: Päästömaksut | C46: =H103 -> 0 | D46: /MWhe | E46: =C46*1.062 -> 0 | H46: Diskonttokerroin | J46: =C$19 -> 2028 | K46: =J46+1 -> 2029 | L46: =K46+1 -> 2030 | M46: =L46+1 -> 2031 | N46: =M46+1 -> 2032 | O46: =N46+1 -> 2033 | P46: =O46+1 -> 2034 | Q46: =P46+1 -> 2035 | R46: =Q46+1 -> 2036 | ... BS46: =BR46+1 -> 2089
B47: Hiilidioksidin talteenoton ja varastoinnin kustannukset | C47: =H112 -> 0 | D47: /MWhe | E47: =C47*1.062 -> 0
B48: Lämmön myynti | C48: =H117 -> 0 | D48: /MWhe | E48: =C48*1.062 -> 0 | I48: Diskonttokerroin | J48: 1 | K48: =J48/(1+$C$33) -> 0.95238095 | L48: =K48/(1+$C$33) -> 0.90702948 | M48: =L48/(1+$C$33) -> 0.8638376 | N48: =M48/(1+$C$33) -> 0.82270247 | O48: =N48/(1+$C$33) -> 0.78352617 | P48: =O48/(1+$C$33) -> 0.7462154 | Q48: =P48/(1+$C$33) -> 0.71068133 | R48: =Q48/(1+$C$33) -> 0.67683936 | ... BS48: =BR48/(1+$C$33) -> 0.050986213
B50: Sähkön tuotanto | H50: Yhteensä | I50: Yksikkö
B51: Nimellistehosta käytössä | D51: 100 % x (100 % + Sähköntuotannon muutos) käyttöiän ajan | I51: % | J51: =IF(AND(J46>=$C$22,J46<$C$23),100%,0%) -> 0 | K51: =(J51*(100%+$C28)+IF(K46=$C$22,100%,0%))*IF(K46>=$C23,0,1) -> 0 | L51: =(K51*(100%+$C28)+IF(L46=$C$22,100%,0%))*IF(L46>=$C23,0,1) -> 0 | M51: =(L51*(100%+$C28)+IF(M46=$C$22,100%,0%))*IF(M46>=$C23,0,1) -> 0 | N51: =(M51*(100%+$C28)+IF(N46=$C$22,100%,0%))*IF(N46>=$C23,0,1) -> 0 | O51: =(N51*(100%+$C28)+IF(O46=$C$22,100%,0%))*IF(O46>=$C23,0,1) -> 0 | P51: =(O51*(100%+$C28)+IF(P46=$C$22,100%,0%))*IF(P46>=$C23,0,1) -> 0 | Q51: =(P51*(100%+$C28)+IF(Q46=$C$22,100%,0%))*IF(Q46>=$C23,0,1) -> 0 | R51: =(Q51*(100%+$C28)+IF(R46=$C$22,100%,0%))*IF(R46>=$C23,0,1) -> 1 | ... BS51: =(BR51*(100%+$C28)+IF(BS46=$C$22,100%,0%))*IF(BS46>=$C23,0,1) -> 1
B52: Käyttöaste | H52: =C29*100 -> 89 | I52: % | J52: =C29 -> 0.89 | K52: =J52 -> 0.89 | L52: =K52 -> 0.89 | M52: =L52 -> 0.89 | N52: =M52 -> 0.89 | O52: =N52 -> 0.89 | P52: =O52 -> 0.89 | Q52: =P52 -> 0.89 | R52: =Q52 -> 0.89 | ... BS52: =BR52 -> 0.89
B53: Sähkön tuotanto yhteensä | D53: Nimellisteho x nimellistehosta käytössä x käyttöaste x 8760 h | H53: =SUM(J53:BS53) -> 526257000 | I53: MWhe | J53: =$C$26*J51*J52*8760 -> 0 | K53: =$C$26*K51*K52*8760 -> 0 | L53: =$C$26*L51*L52*8760 -> 0 | M53: =$C$26*M51*M52*8760 -> 0 | N53: =$C$26*N51*N52*8760 -> 0 | O53: =$C$26*O51*O52*8760 -> 0 | P53: =$C$26*P51*P52*8760 -> 0 | Q53: =$C$26*Q51*Q52*8760 -> 0 | ... BS53: =$C$26*BS51*BS52*8760 -> 9745500
B54: Sähköntuotannon nykyarvo | D54: Sähkön tuotanto yhteensä x diskonttokerroin | H54: =SUM(J54:BS54) -> 1.2858118e+08 | I54: MWhe | J54: =J53*J48 -> 0 | K54: =K53*K48 -> 0 | L54: =L53*L48 -> 0 | M54: =M53*M48 -> 0 | N54: =N53*N48 -> 0 | O54: =O53*O48 -> 0 | P54: =P53*P48 -> 0 | Q54: =Q53*Q48 -> 0 | ... BS54: =BS53*BS48 -> 496886.14
B56: Suunnittelukustannukset | H56: =H63/H54 -> 0 | I56: EUR/MWhe
B57: Suunnittelukustannusten aikataulu | D57: Ensimmäinen vuosi tarkoittaa suunnittelun aloittamisvuotta | I57: % | J57: =$U7 -> 0 | K57: =$U8 -> 0 | L57: =$U9 -> 0 | M57: =$U10 -> 0 | N57: =$U11 -> 0 | O57: =$U12 -> 0 | P57: =$U13 -> 0 | Q57: =$U14 -> 0 | R57: =$U15 -> 0 | S57: =$U16 -> 0
B58: Suunnittelukustannukset | H58: =_xlfn.XLOOKUP(C9,I22:I24,J22:J24) -> 0 | I58: EUR/kWe
D59: =_xlfn.CONCAT("EUR/kW x 1000 x nimellisteho (",C26," MW)") -> EUR/kW x 1000 x nimellisteho (1250 MW) | H59: =H58*C26*1000 -> 0 | I59: EUR | J59: =$H$59*J57 -> 0 | K59: =$H$59*K57 -> 0 | L59: =$H$59*L57 -> 0 | M59: =$H$59*M57 -> 0 | N59: =$H$59*N57 -> 0 | O59: =$H$59*O57 -> 0 | P59: =$H$59*P57 -> 0 | Q59: =$H$59*Q57 -> 0 | ... S59: =$H$59*S57 -> 0
B60: =H21 -> Regulaatio, luvitus, julkiset kuulemiset | H60: =J21 -> 0 | I60: EUR/kWe
D61: =_xlfn.CONCAT("EUR/kW x 1000 x nimellisteho (",C26," MW)") -> EUR/kW x 1000 x nimellisteho (1250 MW) | H61: =H60*C26*1000 -> 0 | I61: EUR | J61: =$H$61*J57 -> 0 | K61: =$H$61*K57 -> 0 | L61: =$H$61*L57 -> 0 | M61: =$H$61*M57 -> 0 | N61: =$H$61*N57 -> 0 | O61: =$H$61*O57 -> 0 | P61: =$H$61*P57 -> 0 | Q61: =$H$61*Q57 -> 0 | ... S61: =$H$61*S57 -> 0
B62: Suunnittelukustannukset yhteensä | D62: Suunnittelu + regulaatiokustannukset | H62: =SUM(J62:BS62) -> 0 | I62: EUR | J62: =J59+J61 -> 0 | K62: =K59+K61 -> 0 | L62: =L59+L61 -> 0 | M62: =M59+M61 -> 0 | N62: =N59+N61 -> 0 | O62: =O59+O61 -> 0 | P62: =P59+P61 -> 0 | Q62: =Q59+Q61 -> 0 | ... S62: =S59+S61 -> 0
B63: Suunnittelukustannusten nykyarvo | D63: Suunnittelukustannukset x diskonttokerroin | H63: =SUM(J63:BS63) -> 0 | I63: EUR | J63: =J62*J48 -> 0 | K63: =K62*K48 -> 0 | L63: =L62*L48 -> 0 | M63: =M62*M48 -> 0 | N63: =N62*N48 -> 0 | O63: =O62*O48 -> 0 | P63: =P62*P48 -> 0 | Q63: =Q62*Q48 -> 0 | ... S63: =S62*S48 -> 0
B65: Pääomakustannukset (rakentamis- ja infrastruktuurikustannukset, CAPEX) | H65: =H71/H54 -> 55.217104 | I65: EUR/MWhe
B66: Rakennuskustannusten aikataulu | D66: Ensimmäinen vuosi tarkoittaa rakentamisen aloittamisvuotta | I66: % | J66: =_xlfn.XLOOKUP((J46-$C$21+1),$W$7:$W$21,$X$7:$X$21,0) -> 0.14285714 | K66: =_xlfn.XLOOKUP((K46-$C$21+1),$W$7:$W$21,$X$7:$X$21,0) -> 0.14285714 | L66: =_xlfn.XLOOKUP((L46-$C$21+1),$W$7:$W$21,$X$7:$X$21,0) -> 0.14285714 | M66: =_xlfn.XLOOKUP((M46-$C$21+1),$W$7:$W$21,$X$7:$X$21,0) -> 0.14285714 | N66: =_xlfn.XLOOKUP((N46-$C$21+1),$W$7:$W$21,$X$7:$X$21,0) -> 0.14285714 | O66: =_xlfn.XLOOKUP((O46-$C$21+1),$W$7:$W$21,$X$7:$X$21,0) -> 0.14285714 | P66: =_xlfn.XLOOKUP((P46-$C$21+1),$W$7:$W$21,$X$7:$X$21,0) -> 0.14285714 | Q66: =_xlfn.XLOOKUP((Q46-$C$21+1),$W$7:$W$21,$X$7:$X$21,0) -> 0 | ... BS66: =_xlfn.XLOOKUP((BS46-$C$21+1),$W$7:$W$21,$X$7:$X$21,0) -> 0
B67: Pääomakustannus (CAPEX) | D67: Pääomakustannukset per kW nimellistehoa | H67: =_xlfn.XLOOKUP(C11,I28:I30,J28:J30) -> 6544 | I67: EUR/kWe
B68: CAPEX yhteensä | D68: =_xlfn.CONCAT("EUR/kW x 1000 x nimellisteho (",C26," MW)") -> EUR/kW x 1000 x nimellisteho (1250 MW) | H68: =(H67*C26*1000) -> 8180000000 | I68: EUR | J68: =$H$68*J66 -> 1.1685714e+09 | K68: =$H$68*K66 -> 1.1685714e+09 | L68: =$H$68*L66 -> 1.1685714e+09 | M68: =$H$68*M66 -> 1.1685714e+09 | N68: =$H$68*N66 -> 1.1685714e+09 | O68: =$H$68*O66 -> 1.1685714e+09 | P68: =$H$68*P66 -> 1.1685714e+09 | Q68: =$H$68*Q66 -> 0 | ... BS68: =$H$68*BS66 -> 0
B69: Infrastruktuurikustannus | D69: Infrastruktuurikustannukset yhteensä | H69: =_xlfn.XLOOKUP(C13,I34:I36,J34:J36) -> 0 | I69: EUR | J69: =$H$69*J66 -> 0 | K69: =$H$69*K66 -> 0 | L69: =$H$69*L66 -> 0 | M69: =$H$69*M66 -> 0 | N69: =$H$69*N66 -> 0 | O69: =$H$69*O66 -> 0 | P69: =$H$69*P66 -> 0 | Q69: =$H$69*Q66 -> 0 | ... BS69: =$H$69*BS66 -> 0
B70: Pääomakustannukset yhteensä | D70: CAPEX + infrastruktuurikustannus | H70: =SUM(J70:BS70) -> 8.18e+09 | I70: EUR | J70: =J68+J69 -> 1.1685714e+09 | K70: =K68+K69 -> 1.1685714e+09 | L70: =L68+L69 -> 1.1685714e+09 | M70: =M68+M69 -> 1.1685714e+09 | N70: =N68+N69 -> 1.1685714e+09 | O70: =O68+O69 -> 1.1685714e+09 | P70: =P68+P69 -> 1.1685714e+09 | Q70: =Q68+Q69 -> 0 | ... BS70: =BS68+BS69 -> 0
B71: Pääomakustannusten nykyarvo | D71: Pääomakustannukset yhteensä x diskonttokerroin | H71: =SUM(J71:BS71) -> 7.0998802e+09 | I71: EUR | J71: =J70*J48 -> 1.1685714e+09 | K71: =K70*K48 -> 1.1129252e+09 | L71: =L70*L48 -> 1.0599287e+09 | M71: =M70*M48 -> 1.0094559e+09 | N71: =N70*N48 -> 9.6138661e+08 | O71: =O70*O48 -> 9.1560629e+08 | P71: =P70*P48 -> 8.7200599e+08 | Q71: =Q70*Q48 -> 0 | ... BS71: =BS70*BS48 -> 0
B73: Kiinteät käyttö- ja huoltokustannukset (OPEX tai O&M) | H73: =H81/H54 -> 0 | I73: EUR/MWhe
B74: Kiinteät käyttö- ja huoltokustannukset | D74: Ensimmäinen vuosi tarkoittaa käytön aloittamisvuotta | H74: =O7 -> 0 | I74: EUR/MWe | J74: =IF(AND(J$46>=$C$22,J$46<$C$23),$H74,0%) -> 0 | K74: =IF(AND(K46>=$C22,K46<$C23),$H74,0%) -> 0 | L74: =IF(AND(L46>=$C22,L46<$C23),$H74,0%) -> 0 | M74: =IF(AND(M46>=$C22,M46<$C23),$H74,0%) -> 0 | N74: =IF(AND(N46>=$C22,N46<$C23),$H74,0%) -> 0 | O74: =IF(AND(O46>=$C22,O46<$C23),$H74,0%) -> 0 | P74: =IF(AND(P46>=$C22,P46<$C23),$H74,0%) -> 0 | Q74: =IF(AND(Q46>=$C22,Q46<$C23),$H74,0%) -> 0 | R74: =IF(AND(R46>=$C22,R46<$C23),$H74,0%) -> 0 | ... BS74: =IF(AND(BS46>=$C22,BS46<$C23),$H74,0%) -> 0
B75: Kiinteät käyttö- ja huoltokustannukset yhteensä | D75: =_xlfn.CONCAT("EUR/MW x nimellisteho (",B26," MW)") -> EUR/MW x nimellisteho (Sähköntuotannon nimellisteho MW) | H75: =SUM(J75:BS75) -> 0 | I75: EUR | J75: =J74*$C$26 -> 0 | K75: =K74*$C$26 -> 0 | L75: =L74*$C$26 -> 0 | M75: =M74*$C$26 -> 0 | N75: =N74*$C$26 -> 0 | O75: =O74*$C$26 -> 0 | P75: =P74*$C$26 -> 0 | Q75: =Q74*$C$26 -> 0 | ... BS75: =BS74*$C$26 -> 0
B76: Vakuutus | H76: =O9 -> 0 | I76: EUR/MWe | J76: =IF(AND(J$46>=$C$22,J$46<$C$23),$H76,0%) -> 0 | K76: =IF(AND(K$46>=$C$22,K$46<$C$23),$H76,0%) -> 0 | L76: =IF(AND(L$46>=$C$22,L$46<$C$23),$H76,0%) -> 0 | M76: =IF(AND(M$46>=$C$22,M$46<$C$23),$H76,0%) -> 0 | N76: =IF(AND(N$46>=$C$22,N$46<$C$23),$H76,0%) -> 0 | O76: =IF(AND(O$46>=$C$22,O$46<$C$23),$H76,0%) -> 0 | P76: =IF(AND(P$46>=$C$22,P$46<$C$23),$H76,0%) -> 0 | Q76: =IF(AND(Q$46>=$C$22,Q$46<$C$23),$H76,0%) -> 0 | ... BS76: =IF(AND(BS$46>=$C$22,BS$46<$C$23),$H76,0%) -> 0
B77: Vakuutus yhteensä | D77: =_xlfn.CONCAT("EUR/MW x nimellisteho (",B26," MW)") -> EUR/MW x nimellisteho (Sähköntuotannon nimellisteho MW) | H77: =SUM(J77:BS77) -> 0 | I77: EUR | J77: =J76*$C$26 -> 0 | K77: =K76*$C$26 -> 0 | L77: =L76*$C$26 -> 0 | M77: =M76*$C$26 -> 0 | N77: =N76*$C$26 -> 0 | O77: =O76*$C$26 -> 0 | P77: =P76*$C$26 -> 0 | Q77: =Q76*$C$26 -> 0 | ... BS77: =BS76*$C$26 -> 0
B78: Liittymis- ym kustannukset | H78: =O10 -> 0 | I78: EUR/MWe | J78: =IF(AND(J$46>=$C$22,J$46<$C$23),$H78,0%) -> 0 | K78: =IF(AND(K$46>=$C$22,K$46<$C$23),$H78,0%) -> 0 | L78: =IF(AND(L$46>=$C$22,L$46<$C$23),$H78,0%) -> 0 | M78: =IF(AND(M$46>=$C$22,M$46<$C$23),$H78,0%) -> 0 | N78: =IF(AND(N$46>=$C$22,N$46<$C$23),$H78,0%) -> 0 | O78: =IF(AND(O$46>=$C$22,O$46<$C$23),$H78,0%) -> 0 | P78: =IF(AND(P$46>=$C$22,P$46<$C$23),$H78,0%) -> 0 | Q78: =IF(AND(Q$46>=$C$22,Q$46<$C$23),$H78,0%) -> 0 | ... BS78: =IF(AND(BS$46>=$C$22,BS$46<$C$23),$H78,0%) -> 0
B79: Liittymis- ym kustannukset yhteensä | D79: =_xlfn.CONCAT("EUR/MW x nimellisteho (",B26," MW)") -> EUR/MW x nimellisteho (Sähköntuotannon nimellisteho MW) | H79: =SUM(J79:BS79) -> 0 | I79: EUR | J79: =J78*$C$26 -> 0 | K79: =K78*$C$26 -> 0 | L79: =L78*$C$26 -> 0 | M79: =M78*$C$26 -> 0 | N79: =N78*$C$26 -> 0 | O79: =O78*$C$26 -> 0 | P79: =P78*$C$26 -> 0 | Q79: =Q78*$C$26 -> 0 | ... BS79: =BS78*$C$26 -> 0
B80: Kiinteät kustannukset yhteensä | D80: Kiinteät kustannukset + vakuutus + liittyminen | H80: =SUM(J80:BS80) -> 0 | I80: EUR | J80: =J75+J77+J79 -> 0 | K80: =K75+K77+K79 -> 0 | L80: =L75+L77+L79 -> 0 | M80: =M75+M77+M79 -> 0 | N80: =N75+N77+N79 -> 0 | O80: =O75+O77+O79 -> 0 | P80: =P75+P77+P79 -> 0 | Q80: =Q75+Q77+Q79 -> 0 | ... BS80: =BS75+BS77+BS79 -> 0
B81: Kiinteiden kustannusten nykyarvo | D81: Kiinteät kustannukset yhteensä x diskonttokerroin | H81: =SUM(J81:BS81) -> 0 | I81: EUR | J81: =J80*J48 -> 0 | K81: =K80*K48 -> 0 | L81: =L80*L48 -> 0 | M81: =M80*M48 -> 0 | N81: =N80*N48 -> 0 | O81: =O80*O48 -> 0 | P81: =P80*P48 -> 0 | Q81: =Q80*Q48 -> 0 | ... BS81: =BS80*BS48 -> 0
B83: Muuttuvat käyttö- ja huoltokustannukset (OPEX tai O&M) | H83: =H86/H54 -> 16.52 | I83: EUR/MWhe
B84: Muuttuvat käyttö- ja huoltokustannukset (OPEX) | D84: Ensimmäinen vuosi tarkoittaa käytön aloittamisvuotta | H84: =O8 -> 16.52 | I84: EUR/MWhe | J84: =IF(AND(J$46>=$C$22,J$46<$C$23),$H84,0%) -> 0 | K84: =IF(AND(K$46>=$C$22,K$46<$C$23),$H84,0%) -> 0 | L84: =IF(AND(L$46>=$C$22,L$46<$C$23),$H84,0%) -> 0 | M84: =IF(AND(M$46>=$C$22,M$46<$C$23),$H84,0%) -> 0 | N84: =IF(AND(N$46>=$C$22,N$46<$C$23),$H84,0%) -> 0 | O84: =IF(AND(O$46>=$C$22,O$46<$C$23),$H84,0%) -> 0 | P84: =IF(AND(P$46>=$C$22,P$46<$C$23),$H84,0%) -> 0 | Q84: =IF(AND(Q$46>=$C$22,Q$46<$C$23),$H84,0%) -> 0 | ... BS84: =IF(AND(BS$46>=$C$22,BS$46<$C$23),$H84,0%) -> 16.52
B85: Muuttuvat käyttö- ja huoltokustannukset yhteensä | D85: EUR/MWh x tuotanto | H85: =SUM(J85:BS85) -> 8693765640 | I85: EUR | J85: =J84*J53 -> 0 | K85: =K84*K53 -> 0 | L85: =L84*L53 -> 0 | M85: =M84*M53 -> 0 | N85: =N84*N53 -> 0 | O85: =O84*O53 -> 0 | P85: =P84*P53 -> 0 | Q85: =Q84*Q53 -> 0 | ... BS85: =BS84*BS53 -> 160995660
B86: Muuttuvien käyttö- ja huoltokustannusten nykyarvo | D86: Muuttuvat käyttö- ja huoltokustannukset x diskonttokerroin | H86: =SUM(J86:BS86) -> 2.124161e+09 | I86: EUR | J86: =J85*J48 -> 0 | K86: =K85*K48 -> 0 | L86: =L85*L48 -> 0 | M86: =M85*M48 -> 0 | N86: =N85*N48 -> 0 | O86: =O85*O48 -> 0 | P86: =P85*P48 -> 0 | Q86: =Q85*Q48 -> 0 | ... BS86: =BS85*BS48 -> 8208559
B88: Polttoainekustannukset | H88: =H93/H54 -> 0 | I88: EUR/MWhe
B89: Polttoaineen hinta | D89: =IF(J12="Kyllä","Sisältyy muuttuvaan OPEXiin",_xlfn.CONCAT("Skenaario: ",H129)) -> Sisältyy muuttuvaan OPEXiin | I89: EUR/MWh | J89: =J40 -> 0 | K89: =K40 -> 0 | L89: =L40 -> 0 | M89: =M40 -> 0 | N89: =N40 -> 0 | O89: =O40 -> 0 | P89: =P40 -> 0 | Q89: =Q40 -> 0 | ... BS89: =BS40 -> 0
B90: Hyötysuhde | D90: Hyötysuhde (alempi lämpöarvo, LHV) | H90: =C27*100 -> 37 | I90: % | J90: =$C27 -> 0.37 | K90: =$C27 -> 0.37 | L90: =$C27 -> 0.37 | M90: =$C27 -> 0.37 | N90: =$C27 -> 0.37 | O90: =$C27 -> 0.37 | P90: =$C27 -> 0.37 | Q90: =$C27 -> 0.37 | ... BS90: =$C27 -> 0.37
B91: Polttoaineen kulutus yhteensä | D91: Tuotanto / hyötysuhde (LHV) | H91: =SUM(J91:BS91) -> 1.4223162e+09 | I91: MWh | J91: =J53/J90 -> 0 | K91: =K53/K90 -> 0 | L91: =L53/L90 -> 0 | M91: =M53/M90 -> 0 | N91: =N53/N90 -> 0 | O91: =O53/O90 -> 0 | P91: =P53/P90 -> 0 | Q91: =Q53/Q90 -> 0 | ... BS91: =BS53/BS90 -> 26339189
B92: Polttoainekustannukset yhteensä | D92: Polttoaineen hinta x polttoaineen kulutus | H92: =SUM(J92:AM92) -> 0 | I92: EUR | J92: =J89*J91 -> 0 | K92: =K89*K91 -> 0 | L92: =L89*L91 -> 0 | M92: =M89*M91 -> 0 | N92: =N89*N91 -> 0 | O92: =O89*O91 -> 0 | P92: =P89*P91 -> 0 | Q92: =Q89*Q91 -> 0 | ... BS92: =BS89*BS91 -> 0
B93: Polttoainekustannusten nykyarvo | D93: Polttoainekustannukset x diskonttokerroin | H93: =SUM(J93:AM93) -> 0 | I93: EUR | J93: =J92*J48 -> 0 | K93: =K92*K48 -> 0 | L93: =L92*L48 -> 0 | M93: =M92*M48 -> 0 | N93: =N92*N48 -> 0 | O93: =O92*O48 -> 0 | P93: =P92*P48 -> 0 | Q93: =Q92*Q48 -> 0 | ... BS93: =BS92*BS48 -> 0
B95: Jäte- ja purkukustannukset | H95: =H101/H54 -> 0 | I95: EUR/MWhe
B96: Jätemaksu | H96: =SUM(J96:BS96) -> 0 | I96: EUR/MWhe | J96: 0 | K96: 0 | L96: 0 | M96: 0 | N96: 0 | O96: 0 | P96: 0 | Q96: 0 | R96: 0 | S96: 0 | T96: 0 | U96: 0 | V96: 0 | W96: 0 | X96: 0 | Y96: 0 | Z96: 0 | AA96: 0 | AB96: 0 | AC96: 0 | AD96: 0 | AE96: 0 | AF96: 0 | AG96: 0 | AH96: 0 | AI96: 0 | AJ96: 0 | AK96: 0 | AL96: 0 | AM96: 0 | AN96: 0 | AO96: 0 | AP96: 0 | AQ96: 0 | AR96: 0 | AS96: 0 | AT96: 0 | AU96: 0 | AV96: 0 | AW96: 0 | AX96: 0 | AY96: 0 | AZ96: 0 | BA96: 0 | BB96: 0 | BC96: 0 | BD96: 0 | BE96: 0 | BF96: 0 | BG96: 0 | BH96: 0 | BI96: 0 | BJ96: 0 | BK96: 0 | BL96: 0 | BM96: 0 | BN96: 0 | BO96: 0 | BP96: 0 | BQ96: 0 | BR96: 0 | BS96: 0
B97: Jätekustannukset | D97: Jätemaksu x tuotanto | H97: =SUM(J97:BS97) -> 0 | I97: EUR | J97: =J96*J53 -> 0 | K97: =K96*K53 -> 0 | L97: =L96*L53 -> 0 | M97: =M96*M53 -> 0 | N97: =N96*N53 -> 0 | O97: =O96*O53 -> 0 | P97: =P96*P53 -> 0 | Q97: =Q96*Q53 -> 0 | ... BS97: =BS96*BS53 -> 0
B98: Purkukustannusten osuus rakentamisen ja infrastruktuurin kustannuksista | H98: =_xlfn.XLOOKUP(C14,N16:N18,O16:O18) -> 0 | I98: % | J98: =H98/100 -> 0 | K98: =J98 -> 0 | L98: =K98 -> 0 | M98: =L98 -> 0 | N98: =M98 -> 0 | O98: =N98 -> 0 | P98: =O98 -> 0 | Q98: =P98 -> 0 | R98: =Q98 -> 0 | ... BS98: =BR98 -> 0
B99: Purkukustannukset | D99: =_xlfn.CONCAT(H98," % rakentamisen ja infrastruktuurin kustannuksista") -> 0 % rakentamisen ja infrastruktuurin kustannuksista | H99: =SUM(J99:BS99) -> 0 | I99: EUR | J99: =IF((J46+$O19)=$C23,(($H68+$H69)*J98),0) -> 0 | K99: =IF((K46+$O19)=$C23,(($H68+$H69)*K98),0) -> 0 | L99: =IF((L46+$O19)=$C23,(($H68+$H69)*L98),0) -> 0 | M99: =IF((M46+$O19)=$C23,(($H68+$H69)*M98),0) -> 0 | N99: =IF((N46+$O19)=$C23,(($H68+$H69)*N98),0) -> 0 | O99: =IF((O46+$O19)=$C23,(($H68+$H69)*O98),0) -> 0 | P99: =IF((P46+$O19)=$C23,(($H68+$H69)*P98),0) -> 0 | Q99: =IF((Q46+$O19)=$C23,(($H68+$H69)*Q98),0) -> 0 | ... BS99: =IF((BS46+$O19)=$C23,(($H68+$H69)*BS98),0) -> 0
B100: Purkamis- ja jätekustannukset yhteensä | D100: Jätekustannukset + purkukustannukset | H100: =SUM(J100:BS100) -> 0 | I100: EUR | J100: =J97+J99 -> 0 | K100: =K97+K99 -> 0 | L100: =L97+L99 -> 0 | M100: =M97+M99 -> 0 | N100: =N97+N99 -> 0 | O100: =O97+O99 -> 0 | P100: =P97+P99 -> 0 | Q100: =Q97+Q99 -> 0 | ... BS100: =BS97+BS99 -> 0
B101: Purkamis- ja jätekustannusten nykyarvo | D101: Purkamis- ja jätekustannukset.x diskonttokerroin | H101: =SUM(Q101:BD101) -> 0 | I101: EUR | J101: =J100*J48 -> 0 | K101: =K100*K48 -> 0 | L101: =L100*L48 -> 0 | M101: =M100*M48 -> 0 | N101: =N100*N48 -> 0 | O101: =O100*O48 -> 0 | P101: =P100*P48 -> 0 | Q101: =Q100*Q48 -> 0 | ... BS101: =BS100*BS48 -> 0
B103: Päästömaksut | H103: =H110/H54 -> 0 | I103: EUR/MWhe
B104: Kasvihuonekaasupäästöjen hinta | D104: =_xlfn.CONCAT("Skenaario: ",H131) -> Skenaario: Suomi, Ilmasto- ja energiastrategia (2021) | I104: EUR/tCO2e | J104: =J42 -> 34.872684 | K104: =K42 -> 35.350392 | L104: =L42 -> 35.8281 | M104: =M42 -> 38.21664 | N104: =N42 -> 40.60518 | O104: =O42 -> 42.99372 | P104: =P42 -> 45.38226 | Q104: =Q42 -> 47.7708 | ... BS104: =BS42 -> 63.23944
B105: Hiilidioksidin talteenotto | D105: Talteenotettujen päästöjen osuus | H105: =O14 -> 0 | I105: % | J105: =$H105/100 -> 0 | K105: =$H105/100 -> 0 | L105: =$H105/100 -> 0 | M105: =$H105/100 -> 0 | N105: =$H105/100 -> 0 | O105: =$H105/100 -> 0 | P105: =$H105/100 -> 0 | Q105: =$H105/100 -> 0 | ... BS105: =$H105/100 -> 0
B106: Polttoaineen ominaispäästöt | D106: Polttoaineen ominaispäästöt per MWh(t) | I106: kgCO2e/MWh | J106: =J41 -> 0 | K106: =K41 -> 0 | L106: =L41 -> 0 | M106: =M41 -> 0 | N106: =N41 -> 0 | O106: =O41 -> 0 | P106: =P41 -> 0 | Q106: =Q41 -> 0 | ... BS106: =BS41 -> 0
B107: Kasvihuonekaasupäästöt yhteensä | D107: Polttoaineenkulutus x ominaispäästöt | H107: =SUM(J107:BS107) -> 0 | I107: tCO2e | J107: =J106*J91/1000 -> 0 | K107: =K106*K91/1000 -> 0 | L107: =L106*L91/1000 -> 0 | M107: =M106*M91/1000 -> 0 | N107: =N106*N91/1000 -> 0 | O107: =O106*O91/1000 -> 0 | P107: =P106*P91/1000 -> 0 | Q107: =Q106*Q91/1000 -> 0 | ... BS107: =BS106*BS91/1000 -> 0
B108: Hiilen talteenotto yhteensä | D108: Päästöt yhteensä x talteenotettujen päästöjen osuus | H108: =SUM(J108:BS108) -> 0 | I108: tCO2e | J108: =J105*J107 -> 0 | K108: =K105*K107 -> 0 | L108: =L105*L107 -> 0 | M108: =M105*M107 -> 0 | N108: =N105*N107 -> 0 | O108: =O105*O107 -> 0 | P108: =P105*P107 -> 0 | Q108: =Q105*Q107 -> 0 | ... BS108: =BS105*BS107 -> 0
B109: Päästöjen kustannus yhteensä | D109: (Päästöt yhteensä - hiilen talteenotto) x khk-päästöjen hinta | H109: =SUM(J109:BS109) -> 0 | I109: EUR | J109: =(J107-J108)*J104 -> 0 | K109: =(K107-K108)*K104 -> 0 | L109: =(L107-L108)*L104 -> 0 | M109: =(M107-M108)*M104 -> 0 | N109: =(N107-N108)*N104 -> 0 | O109: =(O107-O108)*O104 -> 0 | P109: =(P107-P108)*P104 -> 0 | Q109: =(Q107-Q108)*Q104 -> 0 | ... BS109: =(BS107-BS108)*BS104 -> 0
...

Sheet Laitokset
A1: Vuodelta 2023. Hinnat 2022 EUR.
A2: Lähde | D2: https://www.gov.uk/government/publications/electricity-generation-costs-2023 | E2: https://www.gov.uk/government/publications/electricity-generation-costs-2024 | F2: https://www.gov.uk/government/publications/electricity-generation-costs-2025 | G2: https://www.gov.uk/government/publications/electricity-generation-costs-2026 | H2: https://www.gov.uk/government/publications/electricity-generation-costs-2027 | I2: https://www.gov.uk/government/publications/electricity-generation-costs-2028 | J2: https://www.gov.uk/government/publications/electricity-generation-costs-2029 | K2: https://www.gov.uk/government/publications/electricity-generation-costs-2030 | L2: https://www.gov.uk/government/publications/electricity-generation-costs-2031 | M2: https://www.gov.uk/government/publications/electricity-generation-costs-2032 | N2: https://www.gov.uk/government/publications/electricity-generation-costs-2033 | O2: https://www.gov.uk/government/publications/electricity-generation-costs-2034 | P2: https://www.gov.uk/government/publications/electricity-generation-costs-2035 | Q2: https://www.gov.uk/government/publications/electricity-generation-costs-2036 | R2: https://www.gov.uk/government/publications/electricity-generation-costs-2037 | S2: https://www.gov.uk/government/publications/electricity-generation-costs-2038 | T2: https://www.gov.uk/government/publications/electricity-generation-costs-2039 | U2: https://www.gov.uk/government/publications/electricity-generation-costs-2040 | V2: https://www.gov.uk/government/publications/electricity-generation-costs-2041 | W2: https://www.gov.uk/government/publications/electricity-generation-costs-2042 | X2: https://www.gov.uk/government/publications/electricity-generation-costs-2043 | Y2: https://www.gov.uk/government/publications/electricity-generation-costs-2044 | Z2: https://www.gov.uk/government/publications/electricity-generation-costs-2045 | AA2: https://www.gov.uk/government/publications/electricity-generation-costs-2046 | AB2: https://www.gov.uk/government/publications/electricity-generation-costs-2047 | AC2: https://www.gov.uk/government/publications/electricity-generation-costs-2048 | AD2: https://www.gov.uk/government/publications/electricity-generation-costs-2049 | AE2: https://www.gov.uk/government/publications/electricity-generation-costs-2050 | AF2: https://www.gov.uk/government/publications/electricity-generation-costs-2051 | AG2: https://www.gov.uk/government/publications/electricity-generation-costs-2052 | AH2: https://www.gov.uk/government/publications/electricity-generation-costs-2053 | AI2: https://www.gov.uk/government/publications/electricity-generation-costs-2054 | AJ2: https://www.gov.uk/government/publications/electricity-generation-costs-2055 | AK2: https://www.gov.uk/government/publications/electricity-generation-costs-2056 | AL2: https://www.gov.uk/government/publications/electricity-generation-costs-2057 | AM2: https://www.gov.uk/government/publications/electricity-generation-costs-2058 | AN2: https://www.gov.uk/government/publications/electricity-generation-costs-2059 | AO2: https://www.gov.uk/government/publications/electricity-generation-costs-2060 | AP2: https://www.gov.uk/government/publications/electricity-generation-costs-2061 | AQ2: https://www.gov.uk/government/publications/electricity-generation-costs-2062 | AR2: https://www.gov.uk/government/publications/electricity-generation-costs-2063 | AS2: https://www.gov.uk/government/publications/electricity-generation-costs-2064 | AT2: https://www.gov.uk/government/publications/electricity-generation-costs-2065 | AU2: https://www.gov.uk/government/publications/electricity-generation-costs-2066 | AV2: https://www.gov.uk/government/publications/electricity-generation-costs-2067 | AW2: https://www.gov.uk/government/publications/electricity-generation-costs-2068 | AX2: https://www.gov.uk/government/publications/electricity-generation-costs-2069 | AY2: https://www.gov.uk/government/publications/electricity-generation-costs-2070 | AZ2: https://www.gov.uk/government/publications/electricity-generation-costs-2071 | BA2: https://www.gov.uk/government/publications/electricity-generation-costs-2072 | BB2: https://www.gov.uk/government/publications/electricity-generation-costs-2073 | BC2: https://www.gov.uk/government/publications/electricity-generation-costs-2074 | BD2: https://www.gov.uk/government/publications/electricity-generation-costs-2075 | BE2: https://www.gov.uk/government/publications/electricity-generation-costs-2076 | BF2: https://www.gov.uk/government/publications/electricity-generation-costs-2077 | BG2: https://www.gov.uk/government/publications/electricity-generation-costs-2078 | BH2: https://www.gov.uk/government/publications/electricity-generation-costs-2079 | BI2: https://www.gov.uk/government/publications/electricity-generation-costs-2080 | BJ2: https://www.gov.uk/government/publications/electricity-generation-costs-2081 | BK2: https://www.gov.uk/government/publications/electricity-generation-costs-2082 | BL2: https://www.gov.uk/government/publications/electricity-generation-costs-2083 | BM2: https://www.gov.uk/government/publications/electricity-generation-costs-2084 | BN2: https://www.gov.uk/government/publications/electricity-generation-costs-2085 | BO2: https://www.gov.uk/government/publications/electricity-generation-costs-2086 | BP2: https://www.gov.uk/government/publications/electricity-generation-costs-2087 | BQ2: https://www.gov.uk/government/publications/electricity-generation-costs-2088 | BR2: https://www.gov.uk/government/publications/electricity-generation-costs-2089 | BS2: https://www.gov.uk/government/publications/electricity-generation-costs-2090 | BT2: https://www.gov.uk/government/publications/electricity-generation-costs-2091 | BU2: https://www.gov.uk/government/publications/electricity-generation-costs-2092 | BV2: https://www.gov.uk/government/publications/electricity-generation-costs-2093 | BW2: https://www.gov.uk/government/publications/electricity-generation-costs-2094 | BX2: https://www.gov.uk/government/publications/electricity-generation-costs-2095 | BY2: https://www.gov.uk/government/publications/electricity-generation-costs-2096 | BZ2: https://www.gov.uk/government/publications/electricity-generation-costs-2097 | CA2: https://www.gov.uk/government/publications/electricity-generation-costs-2098 | CB2: https://www.gov.uk/government/publications/electricity-generation-costs-2099 | CC2: https://www.gov.uk/government/publications/electricity-generation-costs-2100 | CD2: https://www.gov.uk/government/publications/electricity-generation-costs-2101 | CE2: https://www.gov.uk/government/publications/electricity-generation-costs-2102 | CF2: https://www.gov.uk/government/publications/electricity-generation-costs-2103 | CG2: https://www.gov.uk/government/publications/electricity-generation-costs-2104 | CH2: https://www.gov.uk/government/publications/electricity-generation-costs-2105 | CI2: https://www.gov.uk/government/publications/electricity-generation-costs-2106 | CJ2: https://www.gov.uk/government/publications/electricity-generation-costs-2107 | CK2: https://www.gov.uk/government/publications/electricity-generation-costs-2108 | CL2: https://www.gov.uk/government/publications/electricity-generation-costs-2109 | CM2: https://www.gov.uk/government/publications/electricity-generation-costs-2110 | CN2: Way, R., Ives, M. C., Mealy, P., & Farmer, J. D. (2022). Empirically grounded technology forecasts and the energy transition: Supplementary material. Joule, 6(9), 2057–2082. https://doi.org/10.1016/j.joule.2022.08.009 | CO2: Way, R., Ives, M. C., Mealy, P., & Farmer, J. D. (2022). Empirically grounded technology forecasts and the energy transition: Supplementary material. Joule, 6(9), 2057–2082. https://doi.org/10.1016/j.joule.2022.08.009 | CP2: Way, R., Ives, M. C., Mealy, P., & Farmer, J. D. (2022). Empirically grounded technology forecasts and the energy transition: Supplementary material. Joule, 6(9), 2057–2082. https://doi.org/10.1016/j.joule.2022.08.009 | CQ2: https://www.gov.uk/government/publications/electricity-generation-costs-2111 | CR2: https://www.gov.uk/government/publications/electricity-generation-costs-2112 | CS2: https://www.gov.uk/government/publications/electricity-generation-costs-2113 | CT2: https://www.gov.uk/government/publications/electricity-generation-costs-2114 | CU2: https://www.gov.uk/government/publications/electricity-generation-costs-2115 | CV2: https://www.gov.uk/government/publications/electricity-generation-costs-2116 | CW2: https://www.gov.uk/government/publications/electricity-generation-costs-2117 | CX2: https://www.gov.uk/government/publications/electricity-generation-costs-2118 | CY2: https://www.gov.uk/government/publications/electricity-generation-costs-2119 | CZ2: https://www.gov.uk/government/publications/electricity-generation-costs-2120 | DA2: https://www.gov.uk/government/publications/electricity-generation-costs-2121 | DB2: https://www.gov.uk/government/publications/electricity-generation-costs-2122 | DC2: https://www.gov.uk/government/publications/electricity-generation-costs-2123 | DD2: https://www.gov.uk/government/publications/electricity-generation-costs-2124 | DE2: https://www.gov.uk/government/publications/electricity-generation-costs-2125 | DF2: https://www.gov.uk/government/publications/electricity-generation-costs-2126 | DG2: https://www.gov.uk/government/publications/electricity-generation-costs-2127 | DH2: https://www.gov.uk/government/publications/electricity-generation-costs-2128 | DI2: https://www.gov.uk/government/publications/electricity-generation-costs-2129 | DJ2: https://www.gov.uk/government/publications/electricity-generation-costs-2130 | DK2: https://www.gov.uk/government/publications/electricity-generation-costs-2131 | DL2: https://www.gov.uk/government/publications/electricity-generation-costs-2132 | DM2: https://www.gov.uk/government/publications/electricity-generation-costs-2133 | DN2: https://www.gov.uk/government/publications/electricity-generation-costs-2134 | DO2: https://www.gov.uk/government/publications/electricity-generation-costs-2135 | DP2: https://www.gov.uk/government/publications/electricity-generation-costs-2136 | DQ2: https://www.gov.uk/government/publications/electricity-generation-costs-2137 | DR2: https://www.gov.uk/government/publications/electricity-generation-costs-2138 | DS2: https://www.gov.uk/government/publications/electricity-generation-costs-2139 | DT2: https://www.gov.uk/government/publications/electricity-generation-costs-2140 | DU2: https://www.gov.uk/government/publications/electricity-generation-costs-2141 | DV2: https://www.gov.uk/government/publications/electricity-generation-costs-2142 | DW2: https://www.gov.uk/government/publications/electricity-generation-costs-2143 | DX2: https://www.gov.uk/government/publications/electricity-generation-costs-2144 | DY2: https://www.gov.uk/government/publications/electricity-generation-costs-2145 | DZ2: https://www.gov.uk/government/publications/electricity-generation-costs-2146 | EA2: https://www.gov.uk/government/publications/electricity-generation-costs-2147 | EB2: https://www.gov.uk/government/publications/electricity-generation-costs-2148 | EC2: https://www.gov.uk/government/publications/electricity-generation-costs-2149 | ED2: https://www.gov.uk/government/publications/electricity-generation-costs-2150 | EE2: https://www.gov.uk/government/publications/electricity-generation-costs-2151 | EF2: https://www.gov.uk/government/publications/electricity-generation-costs-2152 | EG2: https://www.gov.uk/government/publications/electricity-generation-costs-2153 | EH2: https://www.gov.uk/government/publications/electricity-generation-costs-2154 | EI2: https://www.gov.uk/government/publications/electricity-generation-costs-2155 | EJ2: https://www.gov.uk/government/publications/electricity-generation-costs-2156 | EK2: https://www.gov.uk/government/publications/electricity-generation-costs-2157 | EL2: https://www.gov.uk/government/publications/electricity-generation-costs-2158 | EM2: https://www.gov.uk/government/publications/electricity-generation-costs-2159 | EN2: https://www.gov.uk/government/publications/electricity-generation-costs-2160 | EO2: https://www.gov.uk/government/publications/electricity-generation-costs-2161 | EP2: https://www.gov.uk/government/publications/electricity-generation-costs-2162 | EQ2: https://www.gov.uk/government/publications/electricity-generation-costs-2163 | ER2: https://www.gov.uk/government/publications/electricity-generation-costs-2164 | ES2: https://www.gov.uk/government/publications/electricity-generation-costs-2165 | ET2: https://www.gov.uk/government/publications/electricity-generation-costs-2166 | EU2: https://www.gov.uk/government/publications/electricity-generation-costs-2167 | EV2: https://www.gov.uk/government/publications/electricity-generation-costs-2168 | EW2: https://www.gov.uk/government/publications/electricity-generation-costs-2169 | EX2: https://www.gov.uk/government/publications/electricity-generation-costs-2170 | EY2: https://www.gov.uk/government/publications/electricity-generation-costs-2171 | EZ2: https://www.gov.uk/government/publications/electricity-generation-costs-2172 | FA2: https://www.gov.uk/government/publications/electricity-generation-costs-2173 | FB2: https://www.gov.uk/government/publications/electricity-generation-costs-2174 | FC2: https://www.gov.uk/government/publications/electricity-generation-costs-2175 | FD2: https://www.gov.uk/government/publications/electricity-generation-costs-2176 | FE2: https://www.gov.uk/government/publications/electricity-generation-costs-2177 | FF2: https://www.gov.uk/government/publications/electricity-generation-costs-2178 | FG2: https://www.gov.uk/government/publications/electricity-generation-costs-2179 | FH2: https://www.gov.uk/government/publications/electricity-generation-costs-2180 | FI2: https://www.gov.uk/government/publications/electricity-generation-costs-2181 | FJ2: https://www.gov.uk/government/publications/electricity-generation-costs-2182 | FK2: Construction costs from Deutsche Welle via Helsingin Sanomat, 1.2.2023. | FL2: Vakkilainen2017
A3: Tiedot vuodelta | D3: 2021 | E3: 2021 | F3: 2021 | G3: 2021 | H3: 2021 | I3: 2021 | J3: 2021 | K3: 2021 | L3: 2021 | M3: 2021 | N3: 2021 | O3: 2021 | P3: 2021 | Q3: 2021 | R3: 2021 | S3: 2021 | T3: 2021 | U3: 2021 | V3: 2021 | W3: 2021 | X3: 2021 | Y3: 2021 | Z3: 2021 | AA3: 2021 | AB3: 2021 | AC3: 2021 | AD3: 2021 | AE3: 2021 | AF3: 2021 | AG3: 2021 | AH3: 2021 | AI3: 2021 | AJ3: 2021 | AK3: 2021 | AL3: 2021 | AM3: 2021 | AN3: 2021 | AO3: 2021 | AP3: 2021 | AQ3: 2021 | AR3: 2021 | AS3: 2021 | AT3: 2021 | AU3: 2021 | AV3: 2021 | AW3: 2021 | AX3: 2021 | AY3: 2021 | AZ3: 2021 | BA3: 2021 | BB3: 2021 | BC3: 2021 | BD3: 2021 | BE3: 2021 | BF3: 2021 | BG3: 2021 | BH3: 2021 | BI3: 2021 | BJ3: 2021 | BK3: 2021 | BL3: 2021 | BM3: 2021 | BN3: 2021 | BO3: 2021 | BP3: 2021 | BQ3: 2021 | BR3: 2021 | BS3: 2021 | BT3: 2021 | BU3: 2021 | BV3: 2021 | BW3: 2021 | BX3: 2021 | BY3: 2021 | BZ3: 2021 | CA3: 2021 | CB3: 2021 | CC3: 2021 | CD3: 2021 | CE3: 2021 | CF3: 2021 | CG3: 2021 | CH3: 2021 | CI3: 2021 | CJ3: 2021 | CK3: 2021 | CL3: 2021 | CM3: 2021 | CQ3: 2021 | CR3: 2021 | CS3: 2021 | CT3: 2021 | CU3: 2021 | CV3: 2021 | CW3: 2021 | CX3: 2021 | CY3: 2021 | CZ3: 2021 | DA3: 2021 | DB3: 2021 | DC3: 2021 | DD3: 2021 | DE3: 2021 | DF3: 2021 | DG3: 2021 | DH3: 2021 | DI3: 2021 | DJ3: 2021 | DK3: 2021 | DL3: 2021 | DM3: 2021 | DN3: 2021 | DO3: 2021 | DP3: 2021 | DQ3: 2021 | DR3: 2021 | DS3: 2021 | DT3: 2021 | DU3: 2021 | DV3: 2021 | DW3: 2021 | DX3: 2021 | DY3: 2021 | DZ3: 2021 | EA3: 2021 | EB3: 2021 | EC3: 2021 | ED3: 2021 | EE3: 2021 | EF3: 2021 | EG3: 2021 | EH3: 2021 | EI3: 2021 | EJ3: 2021 | EK3: 2021 | EL3: 2021 | EM3: 2021 | EN3: 2021 | EO3: 2021 | EP3: 2021 | EQ3: 2021 | ER3: 2021 | ES3: 2021 | ET3: 2021 | EU3: 2021 | EV3: 2021 | EW3: 2021 | EX3: 2021 | EY3: 2021 | EZ3: 2021 | FA3: 2021 | FB3: 2021 | FC3: 2021 | FD3: 2021 | FE3: 2021 | FF3: 2021 | FG3: 2021 | FH3: 2021 | FI3: 2021 | FJ3: 2021 | FK3: 2022 | FL3: 2017 | FM3: 2017 | FN3: 2017 | FO3: 2024
A4: Sijainti | D4: Iso-Britannia | E4: Iso-Britannia | F4: Iso-Britannia | G4: Iso-Britannia | H4: Iso-Britannia | I4: Iso-Britannia | J4: Iso-Britannia | K4: Iso-Britannia | L4: Iso-Britannia | M4: Iso-Britannia | N4: Iso-Britannia | O4: Iso-Britannia | P4: Iso-Britannia | Q4: Iso-Britannia | R4: Iso-Britannia | S4: Iso-Britannia | T4: Iso-Britannia | U4: Iso-Britannia | V4: Iso-Britannia | W4: Iso-Britannia | X4: Iso-Britannia | Y4: Iso-Britannia | Z4: Iso-Britannia | AA4: Iso-Britannia | AB4: Iso-Britannia | AC4: Iso-Britannia | AD4: Iso-Britannia | AE4: Iso-Britannia | AF4: Iso-Britannia | AG4: Iso-Britannia | AH4: Iso-Britannia | AI4: Iso-Britannia | AJ4: Iso-Britannia | AK4: Iso-Britannia | AL4: Iso-Britannia | AM4: Iso-Britannia | AN4: Iso-Britannia | AO4: Iso-Britannia | AP4: Iso-Britannia | AQ4: Iso-Britannia | AR4: Iso-Britannia | AS4: Iso-Britannia | AT4: Iso-Britannia | AU4: Iso-Britannia | AV4: Iso-Britannia | AW4: Iso-Britannia | AX4: Iso-Britannia | AY4: Iso-Britannia | AZ4: Iso-Britannia | BA4: Iso-Britannia | BB4: Iso-Britannia | BC4: Iso-Britannia | BD4: Iso-Britannia | BE4: Iso-Britannia | BF4: Iso-Britannia | BG4: Iso-Britannia | BH4: Iso-Britannia | BI4: Iso-Britannia | BJ4: Iso-Britannia | BK4: Iso-Britannia | BL4: Iso-Britannia | BM4: Iso-Britannia | BN4: Iso-Britannia | BO4: Iso-Britannia | BP4: Iso-Britannia | BQ4: Iso-Britannia | BR4: Iso-Britannia | BS4: Iso-Britannia | BT4: Iso-Britannia | BU4: Iso-Britannia | BV4: Iso-Britannia | BW4: Iso-Britannia | BX4: Iso-Britannia | BY4: Iso-Britannia | BZ4: Iso-Britannia | CA4: Iso-Britannia | CB4: Iso-Britannia | CC4: Iso-Britannia | CD4: Iso-Britannia | CE4: Iso-Britannia | CF4: Iso-Britannia | CG4: Iso-Britannia | CH4: Iso-Britannia | CI4: Iso-Britannia | CJ4: Iso-Britannia | CK4: Iso-Britannia | CL4: Iso-Britannia | CM4: Iso-Britannia | CN4: Maailma | CO4: Maailma | CP4: Maailma | CQ4: Iso-Britannia | CR4: Iso-Britannia | CS4: Iso-Britannia | CT4: Iso-Britannia | CU4: Iso-Britannia | CV4: Iso-Britannia | CW4: Iso-Britannia | CX4: Iso-Britannia | CY4: Iso-Britannia | CZ4: Iso-Britannia | DA4: Iso-Britannia | DB4: Iso-Britannia | DC4: Iso-Britannia | DD4: Iso-Britannia | DE4: Iso-Britannia | DF4: Iso-Britannia | DG4: Iso-Britannia | DH4: Iso-Britannia | DI4: Iso-Britannia | DJ4: Iso-Britannia | DK4: Iso-Britannia | DL4: Iso-Britannia | DM4: Iso-Britannia | DN4: Iso-Britannia | DO4: Iso-Britannia | DP4: Iso-Britannia | DQ4: Iso-Britannia | DR4: Iso-Britannia | DS4: Iso-Britannia | DT4: Iso-Britannia | DU4: Iso-Britannia | DV4: Iso-Britannia | DW4: Iso-Britannia | DX4: Iso-Britannia | DY4: Iso-Britannia | DZ4: Iso-Britannia | EA4: Iso-Britannia | EB4: Iso-Britannia | EC4: Iso-Britannia | ED4: Iso-Britannia | EE4: Iso-Britannia | EF4: Iso-Britannia | EG4: Iso-Britannia | EH4: Iso-Britannia | EI4: Iso-Britannia | EJ4: Iso-Britannia | EK4: Iso-Britannia | EL4: Iso-Britannia | EM4: Iso-Britannia | EN4: Iso-Britannia | EO4: Iso-Britannia | EP4: Iso-Britannia | EQ4: Iso-Britannia | ER4: Iso-Britannia | ES4: Iso-Britannia | ET4: Iso-Britannia | EU4: Iso-Britannia | EV4: Iso-Britannia | EW4: Iso-Britannia | EX4: Iso-Britannia | EY4: Iso-Britannia | EZ4: Iso-Britannia | FA4: Iso-Britannia | FB4: Iso-Britannia | FC4: Iso-Britannia | FD4: Iso-Britannia | FE4: Iso-Britannia | FF4: Iso-Britannia | FG4: Iso-Britannia | FH4: Iso-Britannia | FI4: Iso-Britannia | FJ4: Iso-Britannia | FK4: Puola | FL4: Suomi | FM4: Suomi | FN4: Suomi | FO4: Ruotsi
A5: Tekniikka | D5: CCGT H Class | E5: CCGT H Class | F5: CCGT H Class | G5: CCGT H Class | H5: CCGT CHP mode | I5: CCGT CHP mode | J5: CCGT CHP mode | K5: CCGT CHP mode | L5: OCGT 600MW 500 hr | M5: OCGT 600MW 500 hr | N5: OCGT 600MW 500 hr | O5: OCGT 600MW 500 hr | P5: OCGT 400MW 500 hr | Q5: OCGT 400MW 500 hr | R5: OCGT 400MW 500 hr | S5: OCGT 400MW 500 hr | T5: OCGT 300MW 500 hr | U5: OCGT 300MW 500 hr | V5: OCGT 300MW 500 hr | W5: OCGT 300MW 500 hr | X5: OCGT 299MW 500 hr | Y5: OCGT 299MW 500 hr | Z5: OCGT 299MW 500 hr | AA5: OCGT 299MW 500 hr | AB5: OCGT 100MW 500 hr | AC5: OCGT 100MW 500 hr | AD5: OCGT 100MW 500 hr | AE5: OCGT 100MW 500 hr | AF5: OCGT 600MW 2000 hr | AG5: OCGT 600MW 2000 hr | AH5: OCGT 600MW 2000 hr | AI5: OCGT 600MW 2000 hr | AJ5: OCGT 400MW 2000 hr | AK5: OCGT 400MW 2000 hr | AL5: OCGT 400MW 2000 hr | AM5: OCGT 400MW 2000 hr | AN5: OCGT 300MW 2000 hr | AO5: OCGT 300MW 2000 hr | AP5: OCGT 300MW 2000 hr | AQ5: OCGT 300MW 2000 hr | AR5: OCGT 299MW 2000 hr | AS5: OCGT 299MW 2000 hr | AT5: OCGT 299MW 2000 hr | AU5: OCGT 299MW 2000 hr | AV5: OCGT 100MW 2000 hr | AW5: OCGT 100MW 2000 hr | AX5: OCGT 100MW 2000 hr | AY5: OCGT 100MW 2000 hr | AZ5: Recip Diesel 2000 hr | BA5: Recip Diesel 2000 hr | BB5: Recip Diesel 2000 hr | BC5: Recip Diesel 2000 hr | BD5: Recip Diesel 500 hrs | BE5: Recip Diesel 500 hrs | BF5: Recip Diesel 500 hrs | BG5: Recip Diesel 500 hrs | BH5: Recip Diesel 90 hrs | BI5: Recip Diesel 90 hrs | BJ5: Recip Diesel 90 hrs | BK5: Recip Diesel 90 hrs | BL5: Recip Gas 2000 hr | BM5: Recip Gas 2000 hr | BN5: Recip Gas 2000 hr | BO5: Recip Gas 2000 hr | BP5: Recip Gas 500 hrs | BQ5: Recip Gas 500 hrs | BR5: Recip Gas 500 hrs | BS5: Recip Gas 500 hrs | BT5: Dedicated Biomass | BU5: Dedicated Biomass | BV5: Dedicated Biomass | BW5: Dedicated Biomass | BX5: Biomass CHP | BY5: Biomass CHP | BZ5: Biomass CHP | CA5: Biomass CHP | CB5: Onshore Wind | CC5: Onshore Wind | CD5: Onshore Wind | CE5: Onshore Wind | CF5: Offshore Wind | CG5: Offshore Wind | CH5: Offshore Wind | CI5: Offshore Wind | CJ5: Large-scale Solar | CK5: Large-scale Solar | CL5: Large-scale Solar | CM5: Large-scale Solar | CN5: Teollinen aurinkosähkö, lattiahinta 2000 (Way2022b) | CO5: Teollinen aurinkosähkö, lattiahinta 2005 (Way2022b) | CP5: Teollinen aurinkosähkö, lattiahinta 2015 (Way2022b) | CQ5: Solar PV 10-50kW | CR5: Solar PV 10-50kW | CS5: Solar PV 10-50kW | CT5: Solar PV 10-50kW | CU5: Solar PV 4-10kW | CV5: Solar PV 4-10kW | CW5: Solar PV 4-10kW | CX5: Solar PV 4-10kW | CY5: Solar PV <4kW | CZ5: Solar PV <4kW | DA5: Solar PV <4kW | DB5: Solar PV <4kW | DC5: EfW | DD5: EfW | DE5: EfW | DF5: EfW | DG5: EfW CHP | DH5: EfW CHP | DI5: EfW CHP | DJ5: EfW CHP | DK5: AD | DL5: AD | DM5: AD | DN5: AD | DO5: AD CHP | DP5: AD CHP | DQ5: AD CHP | DR5: AD CHP | DS5: ACT Standard | DT5: ACT Standard | DU5: ACT Standard | DV5: ACT Standard | DW5: ACT Advanced | DX5: ACT Advanced | DY5: ACT Advanced | DZ5: ACT Advanced | EA5: ACT CHP | EB5: ACT CHP | EC5: ACT CHP | ED5: ACT CHP | EE5: Landfill gas | EF5: Landfill gas | EG5: Landfill gas | EH5: Landfill gas | EI5: Sewage gas | EJ5: Sewage gas | EK5: Sewage gas | EL5: Sewage gas | EM5: Geothermal CHP | EN5: Geothermal CHP | EO5: Geothermal CHP | EP5: Geothermal CHP | EQ5: Hydro Large Storage | ER5: Hydro Large Storage | ES5: Hydro Large Storage | ET5: Hydro Large Storage | EU5: Hydro 516MW | EV5: Hydro 516MW | EW5: Hydro 516MW | EX5: Hydro 516MW | EY5: Wave | EZ5: Wave | FA5: Wave | FB5: Wave | FC5: Hydrogen CCGT (FOAK) | FD5: Hydrogen CCGT (FOAK) | FE5: Hydrogen CCGT (FOAK) | FF5: Hydrogen CCGT (FOAK) | FG5: Hydrogen CCGT (NOAK) | FH5: Hydrogen CCGT (NOAK) | FI5: Hydrogen CCGT (NOAK) | FJ5: Hydrogen CCGT (NOAK) | FK5: AP1000 Nuclear | FL5: EPR-reaktori | FM5: Tuulivoima | FN5: Kaasu | FO5: Ydinreaktori, 1 250 MW
A6: Käyttöönottovuosi | D6: 2025 | E6: 2030 | F6: 2035 | G6: 2040 | H6: 2025 | I6: 2030 | J6: 2035 | K6: 2040 | L6: 2025 | M6: 2030 | N6: 2035 | O6: 2040 | P6: 2025 | Q6: 2030 | R6: 2035 | S6: 2040 | T6: 2025 | U6: 2030 | V6: 2035 | W6: 2040 | X6: 2025 | Y6: 2030 | Z6: 2035 | AA6: 2040 | AB6: 2025 | AC6: 2030 | AD6: 2035 | AE6: 2040 | AF6: 2025 | AG6: 2030 | AH6: 2035 | AI6: 2040 | AJ6: 2025 | AK6: 2030 | AL6: 2035 | AM6: 2040 | AN6: 2025 | AO6: 2030 | AP6: 2035 | AQ6: 2040 | AR6: 2025 | AS6: 2030 | AT6: 2035 | AU6: 2040 | AV6: 2025 | AW6: 2030 | AX6: 2035 | AY6: 2040 | AZ6: 2025 | BA6: 2030 | BB6: 2035 | BC6: 2040 | BD6: 2025 | BE6: 2030 | BF6: 2035 | BG6: 2040 | BH6: 2025 | BI6: 2030 | BJ6: 2035 | BK6: 2040 | BL6: 2025 | BM6: 2030 | BN6: 2035 | BO6: 2040 | BP6: 2025 | BQ6: 2030 | BR6: 2035 | BS6: 2040 | BT6: 2025 | BU6: 2030 | BV6: 2035 | BW6: 2040 | BX6: 2025 | BY6: 2030 | BZ6: 2035 | CA6: 2040 | CB6: 2025 | CC6: 2030 | CD6: 2035 | CE6: 2040 | CF6: 2025 | CG6: 2030 | CH6: 2035 | CI6: 2040 | CJ6: 2025 | CK6: 2030 | CL6: 2035 | CM6: 2040 | CN6: 2020 | CO6: 2020 | CP6: 2020 | CQ6: 2025 | CR6: 2030 | CS6: 2035 | CT6: 2040 | CU6: 2025 | CV6: 2030 | CW6: 2035 | CX6: 2040 | CY6: 2025 | CZ6: 2030 | DA6: 2035 | DB6: 2040 | DC6: 2025 | DD6: 2030 | DE6: 2035 | DF6: 2040 | DG6: 2025 | DH6: 2030 | DI6: 2035 | DJ6: 2040 | DK6: 2025 | DL6: 2030 | DM6: 2035 | DN6: 2040 | DO6: 2025 | DP6: 2030 | DQ6: 2035 | DR6: 2040 | DS6: 2025 | DT6: 2030 | DU6: 2035 | DV6: 2040 | DW6: 2025 | DX6: 2030 | DY6: 2035 | DZ6: 2040 | EA6: 2025 | EB6: 2030 | EC6: 2035 | ED6: 2040 | EE6: 2025 | EF6: 2030 | EG6: 2035 | EH6: 2040 | EI6: 2025 | EJ6: 2030 | EK6: 2035 | EL6: 2040 | EM6: 2025 | EN6: 2030 | EO6: 2035 | EP6: 2040 | EQ6: 2025 | ER6: 2030 | ES6: 2035 | ET6: 2040 | EU6: 2025 | EV6: 2030 | EW6: 2035 | EX6: 2040 | EY6: 2025 | EZ6: 2030 | FA6: 2035 | FB6: 2040 | FC6: 2025 | FD6: 2030 | FE6: 2035 | FF6: 2040 | FG6: 2025 | FH6: 2030 | FI6: 2035 | FJ6: 2040 | FK6: 2030 | FL6: 2020 | FM6: 2020 | FN6: 2020 | FO6: 2035
A7: Koodi | D7: CCGT H Class, 2025, UK | E7: CCGT H Class, 2030, UK | F7: CCGT H Class, 2035, UK | G7: CCGT H Class, 2040, UK | H7: CCGT CHP mode, 2025, UK | I7: CCGT CHP mode, 2030, UK | J7: CCGT CHP mode, 2035, UK | K7: CCGT CHP mode, 2040, UK | L7: OCGT 600MW 500 hr, 2025, UK | M7: OCGT 600MW 500 hr, 2030, UK | N7: OCGT 600MW 500 hr, 2035, UK | O7: OCGT 600MW 500 hr, 2040, UK | P7: OCGT 400MW 500 hr, 2025, UK | Q7: OCGT 400MW 500 hr, 2030, UK | R7: OCGT 400MW 500 hr, 2035, UK | S7: OCGT 400MW 500 hr, 2040, UK | T7: OCGT 300MW 500 hr, 2025, UK | U7: OCGT 300MW 500 hr, 2030, UK | V7: OCGT 300MW 500 hr, 2035, UK | W7: OCGT 300MW 500 hr, 2040, UK | X7: OCGT 299MW 500 hr, 2025, UK | Y7: OCGT 299MW 500 hr, 2030, UK | Z7: OCGT 299MW 500 hr, 2035, UK | AA7: OCGT 299MW 500 hr, 2040, UK | AB7: OCGT 100MW 500 hr, 2025, UK | AC7: OCGT 100MW 500 hr, 2030, UK | AD7: OCGT 100MW 500 hr, 2035, UK | AE7: OCGT 100MW 500 hr, 2040, UK | AF7: OCGT 600MW 2000 hr, 2025, UK | AG7: OCGT 600MW 2000 hr, 2030, UK | AH7: OCGT 600MW 2000 hr, 2035, UK | AI7: OCGT 600MW 2000 hr, 2040, UK | AJ7: OCGT 400MW 2000 hr, 2025, UK | AK7: OCGT 400MW 2000 hr, 2030, UK | AL7: OCGT 400MW 2000 hr, 2035, UK | AM7: OCGT 400MW 2000 hr, 2040, UK | AN7: OCGT 300MW 2000 hr, 2025, UK | AO7: OCGT 300MW 2000 hr, 2030, UK | AP7: OCGT 300MW 2000 hr, 2035, UK | AQ7: OCGT 300MW 2000 hr, 2040, UK | AR7: OCGT 299MW 2000 hr, 2025, UK | AS7: OCGT 299MW 2000 hr, 2030, UK | AT7: OCGT 299MW 2000 hr, 2035, UK | AU7: OCGT 299MW 2000 hr, 2040, UK | AV7: OCGT 100MW 2000 hr, 2025, UK | AW7: OCGT 100MW 2000 hr, 2030, UK | AX7: OCGT 100MW 2000 hr, 2035, UK | AY7: OCGT 100MW 2000 hr, 2040, UK | AZ7: Recip Diesel 2000 hr, 2025, UK | BA7: Recip Diesel 2000 hr, 2030, UK | BB7: Recip Diesel 2000 hr, 2035, UK | BC7: Recip Diesel 2000 hr, 2040, UK | BD7: Recip Diesel 500 hrs, 2025, UK | BE7: Recip Diesel 500 hrs, 2030, UK | BF7: Recip Diesel 500 hrs, 2035, UK | BG7: Recip Diesel 500 hrs, 2040, UK | BH7: Recip Diesel 90 hrs, 2025, UK | BI7: Recip Diesel 90 hrs, 2030, UK | BJ7: Recip Diesel 90 hrs, 2035, UK | BK7: Recip Diesel 90 hrs, 2040, UK | BL7: Recip Gas 2000 hr, 2025, UK | BM7: Recip Gas 2000 hr, 2030, UK | BN7: Recip Gas 2000 hr, 2035, UK | BO7: Recip Gas 2000 hr, 2040, UK | BP7: Recip Gas 500 hrs, 2025, UK | BQ7: Recip Gas 500 hrs, 2030, UK | BR7: Recip Gas 500 hrs, 2035, UK | BS7: Recip Gas 500 hrs, 2040, UK | BT7: Dedicated Biomass, 2025, UK | BU7: Dedicated Biomass, 2030, UK | BV7: Dedicated Biomass, 2035, UK | BW7: Dedicated Biomass, 2040, UK | BX7: Biomass CHP, 2025, UK | BY7: Biomass CHP, 2030, UK | BZ7: Biomass CHP, 2035, UK | CA7: Biomass CHP, 2040, UK | CB7: Onshore Wind, 2025, UK | CC7: Onshore Wind, 2030, UK | CD7: Onshore Wind, 2035, UK | CE7: Onshore Wind, 2040, UK | CF7: Offshore Wind, 2025, UK | CG7: Offshore Wind, 2030, UK | CH7: Offshore Wind, 2035, UK | CI7: Offshore Wind, 2040, UK | CJ7: Large-scale Solar, 2025, UK | CK7: Large-scale Solar, 2030, UK | CL7: Large-scale Solar, 2035, UK | CM7: Large-scale Solar, 2040, UK | CN7: Teollinen aurinkosähkö, lattiahinta 1998 ja 2000 (Way2022b) | CO7: Teollinen aurinkosähkö, lattiahinta 2005 (Way2022b) | CP7: Teollinen aurinkosähkö, lattiahinta 2015 (Way2022b) | CQ7: Solar PV 10-50kW, 2025, UK | CR7: Solar PV 10-50kW, 2030, UK | CS7: Solar PV 10-50kW, 2035, UK | CT7: Solar PV 10-50kW, 2040, UK | CU7: Solar PV 4-10kW, 2025, UK | CV7: Solar PV 4-10kW, 2030, UK | CW7: Solar PV 4-10kW, 2035, UK | CX7: Solar PV 4-10kW, 2040, UK | CY7: Solar PV <4kW, 2025, UK | CZ7: Solar PV <4kW, 2030, UK | DA7: Solar PV <4kW, 2035, UK | DB7: Solar PV <4kW, 2040, UK | DC7: EfW, 2025, UK | DD7: EfW, 2030, UK | DE7: EfW, 2035, UK | DF7: EfW, 2040, UK | DG7: EfW CHP, 2025, UK | DH7: EfW CHP, 2030, UK | DI7: EfW CHP, 2035, UK | DJ7: EfW CHP, 2040, UK | DK7: AD, 2025, UK | DL7: AD, 2030, UK | DM7: AD, 2035, UK | DN7: AD, 2040, UK | DO7: AD CHP, 2025, UK | DP7: AD CHP, 2030, UK | DQ7: AD CHP, 2035, UK | DR7: AD CHP, 2040, UK | DS7: ACT Standard, 2025, UK | DT7: ACT Standard, 2030, UK | DU7: ACT Standard, 2035, UK | DV7: ACT Standard, 2040, UK | DW7: ACT Advanced, 2025, UK | DX7: ACT Advanced, 2030, UK | DY7: ACT Advanced, 2035, UK | DZ7: ACT Advanced, 2040, UK | EA7: ACT CHP, 2025, UK | EB7: ACT CHP, 2030, UK | EC7: ACT CHP, 2035, UK | ED7: ACT CHP, 2040, UK | EE7: Landfill gas, 2025, UK | EF7: Landfill gas, 2030, UK | EG7: Landfill gas, 2035, UK | EH7: Landfill gas, 2040, UK | EI7: Sewage gas, 2025, UK | EJ7: Sewage gas, 2030, UK | EK7: Sewage gas, 2035, UK | EL7: Sewage gas, 2040, UK | EM7: Geothermal CHP, 2025, UK | EN7: Geothermal CHP, 2030, UK | EO7: Geothermal CHP, 2035, UK | EP7: Geothermal CHP, 2040, UK | EQ7: Hydro Large Storage, 2025, UK | ER7: Hydro Large Storage, 2030, UK | ES7: Hydro Large Storage, 2035, UK | ET7: Hydro Large Storage, 2040, UK | EU7: Hydro 516MW, 2025, UK | EV7: Hydro 516MW, 2030, UK | EW7: Hydro 516MW, 2035, UK | EX7: Hydro 516MW, 2040, UK | EY7: Wave, 2025, UK | EZ7: Wave, 2030, UK | FA7: Wave, 2035, UK | FB7: Wave, 2040, UK | FC7: Hydrogen CCGT (FOAK), 2025, UK | FD7: Hydrogen CCGT (FOAK), 2030, UK | FE7: Hydrogen CCGT (FOAK), 2035, UK | FF7: Hydrogen CCGT (FOAK), 2040, UK | FG7: Hydrogen CCGT (NOAK), 2025, UK | FH7: Hydrogen CCGT (NOAK), 2030, UK | FI7: Hydrogen CCGT (NOAK), 2035, UK | FJ7: Hydrogen CCGT (NOAK), 2040, UK | FK7: AP1000-reaktori, Puola | FL7: EPR-reaktori, Suomi | FM7: Tuulivoima, Suomi, 2017 | FN7: Kaasuvoima, Suomi, 2017 | FO7: Ydinreaktori, 1 250 MW, Ruotsi 2024 referenssilaskelma
A8: Case | D8: 1 | E8: 2 | F8: 3 | G8: 4 | H8: 5 | I8: 6 | J8: 7 | K8: 8 | L8: 9 | M8: 10 | N8: 11 | O8: 12 | P8: 13 | Q8: 14 | R8: 15 | S8: 16 | T8: 17 | U8: 18 | V8: 19 | W8: 20 | X8: 21 | Y8: 22 | Z8: 23 | AA8: 24 | AB8: 25 | AC8: 26 | AD8: 27 | AE8: 28 | AF8: 29 | AG8: 30 | AH8: 31 | AI8: 32 | AJ8: 33 | AK8: 34 | AL8: 35 | AM8: 36 | AN8: 37 | AO8: 38 | AP8: 39 | AQ8: 40 | AR8: 41 | AS8: 42 | AT8: 43 | AU8: 44 | AV8: 45 | AW8: 46 | AX8: 47 | AY8: 48 | AZ8: 49 | BA8: 50 | BB8: 51 | BC8: 52 | BD8: 53 | BE8: 54 | BF8: 55 | BG8: 56 | BH8: 57 | BI8: 58 | BJ8: 59 | BK8: 60 | BL8: 61 | BM8: 62 | BN8: 63 | BO8: 64 | BP8: 65 | BQ8: 66 | BR8: 67 | BS8: 68 | BT8: 69 | BU8: 70 | BV8: 71 | BW8: 72 | BX8: 73 | BY8: 74 | BZ8: 75 | CA8: 76 | CB8: 77 | CC8: 78 | CD8: 79 | CE8: 80 | CF8: 81 | CG8: 82 | CH8: 83 | CI8: 84 | CJ8: 85 | CK8: 86 | CL8: 87 | CM8: 88 | CQ8: 89 | CR8: 90 | CS8: 91 | CT8: 92 | CU8: 93 | CV8: 94 | CW8: 95 | CX8: 96 | CY8: 97 | CZ8: 98 | DA8: 99 | DB8: 100 | DC8: 101 | DD8: 102 | DE8: 103 | DF8: 104 | DG8: 105 | DH8: 106 | DI8: 107 | DJ8: 108 | DK8: 109 | DL8: 110 | DM8: 111 | DN8: 112 | DO8: 113 | DP8: 114 | DQ8: 115 | DR8: 116 | DS8: 117 | DT8: 118 | DU8: 119 | DV8: 120 | DW8: 121 | DX8: 122 | DY8: 123 | DZ8: 124 | EA8: 125 | EB8: 126 | EC8: 127 | ED8: 128 | EE8: 129 | EF8: 130 | EG8: 131 | EH8: 132 | EI8: 133 | EJ8: 134 | EK8: 135 | EL8: 136 | EM8: 137 | EN8: 138 | EO8: 139 | EP8: 140 | EQ8: 141 | ER8: 142 | ES8: 143 | ET8: 144 | EU8: 145 | EV8: 146 | EW8: 147 | EX8: 148 | EY8: 149 | EZ8: 150 | FA8: 151 | FB8: 152 | FC8: 153 | FD8: 154 | FE8: 155 | FF8: 156 | FG8: 157 | FH8: 158 | FI8: 159 | FJ8: 160 | FK8: 161 | FL8: 162 | FM8: 163 | FN8: 164 | FO8: 165
A9: Polttoaine | D9: Maakaasu | E9: Maakaasu | F9: Maakaasu | G9: Maakaasu | H9: Maakaasu | I9: Maakaasu | J9: Maakaasu | K9: Maakaasu | L9: Maakaasu | M9: Maakaasu | N9: Maakaasu | O9: Maakaasu | P9: Maakaasu | Q9: Maakaasu | R9: Maakaasu | S9: Maakaasu | T9: Maakaasu | U9: Maakaasu | V9: Maakaasu | W9: Maakaasu | X9: Maakaasu | Y9: Maakaasu | Z9: Maakaasu | AA9: Maakaasu | AB9: Maakaasu | AC9: Maakaasu | AD9: Maakaasu | AE9: Maakaasu | AF9: Maakaasu | AG9: Maakaasu | AH9: Maakaasu | AI9: Maakaasu | AJ9: Maakaasu | AK9: Maakaasu | AL9: Maakaasu | AM9: Maakaasu | AN9: Maakaasu | AO9: Maakaasu | AP9: Maakaasu | AQ9: Maakaasu | AR9: Maakaasu | AS9: Maakaasu | AT9: Maakaasu | AU9: Maakaasu | AV9: Maakaasu | AW9: Maakaasu | AX9: Maakaasu | AY9: Maakaasu | AZ9: Diesel | BA9: Diesel | BB9: Diesel | BC9: Diesel | BD9: Diesel | BE9: Diesel | BF9: Diesel | BG9: Diesel | BH9: Diesel | BI9: Diesel | BJ9: Diesel | BK9: Diesel | BL9: Maakaasu | BM9: Maakaasu | BN9: Maakaasu | BO9: Maakaasu | BP9: Maakaasu | BQ9: Maakaasu | BR9: Maakaasu | BS9: Maakaasu | BT9: Biomassa | BU9: Biomassa | BV9: Biomassa | BW9: Biomassa | BX9: Biomassa | BY9: Biomassa | BZ9: Biomassa | CA9: Biomassa | CB9: Tuuli | CC9: Tuuli | CD9: Tuuli | CE9: Tuuli | CF9: Tuuli | CG9: Tuuli | CH9: Tuuli | CI9: Tuuli | CJ9: Aurinko | CK9: Aurinko | CL9: Aurinko | CM9: Aurinko | CN9: Aurinko | CO9: Aurinko | CP9: Aurinko | CQ9: Aurinko | CR9: Aurinko | CS9: Aurinko | CT9: Aurinko | CU9: Aurinko | CV9: Aurinko | CW9: Aurinko | CX9: Aurinko | CY9: Aurinko | CZ9: Aurinko | DA9: Aurinko | DB9: Aurinko | DC9: Jäte | DD9: Jäte | DE9: Jäte | DF9: Jäte | DG9: Jäte | DH9: Jäte | DI9: Jäte | DJ9: Jäte | EM9: Geoterminen | EN9: Geoterminen | EO9: Geoterminen | EP9: Geoterminen | EQ9: Vesi | ER9: Vesi | ES9: Vesi | ET9: Vesi | EU9: Vesi | EV9: Vesi | EW9: Vesi | EX9: Vesi | EY9: Vesi | EZ9: Vesi | FA9: Vesi | FB9: Vesi | FC9: Vety | FD9: Vety | FE9: Vety | FF9: Vety | FG9: Vety | FH9: Vety | FI9: Vety | FJ9: Vety | FK9: Uraani | FL9: Uraani | FM9: Tuuli | FN9: Maakaasu | FO9: Uraani
FO10: Kyllä
A11: Huom1 | D11: N/A | E11: N/A | F11: N/A | G11: N/A | H11: N/A | I11: N/A | J11: N/A | K11: N/A | L11: N/A | M11: N/A | N11: N/A | O11: N/A | P11: N/A | Q11: N/A | R11: N/A | S11: N/A | T11: N/A | U11: N/A | V11: N/A | W11: N/A | X11: N/A | Y11: N/A | Z11: N/A | AA11: N/A | AB11: N/A | AC11: N/A | AD11: N/A | AE11: N/A | AF11: N/A | AG11: N/A | AH11: N/A | AI11: N/A | AJ11: N/A | AK11: N/A | AL11: N/A | AM11: N/A | AN11: N/A | AO11: N/A | AP11: N/A | AQ11: N/A | AR11: N/A | AS11: N/A | AT11: N/A | AU11: N/A | AV11: N/A | AW11: N/A | AX11: N/A | AY11: N/A | AZ11: N/A | BA11: N/A | BB11: N/A | BC11: N/A | BD11: N/A | BE11: N/A | BF11: N/A | BG11: N/A | BH11: N/A | BI11: N/A | BJ11: N/A | BK11: N/A | BL11: N/A | BM11: N/A | BN11: N/A | BO11: N/A | BP11: N/A | BQ11: N/A | BR11: N/A | BS11: N/A | BT11: N/A | BU11: N/A | BV11: N/A | BW11: N/A | BX11: N/A | BY11: N/A | BZ11: N/A | CA11: N/A | CB11: N/A | CC11: N/A | CD11: N/A | CE11: N/A | CF11: N/A | CG11: N/A | CH11: N/A | CI11: N/A | CJ11: N/A | CK11: N/A | CL11: N/A | CM11: N/A | CN11: Lattiahinta lähteen Way2022b:99 perusteella ERIS (1998), MERGE-ETL ja TIMES-G5 malleista, muut tiedot Iso-Britannian Large-scale solar 2025 | CO11: Lattiahinta 2005 lähteen Way2022b:99 perusteella ReMIND-R, POLES, ja WITCH-malleista, muut tiedot Iso-Britannian Large-scale solar 2025 | CP11: Lattiahinta 2015 lähteen Way2022b:99 perusteella REMIND- ja POLES-malleista, muut tiedot Iso-Britannian Large-scale solar 2025 | CQ11: N/A | CR11: N/A | CS11: N/A | CT11: N/A | CU11: N/A | CV11: N/A | CW11: N/A | CX11: N/A | CY11: N/A | CZ11: N/A | DA11: N/A | DB11: N/A | DC11: N/A | DD11: N/A | DE11: N/A | DF11: N/A | DG11: N/A | DH11: N/A | DI11: N/A | DJ11: N/A | DK11: N/A | DL11: N/A | DM11: N/A | DN11: N/A | DO11: N/A | DP11: N/A | DQ11: N/A | DR11: N/A | DS11: N/A | DT11: N/A | DU11: N/A | DV11: N/A | DW11: N/A | DX11: N/A | DY11: N/A | DZ11: N/A | EA11: N/A | EB11: N/A | EC11: N/A | ED11: N/A | EE11: N/A | EF11: N/A | EG11: N/A | EH11: N/A | EI11: N/A | EJ11: N/A | EK11: N/A | EL11: N/A | EM11: N/A | EN11: N/A | EO11: N/A | EP11: N/A | EQ11: N/A | ER11: N/A | ES11: N/A | ET11: N/A | EU11: N/A | EV11: N/A | EW11: N/A | EX11: N/A | EY11: N/A | EZ11: N/A | FA11: N/A | FB11: N/A | FC11: N/A | FD11: N/A | FE11: N/A | FF11: N/A | FG11: N/A | FH11: N/A | FI11: N/A | FJ11: N/A | FK11: Westinghouse winning bid for 3+3 reactors in Poland, 2022 | FL11: Lähteestä Vakkilainen2017 | FM11: Lähteestä Vakkilainen2017 | FN11: Lähteestä Vakkilainen2017 | FO11: Ruotsin hallituksen selvityksestä
A12: Valuutta | D12: 2022 real EUR | E12: 2022 real EUR | F12: 2022 real EUR | G12: 2022 real EUR | H12: 2022 real EUR | I12: 2022 real EUR | J12: 2022 real EUR | K12: 2022 real EUR | L12: 2022 real EUR | M12: 2022 real EUR | N12: 2022 real EUR | O12: 2022 real EUR | P12: 2022 real EUR | Q12: 2022 real EUR | R12: 2022 real EUR | S12: 2022 real EUR | T12: 2022 real EUR | U12: 2022 real EUR | V12: 2022 real EUR | W12: 2022 real EUR | X12: 2022 real EUR | Y12: 2022 real EUR | Z12: 2022 real EUR | AA12: 2022 real EUR | AB12: 2022 real EUR | AC12: 2022 real EUR | AD12: 2022 real EUR | AE12: 2022 real EUR | AF12: 2022 real EUR | AG12: 2022 real EUR | AH12: 2022 real EUR | AI12: 2022 real EUR | AJ12: 2022 real EUR | AK12: 2022 real EUR | AL12: 2022 real EUR | AM12: 2022 real EUR | AN12: 2022 real EUR | AO12: 2022 real EUR | AP12: 2022 real EUR | AQ12: 2022 real EUR | AR12: 2022 real EUR | AS12: 2022 real EUR | AT12: 2022 real EUR | AU12: 2022 real EUR | AV12: 2022 real EUR | AW12: 2022 real EUR | AX12: 2022 real EUR | AY12: 2022 real EUR | AZ12: 2022 real EUR | BA12: 2022 real EUR | BB12: 2022 real EUR | BC12: 2022 real EUR | BD12: 2022 real EUR | BE12: 2022 real EUR | BF12: 2022 real EUR | BG12: 2022 real EUR | BH12: 2022 real EUR | BI12: 2022 real EUR | BJ12: 2022 real EUR | BK12: 2022 real EUR | BL12: 2022 real EUR | BM12: 2022 real EUR | BN12: 2022 real EUR | BO12: 2022 real EUR | BP12: 2022 real EUR | BQ12: 2022 real EUR | BR12: 2022 real EUR | BS12: 2022 real EUR | BT12: 2022 real EUR | BU12: 2022 real EUR | BV12: 2022 real EUR | BW12: 2022 real EUR | BX12: 2022 real EUR | BY12: 2022 real EUR | BZ12: 2022 real EUR | CA12: 2022 real EUR | CB12: 2022 real EUR | CC12: 2022 real EUR | CD12: 2022 real EUR | CE12: 2022 real EUR | CF12: 2022 real EUR | CG12: 2022 real EUR | CH12: 2022 real EUR | CI12: 2022 real EUR | CJ12: 2022 real EUR | CK12: 2022 real EUR | CL12: 2022 real EUR | CM12: 2022 real EUR | CN12: 2022 real EUR | CO12: 2022 real EUR | CP12: 2022 real EUR | CQ12: 2022 real EUR | CR12: 2022 real EUR | CS12: 2022 real EUR | CT12: 2022 real EUR | CU12: 2022 real EUR | CV12: 2022 real EUR | CW12: 2022 real EUR | CX12: 2022 real EUR | CY12: 2022 real EUR | CZ12: 2022 real EUR | DA12: 2022 real EUR | DB12: 2022 real EUR | DC12: 2022 real EUR | DD12: 2022 real EUR | DE12: 2022 real EUR | DF12: 2022 real EUR | DG12: 2022 real EUR | DH12: 2022 real EUR | DI12: 2022 real EUR | DJ12: 2022 real EUR | DK12: 2022 real EUR | DL12: 2022 real EUR | DM12: 2022 real EUR | DN12: 2022 real EUR | DO12: 2022 real EUR | DP12: 2022 real EUR | DQ12: 2022 real EUR | DR12: 2022 real EUR | DS12: 2022 real EUR | DT12: 2022 real EUR | DU12: 2022 real EUR | DV12: 2022 real EUR | DW12: 2022 real EUR | DX12: 2022 real EUR | DY12: 2022 real EUR | DZ12: 2022 real EUR | EA12: 2022 real EUR | EB12: 2022 real EUR | EC12: 2022 real EUR | ED12: 2022 real EUR | EE12: 2022 real EUR | EF12: 2022 real EUR | EG12: 2022 real EUR | EH12: 2022 real EUR | EI12: 2022 real EUR | EJ12: 2022 real EUR | EK12: 2022 real EUR | EL12: 2022 real EUR | EM12: 2022 real EUR | EN12: 2022 real EUR | EO12: 2022 real EUR | EP12: 2022 real EUR | EQ12: 2022 real EUR | ER12: 2022 real EUR | ES12: 2022 real EUR | ET12: 2022 real EUR | EU12: 2022 real EUR | EV12: 2022 real EUR | EW12: 2022 real EUR | EX12: 2022 real EUR | EY12: 2022 real EUR | EZ12: 2022 real EUR | FA12: 2022 real EUR | FB12: 2022 real EUR | FC12: 2022 real EUR | FD12: 2022 real EUR | FE12: 2022 real EUR | FF12: 2022 real EUR | FG12: 2022 real EUR | FH12: 2022 real EUR | FI12: 2022 real EUR | FJ12: 2022 real EUR | FK12: 2022 real EUR | FL12: 2022 real EUR | FM12: 2022 real EUR | FN12: 2022 real EUR | FO12: 2022 real EUR
A13: Sähköntuotannon nimellisteho | C13: MWe | D13: 1200 | E13: 1200 | F13: 1200 | G13: 1200 | H13: 168 | I13: 168 | J13: 168 | K13: 168 | L13: 625 | M13: 625 | N13: 625 | O13: 625 | P13: 400 | Q13: 400 | R13: 400 | S13: 400 | T13: 311 | U13: 311 | V13: 311 | W13: 311 | X13: 299 | Y13: 299 | Z13: 299 | AA13: 299 | AB13: 96 | AC13: 96 | AD13: 96 | AE13: 96 | AF13: 625 | AG13: 625 | AH13: 625 | AI13: 625 | AJ13: 400 | AK13: 400 | AL13: 400 | AM13: 400 | AN13: 311 | AO13: 311 | AP13: 311 | AQ13: 311 | AR13: 299 | AS13: 299 | AT13: 299 | AU13: 299 | AV13: 96 | AW13: 96 | AX13: 96 | AY13: 96 | AZ13: 20 | BA13: 20 | BB13: 20 | BC13: 20 | BD13: 20 | BE13: 20 | BF13: 20 | BG13: 20 | BH13: 20 | BI13: 20 | BJ13: 20 | BK13: 20 | BL13: 20 | BM13: 20 | BN13: 20 | BO13: 20 | BP13: 20 | BQ13: 20 | BR13: 20 | BS13: 20 | BT13: 23 | BU13: 23 | BV13: 23 | BW13: 23 | BX13: 14 | BY13: 14 | BZ13: 14 | CA13: 14 | CB13: 51 | CC13: 51 | CD13: 51 | CE13: 51 | CF13: 1000 | CG13: 1000 | CH13: 1000 | CI13: 1000 | CJ13: 20 | CK13: 20 | CL13: 20 | CM13: 20 | CN13: 20 | CO13: 20 | CP13: 20 | CQ13: 0.025 | CR13: 0.025 | CS13: 0.025 | CT13: 0.025 | CU13: 0.007 | CV13: 0.007 | CW13: 0.007 | CX13: 0.007 | CY13: 0.002 | CZ13: 0.002 | DA13: 0.002 | DB13: 0.002 | DC13: 30 | DD13: 30 | DE13: 30 | DF13: 30 | DG13: 25 | DH13: 25 | DI13: 25 | DJ13: 25 | DK13: 2 | DL13: 2 | DM13: 2 | DN13: 2 | DO13: 2 | DP13: 2 | DQ13: 2 | DR13: 2 | DS13: 12 | DT13: 12 | DU13: 12 | DV13: 12 | DW13: 15 | DX13: 15 | DY13: 15 | DZ13: 15 | EA13: 7 | EB13: 7 | EC13: 7 | ED13: 7 | EE13: 2 | EF13: 2 | EG13: 2 | EH13: 2 | EI13: 3 | EJ13: 3 | EK13: 3 | EL13: 3 | EM13: 3 | EN13: 3 | EO13: 3 | EP13: 3 | EQ13: 11 | ER13: 11 | ES13: 11 | ET13: 11 | EU13: 11 | EV13: 11 | EW13: 11 | EX13: 11 | EY13: 9 | EZ13: 9 | FA13: 9 | FB13: 9 | FC13: 1200 | FD13: 1200 | FE13: 1200 | FF13: 1200 | FG13: 1200 | FH13: 1200 | FI13: 1200 | FJ13: 1200 | FK13: 1117 | FL13: 1650 | FM13: 50 | FN13: 850 | FO13: 1250
A14: Sähköntuotannon kapasiteettikerroin | C14: % | D14: 0.93 | E14: 0.93 | F14: 0.93 | G14: 0.93 | H14: 0.93 | I14: 0.93 | J14: 0.93 | K14: 0.93 | L14: 0.06 | M14: 0.06 | N14: 0.06 | O14: 0.06 | P14: 0.06 | Q14: 0.06 | R14: 0.06 | S14: 0.06 | T14: 0.06 | U14: 0.06 | V14: 0.06 | W14: 0.06 | X14: 0.06 | Y14: 0.06 | Z14: 0.06 | AA14: 0.06 | AB14: 0.06 | AC14: 0.06 | AD14: 0.06 | AE14: 0.06 | AF14: 0.22 | AG14: 0.22 | AH14: 0.22 | AI14: 0.22 | AJ14: 0.22 | AK14: 0.22 | AL14: 0.22 | AM14: 0.22 | AN14: 0.22 | AO14: 0.22 | AP14: 0.22 | AQ14: 0.22 | AR14: 0.22 | AS14: 0.22 | AT14: 0.22 | AU14: 0.22 | AV14: 0.22 | AW14: 0.22 | AX14: 0.22 | AY14: 0.22 | AZ14: 0.22 | BA14: 0.22 | BB14: 0.22 | BC14: 0.22 | BD14: 0.05 | BE14: 0.05 | BF14: 0.05 | BG14: 0.05 | BH14: 0.01 | BI14: 0.01 | BJ14: 0.01 | BK14: 0.01 | BL14: 0.22 | BM14: 0.22 | BN14: 0.22 | BO14: 0.22 | BP14: 0.05 | BQ14: 0.05 | BR14: 0.05 | BS14: 0.05 | BT14: 0.84 | BU14: 0.84 | BV14: 0.84 | BW14: 0.84 | BX14: 0.8 | BY14: 0.8 | BZ14: 0.8 | CA14: 0.8 | CB14: 0.38 | CC14: 0.41 | CD14: 0.41 | CE14: 0.41 | CF14: 0.61 | CG14: 0.65 | CH14: 0.69 | CI14: 0.69 | CJ14: 0.11 | CK14: 0.11 | CL14: 0.11 | CM14: 0.11 | CN14: 0.11 | CO14: 0.11 | CP14: 0.11 | CQ14: 0.11 | CR14: 0.11 | CS14: 0.11 | CT14: 0.11 | CU14: 0.11 | CV14: 0.11 | CW14: 0.11 | CX14: 0.11 | CY14: 0.11 | CZ14: 0.11 | DA14: 0.11 | DB14: 0.11 | DC14: 0.81 | DD14: 0.81 | DE14: 0.81 | DF14: 0.81 | DG14: 0.81 | DH14: 0.81 | DI14: 0.81 | DJ14: 0.81 | DK14: 0.79 | DL14: 0.79 | DM14: 0.79 | DN14: 0.79 | DO14: 0.79 | DP14: 0.79 | DQ14: 0.79 | DR14: 0.79 | DS14: 0.83 | DT14: 0.83 | DU14: 0.83 | DV14: 0.83 | DW14: 0.71 | DX14: 0.71 | DY14: 0.71 | DZ14: 0.71 | EA14: 0.71 | EB14: 0.71 | EC14: 0.71 | ED14: 0.71 | EE14: 0.58 | EF14: 0.58 | EG14: 0.58 | EH14: 0.58 | EI14: 0.46 | EJ14: 0.46 | EK14: 0.46 | EL14: 0.46 | EM14: 0.9 | EN14: 0.9 | EO14: 0.9 | EP14: 0.9 | EQ14: 0.45 | ER14: 0.45 | ES14: 0.45 | ET14: 0.45 | EU14: 0.35 | EV14: 0.35 | EW14: 0.35 | EX14: 0.35 | EY14: 0.3 | EZ14: 0.3 | FA14: 0.3 | FB14: 0.3 | FC14: 0.93 | FD14: 0.93 | FE14: 0.93 | FF14: 0.93 | FG14: 0.93 | FH14: 0.93 | FI14: 0.93 | FJ14: 0.93 | FK14: 0.9 | FL14: 0.926 | FM14: 0.331 | FN14: 0.926 | FO14: 0.89
A15: Sähköntuotannon hyötysuhde | C15: % | D15: 0.53 | E15: 0.53 | F15: 0.53 | G15: 0.53 | H15: 0.33 | I15: 0.33 | J15: 0.33 | K15: 0.33 | L15: 0.35 | M15: 0.35 | N15: 0.35 | O15: 0.35 | P15: 0.34 | Q15: 0.34 | R15: 0.34 | S15: 0.34 | T15: 0.34 | U15: 0.34 | V15: 0.34 | W15: 0.34 | X15: 0.34 | Y15: 0.34 | Z15: 0.34 | AA15: 0.34 | AB15: 0.35 | AC15: 0.35 | AD15: 0.35 | AE15: 0.35 | AF15: 0.35 | AG15: 0.35 | AH15: 0.35 | AI15: 0.35 | AJ15: 0.34 | AK15: 0.34 | AL15: 0.34 | AM15: 0.34 | AN15: 0.34 | AO15: 0.34 | AP15: 0.34 | AQ15: 0.34 | AR15: 0.34 | AS15: 0.34 | AT15: 0.34 | AU15: 0.34 | AV15: 0.35 | AW15: 0.35 | AX15: 0.35 | AY15: 0.35 | AZ15: 0.34 | BA15: 0.34 | BB15: 0.34 | BC15: 0.34 | BD15: 0.34 | BE15: 0.34 | BF15: 0.34 | BG15: 0.34 | BH15: 0.34 | BI15: 0.34 | BJ15: 0.34 | BK15: 0.34 | BL15: 0.32 | BM15: 0.32 | BN15: 0.32 | BO15: 0.32 | BP15: 0.32 | BQ15: 0.32 | BR15: 0.32 | BS15: 0.32 | BT15: 0 | BU15: 0 | BV15: 0 | BW15: 0 | BX15: 0.21 | BY15: 0.21 | BZ15: 0.21 | CA15: 0.21 | CB15: 1 | CC15: 1 | CD15: 1 | CE15: 1 | CF15: 1 | CG15: 1 | CH15: 1 | CI15: 1 | CJ15: 1 | CK15: 1 | CL15: 1 | CM15: 1 | CN15: 1 | CO15: 1 | CP15: 1 | CQ15: 1 | CR15: 1 | CS15: 1 | CT15: 1 | CU15: 1 | CV15: 1 | CW15: 1 | CX15: 1 | CY15: 1 | CZ15: 1 | DA15: 1 | DB15: 1 | DC15: 0.28 | DD15: 0.28 | DE15: 0.28 | DF15: 0.28 | DG15: 0.24 | DH15: 0.24 | DI15: 0.24 | DJ15: 0.24 | DK15: 0 | DL15: 0 | DM15: 0 | DN15: 0 | DO15: 0 | DP15: 0 | DQ15: 0 | DR15: 0 | DS15: 0.19 | DT15: 0.19 | DU15: 0.19 | DV15: 0.19 | DW15: 0.22 | DX15: 0.22 | DY15: 0.22 | DZ15: 0.22 | EA15: 0 | EB15: 0 | EC15: 0 | ED15: 0 | EE15: 1 | EF15: 1 | EG15: 1 | EH15: 1 | EI15: 1 | EJ15: 1 | EK15: 1 | EL15: 1 | EM15: 0 | EN15: 0 | EO15: 0 | EP15: 0 | EQ15: 1 | ER15: 1 | ES15: 1 | ET15: 1 | EU15: 1 | EV15: 1 | EW15: 1 | EX15: 1 | EY15: 1 | EZ15: 1 | FA15: 1 | FB15: 1 | FC15: 0.48 | FD15: 0.48 | FE15: 0.48 | FF15: 0.48 | FG15: 0.53 | FH15: 0.53 | FI15: 0.53 | FJ15: 0.53 | FK15: 1 | FL15: 0.37 | FM15: 1 | FN15: 0.583 | FO15: 0.37
A16: Nimellistehon muutos | C16: %/vvuosi | CJ16: -0.01 | CK16: -0.01 | CL16: -0.01 | CM16: -0.01 | CN16: -0.01 | CO16: -0.01 | CP16: -0.01 | CQ16: -0.01 | CR16: -0.01 | CS16: -0.01 | CT16: -0.01 | CU16: -0.01 | CV16: -0.01 | CW16: -0.01 | CX16: -0.01 | CY16: -0.01 | CZ16: -0.01 | DA16: -0.01 | DB16: -0.01
A17: Lämmöntuotannon kapasiteettikerroin | C17: % | H17: 0.25 | I17: 0.25 | J17: 0.25 | K17: 0.25
A18: Yhteistuotannon hyötysuhde | C18: % | D18: 0.95 | E18: 0.95 | F18: 0.95 | G18: 0.95 | H18: 0.95 | I18: 0.95 | J18: 0.95 | K18: 0.95 | L18: 0.95 | M18: 0.95 | N18: 0.95 | O18: 0.95 | P18: 0.95 | Q18: 0.95 | R18: 0.95 | S18: 0.95 | T18: 0.95 | U18: 0.95 | V18: 0.95 | W18: 0.95 | X18: 0.95 | Y18: 0.95 | Z18: 0.95 | AA18: 0.95 | AB18: 0.95 | AC18: 0.95 | AD18: 0.95 | AE18: 0.95 | AF18: 0.95 | AG18: 0.95 | AH18: 0.95 | AI18: 0.95 | AJ18: 0.95 | AK18: 0.95 | AL18: 0.95 | AM18: 0.95 | AN18: 0.95 | AO18: 0.95 | AP18: 0.95 | AQ18: 0.95 | AR18: 0.95 | AS18: 0.95 | AT18: 0.95 | AU18: 0.95 | AV18: 0.95 | AW18: 0.95 | AX18: 0.95 | AY18: 0.95 | AZ18: 0.95 | BA18: 0.95 | BB18: 0.95 | BC18: 0.95 | BD18: 0.95 | BE18: 0.95 | BF18: 0.95 | BG18: 0.95 | BH18: 0.95 | BI18: 0.95 | BJ18: 0.95 | BK18: 0.95 | BL18: 0.95 | BM18: 0.95 | BN18: 0.95 | BO18: 0.95 | BP18: 0.95 | BQ18: 0.95 | BR18: 0.95 | BS18: 0.95 | BT18: 0.95 | BU18: 0.95 | BV18: 0.95 | BW18: 0.95 | BX18: 0.95 | BY18: 0.95 | BZ18: 0.95 | CA18: 0.95 | CB18: 0.95 | CC18: 0.95 | CD18: 0.95 | CE18: 0.95 | CF18: 0.95 | CG18: 0.95 | CH18: 0.95 | CI18: 0.95 | CJ18: 0.95 | CK18: 0.95 | CL18: 0.95 | CM18: 0.95 | CN18: 0.95 | CO18: 0.95 | CP18: 0.95 | CQ18: 0.95 | CR18: 0.95 | CS18: 0.95 | CT18: 0.95 | CU18: 0.95 | CV18: 0.95 | CW18: 0.95 | CX18: 0.95 | CY18: 0.95 | CZ18: 0.95 | DA18: 0.95 | DB18: 0.95 | DC18: 0.95 | DD18: 0.95 | DE18: 0.95 | DF18: 0.95 | DG18: 0.95 | DH18: 0.95 | DI18: 0.95 | DJ18: 0.95 | DK18: 0.95 | DL18: 0.95 | DM18: 0.95 | DN18: 0.95 | DO18: 0.95 | DP18: 0.95 | DQ18: 0.95 | DR18: 0.95 | DS18: 0.95 | DT18: 0.95 | DU18: 0.95 | DV18: 0.95 | DW18: 0.95 | DX18: 0.95 | DY18: 0.95 | DZ18: 0.95 | EA18: 0.95 | EB18: 0.95 | EC18: 0.95 | ED18: 0.95 | EE18: 0.95 | EF18: 0.95 | EG18: 0.95 | EH18: 0.95 | EI18: 0.95 | EJ18: 0.95 | EK18: 0.95 | EL18: 0.95 | EM18: 0.95 | EN18: 0.95 | EO18: 0.95 | EP18: 0.95 | EQ18: 0.95 | ER18: 0.95 | ES18: 0.95 | ET18: 0.95 | EU18: 0.95 | EV18: 0.95 | EW18: 0.95 | EX18: 0.95 | EY18: 0.95 | EZ18: 0.95 | FA18: 0.95 | FB18: 0.95 | FC18: 0.95 | FD18: 0.95 | FE18: 0.95 | FF18: 0.95 | FG18: 0.95 | FH18: 0.95 | FI18: 0.95 | FJ18: 0.95
A19: Käyttöikä | C19: vuotta | D19: 25 | E19: 25 | F19: 25 | G19: 25 | H19: 25 | I19: 25 | J19: 25 | K19: 25 | L19: 25 | M19: 25 | N19: 25 | O19: 25 | P19: 25 | Q19: 25 | R19: 25 | S19: 25 | T19: 25 | U19: 25 | V19: 25 | W19: 25 | X19: 25 | Y19: 25 | Z19: 25 | AA19: 25 | AB19: 25 | AC19: 25 | AD19: 25 | AE19: 25 | AF19: 25 | AG19: 25 | AH19: 25 | AI19: 25 | AJ19: 25 | AK19: 25 | AL19: 25 | AM19: 25 | AN19: 25 | AO19: 25 | AP19: 25 | AQ19: 25 | AR19: 25 | AS19: 25 | AT19: 25 | AU19: 25 | AV19: 25 | AW19: 25 | AX19: 25 | AY19: 25 | AZ19: 15 | BA19: 15 | BB19: 15 | BC19: 15 | BD19: 15 | BE19: 15 | BF19: 15 | BG19: 15 | BH19: 15 | BI19: 15 | BJ19: 15 | BK19: 15 | BL19: 15 | BM19: 15 | BN19: 15 | BO19: 15 | BP19: 15 | BQ19: 15 | BR19: 15 | BS19: 15 | BT19: 25 | BU19: 25 | BV19: 25 | BW19: 25 | BX19: 24 | BY19: 24 | BZ19: 24 | CA19: 24 | CB19: 25 | CC19: 25 | CD19: 25 | CE19: 25 | CF19: 30 | CG19: 30 | CH19: 30 | CI19: 30 | CJ19: 35 | CK19: 35 | CL19: 35 | CM19: 35 | CN19: 35 | CO19: 35 | CP19: 35 | CQ19: 30 | CR19: 30 | CS19: 30 | CT19: 30 | CU19: 30 | CV19: 30 | CW19: 30 | CX19: 30 | CY19: 30 | CZ19: 30 | DA19: 30 | DB19: 30 | DC19: 35 | DD19: 35 | DE19: 35 | DF19: 35 | DG19: 27 | DH19: 27 | DI19: 27 | DJ19: 27 | DK19: 20 | DL19: 20 | DM19: 20 | DN19: 20 | DO19: 20 | DP19: 20 | DQ19: 20 | DR19: 20 | DS19: 25 | DT19: 25 | DU19: 25 | DV19: 25 | DW19: 27 | DX19: 27 | DY19: 27 | DZ19: 27 | EA19: 25 | EB19: 25 | EC19: 25 | ED19: 25 | EE19: 28 | EF19: 28 | EG19: 28 | EH19: 28 | EI19: 20 | EJ19: 20 | EK19: 20 | EL19: 20 | EM19: 25 | EN19: 25 | EO19: 25 | EP19: 25 | EQ19: 41 | ER19: 41 | ES19: 41 | ET19: 41 | EU19: 41 | EV19: 41 | EW19: 41 | EX19: 41 | EY19: 20 | EZ19: 20 | FA19: 20 | FB19: 20 | FC19: 25 | FD19: 25 | FE19: 25 | FJ19: 25 | FK19: 60 | FL19: 40 | FM19: 25 | FN19: 25 | FO19: 60
A20: Regulaatio, luvitus, julkiset kuulemiset | C20: EUR/kW
A21: Suunnittelukustannukset | B21: Matala | C21: EUR/kW | D21: 12.783568 | E21: 12.783568 | F21: 12.783568 | G21: 12.783568 | H21: 51.134272 | I21: 51.134272 | J21: 51.134272 | K21: 51.134272 | L21: 25.567136 | M21: 25.567136 | N21: 25.567136 | O21: 25.567136 | P21: 38.350704 | Q21: 38.350704 | R21: 38.350704 | S21: 38.350704 | T21: 38.350704 | U21: 38.350704 | V21: 38.350704 | W21: 38.350704 | X21: 38.350704 | Y21: 38.350704 | Z21: 38.350704 | AA21: 38.350704 | AB21: 102.26854 | AC21: 102.26854 | AD21: 102.26854 | AE21: 102.26854 | AF21: 25.567136 | AG21: 25.567136 | AH21: 25.567136 | AI21: 25.567136 | AJ21: 38.350704 | AK21: 38.350704 | AL21: 38.350704 | AM21: 38.350704 | AN21: 38.350704 | AO21: 38.350704 | AP21: 38.350704 | AQ21: 38.350704 | AR21: 38.350704 | AS21: 38.350704 | AT21: 38.350704 | AU21: 38.350704 | AV21: 102.26854 | AW21: 102.26854 | AX21: 102.26854 | AY21: 102.26854 | AZ21: 12.783568 | BA21: 12.783568 | BB21: 12.783568 | BC21: 12.783568 | BD21: 12.783568 | BE21: 12.783568 | BF21: 12.783568 | BG21: 12.783568 | BH21: 12.783568 | BI21: 12.783568 | BJ21: 12.783568 | BK21: 12.783568 | BL21: 12.783568 | BM21: 12.783568 | BN21: 12.783568 | BO21: 12.783568 | BP21: 12.783568 | BQ21: 12.783568 | BR21: 12.783568 | BS21: 12.783568 | BT21: 115.05211 | BU21: 115.05211 | BV21: 115.05211 | BW21: 115.05211 | BX21: 63.91784 | BY21: 63.91784 | BZ21: 63.91784 | CA21: 63.91784 | CB21: 51.134272 | CC21: 51.134272 | CD21: 51.134272 | CE21: 51.134272 | CF21: 76.701408 | CG21: 76.701408 | CH21: 76.701408 | CI21: 76.701408 | CJ21: 12.783568 | CK21: 12.783568 | CL21: 12.783568 | CM21: 12.783568 | CN21: 12.783568 | CO21: 12.783568 | CP21: 12.783568 | CQ21: 0 | CR21: 0 | CS21: 0 | CT21: 0 | CU21: 0 | CV21: 0 | CW21: 0 | CX21: 0 | CY21: 0 | CZ21: 0 | DA21: 0 | DB21: 0 | DC21: 166.18638 | DD21: 166.18638 | DE21: 166.18638 | DF21: 166.18638 | DG21: 191.75352 | DH21: 191.75352 | DI21: 191.75352 | DJ21: 191.75352 | DK21: 383.50704 | DL21: 383.50704 | DM21: 383.50704 | DN21: 383.50704 | DO21: 383.50704 | DP21: 383.50704 | DQ21: 383.50704 | DR21: 383.50704 | DS21: 63.91784 | DT21: 63.91784 | DU21: 63.91784 | DV21: 63.91784 | DW21: 127.83568 | DX21: 127.83568 | DY21: 127.83568 | DZ21: 127.83568 | EA21: 127.83568 | EB21: 127.83568 | EC21: 127.83568 | ED21: 127.83568 | EE21: 38.350704 | EF21: 38.350704 | EG21: 38.350704 | EH21: 38.350704 | EI21: 600.8277 | EJ21: 600.8277 | EK21: 600.8277 | EL21: 600.8277 | EM21: 115.05211 | EN21: 115.05211 | EO21: 115.05211 | EP21: 115.05211 | EQ21: 0 | ER21: 0 | ES21: 0 | ET21: 0 | EU21: 63.91784 | EV21: 63.91784 | EW21: 63.91784 | EX21: 63.91784 | EY21: 63.91784 | EZ21: 63.91784 | FA21: 63.91784 | FB21: 63.91784 | FC21: 12.783568 | FD21: 12.783568 | FE21: 12.783568 | FF21: 0 | FG21: 0 | FH21: 0 | FI21: 0 | FJ21: 12.783568 | FL21: 0 | FM21: 0 | FN21: 0
B22: Keski | C22: EUR/kW | D22: 12.783568 | E22: 12.783568 | F22: 12.783568 | G22: 12.783568 | H22: 89.484976 | I22: 89.484976 | J22: 89.484976 | K22: 89.484976 | L22: 25.567136 | M22: 25.567136 | N22: 25.567136 | O22: 25.567136 | P22: 38.350704 | Q22: 38.350704 | R22: 38.350704 | S22: 38.350704 | T22: 38.350704 | U22: 38.350704 | V22: 38.350704 | W22: 38.350704 | X22: 51.134272 | Y22: 51.134272 | Z22: 51.134272 | AA22: 51.134272 | AB22: 115.05211 | AC22: 115.05211 | AD22: 115.05211 | AE22: 115.05211 | AF22: 25.567136 | AG22: 25.567136 | AH22: 25.567136 | AI22: 25.567136 | AJ22: 38.350704 | AK22: 38.350704 | AL22: 38.350704 | AM22: 38.350704 | AN22: 38.350704 | AO22: 38.350704 | AP22: 38.350704 | AQ22: 38.350704 | AR22: 51.134272 | AS22: 51.134272 | AT22: 51.134272 | AU22: 51.134272 | AV22: 115.05211 | AW22: 115.05211 | AX22: 115.05211 | AY22: 115.05211 | AZ22: 12.783568 | BA22: 12.783568 | BB22: 12.783568 | BC22: 12.783568 | BD22: 12.783568 | BE22: 12.783568 | BF22: 12.783568 | BG22: 12.783568 | BH22: 12.783568 | BI22: 12.783568 | BJ22: 12.783568 | BK22: 12.783568 | BL22: 12.783568 | BM22: 12.783568 | BN22: 12.783568 | BO22: 12.783568 | BP22: 12.783568 | BQ22: 12.783568 | BR22: 12.783568 | BS22: 12.783568 | BT22: 166.18638 | BU22: 166.18638 | BV22: 166.18638 | BW22: 166.18638 | BX22: 383.50704 | BY22: 383.50704 | BZ22: 383.50704 | CA22: 383.50704 | CB22: 166.18638 | CC22: 166.18638 | CD22: 166.18638 | CE22: 166.18638 | CF22: 166.18638 | CG22: 524.12629 | CH22: 588.04413 | CI22: 588.04413 | CJ22: 63.91784 | CK22: 63.91784 | CL22: 63.91784 | CM22: 63.91784 | CN22: 63.91784 | CO22: 63.91784 | CP22: 63.91784 | CQ22: 0 | CR22: 0 | CS22: 0 | CT22: 0 | CU22: 0 | CV22: 0 | CW22: 0 | CX22: 0 | CY22: 0 | CZ22: 0 | DA22: 0 | DB22: 0 | DC22: 332.37277 | DD22: 332.37277 | DE22: 332.37277 | DF22: 332.37277 | DG22: 306.80563 | DH22: 306.80563 | DI22: 306.80563 | DJ22: 306.80563 | DK22: 498.55915 | DL22: 498.55915 | DM22: 498.55915 | DN22: 498.55915 | DO22: 498.55915 | DP22: 498.55915 | DQ22: 498.55915 | DR22: 498.55915 | DS22: 268.45493 | DT22: 268.45493 | DU22: 268.45493 | DV22: 268.45493 | DW22: 588.04413 | DX22: 588.04413 | DY22: 588.04413 | DZ22: 588.04413 | EA22: 588.04413 | EB22: 588.04413 | EC22: 588.04413 | ED22: 588.04413 | EE22: 63.91784 | EF22: 63.91784 | EG22: 63.91784 | EH22: 63.91784 | EI22: 613.61126 | EJ22: 613.61126 | EK22: 613.61126 | EL22: 613.61126 | EM22: 153.40282 | EN22: 153.40282 | EO22: 153.40282 | EP22: 153.40282 | EQ22: 76.701408 | ER22: 76.701408 | ES22: 76.701408 | ET22: 76.701408 | EU22: 76.701408 | EV22: 76.701408 | EW22: 76.701408 | EX22: 76.701408 | EY22: 191.75352 | EZ22: 191.75352 | FA22: 191.75352 | FB22: 191.75352 | FC22: 12.783568 | FD22: 12.783568 | FE22: 12.783568 | FF22: 0 | FG22: 0 | FH22: 0 | FI22: 0 | FJ22: 12.783568 | FL22: 0 | FM22: 0 | FN22: 0
B23: Korkea | C23: EUR/kW | D23: 25.567136 | E23: 25.567136 | F23: 25.567136 | G23: 25.567136 | H23: 115.05211 | I23: 115.05211 | J23: 115.05211 | K23: 115.05211 | L23: 38.350704 | M23: 38.350704 | N23: 38.350704 | O23: 38.350704 | P23: 51.134272 | Q23: 51.134272 | R23: 51.134272 | S23: 51.134272 | T23: 51.134272 | U23: 51.134272 | V23: 51.134272 | W23: 51.134272 | X23: 51.134272 | Y23: 51.134272 | Z23: 51.134272 | AA23: 51.134272 | AB23: 140.61925 | AC23: 140.61925 | AD23: 140.61925 | AE23: 140.61925 | AF23: 38.350704 | AG23: 38.350704 | AH23: 38.350704 | AI23: 38.350704 | AJ23: 51.134272 | AK23: 51.134272 | AL23: 51.134272 | AM23: 51.134272 | AN23: 51.134272 | AO23: 51.134272 | AP23: 51.134272 | AQ23: 51.134272 | AR23: 51.134272 | AS23: 51.134272 | AT23: 51.134272 | AU23: 51.134272 | AV23: 140.61925 | AW23: 140.61925 | AX23: 140.61925 | AY23: 140.61925 | AZ23: 25.567136 | BA23: 25.567136 | BB23: 25.567136 | BC23: 25.567136 | BD23: 25.567136 | BE23: 25.567136 | BF23: 25.567136 | BG23: 25.567136 | BH23: 25.567136 | BI23: 25.567136 | BJ23: 25.567136 | BK23: 25.567136 | BL23: 25.567136 | BM23: 25.567136 | BN23: 25.567136 | BO23: 25.567136 | BP23: 25.567136 | BQ23: 25.567136 | BR23: 25.567136 | BS23: 25.567136 | BT23: 230.10422 | BU23: 230.10422 | BV23: 230.10422 | BW23: 230.10422 | BX23: 856.49906 | BY23: 856.49906 | BZ23: 856.49906 | CA23: 856.49906 | CB23: 268.45493 | CC23: 268.45493 | CD23: 268.45493 | CE23: 268.45493 | CF23: 255.67136 | CG23: 549.69342 | CH23: 1227.2225 | CI23: 1227.2225 | CJ23: 140.61925 | CK23: 140.61925 | CL23: 140.61925 | CM23: 140.61925 | CN23: 140.61925 | CO23: 140.61925 | CP23: 140.61925 | CQ23: 0 | CR23: 0 | CS23: 0 | CT23: 0 | CU23: 0 | CV23: 0 | CW23: 0 | CX23: 0 | CY23: 0 | CZ23: 0 | DA23: 0 | DB23: 0 | DC23: 575.26056 | DD23: 575.26056 | DE23: 575.26056 | DF23: 575.26056 | DG23: 434.64131 | DH23: 434.64131 | DI23: 434.64131 | DJ23: 434.64131 | DK23: 651.96197 | DL23: 651.96197 | DM23: 651.96197 | DN23: 651.96197 | DO23: 651.96197 | DP23: 651.96197 | DQ23: 651.96197 | DR23: 651.96197 | DS23: 447.42488 | DT23: 447.42488 | DU23: 447.42488 | DV23: 447.42488 | DW23: 1431.7596 | DX23: 1431.7596 | DY23: 1431.7596 | DZ23: 1431.7596 | EA23: 1431.7596 | EB23: 1431.7596 | EC23: 1431.7596 | ED23: 1431.7596 | EE23: 76.701408 | EF23: 76.701408 | EG23: 76.701408 | EH23: 76.701408 | EI23: 613.61126 | EJ23: 613.61126 | EK23: 613.61126 | EL23: 613.61126 | EM23: 191.75352 | EN23: 191.75352 | EO23: 191.75352 | EP23: 191.75352 | EQ23: 0 | ER23: 0 | ES23: 0 | ET23: 0 | EU23: 447.42488 | EV23: 447.42488 | EW23: 447.42488 | EX23: 447.42488 | EY23: 383.50704 | EZ23: 383.50704 | FA23: 383.50704 | FB23: 383.50704 | FC23: 25.567136 | FD23: 25.567136 | FE23: 25.567136 | FF23: 0 | FG23: 0 | FH23: 0 | FI23: 0 | FJ23: 12.783568 | FL23: 0 | FM23: 0 | FN23: 0
A24: Suunnittelun kesto | B24: Lyhyt | C24: vuotta | D24: 2 | E24: 2 | F24: 2 | G24: 2 | H24: 2 | I24: 2 | J24: 2 | K24: 2 | L24: 2 | M24: 2 | N24: 2 | O24: 2 | P24: 2 | Q24: 2 | R24: 2 | S24: 2 | T24: 2 | U24: 2 | V24: 2 | W24: 2 | X24: 2 | Y24: 2 | Z24: 2 | AA24: 2 | AB24: 2 | AC24: 2 | AD24: 2 | AE24: 2 | AF24: 2 | AG24: 2 | AH24: 2 | AI24: 2 | AJ24: 2 | AK24: 2 | AL24: 2 | AM24: 2 | AN24: 2 | AO24: 2 | AP24: 2 | AQ24: 2 | AR24: 2 | AS24: 2 | AT24: 2 | AU24: 2 | AV24: 2 | AW24: 2 | AX24: 2 | AY24: 2 | AZ24: 1 | BA24: 1 | BB24: 1 | BC24: 1 | BD24: 1 | BE24: 1 | BF24: 1 | BG24: 1 | BH24: 1 | BI24: 1 | BJ24: 1 | BK24: 1 | BL24: 1 | BM24: 1 | BN24: 1 | BO24: 1 | BP24: 1 | BQ24: 1 | BR24: 1 | BS24: 1 | BT24: 2 | BU24: 2 | BV24: 2 | BW24: 2 | BX24: 2 | BY24: 2 | BZ24: 2 | CA24: 2 | CB24: 3 | CC24: 3 | CD24: 3 | CE24: 3 | CF24: 3 | CG24: 3 | CH24: 3 | CI24: 3 | CJ24: 1 | CK24: 1 | CL24: 1 | CM24: 1 | CN24: 1 | CO24: 1 | CP24: 1 | CQ24: 0 | CR24: 0 | CS24: 0 | CT24: 0 | CU24: 0 | CV24: 0 | CW24: 0 | CX24: 0 | CY24: 0 | CZ24: 0 | DA24: 0 | DB24: 0 | DC24: 2 | DD24: 2 | DE24: 2 | DF24: 2 | DG24: 2 | DH24: 2 | DI24: 2 | DJ24: 2 | DK24: 2 | DL24: 2 | DM24: 2 | DN24: 2 | DO24: 2 | DP24: 2 | DQ24: 2 | DR24: 2 | DS24: 1 | DT24: 1 | DU24: 1 | DV24: 1 | DW24: 1 | DX24: 1 | DY24: 1 | DZ24: 1 | EA24: 1 | EB24: 1 | EC24: 1 | ED24: 1 | EE24: 1 | EF24: 1 | EG24: 1 | EH24: 1 | EI24: 1 | EJ24: 1 | EK24: 1 | EL24: 1 | EM24: 1 | EN24: 1 | EO24: 1 | EP24: 1 | EQ24: 0 | ER24: 0 | ES24: 0 | ET24: 0 | EU24: 2 | EV24: 2 | EW24: 2 | EX24: 2 | EY24: 3 | EZ24: 3 | FA24: 3 | FB24: 3 | FC24: 2 | FD24: 2 | FE24: 2 | FJ24: 2
B25: Keski | C25: vuotta | D25: 2 | E25: 2 | F25: 2 | G25: 2 | H25: 2 | I25: 2 | J25: 2 | K25: 2 | L25: 2 | M25: 2 | N25: 2 | O25: 2 | P25: 2 | Q25: 2 | R25: 2 | S25: 2 | T25: 2 | U25: 2 | V25: 2 | W25: 2 | X25: 2 | Y25: 2 | Z25: 2 | AA25: 2 | AB25: 2 | AC25: 2 | AD25: 2 | AE25: 2 | AF25: 2 | AG25: 2 | AH25: 2 | AI25: 2 | AJ25: 2 | AK25: 2 | AL25: 2 | AM25: 2 | AN25: 2 | AO25: 2 | AP25: 2 | AQ25: 2 | AR25: 2 | AS25: 2 | AT25: 2 | AU25: 2 | AV25: 2 | AW25: 2 | AX25: 2 | AY25: 2 | AZ25: 2 | BA25: 2 | BB25: 2 | BC25: 2 | BD25: 2 | BE25: 2 | BF25: 2 | BG25: 2 | BH25: 2 | BI25: 2 | BJ25: 2 | BK25: 2 | BL25: 2 | BM25: 2 | BN25: 2 | BO25: 2 | BP25: 2 | BQ25: 2 | BR25: 2 | BS25: 2 | BT25: 3 | BU25: 3 | BV25: 3 | BW25: 3 | BX25: 3 | BY25: 3 | BZ25: 3 | CA25: 3 | CB25: 4 | CC25: 4 | CD25: 4 | CE25: 4 | CF25: 5 | CG25: 5 | CH25: 5 | CI25: 5 | CJ25: 1 | CK25: 1 | CL25: 1 | CM25: 1 | CN25: 1 | CO25: 1 | CP25: 1 | CQ25: 0 | CR25: 0 | CS25: 0 | CT25: 0 | CU25: 0 | CV25: 0 | CW25: 0 | CX25: 0 | CY25: 0 | CZ25: 0 | DA25: 0 | DB25: 0 | DC25: 4 | DD25: 4 | DE25: 4 | DF25: 4 | DG25: 4 | DH25: 4 | DI25: 4 | DJ25: 4 | DK25: 2 | DL25: 2 | DM25: 2 | DN25: 2 | DO25: 2 | DP25: 2 | DQ25: 2 | DR25: 2 | DS25: 3 | DT25: 3 | DU25: 3 | DV25: 3 | DW25: 3 | DX25: 3 | DY25: 3 | DZ25: 3 | EA25: 3 | EB25: 3 | EC25: 3 | ED25: 3 | EE25: 1 | EF25: 1 | EG25: 1 | EH25: 1 | EI25: 1 | EJ25: 1 | EK25: 1 | EL25: 1 | EM25: 1 | EN25: 1 | EO25: 1 | EP25: 1 | EQ25: 0 | ER25: 0 | ES25: 0 | ET25: 0 | EU25: 2 | EV25: 2 | EW25: 2 | EX25: 2 | EY25: 3 | EZ25: 3 | FA25: 3 | FB25: 3 | FC25: 2 | FD25: 2 | FE25: 2 | FJ25: 2 | FK25: 3 | FL25: 3 | FM25: 2 | FN25: 2
B26: Pitkä | C26: vuotta | D26: 5 | E26: 5 | F26: 5 | G26: 5 | H26: 5 | I26: 5 | J26: 5 | K26: 5 | L26: 5 | M26: 5 | N26: 5 | O26: 5 | P26: 5 | Q26: 5 | R26: 5 | S26: 5 | T26: 5 | U26: 5 | V26: 5 | W26: 5 | X26: 5 | Y26: 5 | Z26: 5 | AA26: 5 | AB26: 5 | AC26: 5 | AD26: 5 | AE26: 5 | AF26: 5 | AG26: 5 | AH26: 5 | AI26: 5 | AJ26: 5 | AK26: 5 | AL26: 5 | AM26: 5 | AN26: 5 | AO26: 5 | AP26: 5 | AQ26: 5 | AR26: 5 | AS26: 5 | AT26: 5 | AU26: 5 | AV26: 5 | AW26: 5 | AX26: 5 | AY26: 5 | AZ26: 3 | BA26: 3 | BB26: 3 | BC26: 3 | BD26: 3 | BE26: 3 | BF26: 3 | BG26: 3 | BH26: 3 | BI26: 3 | BJ26: 3 | BK26: 3 | BL26: 3 | BM26: 3 | BN26: 3 | BO26: 3 | BP26: 3 | BQ26: 3 | BR26: 3 | BS26: 3 | BT26: 4 | BU26: 4 | BV26: 4 | BW26: 4 | BX26: 4 | BY26: 4 | BZ26: 4 | CA26: 4 | CB26: 6 | CC26: 6 | CD26: 6 | CE26: 6 | CF26: 6 | CG26: 6 | CH26: 6 | CI26: 6 | CJ26: 1 | CK26: 1 | CL26: 1 | CM26: 1 | CN26: 1 | CO26: 1 | CP26: 1 | CQ26: 0 | CR26: 0 | CS26: 0 | CT26: 0 | CU26: 0 | CV26: 0 | CW26: 0 | CX26: 0 | CY26: 0 | CZ26: 0 | DA26: 0 | DB26: 0 | DC26: 6 | DD26: 6 | DE26: 6 | DF26: 6 | DG26: 6 | DH26: 6 | DI26: 6 | DJ26: 6 | DK26: 2 | DL26: 2 | DM26: 2 | DN26: 2 | DO26: 2 | DP26: 2 | DQ26: 2 | DR26: 2 | DS26: 7 | DT26: 7 | DU26: 7 | DV26: 7 | DW26: 5 | DX26: 5 | DY26: 5 | DZ26: 5 | EA26: 5 | EB26: 5 | EC26: 5 | ED26: 5 | EE26: 1 | EF26: 1 | EG26: 1 | EH26: 1 | EI26: 1 | EJ26: 1 | EK26: 1 | EL26: 1 | EM26: 1 | EN26: 1 | EO26: 1 | EP26: 1 | EQ26: 0 | ER26: 0 | ES26: 0 | ET26: 0 | EU26: 3 | EV26: 3 | EW26: 3 | EX26: 3 | EY26: 3 | EZ26: 3 | FA26: 3 | FB26: 3 | FC26: 5 | FD26: 5 | FE26: 5 | FJ26: 5
A27: Suunnittelun aikataulu | B27: Vuosi 1 | C27: % | D27: 0.43 | E27: 0.43 | F27: 0.43 | G27: 0.43 | H27: 0.43 | I27: 0.43 | J27: 0.43 | K27: 0.43 | L27: 0.56 | M27: 0.56 | N27: 0.56 | O27: 0.56 | P27: 0.56 | Q27: 0.56 | R27: 0.56 | S27: 0.56 | T27: 0.56 | U27: 0.56 | V27: 0.56 | W27: 0.56 | X27: 0.56 | Y27: 0.56 | Z27: 0.56 | AA27: 0.56 | AB27: 0.56 | AC27: 0.56 | AD27: 0.56 | AE27: 0.56 | AF27: 0.56 | AG27: 0.56 | AH27: 0.56 | AI27: 0.56 | AJ27: 0.56 | AK27: 0.56 | AL27: 0.56 | AM27: 0.56 | AN27: 0.56 | AO27: 0.56 | AP27: 0.56 | AQ27: 0.56 | AR27: 0.56 | AS27: 0.56 | AT27: 0.56 | AU27: 0.56 | AV27: 0.56 | AW27: 0.56 | AX27: 0.56 | AY27: 0.56 | AZ27: 0.5 | BA27: 0.5 | BB27: 0.5 | BC27: 0.5 | BD27: 0.5 | BE27: 0.5 | BF27: 0.5 | BG27: 0.5 | BH27: 0.5 | BI27: 0.5 | BJ27: 0.5 | BK27: 0.5 | BL27: 0.5 | BM27: 0.5 | BN27: 0.5 | BO27: 0.5 | BP27: 0.5 | BQ27: 0.5 | BR27: 0.5 | BS27: 0.5 | BT27: 0.33 | BU27: 0.33 | BV27: 0.33 | BW27: 0.33 | BX27: 0.33 | BY27: 0.33 | BZ27: 0.33 | CA27: 0.33 | CB27: 0.25 | CC27: 0.25 | CD27: 0.25 | CE27: 0.25 | CF27: 0.2 | CG27: 0.2 | CH27: 0.2 | CI27: 0.2 | CJ27: 1 | CK27: 1 | CL27: 1 | CM27: 1 | CN27: 1 | CO27: 1 | CP27: 1 | CQ27: 1 | CR27: 1 | CS27: 1 | CT27: 1 | CU27: 1 | CV27: 1 | CW27: 1 | CX27: 1 | CY27: 1 | CZ27: 1 | DA27: 1 | DB27: 1 | DC27: 0.23 | DD27: 0.23 | DE27: 0.23 | DF27: 0.23 | DG27: 0.23 | DH27: 0.23 | DI27: 0.23 | DJ27: 0.23 | DK27: 0.67 | DL27: 0.67 | DM27: 0.67 | DN27: 0.67 | DO27: 0.67 | DP27: 0.67 | DQ27: 0.67 | DR27: 0.67 | DS27: 0.36 | DT27: 0.36 | DU27: 0.36 | DV27: 0.36 | DW27: 0.36 | DX27: 0.36 | DY27: 0.36 | DZ27: 0.36 | EA27: 0.36 | EB27: 0.36 | EC27: 0.36 | ED27: 0.36 | EE27: 1 | EF27: 1 | EG27: 1 | EH27: 1 | EI27: 1 | EJ27: 1 | EK27: 1 | EL27: 1 | EM27: 1 | EN27: 1 | EO27: 1 | EP27: 1 | EQ27: 1 | ER27: 1 | ES27: 1 | ET27: 1 | EU27: 0.48 | EV27: 0.48 | EW27: 0.48 | EX27: 0.48 | EY27: 0.33 | EZ27: 0.33 | FA27: 0.33 | FB27: 0.33 | FC27: 0.43 | FD27: 0.43 | FE27: 0.43 | FJ27: 0.43 | FK27: 0.2 | FL27: 0.2 | FM27: 0.5 | FN27: 0.5
A28: (% käytetty vuodessa) | B28: Vuosi 2 | C28: % | D28: 0.57 | E28: 0.57 | F28: 0.57 | G28: 0.57 | H28: 0.57 | I28: 0.57 | J28: 0.57 | K28: 0.57 | L28: 0.44 | M28: 0.44 | N28: 0.44 | O28: 0.44 | P28: 0.44 | Q28: 0.44 | R28: 0.44 | S28: 0.44 | T28: 0.44 | U28: 0.44 | V28: 0.44 | W28: 0.44 | X28: 0.44 | Y28: 0.44 | Z28: 0.44 | AA28: 0.44 | AB28: 0.44 | AC28: 0.44 | AD28: 0.44 | AE28: 0.44 | AF28: 0.44 | AG28: 0.44 | AH28: 0.44 | AI28: 0.44 | AJ28: 0.44 | AK28: 0.44 | AL28: 0.44 | AM28: 0.44 | AN28: 0.44 | AO28: 0.44 | AP28: 0.44 | AQ28: 0.44 | AR28: 0.44 | AS28: 0.44 | AT28: 0.44 | AU28: 0.44 | AV28: 0.44 | AW28: 0.44 | AX28: 0.44 | AY28: 0.44 | AZ28: 0.5 | BA28: 0.5 | BB28: 0.5 | BC28: 0.5 | BD28: 0.5 | BE28: 0.5 | BF28: 0.5 | BG28: 0.5 | BH28: 0.5 | BI28: 0.5 | BJ28: 0.5 | BK28: 0.5 | BL28: 0.5 | BM28: 0.5 | BN28: 0.5 | BO28: 0.5 | BP28: 0.5 | BQ28: 0.5 | BR28: 0.5 | BS28: 0.5 | BT28: 0.33 | BU28: 0.33 | BV28: 0.33 | BW28: 0.33 | BX28: 0.33 | BY28: 0.33 | BZ28: 0.33 | CA28: 0.33 | CB28: 0.25 | CC28: 0.25 | CD28: 0.25 | CE28: 0.25 | CF28: 0.2 | CG28: 0.2 | CH28: 0.2 | CI28: 0.2 | DC28: 0.23 | DD28: 0.23 | DE28: 0.23 | DF28: 0.23 | DG28: 0.23 | DH28: 0.23 | DI28: 0.23 | DJ28: 0.23 | DK28: 0.33 | DL28: 0.33 | DM28: 0.33 | DN28: 0.33 | DO28: 0.33 | DP28: 0.33 | DQ28: 0.33 | DR28: 0.33 | DS28: 0.36 | DT28: 0.36 | DU28: 0.36 | DV28: 0.36 | DW28: 0.36 | DX28: 0.36 | DY28: 0.36 | DZ28: 0.36 | EA28: 0.36 | EB28: 0.36 | EC28: 0.36 | ED28: 0.36 | EU28: 0.52 | EV28: 0.52 | EW28: 0.52 | EX28: 0.52 | EY28: 0.33 | EZ28: 0.33 | FA28: 0.33 | FB28: 0.33 | FC28: 0.57 | FD28: 0.57 | FE28: 0.57 | FJ28: 0.57 | FK28: 0.4 | FL28: 0.4 | FM28: 0.5 | FN28: 0.5
B29: Vuosi 3 | C29: % | BT29: 0.33 | BU29: 0.33 | BV29: 0.33 | BW29: 0.33 | BX29: 0.33 | BY29: 0.33 | BZ29: 0.33 | CA29: 0.33 | CB29: 0.25 | CC29: 0.25 | CD29: 0.25 | CE29: 0.25 | CF29: 0.2 | CG29: 0.2 | CH29: 0.2 | CI29: 0.2 | DC29: 0.23 | DD29: 0.23 | DE29: 0.23 | DF29: 0.23 | DG29: 0.23 | DH29: 0.23 | DI29: 0.23 | DJ29: 0.23 | DS29: 0.27 | DT29: 0.27 | DU29: 0.27 | DV29: 0.27 | DW29: 0.27 | DX29: 0.27 | DY29: 0.27 | DZ29: 0.27 | EA29: 0.27 | EB29: 0.27 | EC29: 0.27 | ED29: 0.27 | EY29: 0.33 | EZ29: 0.33 | FA29: 0.33 | FB29: 0.33 | FK29: 0.4 | FL29: 0.4
B30: Vuosi 4 | C30: % | CB30: 0.25 | CC30: 0.25 | CD30: 0.25 | CE30: 0.25 | CF30: 0.2 | CG30: 0.2 | CH30: 0.2 | CI30: 0.2 | DC30: 0.32 | DD30: 0.32 | DE30: 0.32 | DF30: 0.32 | DG30: 0.32 | DH30: 0.32 | DI30: 0.32 | DJ30: 0.32
B31: Vuosi 5 | C31: % | CF31: 0.2 | CG31: 0.2 | CH31: 0.2 | CI31: 0.2
B32: Vuosi 6 | C32: %
B33: Vuosi 7 | C33: %
B34: Vuosi 8 | C34: %
B35: Vuosi 9 | C35: %
B36: Vuosi 10 | C36: %
A37: Rakentamiskustannukset | B37: Matala | C37: EUR/kW | D37: 639.1784 | E37: 639.1784 | F37: 639.1784 | G37: 639.1784 | H37: 894.84976 | I37: 894.84976 | J37: 894.84976 | K37: 894.84976 | L37: 383.50704 | M37: 383.50704 | N37: 383.50704 | O37: 383.50704 | P37: 383.50704 | Q37: 383.50704 | R37: 383.50704 | S37: 383.50704 | T37: 383.50704 | U37: 383.50704 | V37: 383.50704 | W37: 383.50704 | X37: 383.50704 | Y37: 383.50704 | Z37: 383.50704 | AA37: 383.50704 | AB37: 767.01408 | AC37: 767.01408 | AD37: 767.01408 | AE37: 767.01408 | AF37: 383.50704 | AG37: 383.50704 | AH37: 383.50704 | AI37: 383.50704 | AJ37: 383.50704 | AK37: 383.50704 | AL37: 383.50704 | AM37: 383.50704 | AN37: 383.50704 | AO37: 383.50704 | AP37: 383.50704 | AQ37: 383.50704 | AR37: 383.50704 | AS37: 383.50704 | AT37: 383.50704 | AU37: 383.50704 | AV37: 767.01408 | AW37: 767.01408 | AX37: 767.01408 | AY37: 767.01408 | AZ37: 255.67136 | BA37: 255.67136 | BB37: 255.67136 | BC37: 255.67136 | BD37: 255.67136 | BE37: 255.67136 | BF37: 255.67136 | BG37: 255.67136 | BH37: 255.67136 | BI37: 255.67136 | BJ37: 255.67136 | BK37: 255.67136 | BL37: 383.50704 | BM37: 383.50704 | BN37: 383.50704 | BO37: 383.50704 | BP37: 383.50704 | BQ37: 383.50704 | BR37: 383.50704 | BS37: 383.50704 | BT37: 3323.7277 | BU37: 3323.7277 | BV37: 3323.7277 | BW37: 3323.7277 | BX37: 5369.0986 | BY37: 5369.0986 | BZ37: 5369.0986 | CA37: 5369.0986 | CB37: 1150.5211 | CC37: 1150.5211 | CD37: 1150.5211 | CE37: 1150.5211 | CF37: 1661.8638 | CG37: 1534.0282 | CH37: 1406.1925 | CI37: 1406.1925 | CJ37: 383.50704 | CK37: 383.50704 | CL37: 255.67136 | CM37: 255.67136 | CN37: 757 | CO37: =0.877*1.099*400 -> 385.5292 | CP37: =0.877*1.099*245 -> 236.13663 | CQ37: 894.84976 | CR37: 894.84976 | CS37: 894.84976 | CT37: 894.84976 | CU37: 1150.5211 | CV37: 1150.5211 | CW37: 1150.5211 | CX37: 1150.5211 | CY37: 1406.1925 | CZ37: 1278.3568 | DA37: 1278.3568 | DB37: 1278.3568 | DC37: 6647.4554 | DD37: 6519.6197 | DE37: 6519.6197 | DF37: 6519.6197 | DG37: 10354.69 | DH37: 10226.854 | DI37: 10099.019 | DJ37: 10099.019 | DK37: 4218.5774 | DL37: 4218.5774 | DM37: 4218.5774 | DN37: 4218.5774 | DO37: 4857.7558 | DP37: 4857.7558 | DQ37: 4857.7558 | DR37: 4857.7558 | DS37: 5752.6056 | DT37: 5369.0986 | DU37: 5241.2629 | DV37: 5241.2629 | DW37: 4346.4131 | DX37: 4090.7418 | DY37: 3962.9061 | DZ37: 3835.0704 | EA37: 4985.5915 | EB37: 4729.9202 | EC37: 4474.2488 | ED37: 4474.2488 | EE37: 1150.5211 | EF37: 1150.5211 | EG37: 1150.5211 | EH37: 1150.5211 | EI37: 2684.5493 | EJ37: 2684.5493 | EK37: 2684.5493 | EL37: 2684.5493 | EM37: 4218.5774 | EN37: 4090.7418 | EO37: 4090.7418 | EP37: 4090.7418 | EQ37: 0 | ER37: 0 | ES37: 0 | ET37: 0 | EU37: 2301.0422 | EV37: 2301.0422 | EW37: 2301.0422 | EX37: 2301.0422 | EY37: 3835.0704 | EZ37: 2940.2206 | FA37: 2684.5493 | FB37: 2684.5493 | FC37: 767.01408 | FD37: 767.01408 | FE37: 767.01408 | FF37: 0 | FG37: 0 | FH37: 0 | FI37: 0 | FJ37: 767.01408 | FO37: 3272
B38: Keski | C38: EUR/kW | D38: 767.01408 | E38: 767.01408 | F38: 767.01408 | G38: 767.01408 | H38: 1022.6854 | I38: 1022.6854 | J38: 1022.6854 | K38: 1022.6854 | L38: 383.50704 | M38: 383.50704 | N38: 383.50704 | O38: 383.50704 | P38: 511.34272 | Q38: 511.34272 | R38: 511.34272 | S38: 511.34272 | T38: 639.1784 | U38: 639.1784 | V38: 639.1784 | W38: 639.1784 | X38: 639.1784 | Y38: 639.1784 | Z38: 639.1784 | AA38: 639.1784 | AB38: 894.84976 | AC38: 894.84976 | AD38: 894.84976 | AE38: 894.84976 | AF38: 383.50704 | AG38: 383.50704 | AH38: 383.50704 | AI38: 383.50704 | AJ38: 511.34272 | AK38: 511.34272 | AL38: 511.34272 | AM38: 511.34272 | AN38: 639.1784 | AO38: 639.1784 | AP38: 639.1784 | AQ38: 639.1784 | AR38: 639.1784 | AS38: 639.1784 | AT38: 639.1784 | AU38: 639.1784 | AV38: 894.84976 | AW38: 894.84976 | AX38: 894.84976 | AY38: 894.84976 | AZ38: 383.50704 | BA38: 383.50704 | BB38: 383.50704 | BC38: 383.50704 | BD38: 383.50704 | BE38: 383.50704 | BF38: 383.50704 | BG38: 383.50704 | BH38: 383.50704 | BI38: 383.50704 | BJ38: 383.50704 | BK38: 383.50704 | BL38: 383.50704 | BM38: 383.50704 | BN38: 383.50704 | BO38: 383.50704 | BP38: 383.50704 | BQ38: 383.50704 | BR38: 383.50704 | BS38: 383.50704 | BT38: 4090.7418 | BU38: 4090.7418 | BV38: 4090.7418 | BW38: 4090.7418 | BX38: 7158.7981 | BY38: 7158.7981 | BZ38: 7158.7981 | CA38: 7158.7981 | CB38: 1406.1925 | CC38: 1406.1925 | CD38: 1406.1925 | CE38: 1406.1925 | CF38: 1917.5352 | CG38: 1789.6995 | CH38: 1661.8638 | CI38: 1661.8638 | CJ38: 511.34272 | CK38: 383.50704 | CL38: 255.67136 | CM38: 255.67136 | CN38: =0.877*1.099*1465 -> 1412.0007 | CO38: =0.877*1.099*1100 -> 1060.2053 | CP38: =0.877*1.099*491 -> 473.23709 | CQ38: 1278.3568 | CR38: 1150.5211 | CS38: 1150.5211 | CT38: 1150.5211 | CU38: 1534.0282 | CV38: 1406.1925 | CW38: 1406.1925 | CX38: 1406.1925 | CY38: 1789.6995 | CZ38: 1789.6995 | DA38: 1789.6995 | DB38: 1789.6995 | DC38: 11760.883 | DD38: 11633.047 | DE38: 11505.211 | DF38: 11505.211 | DG38: 18152.667 | DH38: 17896.995 | DI38: 17769.16 | DJ38: 17641.324 | DK38: 5496.9342 | DL38: 5496.9342 | DM38: 5496.9342 | DN38: 5496.9342 | DO38: 6263.9483 | DP38: 6263.9483 | DQ38: 6263.9483 | DR38: 6263.9483 | DS38: 8309.3192 | DT38: 7797.9765 | DU38: 7670.1408 | DV38: 7670.1408 | DW38: 8820.6619 | DX38: 8309.3192 | DY38: 7925.8122 | DZ38: 7797.9765 | EA38: 10099.019 | EB38: 9587.676 | EC38: 9076.3333 | ED38: 8948.4976 | EE38: 3195.892 | EF38: 3195.892 | EG38: 3195.892 | EH38: 3195.892 | EI38: 7414.4694 | EJ38: 7414.4694 | EK38: 7414.4694 | EL38: 7414.4694 | EM38: 9715.5117 | EN38: 9587.676 | EO38: 9459.8403 | EP38: 9459.8403 | EQ38: 4729.9202 | ER38: 4729.9202 | ES38: 4729.9202 | ET38: 4729.9202 | EU38: 4346.4131 | EV38: 4346.4131 | EW38: 4346.4131 | EX38: 4346.4131 | EY38: 6647.4554 | EZ38: 5113.4272 | FA38: 4602.0845 | FB38: 4602.0845 | FC38: 894.84976 | FD38: 894.84976 | FE38: 894.84976 | FF38: 0 | FG38: 0 | FH38: 0 | FI38: 0 | FJ38: 767.01408 | FK38: 4441.17 | FL38: 4038.7 | FM38: 1523.2 | FN38: 1103.2 | FO38: 6544
B39: Korkea | C39: EUR/kW | D39: 894.84976 | E39: 894.84976 | F39: 894.84976 | G39: 894.84976 | H39: 1278.3568 | I39: 1278.3568 | J39: 1278.3568 | K39: 1278.3568 | L39: 383.50704 | M39: 511.34272 | N39: 511.34272 | O39: 511.34272 | P39: 511.34272 | Q39: 511.34272 | R39: 511.34272 | S39: 511.34272 | T39: 1022.6854 | U39: 1022.6854 | V39: 1022.6854 | W39: 1022.6854 | X39: 1022.6854 | Y39: 1022.6854 | Z39: 1022.6854 | AA39: 1022.6854 | AB39: 1150.5211 | AC39: 1150.5211 | AD39: 1150.5211 | AE39: 1150.5211 | AF39: 383.50704 | AG39: 511.34272 | AH39: 511.34272 | AI39: 511.34272 | AJ39: 511.34272 | AK39: 511.34272 | AL39: 511.34272 | AM39: 511.34272 | AN39: 1022.6854 | AO39: 1022.6854 | AP39: 1022.6854 | AQ39: 1022.6854 | AR39: 1022.6854 | AS39: 1022.6854 | AT39: 1022.6854 | AU39: 1022.6854 | AV39: 1150.5211 | AW39: 1150.5211 | AX39: 1150.5211 | AY39: 1150.5211 | AZ39: 383.50704 | BA39: 383.50704 | BB39: 383.50704 | BC39: 383.50704 | BD39: 383.50704 | BE39: 383.50704 | BF39: 383.50704 | BG39: 383.50704 | BH39: 383.50704 | BI39: 383.50704 | BJ39: 383.50704 | BK39: 383.50704 | BL39: 511.34272 | BM39: 511.34272 | BN39: 511.34272 | BO39: 511.34272 | BP39: 511.34272 | BQ39: 511.34272 | BR39: 511.34272 | BS39: 511.34272 | BT39: 4857.7558 | BU39: 4729.9202 | BV39: 4729.9202 | BW39: 4729.9202 | BX39: 8564.9906 | BY39: 8564.9906 | BZ39: 8437.1549 | CA39: 8437.1549 | CB39: 1534.0282 | CC39: 1534.0282 | CD39: 1534.0282 | CE39: 1534.0282 | CF39: 2556.7136 | CG39: 2173.2066 | CH39: 1917.5352 | CI39: 1917.5352 | CJ39: 511.34272 | CK39: 383.50704 | CL39: 383.50704 | CM39: 255.67136 | CN39: =0.877*1.099*3123 -> 3010.0192 | CO39: =0.877*1.099*2626 -> 2530.9992 | CP39: =0.877*1.099*675 -> 650.58052 | CQ39: 1534.0282 | CR39: 1406.1925 | CS39: 1406.1925 | CT39: 1406.1925 | CU39: 1917.5352 | CV39: 1789.6995 | CW39: 1789.6995 | CX39: 1789.6995 | CY39: 2301.0422 | CZ39: 2173.2066 | DA39: 2173.2066 | DB39: 2173.2066 | DC39: 17896.995 | DD39: 17769.16 | DE39: 17641.324 | DF39: 17641.324 | DG39: 22115.573 | DH39: 21732.066 | DI39: 21476.394 | DJ39: 21348.559 | DK39: 7158.7981 | DL39: 7158.7981 | DM39: 7158.7981 | DN39: 7158.7981 | DO39: 8181.4835 | DP39: 8181.4835 | DQ39: 8181.4835 | DR39: 8181.4835 | DS39: 9715.5117 | DT39: 9204.169 | DU39: 8948.4976 | DV39: 8948.4976 | DW39: 12655.732 | DX39: 11888.718 | DY39: 11377.376 | DZ39: 11121.704 | EA39: 15212.446 | EB39: 14317.596 | EC39: 13678.418 | ED39: 13294.911 | EE39: 5241.2629 | EF39: 5241.2629 | EG39: 5241.2629 | EH39: 5241.2629 | EI39: 10226.854 | EJ39: 10226.854 | EK39: 10226.854 | EL39: 10226.854 | EM39: 13294.911 | EN39: 13039.239 | EO39: 12783.568 | EP39: 12783.568 | EQ39: 0 | ER39: 0 | ES39: 0 | ET39: 0 | EU39: 4474.2488 | EV39: 4474.2488 | EW39: 4474.2488 | EX39: 4474.2488 | EY39: 9076.3333 | EZ39: 7030.9624 | FA39: 6263.9483 | FB39: 6263.9483 | FC39: 1022.6854 | FD39: 1022.6854 | FE39: 1022.6854 | FF39: 0 | FG39: 0 | FH39: 0 | FI39: 0 | FJ39: 767.01408 | FO39: 9816
A40: Rakentamisaikataulu | B40: Lyhyt | C40: vuotta | D40: 2 | E40: 2 | F40: 2 | G40: 2 | H40: 2 | I40: 2 | J40: 2 | K40: 2 | L40: 2 | M40: 2 | N40: 2 | O40: 2 | P40: 2 | Q40: 2 | R40: 2 | S40: 2 | T40: 2 | U40: 2 | V40: 2 | W40: 2 | X40: 2 | Y40: 2 | Z40: 2 | AA40: 2 | AB40: 2 | AC40: 2 | AD40: 2 | AE40: 2 | AF40: 2 | AG40: 2 | AH40: 2 | AI40: 2 | AJ40: 2 | AK40: 2 | AL40: 2 | AM40: 2 | AN40: 2 | AO40: 2 | AP40: 2 | AQ40: 2 | AR40: 2 | AS40: 2 | AT40: 2 | AU40: 2 | AV40: 2 | AW40: 2 | AX40: 2 | AY40: 2 | AZ40: 0 | BA40: 0 | BB40: 0 | BC40: 0 | BD40: 0 | BE40: 0 | BF40: 0 | BG40: 0 | BH40: 0 | BI40: 0 | BJ40: 0 | BK40: 0 | BL40: 0 | BM40: 0 | BN40: 0 | BO40: 0 | BP40: 0 | BQ40: 0 | BR40: 0 | BS40: 0 | BT40: 2 | BU40: 2 | BV40: 2 | BW40: 2 | BX40: 2 | BY40: 2 | BZ40: 2 | CA40: 2 | CB40: 1 | CC40: 1 | CD40: 1 | CE40: 1 | CF40: 2 | CG40: 2 | CH40: 2 | CI40: 2 | CJ40: 0 | CK40: 0 | CL40: 0 | CM40: 0 | CN40: 0 | CO40: 0 | CP40: 0 | CQ40: 1 | CR40: 1 | CS40: 1 | CT40: 1 | CU40: 1 | CV40: 1 | CW40: 1 | CX40: 1 | CY40: 1 | CZ40: 1 | DA40: 1 | DB40: 1 | DC40: 3 | DD40: 3 | DE40: 3 | DF40: 3 | DG40: 3 | DH40: 3 | DI40: 3 | DJ40: 3 | DK40: 1 | DL40: 1 | DM40: 1 | DN40: 1 | DO40: 1 | DP40: 1 | DQ40: 1 | DR40: 1 | DS40: 2 | DT40: 2 | DU40: 2 | DV40: 2 | DW40: 2 | DX40: 2 | DY40: 2 | DZ40: 2 | EA40: 2 | EB40: 2 | EC40: 2 | ED40: 2 | EE40: 0 | EF40: 0 | EG40: 0 | EH40: 0 | EI40: 2 | EJ40: 2 | EK40: 2 | EL40: 2 | EM40: 2 | EN40: 2 | EO40: 2 | EP40: 2 | EQ40: 0 | ER40: 0 | ES40: 0 | ET40: 0 | EU40: 1 | EV40: 1 | EW40: 1 | EX40: 1 | EY40: 2 | EZ40: 2 | FA40: 2 | FB40: 2 | FC40: 2 | FD40: 2 | FE40: 2 | FJ40: 2 | FO40: 5
B41: Keski | C41: vuotta | D41: 3 | E41: 3 | F41: 3 | G41: 3 | H41: 3 | I41: 3 | J41: 3 | K41: 3 | L41: 2 | M41: 2 | N41: 2 | O41: 2 | P41: 2 | Q41: 2 | R41: 2 | S41: 2 | T41: 2 | U41: 2 | V41: 2 | W41: 2 | X41: 2 | Y41: 2 | Z41: 2 | AA41: 2 | AB41: 2 | AC41: 2 | AD41: 2 | AE41: 2 | AF41: 2 | AG41: 2 | AH41: 2 | AI41: 2 | AJ41: 2 | AK41: 2 | AL41: 2 | AM41: 2 | AN41: 2 | AO41: 2 | AP41: 2 | AQ41: 2 | AR41: 2 | AS41: 2 | AT41: 2 | AU41: 2 | AV41: 2 | AW41: 2 | AX41: 2 | AY41: 2 | AZ41: 1 | BA41: 1 | BB41: 1 | BC41: 1 | BD41: 1 | BE41: 1 | BF41: 1 | BG41: 1 | BH41: 1 | BI41: 1 | BJ41: 1 | BK41: 1 | BL41: 1 | BM41: 1 | BN41: 1 | BO41: 1 | BP41: 1 | BQ41: 1 | BR41: 1 | BS41: 1 | BT41: 2 | BU41: 2 | BV41: 2 | BW41: 2 | BX41: 2 | BY41: 2 | BZ41: 2 | CA41: 2 | CB41: 2 | CC41: 2 | CD41: 2 | CE41: 2 | CF41: 2 | CG41: 2 | CH41: 2 | CI41: 2 | CJ41: 1 | CK41: 1 | CL41: 1 | CM41: 1 | CN41: 1 | CO41: 1 | CP41: 1 | CQ41: 1 | CR41: 1 | CS41: 1 | CT41: 1 | CU41: 1 | CV41: 1 | CW41: 1 | CX41: 1 | CY41: 1 | CZ41: 1 | DA41: 1 | DB41: 1 | DC41: 3 | DD41: 3 | DE41: 3 | DF41: 3 | DG41: 3 | DH41: 3 | DI41: 3 | DJ41: 3 | DK41: 1 | DL41: 1 | DM41: 1 | DN41: 1 | DO41: 1 | DP41: 1 | DQ41: 1 | DR41: 1 | DS41: 2 | DT41: 2 | DU41: 2 | DV41: 2 | DW41: 2 | DX41: 2 | DY41: 2 | DZ41: 2 | EA41: 2 | EB41: 2 | EC41: 2 | ED41: 2 | EE41: 0 | EF41: 0 | EG41: 0 | EH41: 0 | EI41: 2 | EJ41: 2 | EK41: 2 | EL41: 2 | EM41: 3 | EN41: 3 | EO41: 3 | EP41: 3 | EQ41: 2 | ER41: 2 | ES41: 2 | ET41: 2 | EU41: 2 | EV41: 2 | EW41: 2 | EX41: 2 | EY41: 2 | EZ41: 2 | FA41: 2 | FB41: 2 | FC41: 3 | FD41: 3 | FE41: 3 | FJ41: 3 | FK41: 7 | FL41: 7 | FM41: 2 | FN41: 2 | FO41: 7
B42: Pitkä | C42: vuotta | D42: 3 | E42: 3 | F42: 3 | G42: 3 | H42: 3 | I42: 3 | J42: 3 | K42: 3 | L42: 3 | M42: 3 | N42: 3 | O42: 3 | P42: 3 | Q42: 3 | R42: 3 | S42: 3 | T42: 3 | U42: 3 | V42: 3 | W42: 3 | X42: 3 | Y42: 3 | Z42: 3 | AA42: 3 | AB42: 3 | AC42: 3 | AD42: 3 | AE42: 3 | AF42: 3 | AG42: 3 | AH42: 3 | AI42: 3 | AJ42: 3 | AK42: 3 | AL42: 3 | AM42: 3 | AN42: 3 | AO42: 3 | AP42: 3 | AQ42: 3 | AR42: 3 | AS42: 3 | AT42: 3 | AU42: 3 | AV42: 3 | AW42: 3 | AX42: 3 | AY42: 3 | AZ42: 1 | BA42: 1 | BB42: 1 | BC42: 1 | BD42: 1 | BE42: 1 | BF42: 1 | BG42: 1 | BH42: 1 | BI42: 1 | BJ42: 1 | BK42: 1 | BL42: 1 | BM42: 1 | BN42: 1 | BO42: 1 | BP42: 1 | BQ42: 1 | BR42: 1 | BS42: 1 | BT42: 2 | BU42: 2 | BV42: 2 | BW42: 2 | BX42: 2 | BY42: 2 | BZ42: 2 | CA42: 2 | CB42: 3 | CC42: 3 | CD42: 3 | CE42: 3 | CF42: 5 | CG42: 5 | CH42: 5 | CI42: 5 | CJ42: 1 | CK42: 1 | CL42: 1 | CM42: 1 | CN42: 1 | CO42: 1 | CP42: 1 | CQ42: 1 | CR42: 1 | CS42: 1 | CT42: 1 | CU42: 1 | CV42: 1 | CW42: 1 | CX42: 1 | CY42: 1 | CZ42: 1 | DA42: 1 | DB42: 1 | DC42: 3 | DD42: 3 | DE42: 3 | DF42: 3 | DG42: 4 | DH42: 4 | DI42: 4 | DJ42: 4 | DK42: 1 | DL42: 1 | DM42: 1 | DN42: 1 | DO42: 1 | DP42: 1 | DQ42: 1 | DR42: 1 | DS42: 2 | DT42: 2 | DU42: 2 | DV42: 2 | DW42: 3 | DX42: 3 | DY42: 3 | DZ42: 3 | EA42: 3 | EB42: 3 | EC42: 3 | ED42: 3 | EE42: 1 | EF42: 1 | EG42: 1 | EH42: 1 | EI42: 2 | EJ42: 2 | EK42: 2 | EL42: 2 | EM42: 4 | EN42: 4 | EO42: 4 | EP42: 4 | EQ42: 0 | ER42: 0 | ES42: 0 | ET42: 0 | EU42: 2 | EV42: 2 | EW42: 2 | EX42: 2 | EY42: 2 | EZ42: 2 | FA42: 2 | FB42: 2 | FC42: 3 | FD42: 3 | FE42: 3 | FJ42: 3 | FO42: 8
A43: Rakentamisaikataulutus | B43: Vuosi 1 | C43: % | D43: 0.4 | E43: 0.4 | F43: 0.4 | G43: 0.4 | H43: 0.4 | I43: 0.4 | J43: 0.4 | K43: 0.4 | L43: 0.5 | M43: 0.5 | N43: 0.5 | O43: 0.5 | P43: 0.5 | Q43: 0.5 | R43: 0.5 | S43: 0.5 | T43: 0.5 | U43: 0.5 | V43: 0.5 | W43: 0.5 | X43: 0.5 | Y43: 0.5 | Z43: 0.5 | AA43: 0.5 | AB43: 0.5 | AC43: 0.5 | AD43: 0.5 | AE43: 0.5 | AF43: 0.5 | AG43: 0.5 | AH43: 0.5 | AI43: 0.5 | AJ43: 0.5 | AK43: 0.5 | AL43: 0.5 | AM43: 0.5 | AN43: 0.5 | AO43: 0.5 | AP43: 0.5 | AQ43: 0.5 | AR43: 0.5 | AS43: 0.5 | AT43: 0.5 | AU43: 0.5 | AV43: 0.5 | AW43: 0.5 | AX43: 0.5 | AY43: 0.5 | AZ43: 1 | BA43: 1 | BB43: 1 | BC43: 1 | BD43: 1 | BE43: 1 | BF43: 1 | BG43: 1 | BH43: 1 | BI43: 1 | BJ43: 1 | BK43: 1 | BL43: 1 | BM43: 1 | BN43: 1 | BO43: 1 | BP43: 1 | BQ43: 1 | BR43: 1 | BS43: 1 | BT43: 0.46 | BU43: 0.46 | BV43: 0.46 | BW43: 0.46 | BX43: 0.47 | BY43: 0.47 | BZ43: 0.47 | CA43: 0.47 | CB43: 0.5 | CC43: 0.5 | CD43: 0.5 | CE43: 0.5 | CF43: 0.5 | CG43: 0.5 | CH43: 0.5 | CI43: 0.5 | CJ43: 1 | CK43: 1 | CL43: 1 | CM43: 1 | CN43: 1 | CO43: 1 | CP43: 1 | CQ43: 1 | CR43: 1 | CS43: 1 | CT43: 1 | CU43: 1 | CV43: 1 | CW43: 1 | CX43: 1 | CY43: 1 | CZ43: 1 | DA43: 1 | DB43: 1 | DC43: 0.34 | DD43: 0.34 | DE43: 0.34 | DF43: 0.34 | DG43: 0.34 | DH43: 0.34 | DI43: 0.34 | DJ43: 0.34 | DK43: 1 | DL43: 1 | DM43: 1 | DN43: 1 | DO43: 1 | DP43: 1 | DQ43: 1 | DR43: 1 | DS43: 0.5 | DT43: 0.5 | DU43: 0.5 | DV43: 0.5 | DW43: 0.44 | DX43: 0.44 | DY43: 0.44 | DZ43: 0.44 | EA43: 0.44 | EB43: 0.44 | EC43: 0.44 | ED43: 0.44 | EE43: 1 | EF43: 1 | EG43: 1 | EH43: 1 | EI43: 0.55 | EJ43: 0.55 | EK43: 0.55 | EL43: 0.55 | EM43: 0.33 | EN43: 0.33 | EO43: 0.33 | EP43: 0.33 | EQ43: 0.5 | ER43: 0.5 | ES43: 0.5 | ET43: 0.5 | EU43: 0.5 | EV43: 0.5 | EW43: 0.5 | EX43: 0.5 | EY43: 0.5 | EZ43: 0.5 | FA43: 0.5 | FB43: 0.5 | FC43: 0.4 | FD43: 0.4 | FE43: 0.4 | FJ43: 0.4 | FK43: 0.1 | FL43: 0.1 | FM43: 0.5 | FN43: 0.5 | FO43: =100%/7 -> 0.14285714
A44: (% käytetty vuodessa) | B44: Vuosi 2 | C44: % | D44: 0.4 | E44: 0.4 | F44: 0.4 | G44: 0.4 | H44: 0.4 | I44: 0.4 | J44: 0.4 | K44: 0.4 | L44: 0.5 | M44: 0.5 | N44: 0.5 | O44: 0.5 | P44: 0.5 | Q44: 0.5 | R44: 0.5 | S44: 0.5 | T44: 0.5 | U44: 0.5 | V44: 0.5 | W44: 0.5 | X44: 0.5 | Y44: 0.5 | Z44: 0.5 | AA44: 0.5 | AB44: 0.5 | AC44: 0.5 | AD44: 0.5 | AE44: 0.5 | AF44: 0.5 | AG44: 0.5 | AH44: 0.5 | AI44: 0.5 | AJ44: 0.5 | AK44: 0.5 | AL44: 0.5 | AM44: 0.5 | AN44: 0.5 | AO44: 0.5 | AP44: 0.5 | AQ44: 0.5 | AR44: 0.5 | AS44: 0.5 | AT44: 0.5 | AU44: 0.5 | AV44: 0.5 | AW44: 0.5 | AX44: 0.5 | AY44: 0.5 | BT44: 0.54 | BU44: 0.54 | BV44: 0.54 | BW44: 0.54 | BX44: 0.53 | BY44: 0.53 | BZ44: 0.53 | CA44: 0.53 | CB44: 0.5 | CC44: 0.5 | CD44: 0.5 | CE44: 0.5 | CF44: 0.5 | CG44: 0.5 | CH44: 0.5 | CI44: 0.5 | DC44: 0.34 | DD44: 0.34 | DE44: 0.34 | DF44: 0.34 | DG44: 0.34 | DH44: 0.34 | DI44: 0.34 | DJ44: 0.34 | DK44: - | DL44: - | DM44: - | DN44: - | DO44: - | DP44: - | DQ44: - | DR44: - | DS44: 0.5 | DT44: 0.5 | DU44: 0.5 | DV44: 0.5 | DW44: 0.56 | DX44: 0.56 | DY44: 0.56 | DZ44: 0.56 | EA44: 0.56 | EB44: 0.56 | EC44: 0.56 | ED44: 0.56 | EE44: - | EF44: - | EG44: - | EH44: - | EI44: 0.45 | EJ44: 0.45 | EK44: 0.45 | EL44: 0.45 | EM44: 0.33 | EN44: 0.33 | EO44: 0.33 | EP44: 0.33 | EQ44: 0.5 | ER44: 0.5 | ES44: 0.5 | ET44: 0.5 | EU44: 0.5 | EV44: 0.5 | EW44: 0.5 | EX44: 0.5 | EY44: 0.5 | EZ44: 0.5 | FA44: 0.5 | FB44: 0.5 | FC44: 0.4 | FD44: 0.4 | FE44: 0.4 | FJ44: 0.4 | FK44: 0.1 | FL44: 0.1 | FM44: 0.5 | FN44: 0.5 | FO44: =100%/7 -> 0.14285714
B45: Vuosi 3 | C45: % | D45: 0.2 | E45: 0.2 | F45: 0.2 | G45: 0.2 | H45: 0.2 | I45: 0.2 | J45: 0.2 | K45: 0.2 | DC45: 0.33 | DD45: 0.33 | DE45: 0.33 | DF45: 0.33 | DG45: 0.33 | DH45: 0.33 | DI45: 0.33 | DJ45: 0.33 | DK45: - | DL45: - | DM45: - | DN45: - | DO45: - | DP45: - | DQ45: - | DR45: - | DS45: - | DT45: - | DU45: - | DV45: - | DW45: - | DX45: - | DY45: - | DZ45: - | EA45: - | EB45: - | EC45: - | ED45: - | EE45: - | EF45: - | EG45: - | EH45: - | EI45: - | EJ45: - | EK45: - | EL45: - | EM45: 0.33 | EN45: 0.33 | EO45: 0.33 | EP45: 0.33 | EQ45: - | ER45: - | ES45: - | ET45: - | EU45: - | EV45: - | EW45: - | EX45: - | EY45: - | EZ45: - | FA45: - | FB45: - | FC45: 0.2 | FD45: 0.2 | FE45: 0.2 | FJ45: 0.2 | FK45: 0.15 | FL45: 0.15 | FO45: =100%/7 -> 0.14285714
B46: Vuosi 4 | C46: % | FK46: 0.2 | FL46: 0.2 | FO46: =100%/7 -> 0.14285714
B47: Vuosi 5 | C47: % | FK47: 0.2 | FL47: 0.2 | FO47: =100%/7 -> 0.14285714
B48: Vuosi 6 | C48: % | FK48: 0.15 | FL48: 0.15 | FO48: =100%/7 -> 0.14285714
B49: Vuosi 7 | C49: % | FK49: 0.1 | FL49: 0.1 | FO49: =100%/7 -> 0.14285714
B50: Vuosi 8 | C50: %
B51: Vuosi 9 | C51: %
B52: Vuosi 10 | C52: %
B53: Vuosi 11 | C53: %
B54: Vuosi 12 | C54: %
B55: Vuosi 13 | C55: %
B56: Vuosi 14 | C56: %
B57: Vuosi 15 | C57: %
A58: Infrastruktuurin hinta | B58: Matala | C58: EUR | D58: 10993868 | E58: 10993868 | F58: 10993868 | G58: 10993868 | H58: 9971183 | I58: 9971183 | J58: 9971183 | K58: 9971183 | L58: 10993868 | M58: 10993868 | N58: 10993868 | O58: 10993868 | P58: 10993868 | Q58: 10993868 | R58: 10993868 | S58: 10993868 | T58: 9971183 | U58: 9971183 | V58: 9971183 | W58: 9971183 | X58: 9971183 | Y58: 9971183 | Z58: 9971183 | AA58: 9971183 | AB58: 9204169 | AC58: 9204169 | AD58: 9204169 | AE58: 9204169 | AF58: 10993868 | AG58: 10993868 | AH58: 10993868 | AI58: 10993868 | AJ58: 10993868 | AK58: 10993868 | AL58: 10993868 | AM58: 10993868 | AN58: 9971183 | AO58: 9971183 | AP58: 9971183 | AQ58: 9971183 | AR58: 9971183 | AS58: 9971183 | AT58: 9971183 | AU58: 9971183 | AV58: 9204169 | AW58: 9204169 | AX58: 9204169 | AY58: 9204169 | AZ58: 639178.4 | BA58: 639178.4 | BB58: 639178.4 | BC58: 639178.4 | BD58: 639178.4 | BE58: 639178.4 | BF58: 639178.4 | BG58: 639178.4 | BH58: 639178.4 | BI58: 639178.4 | BJ58: 639178.4 | BK58: 639178.4 | BL58: 1022685.4 | BM58: 1022685.4 | BN58: 1022685.4 | BO58: 1022685.4 | BP58: 1022685.4 | BQ58: 1022685.4 | BR58: 1022685.4 | BS58: 1022685.4 | BT58: 255671.36 | BU58: 255671.36 | BV58: 255671.36 | BW58: 255671.36 | BX58: 1022685.4 | BY58: 1022685.4 | BZ58: 1022685.4 | CA58: 1022685.4 | CB58: 3451563.4 | CC58: 3451563.4 | CD58: 3451563.4 | CE58: 3451563.4 | CF58: 71587981 | CG58: 71587981 | CH58: 71587981 | CI58: 71587981 | CJ58: 1661863.8 | CK58: 1661863.8 | CL58: 1661863.8 | CM58: 1661863.8 | CN58: 1661863.8 | CO58: 1661863.8 | CP58: 1661863.8 | CQ58: 0 | CR58: 0 | CS58: 0 | CT58: 0 | CU58: 0 | CV58: 0 | CW58: 0 | CX58: 0 | CY58: 0 | CZ58: 0 | DA58: 0 | DB58: 0 | DC58: 3707234.7 | DD58: 3707234.7 | DE58: 3707234.7 | DF58: 3707234.7 | DG58: 4346413.1 | DH58: 4346413.1 | DI58: 4346413.1 | DJ58: 4346413.1 | DK58: 639178.4 | DL58: 639178.4 | DM58: 639178.4 | DN58: 639178.4 | DO58: 639178.4 | DP58: 639178.4 | DQ58: 639178.4 | DR58: 639178.4 | DS58: 1406192.5 | DT58: 1406192.5 | DU58: 1406192.5 | DV58: 1406192.5 | DW58: 1406192.5 | DX58: 1406192.5 | DY58: 1406192.5 | DZ58: 1406192.5 | EA58: 1406192.5 | EB58: 1406192.5 | EC58: 1406192.5 | ED58: 1406192.5 | EE58: 639178.4 | EF58: 639178.4 | EG58: 639178.4 | EH58: 639178.4 | EI58: 127835.68 | EJ58: 127835.68 | EK58: 127835.68 | EL58: 127835.68 | EM58: 255671.36 | EN58: 255671.36 | EO58: 255671.36 | EP58: 255671.36 | EQ58: 0 | ER58: 0 | ES58: 0 | ET58: 0 | EU58: 0 | EV58: 0 | EW58: 0 | EX58: 0 | EY58: 4346413.1 | EZ58: 4346413.1 | FA58: 4346413.1 | FB58: 4346413.1 | FC58: 22754751 | FD58: 22754751 | FE58: 22754751 | FF58: 0 | FG58: 0 | FH58: 0 | FI58: 0 | FJ58: 22115573 | FK58: 0 | FM58: 0 | FN58: 0 | FO58: 0
B59: Keski | C59: EUR | D59: 22115573 | E59: 22115573 | F59: 22115573 | G59: 22115573 | H59: 19814530 | I59: 19814530 | J59: 19814530 | K59: 19814530 | L59: 22115573 | M59: 22115573 | N59: 22115573 | O59: 22115573 | P59: 22115573 | Q59: 22115573 | R59: 22115573 | S59: 22115573 | T59: 19814530 | U59: 19814530 | V59: 19814530 | W59: 19814530 | X59: 19814530 | Y59: 19814530 | Z59: 19814530 | AA59: 19814530 | AB59: 18408338 | AC59: 18408338 | AD59: 18408338 | AE59: 18408338 | AF59: 22115573 | AG59: 22115573 | AH59: 22115573 | AI59: 22115573 | AJ59: 22115573 | AK59: 22115573 | AL59: 22115573 | AM59: 22115573 | AN59: 19814530 | AO59: 19814530 | AP59: 19814530 | AQ59: 19814530 | AR59: 19814530 | AS59: 19814530 | AT59: 19814530 | AU59: 19814530 | AV59: 18408338 | AW59: 18408338 | AX59: 18408338 | AY59: 18408338 | AZ59: 3195892 | BA59: 3195892 | BB59: 3195892 | BC59: 3195892 | BD59: 3195892 | BE59: 3195892 | BF59: 3195892 | BG59: 3195892 | BH59: 3195892 | BI59: 3195892 | BJ59: 3195892 | BK59: 3195892 | BL59: 4985591.5 | BM59: 4985591.5 | BN59: 4985591.5 | BO59: 4985591.5 | BP59: 4985591.5 | BQ59: 4985591.5 | BR59: 4985591.5 | BS59: 4985591.5 | BT59: 639178.4 | BU59: 639178.4 | BV59: 639178.4 | BW59: 639178.4 | BX59: 1278356.8 | BY59: 1278356.8 | BZ59: 1278356.8 | CA59: 1278356.8 | CB59: 4857755.8 | CC59: 4857755.8 | CD59: 4857755.8 | CE59: 4857755.8 | CF59: 82198342 | CG59: 82198342 | CH59: 82198342 | CI59: 82198342 | CJ59: 1789699.5 | CK59: 1789699.5 | CL59: 1789699.5 | CM59: 1789699.5 | CN59: 1789699.5 | CO59: 1789699.5 | CP59: 1789699.5 | CQ59: 0 | CR59: 0 | CS59: 0 | CT59: 0 | CU59: 0 | CV59: 0 | CW59: 0 | CX59: 0 | CY59: 0 | CZ59: 0 | DA59: 0 | DB59: 0 | DC59: 6775291 | DD59: 6775291 | DE59: 6775291 | DF59: 6775291 | DG59: 8692826.2 | DH59: 8692826.2 | DI59: 8692826.2 | DJ59: 8692826.2 | DK59: 1022685.4 | DL59: 1022685.4 | DM59: 1022685.4 | DN59: 1022685.4 | DO59: 1022685.4 | DP59: 1022685.4 | DQ59: 1022685.4 | DR59: 1022685.4 | DS59: 2045370.9 | DT59: 2045370.9 | DU59: 2045370.9 | DV59: 2045370.9 | DW59: 2045370.9 | DX59: 2045370.9 | DY59: 2045370.9 | DZ59: 2045370.9 | EA59: 2045370.9 | EB59: 2045370.9 | EC59: 2045370.9 | ED59: 2045370.9 | EE59: 1022685.4 | EF59: 1022685.4 | EG59: 1022685.4 | EH59: 1022685.4 | EI59: 255671.36 | EJ59: 255671.36 | EK59: 255671.36 | EL59: 255671.36 | EM59: 511342.72 | EN59: 511342.72 | EO59: 511342.72 | EP59: 511342.72 | EQ59: 0 | ER59: 0 | ES59: 0 | ET59: 0 | EU59: 0 | EV59: 0 | EW59: 0 | EX59: 0 | EY59: 7414469.4 | EZ59: 7414469.4 | FA59: 7414469.4 | FB59: 7414469.4 | FC59: 25694972 | FD59: 25694972 | FE59: 25694972 | FF59: 0 | FG59: 0 | FH59: 0 | FI59: 0 | FJ59: 23138258 | FK59: 0 | FM59: 0 | FN59: 0 | FO59: 0
B60: Korkea | C60: EUR | D60: 44231145 | E60: 44231145 | F60: 44231145 | G60: 44231145 | H60: 39629061 | I60: 39629061 | J60: 39629061 | K60: 39629061 | L60: 44231145 | M60: 44231145 | N60: 44231145 | O60: 44231145 | P60: 44231145 | Q60: 44231145 | R60: 44231145 | S60: 44231145 | T60: 39629061 | U60: 39629061 | V60: 39629061 | W60: 39629061 | X60: 39629061 | Y60: 39629061 | Z60: 39629061 | AA60: 39629061 | AB60: 36688840 | AC60: 36688840 | AD60: 36688840 | AE60: 36688840 | AF60: 44231145 | AG60: 44231145 | AH60: 44231145 | AI60: 44231145 | AJ60: 44231145 | AK60: 44231145 | AL60: 44231145 | AM60: 44231145 | AN60: 39629061 | AO60: 39629061 | AP60: 39629061 | AQ60: 39629061 | AR60: 39629061 | AS60: 39629061 | AT60: 39629061 | AU60: 39629061 | AV60: 36688840 | AW60: 36688840 | AX60: 36688840 | AY60: 36688840 | AZ60: 9459840.3 | BA60: 9459840.3 | BB60: 9459840.3 | BC60: 9459840.3 | BD60: 9459840.3 | BE60: 9459840.3 | BF60: 9459840.3 | BG60: 9459840.3 | BH60: 9459840.3 | BI60: 9459840.3 | BJ60: 9459840.3 | BK60: 9459840.3 | BL60: 15084610 | BM60: 15084610 | BN60: 15084610 | BO60: 15084610 | BP60: 15084610 | BQ60: 15084610 | BR60: 15084610 | BS60: 15084610 | BT60: 767014.08 | BU60: 767014.08 | BV60: 767014.08 | BW60: 767014.08 | BX60: 1661863.8 | BY60: 1661863.8 | BZ60: 1661863.8 | CA60: 1661863.8 | CB60: 6008277 | CC60: 6008277 | CD60: 6008277 | CE60: 6008277 | CF60: 94726239 | CG60: 94726239 | CH60: 94726239 | CI60: 94726239 | CJ60: 1917535.2 | CK60: 1917535.2 | CL60: 1917535.2 | CM60: 1917535.2 | CN60: 1917535.2 | CO60: 1917535.2 | CP60: 1917535.2 | CQ60: 0 | CR60: 0 | CS60: 0 | CT60: 0 | CU60: 0 | CV60: 0 | CW60: 0 | CX60: 0 | CY60: 0 | CZ60: 0 | DA60: 0 | DB60: 0 | DC60: 9587676 | DD60: 9587676 | DE60: 9587676 | DF60: 9587676 | DG60: 12400061 | DH60: 12400061 | DI60: 12400061 | DJ60: 12400061 | DK60: 1534028.2 | DL60: 1534028.2 | DM60: 1534028.2 | DN60: 1534028.2 | DO60: 1534028.2 | DP60: 1534028.2 | DQ60: 1534028.2 | DR60: 1534028.2 | DS60: 2301042.2 | DT60: 2301042.2 | DU60: 2301042.2 | DV60: 2301042.2 | DW60: 2301042.2 | DX60: 2301042.2 | DY60: 2301042.2 | DZ60: 2301042.2 | EA60: 2301042.2 | EB60: 2301042.2 | EC60: 2301042.2 | ED60: 2301042.2 | EE60: 1534028.2 | EF60: 1534028.2 | EG60: 1534028.2 | EH60: 1534028.2 | EI60: 383507.04 | EJ60: 383507.04 | EK60: 383507.04 | EL60: 383507.04 | EM60: 639178.4 | EN60: 639178.4 | EO60: 639178.4 | EP60: 639178.4 | EQ60: 0 | ER60: 0 | ES60: 0 | ET60: 0 | EU60: 0 | EV60: 0 | EW60: 0 | EX60: 0 | EY60: 10226854 | EZ60: 10226854 | FA60: 10226854 | FB60: 10226854 | FC60: 28763028 | FD60: 28763028 | FE60: 28763028 | FF60: 0 | FG60: 0 | FH60: 0 | FI60: 0 | FJ60: 24288779 | FK60: 0 | FM60: 0 | FN60: 0 | FO60: 0
A61: Kiinteä OPEX | C61: EUR/MW/vuosi | D61: 17896.995 | E61: 17896.995 | F61: 17896.995 | G61: 17896.995 | H61: 41290.925 | I61: 41290.925 | J61: 41290.925 | K61: 41290.925 | L61: 6647.4554 | M61: 6647.4554 | N61: 6647.4554 | O61: 6647.4554 | P61: 7670.1408 | Q61: 7670.1408 | R61: 7670.1408 | S61: 7670.1408 | T61: 9332.0046 | U61: 9332.0046 | V61: 9332.0046 | W61: 9332.0046 | X61: 9332.0046 | Y61: 9332.0046 | Z61: 9332.0046 | AA61: 9332.0046 | AB61: 14445.432 | AC61: 14445.432 | AD61: 14445.432 | AE61: 14445.432 | AF61: 9971.183 | AG61: 9971.183 | AH61: 9971.183 | AI61: 9971.183 | AJ61: 11377.376 | AK61: 11377.376 | AL61: 11377.376 | AM61: 11377.376 | AN61: 13934.089 | AO61: 13934.089 | AP61: 13934.089 | AQ61: 13934.089 | AR61: 13934.089 | AS61: 13934.089 | AT61: 13934.089 | AU61: 13934.089 | AV61: 21604.23 | AW61: 21604.23 | AX61: 21604.23 | AY61: 21604.23 | AZ61: 14573.268 | BA61: 14573.268 | BB61: 14573.268 | BC61: 14573.268 | BD61: 14573.268 | BE61: 14573.268 | BF61: 14573.268 | BG61: 14573.268 | BH61: 14573.268 | BI61: 14573.268 | BJ61: 14573.268 | BK61: 14573.268 | BL61: 14573.268 | BM61: 14573.268 | BN61: 14573.268 | BO61: 14573.268 | BP61: 14573.268 | BQ61: 14573.268 | BR61: 14573.268 | BS61: 14573.268 | BT61: 95748.924 | BU61: 95748.924 | BV61: 95748.924 | BW61: 95748.924 | BX61: 351675.96 | BY61: 351292.45 | BZ61: 351292.45 | CA61: 351292.45 | CB61: 32470.263 | CC61: 32598.098 | CD61: 32853.77 | CE61: 33109.441 | CF61: 55352.849 | CG61: 53818.821 | CH61: 53946.657 | CI61: 54202.328 | CJ61: 7670.1408 | CK61: 7158.7981 | CL61: 6775.291 | CM61: 6263.9483 | CN61: 7670.1408 | CO61: 7670.1408 | CP61: 7670.1408 | CQ61: 9843.3474 | CR61: 8948.4976 | CS61: 8948.4976 | CT61: 8948.4976 | CU61: 9843.3474 | CV61: 9587.676 | CW61: 9587.676 | CX61: 9587.676 | CY61: 24416.615 | CZ61: 23649.601 | DA61: 23649.601 | DB61: 23649.601 | DC61: 195332.92 | DD61: 192392.7 | DE61: 192392.7 | DF61: 192392.7 | DG61: 214252.6 | DH61: 211056.71 | DI61: 211056.71 | DJ61: 211056.71 | DK61: 114157.26 | DL61: 114157.26 | DM61: 114157.26 | DN61: 114157.26 | DO61: 193031.88 | DP61: 193031.88 | DQ61: 193031.88 | DR61: 193031.88 | DS61: 322785.09 | DT61: 313580.92 | DU61: 313580.92 | DV61: 313580.92 | DW61: 219110.36 | DX61: 212846.41 | DY61: 212846.41 | DZ61: 212846.41 | EA61: 219110.36 | EB61: 212846.41 | EC61: 212846.41 | ED61: 212846.41 | EE61: 118503.68 | EF61: 118503.68 | EG61: 118503.68 | EH61: 118503.68 | EI61: 71076.638 | EJ61: 71076.638 | EK61: 71076.638 | EL61: 71076.638 | EM61: 118503.68 | EN61: 118503.68 | EO61: 118503.68 | EP61: 118503.68 | EQ61: 37455.854 | ER61: 37455.854 | ES61: 37455.854 | ET61: 37455.854 | EU61: 65835.375 | EV61: 65835.375 | EW61: 65835.375 | EX61: 65835.375 | EY61: 52668.3 | EZ61: 36177.497 | FA61: 36177.497 | FB61: 36177.497 | FC61: 19814.53 | FD61: 19814.53 | FE61: 19814.53 | FF61: 0 | FG61: 0 | FH61: 0 | FI61: 0 | FJ61: 17896.995
A62: Muuttuva OPEX | C62: EUR/MWh | D62: 2.5567136 | E62: 2.5567136 | F62: 2.5567136 | G62: 2.5567136 | H62: 5.1134272 | I62: 5.1134272 | J62: 5.1134272 | K62: 5.1134272 | L62: 1.2783568 | M62: 1.2783568 | N62: 1.2783568 | O62: 1.2783568 | P62: 1.2783568 | Q62: 1.2783568 | R62: 1.2783568 | S62: 1.2783568 | T62: 1.2783568 | U62: 1.2783568 | V62: 1.2783568 | W62: 1.2783568 | X62: 1.2783568 | Y62: 1.2783568 | Z62: 1.2783568 | AA62: 1.2783568 | AB62: 2.5567136 | AC62: 2.5567136 | AD62: 2.5567136 | AE62: 2.5567136 | AF62: 1.2783568 | AG62: 1.2783568 | AH62: 1.2783568 | AI62: 1.2783568 | AJ62: 1.2783568 | AK62: 1.2783568 | AL62: 1.2783568 | AM62: 1.2783568 | AN62: 1.2783568 | AO62: 1.2783568 | AP62: 1.2783568 | AQ62: 1.2783568 | AR62: 1.2783568 | AS62: 1.2783568 | AT62: 1.2783568 | AU62: 1.2783568 | AV62: 2.5567136 | AW62: 2.5567136 | AX62: 2.5567136 | AY62: 2.5567136 | AZ62: 0 | BA62: 0 | BB62: 0 | BC62: 0 | BD62: 0 | BE62: 0 | BF62: 0 | BG62: 0 | BH62: 0 | BI62: 0 | BJ62: 0 | BK62: 0 | BL62: 0 | BM62: 0 | BN62: 0 | BO62: 0 | BP62: 0 | BQ62: 0 | BR62: 0 | BS62: 0 | BT62: 8.9484976 | BU62: 8.9484976 | BV62: 8.9484976 | BW62: 8.9484976 | BX62: 12.783568 | BY62: 12.783568 | BZ62: 12.783568 | CA62: 12.783568 | CB62: 7.6701408 | CC62: 7.6701408 | CD62: 7.6701408 | CE62: 7.6701408 | CF62: 1.2783568 | CG62: 1.2783568 | CH62: 1.2783568 | CI62: 1.2783568 | CJ62: 0 | CK62: 0 | CL62: 0 | CM62: 0 | CN62: 0 | CO62: 0 | CP62: 0 | CQ62: 0 | CR62: 0 | CS62: 0 | CT62: 0 | CU62: 0 | CV62: 0 | CW62: 0 | CX62: 0 | CY62: 0 | CZ62: 0 | DA62: 0 | DB62: 0 | DC62: 34.515634 | DD62: 34.515634 | DE62: 34.515634 | DF62: 34.515634 | DG62: 77.979765 | DH62: 77.979765 | DI62: 77.979765 | DJ62: 77.979765 | DK62: 75.423051 | DL62: 75.423051 | DM62: 75.423051 | DN62: 75.423051 | DO62: 75.423051 | DP62: 75.423051 | DQ62: 75.423051 | DR62: 75.423051 | DS62: 28.12385 | DT62: 28.12385 | DU62: 28.12385 | DV62: 28.12385 | DW62: 56.247699 | DX62: 56.247699 | DY62: 56.247699 | DZ62: 56.247699 | EA62: 56.247699 | EB62: 56.247699 | EC62: 56.247699 | ED62: 56.247699 | EE62: 12.783568 | EF62: 12.783568 | EG62: 12.783568 | EH62: 12.783568 | EI62: 15.340282 | EJ62: 15.340282 | EK62: 15.340282 | EL62: 15.340282 | EM62: 14.061925 | EN62: 14.061925 | EO62: 14.061925 | EP62: 14.061925 | EQ62: 8.9484976 | ER62: 8.9484976 | ES62: 8.9484976 | ET62: 8.9484976 | EU62: 5.1134272 | EV62: 5.1134272 | EW62: 5.1134272 | EX62: 5.1134272 | EY62: 47.299202 | EZ62: 47.299202 | FA62: 47.299202 | FB62: 47.299202 | FC62: 2.5567136 | FD62: 2.5567136 | FE62: 2.5567136 | FF62: 0 | FG62: 0 | FH62: 0 | FI62: 0 | FJ62: 2.5567136 | FL62: 11.66 | FM62: 8.6 | FN62: 7.87 | FO62: 16.52
A63: Vakuutus | C63: EUR/MW/vuosi | D63: 3068.0563 | E63: 3068.0563 | F63: 3068.0563 | G63: 3068.0563 | H63: 4218.5774 | I63: 4218.5774 | J63: 4218.5774 | K63: 4218.5774 | L63: 1661.8638 | M63: 1661.8638 | N63: 1661.8638 | O63: 1661.8638 | P63: 1917.5352 | Q63: 1917.5352 | R63: 1917.5352 | S63: 1917.5352 | T63: 2301.0422 | U63: 2301.0422 | V63: 2301.0422 | W63: 2301.0422 | X63: 2301.0422 | Y63: 2301.0422 | Z63: 2301.0422 | AA63: 2301.0422 | AB63: 3707.2347 | AC63: 3707.2347 | AD63: 3707.2347 | AE63: 3707.2347 | AF63: 1661.8638 | AG63: 1661.8638 | AH63: 1661.8638 | AI63: 1661.8638 | AJ63: 1917.5352 | AK63: 1917.5352 | AL63: 1917.5352 | AM63: 1917.5352 | AN63: 2301.0422 | AO63: 2301.0422 | AP63: 2301.0422 | AQ63: 2301.0422 | AR63: 2301.0422 | AS63: 2301.0422 | AT63: 2301.0422 | AU63: 2301.0422 | AV63: 3707.2347 | AW63: 3707.2347 | AX63: 3707.2347 | AY63: 3707.2347 | AZ63: 1406.1925 | BA63: 1406.1925 | BB63: 1406.1925 | BC63: 1406.1925 | BD63: 1406.1925 | BE63: 1406.1925 | BF63: 1406.1925 | BG63: 1406.1925 | BH63: 1406.1925 | BI63: 1406.1925 | BJ63: 1406.1925 | BK63: 1406.1925 | BL63: 1406.1925 | BM63: 1406.1925 | BN63: 1406.1925 | BO63: 1406.1925 | BP63: 1406.1925 | BQ63: 1406.1925 | BR63: 1406.1925 | BS63: 1406.1925 | BT63: 16874.31 | BU63: 16874.31 | BV63: 16874.31 | BW63: 16874.31 | BX63: 69286.939 | BY63: 69159.103 | BZ63: 69159.103 | CA63: 69159.103 | CB63: 2173.2066 | CC63: 2173.2066 | CD63: 2173.2066 | CE63: 2173.2066 | CF63: 3835.0704 | CG63: 3707.2347 | CH63: 3707.2347 | CI63: 3707.2347 | CJ63: 2556.7136 | CK63: 2428.8779 | CL63: 2301.0422 | CM63: 2173.2066 | CN63: 2556.7136 | CO63: 2556.7136 | CP63: 2556.7136 | CQ63: 0 | CR63: 0 | CS63: 0 | CT63: 0 | CU63: 0 | CV63: 0 | CW63: 0 | CX63: 0 | CY63: 0 | CZ63: 0 | DA63: 0 | DB63: 0 | DC63: 42697.117 | DD63: 42057.939 | DE63: 42057.939 | DF63: 42057.939 | DG63: 119398.53 | DH63: 117608.83 | DI63: 117608.83 | DJ63: 117608.83 | DK63: 79258.122 | DL63: 79258.122 | DM63: 79258.122 | DN63: 79258.122 | DO63: 79258.122 | DP63: 79258.122 | DQ63: 79258.122 | DR63: 79258.122 | DS63: 78746.779 | DT63: 76445.737 | DU63: 76445.737 | DV63: 76445.737 | DW63: 115819.13 | DX63: 112495.4 | DY63: 112495.4 | DZ63: 112495.4 | EA63: 115819.13 | EB63: 112495.4 | EC63: 112495.4 | ED63: 112495.4 | EE63: 2428.8779 | EF63: 2428.8779 | EG63: 2428.8779 | EH63: 2428.8779 | EI63: 53435.314 | EJ63: 53435.314 | EK63: 53435.314 | EL63: 53435.314 | EM63: 2428.8779 | EN63: 2428.8779 | EO63: 2428.8779 | EP63: 2428.8779 | EQ63: 1406.1925 | ER63: 1406.1925 | ES63: 1406.1925 | ET63: 1406.1925 | EU63: 0 | EV63: 0 | EW63: 0 | EX63: 0 | EY63: 15468.117 | EZ63: 10610.361 | FA63: 10610.361 | FB63: 10610.361 | FC63: 3579.399 | FD63: 3579.399 | FE63: 3579.399 | FF63: 0 | FG63: 0 | FH63: 0 | FI63: 0 | FJ63: 3195.892
A64: Liittymis- ja muut kustannukset | C64: EUR/MW/vuosi | D64: 4857.7558 | E64: 4857.7558 | F64: 4857.7558 | G64: 4857.7558 | H64: 4857.7558 | I64: 4857.7558 | J64: 4857.7558 | K64: 4857.7558 | L64: 3451.5634 | M64: 3451.5634 | N64: 3451.5634 | O64: 3451.5634 | P64: 3451.5634 | Q64: 3451.5634 | R64: 3451.5634 | S64: 3451.5634 | T64: 3451.5634 | U64: 3451.5634 | V64: 3451.5634 | W64: 3451.5634 | X64: 3451.5634 | Y64: 3451.5634 | Z64: 3451.5634 | AA64: 3451.5634 | AB64: 3451.5634 | AC64: 3451.5634 | AD64: 3451.5634 | AE64: 3451.5634 | AF64: 3707.2347 | AG64: 3707.2347 | AH64: 3707.2347 | AI64: 3707.2347 | AJ64: 3707.2347 | AK64: 3707.2347 | AL64: 3707.2347 | AM64: 3707.2347 | AN64: 3707.2347 | AO64: 3707.2347 | AP64: 3707.2347 | AQ64: 3707.2347 | AR64: 3707.2347 | AS64: 3707.2347 | AT64: 3707.2347 | AU64: 3707.2347 | AV64: 3707.2347 | AW64: 3707.2347 | AX64: 3707.2347 | AY64: 3707.2347 | AZ64: -46660.023 | BA64: -46660.023 | BB64: -46660.023 | BC64: -46660.023 | BD64: -41674.432 | BE64: -41674.432 | BF64: -41674.432 | BG64: -41674.432 | BH64: -40907.418 | BI64: -40907.418 | BJ64: -40907.418 | BK64: -40907.418 | BL64: -46660.023 | BM64: -46660.023 | BN64: -46660.023 | BO64: -46660.023 | BP64: -41674.432 | BQ64: -41674.432 | BR64: -41674.432 | BS64: -41674.432 | BT64: 18919.681 | BU64: 18919.681 | BV64: 18919.681 | BW64: 18919.681 | BX64: 24416.615 | BY64: 24416.615 | BZ64: 24416.615 | CA64: 24416.615 | CB64: 4602.0845 | CC64: 4602.0845 | CD64: 4602.0845 | CE64: 4729.9202 | CF64: 57270.385 | CG64: 55736.356 | CH64: 55736.356 | CI64: 56119.864 | CJ64: 1661.8638 | CK64: 1534.0282 | CL64: 1534.0282 | CM64: 1406.1925 | CN64: 1661.8638 | CO64: 1661.8638 | CP64: 1661.8638 | CQ64: 0 | CR64: 0 | CS64: 0 | CT64: 0 | CU64: 0 | CV64: 0 | CW64: 0 | CX64: 0 | CY64: 0 | CZ64: 0 | DA64: 0 | DB64: 0 | DC64: 23393.929 | DD64: 23010.422 | DE64: 23010.422 | DF64: 23010.422 | DG64: 23393.929 | DH64: 23010.422 | DI64: 23010.422 | DJ64: 23010.422 | DK64: 18919.681 | DL64: 18919.681 | DM64: 18919.681 | DN64: 18919.681 | DO64: 18919.681 | DP64: 18919.681 | DQ64: 18919.681 | DR64: 18919.681 | DS64: 17641.324 | DT64: 17129.981 | DU64: 17129.981 | DV64: 17129.981 | DW64: 17641.324 | DX64: 17129.981 | DY64: 17129.981 | DZ64: 17129.981 | EA64: 17641.324 | EB64: 17129.981 | EC64: 17129.981 | ED64: 17129.981 | EE64: 9459.8403 | EF64: 9459.8403 | EG64: 9459.8403 | EH64: 9459.8403 | EI64: 18919.681 | EJ64: 18919.681 | EK64: 18919.681 | EL64: 18919.681 | EM64: 18919.681 | EN64: 18919.681 | EO64: 18919.681 | EP64: 18919.681 | EQ64: 11121.704 | ER64: 11121.704 | ES64: 11121.704 | ET64: 11121.704 | EU64: 0 | EV64: 0 | EW64: 0 | EX64: 0 | EY64: 41930.103 | EZ64: 28763.028 | FA64: 28763.028 | FB64: 28763.028 | FC64: 4857.7558 | FD64: 4857.7558 | FE64: 4857.7558 | FF64: 0 | FG64: 0 | FH64: 0 | FI64: 0 | FJ64: 4857.7558
A65: Lämmönmyyntisopimuksen kesto | C65: vuotta | D65: 20 | H65: 20 | I65: 20 | J65: 20 | K65: 20
A66: Pääoman kustannus (WACC) | C66: % | D66: 0.075 | E66: 0.075 | F66: 0.075 | G66: 0.075 | H66: 0.09 | I66: 0.09 | J66: 0.09 | K66: 0.09 | L66: 0.071 | M66: 0.071 | N66: 0.071 | O66: 0.071 | P66: 0.071 | Q66: 0.071 | R66: 0.071 | S66: 0.071 | T66: 0.071 | U66: 0.071 | V66: 0.071 | W66: 0.071 | X66: 0.068 | Y66: 0.068 | Z66: 0.068 | AA66: 0.068 | AB66: 0.071 | AC66: 0.071 | AD66: 0.071 | AE66: 0.071 | AF66: 0.071 | AG66: 0.071 | AH66: 0.071 | AI66: 0.071 | AJ66: 0.071 | AK66: 0.071 | AL66: 0.071 | AM66: 0.071 | AN66: 0.071 | AO66: 0.071 | AP66: 0.071 | AQ66: 0.071 | AR66: 0.068 | AS66: 0.068 | AT66: 0.068 | AU66: 0.068 | AV66: 0.071 | AW66: 0.071 | AX66: 0.071 | AY66: 0.071 | AZ66: 0.071 | BA66: 0.071 | BB66: 0.071 | BC66: 0.071 | BD66: 0.071 | BE66: 0.071 | BF66: 0.071 | BG66: 0.071 | BH66: 0.071 | BI66: 0.071 | BJ66: 0.071 | BK66: 0.071 | BL66: 0.071 | BM66: 0.071 | BN66: 0.071 | BO66: 0.071 | BP66: 0.071 | BQ66: 0.071 | BR66: 0.071 | BS66: 0.071 | BT66: 0.079 | BU66: 0.079 | BV66: 0.079 | BW66: 0.079 | BX66: 0.099 | BY66: 0.099 | BZ66: 0.099 | CA66: 0.099 | CB66: 0.052 | CC66: 0.052 | CD66: 0.052 | CE66: 0.052 | CF66: 0.063 | CG66: 0.063 | CH66: 0.063 | CI66: 0.063 | CJ66: 0.05 | CK66: 0.05 | CL66: 0.05 | CM66: 0.05 | CN66: 0.05 | CO66: 0.05 | CP66: 0.05 | CQ66: 0.056 | CR66: 0.056 | CS66: 0.056 | CT66: 0.056 | CU66: 0.051 | CV66: 0.051 | CW66: 0.051 | CX66: 0.051 | CY66: 0.051 | CZ66: 0.051 | DA66: 0.051 | DB66: 0.051 | DC66: 0.065 | DD66: 0.065 | DE66: 0.065 | DF66: 0.065 | DG66: 0.076 | DH66: 0.076 | DI66: 0.076 | DJ66: 0.076 | DK66: 0.083 | DL66: 0.083 | DM66: 0.083 | DN66: 0.083 | DO66: 0.099 | DP66: 0.099 | DQ66: 0.099 | DR66: 0.099 | DS66: 0.072 | DT66: 0.072 | DU66: 0.072 | DV66: 0.072 | DW66: 0.081 | DX66: 0.081 | DY66: 0.081 | DZ66: 0.081 | EA66: 0.089 | EB66: 0.089 | EC66: 0.089 | ED66: 0.089 | EE66: 0.061 | EF66: 0.061 | EG66: 0.061 | EH66: 0.061 | EI66: 0.071 | EJ66: 0.071 | EK66: 0.071 | EL66: 0.071 | EM66: 0.188 | EN66: 0.188 | EO66: 0.188 | EP66: 0.188 | EQ66: 0.054 | ER66: 0.054 | ES66: 0.054 | ET66: 0.054 | EU66: 0.054 | EV66: 0.054 | EW66: 0.054 | EX66: 0.054 | EY66: 0.086 | EZ66: 0.086 | FA66: 0.086 | FB66: 0.086 | FC66: 0.09 | FD66: 0.09 | FE66: 0.09 | FF66: 0.09 | FG66: 0.075 | FH66: 0.075 | FI66: 0.075 | FJ66: 0.075 | FK66: 0.075 | FL66: 0.05 | FM66: 0.05 | FN66: 0.05 | FO66: 0.04
A67: Jätemaksu | C67: EUR/MWh | D67: 0 | E67: 0 | F67: 0 | G67: 0 | H67: 0 | I67: 0 | J67: 0 | K67: 0 | L67: 0 | M67: 0 | N67: 0 | O67: 0 | P67: 0 | Q67: 0 | R67: 0 | S67: 0 | T67: 0 | U67: 0 | V67: 0 | W67: 0 | X67: 0 | Y67: 0 | Z67: 0 | AA67: 0 | AB67: 0 | AC67: 0 | AD67: 0 | AE67: 0 | AF67: 0 | AG67: 0 | AH67: 0 | AI67: 0 | AJ67: 0 | AK67: 0 | AL67: 0 | AM67: 0 | AN67: 0 | AO67: 0 | AP67: 0 | AQ67: 0 | AR67: 0 | AS67: 0 | AT67: 0 | AU67: 0 | AV67: 0 | AW67: 0 | AX67: 0 | AY67: 0 | AZ67: 0 | BA67: 0 | BB67: 0 | BC67: 0 | BD67: 0 | BE67: 0 | BF67: 0 | BG67: 0 | BH67: 0 | BI67: 0 | BJ67: 0 | BK67: 0 | BL67: 0 | BM67: 0 | BN67: 0 | BO67: 0 | BP67: 0 | BQ67: 0 | BR67: 0 | BS67: 0 | BT67: 0 | BU67: 0 | BV67: 0 | BW67: 0 | BX67: 0 | BY67: 0 | BZ67: 0 | CA67: 0 | CB67: 0 | CC67: 0 | CD67: 0 | CE67: 0 | CF67: 0 | CG67: 0 | CH67: 0 | CI67: 0 | CJ67: 0 | CK67: 0 | CL67: 0 | CM67: 0 | CN67: 0 | CO67: 0 | CP67: 0 | CQ67: 0 | CR67: 0 | CS67: 0 | CT67: 0 | CU67: 0 | CV67: 0 | CW67: 0 | CX67: 0 | CY67: 0 | CZ67: 0 | DA67: 0 | DB67: 0 | DC67: 0 | DD67: 0 | DE67: 0 | DF67: 0 | DG67: 0 | DH67: 0 | DI67: 0 | DJ67: 0 | DK67: 0 | DL67: 0 | DM67: 0 | DN67: 0 | DO67: 0 | DP67: 0 | DQ67: 0 | DR67: 0 | DS67: 0 | DT67: 0 | DU67: 0 | DV67: 0 | DW67: 0 | DX67: 0 | DY67: 0 | DZ67: 0 | EA67: 0 | EB67: 0 | EC67: 0 | ED67: 0 | EE67: 0 | EF67: 0 | EG67: 0 | EH67: 0 | EI67: 0 | EJ67: 0 | EK67: 0 | EL67: 0 | EM67: 0 | EN67: 0 | EO67: 0 | EP67: 0 | EQ67: 0 | ER67: 0 | ES67: 0 | ET67: 0 | EU67: 0 | EV67: 0 | EW67: 0 | EX67: 0 | EY67: 0 | EZ67: 0 | FA67: 0 | FB67: 0 | FC67: 0 | FD67: 0 | FE67: 0 | FF67: 0 | FG67: 0 | FH67: 0 | FI67: 0 | FJ67: 0
A68: Hiilen talteenotto | C68: % | D68: 0 | E68: 0 | F68: 0 | G68: 0 | H68: 0 | I68: 0 | J68: 0 | K68: 0 | L68: 0 | M68: 0 | N68: 0 | O68: 0 | P68: 0 | Q68: 0 | R68: 0 | S68: 0 | T68: 0 | U68: 0 | V68: 0 | W68: 0 | X68: 0 | Y68: 0 | Z68: 0 | AA68: 0 | AB68: 0 | AC68: 0 | AD68: 0 | AE68: 0 | AF68: 0 | AG68: 0 | AH68: 0 | AI68: 0 | AJ68: 0 | AK68: 0 | AL68: 0 | AM68: 0 | AN68: 0 | AO68: 0 | AP68: 0 | AQ68: 0 | AR68: 0 | AS68: 0 | AT68: 0 | AU68: 0 | AV68: 0 | AW68: 0 | AX68: 0 | AY68: 0 | AZ68: 0 | BA68: 0 | BB68: 0 | BC68: 0 | BD68: 0 | BE68: 0 | BF68: 0 | BG68: 0 | BH68: 0 | BI68: 0 | BJ68: 0 | BK68: 0 | BL68: 0 | BM68: 0 | BN68: 0 | BO68: 0 | BP68: 0 | BQ68: 0 | BR68: 0 | BS68: 0 | BT68: 0 | BU68: 0 | BV68: 0 | BW68: 0 | BX68: 0 | BY68: 0 | BZ68: 0 | CA68: 0 | CB68: 0 | CC68: 0 | CD68: 0 | CE68: 0 | CF68: 0 | CG68: 0 | CH68: 0 | CI68: 0 | CJ68: 0 | CK68: 0 | CL68: 0 | CM68: 0 | CN68: 0 | CO68: 0 | CP68: 0 | CQ68: 0 | CR68: 0 | CS68: 0 | CT68: 0 | CU68: 0 | CV68: 0 | CW68: 0 | CX68: 0 | CY68: 0 | CZ68: 0 | DA68: 0 | DB68: 0 | DC68: 0 | DD68: 0 | DE68: 0 | DF68: 0 | DG68: 0 | DH68: 0 | DI68: 0 | DJ68: 0 | DK68: 0 | DL68: 0 | DM68: 0 | DN68: 0 | DO68: 0 | DP68: 0 | DQ68: 0 | DR68: 0 | DS68: 0 | DT68: 0 | DU68: 0 | DV68: 0 | DW68: 0 | DX68: 0 | DY68: 0 | DZ68: 0 | EA68: 0 | EB68: 0 | EC68: 0 | ED68: 0 | EE68: 0 | EF68: 0 | EG68: 0 | EH68: 0 | EI68: 0 | EJ68: 0 | EK68: 0 | EL68: 0 | EM68: 0 | EN68: 0 | EO68: 0 | EP68: 0 | EQ68: 0 | ER68: 0 | ES68: 0 | ET68: 0 | EU68: 0 | EV68: 0 | EW68: 0 | EX68: 0 | EY68: 0 | EZ68: 0 | FA68: 0 | FB68: 0 | FC68: 0 | FD68: 0 | FE68: 0 | FF68: 0 | FG68: 0 | FH68: 0 | FI68: 0 | FJ68: 0 | FK68: 0 | FL68: 0 | FM68: 0 | FN68: 0
A69: Talteenoton hinta | C69: EUR/tCO2 | D69: 0 | E69: 0 | F69: 0 | G69: 0 | H69: 0 | I69: 0 | J69: 0 | K69: 0 | L69: 0 | M69: 0 | N69: 0 | O69: 0 | P69: 0 | Q69: 0 | R69: 0 | S69: 0 | T69: 0 | U69: 0 | V69: 0 | W69: 0 | X69: 0 | Y69: 0 | Z69: 0 | AA69: 0 | AB69: 0 | AC69: 0 | AD69: 0 | AE69: 0 | AF69: 0 | AG69: 0 | AH69: 0 | AI69: 0 | AJ69: 0 | AK69: 0 | AL69: 0 | AM69: 0 | AN69: 0 | AO69: 0 | AP69: 0 | AQ69: 0 | AR69: 0 | AS69: 0 | AT69: 0 | AU69: 0 | AV69: 0 | AW69: 0 | AX69: 0 | AY69: 0 | AZ69: 0 | BA69: 0 | BB69: 0 | BC69: 0 | BD69: 0 | BE69: 0 | BF69: 0 | BG69: 0 | BH69: 0 | BI69: 0 | BJ69: 0 | BK69: 0 | BL69: 0 | BM69: 0 | BN69: 0 | BO69: 0 | BP69: 0 | BQ69: 0 | BR69: 0 | BS69: 0 | BT69: 0 | BU69: 0 | BV69: 0 | BW69: 0 | BX69: 0 | BY69: 0 | BZ69: 0 | CA69: 0 | CB69: 0 | CC69: 0 | CD69: 0 | CE69: 0 | CF69: 0 | CG69: 0 | CH69: 0 | CI69: 0 | CJ69: 0 | CK69: 0 | CL69: 0 | CM69: 0 | CN69: 0 | CO69: 0 | CP69: 0 | CQ69: 0 | CR69: 0 | CS69: 0 | CT69: 0 | CU69: 0 | CV69: 0 | CW69: 0 | CX69: 0 | CY69: 0 | CZ69: 0 | DA69: 0 | DB69: 0 | DC69: 0 | DD69: 0 | DE69: 0 | DF69: 0 | DG69: 0 | DH69: 0 | DI69: 0 | DJ69: 0 | DK69: 0 | DL69: 0 | DM69: 0 | DN69: 0 | DO69: 0 | DP69: 0 | DQ69: 0 | DR69: 0 | DS69: 0 | DT69: 0 | DU69: 0 | DV69: 0 | DW69: 0 | DX69: 0 | DY69: 0 | DZ69: 0 | EA69: 0 | EB69: 0 | EC69: 0 | ED69: 0 | EE69: 0 | EF69: 0 | EG69: 0 | EH69: 0 | EI69: 0 | EJ69: 0 | EK69: 0 | EL69: 0 | EM69: 0 | EN69: 0 | EO69: 0 | EP69: 0 | EQ69: 0 | ER69: 0 | ES69: 0 | ET69: 0 | EU69: 0 | EV69: 0 | EW69: 0 | EX69: 0 | EY69: 0 | EZ69: 0 | FA69: 0 | FB69: 0 | FC69: 0 | FD69: 0 | FE69: 0 | FF69: 0 | FG69: 0 | FH69: 0 | FI69: 0 | FJ69: 0 | FK69: 0 | FL69: 0 | FM69: 0 | FN69: 0
A70: Purkukustannukset | B70: Matala | C70: % | D70: 0.03 | E70: 0.03 | F70: 0.03 | G70: 0.03 | H70: 0.03 | I70: 0.03 | J70: 0.03 | K70: 0.03 | L70: 0.03 | M70: 0.03 | N70: 0.03 | O70: 0.03 | P70: 0.03 | Q70: 0.03 | R70: 0.03 | S70: 0.03 | T70: 0.03 | U70: 0.03 | V70: 0.03 | W70: 0.03 | X70: 0.03 | Y70: 0.03 | Z70: 0.03 | AA70: 0.03 | AB70: 0.03 | AC70: 0.03 | AD70: 0.03 | AE70: 0.03 | AF70: 0.03 | AG70: 0.03 | AH70: 0.03 | AI70: 0.03 | AJ70: 0.03 | AK70: 0.03 | AL70: 0.03 | AM70: 0.03 | AN70: 0.03 | AO70: 0.03 | AP70: 0.03 | AQ70: 0.03 | AR70: 0.03 | AS70: 0.03 | AT70: 0.03 | AU70: 0.03 | AV70: 0.03 | AW70: 0.03 | AX70: 0.03 | AY70: 0.03 | AZ70: 0.03 | BA70: 0.03 | BB70: 0.03 | BC70: 0.03 | BD70: 0.03 | BE70: 0.03 | BF70: 0.03 | BG70: 0.03 | BH70: 0.03 | BI70: 0.03 | BJ70: 0.03 | BK70: 0.03 | BL70: 0.03 | BM70: 0.03 | BN70: 0.03 | BO70: 0.03 | BP70: 0.03 | BQ70: 0.03 | BR70: 0.03 | BS70: 0.03 | BT70: 0.03 | BU70: 0.03 | BV70: 0.03 | BW70: 0.03 | BX70: 0.03 | BY70: 0.03 | BZ70: 0.03 | CA70: 0.03 | CB70: 0.03 | CC70: 0.03 | CD70: 0.03 | CE70: 0.03 | CF70: 0.03 | CG70: 0.03 | CH70: 0.03 | CI70: 0.03 | CJ70: 0.03 | CK70: 0.03 | CL70: 0.03 | CM70: 0.03 | CN70: 0.03 | CO70: 0.03 | CP70: 0.03 | CQ70: 0.03 | CR70: 0.03 | CS70: 0.03 | CT70: 0.03 | CU70: 0.03 | CV70: 0.03 | CW70: 0.03 | CX70: 0.03 | CY70: 0.03 | CZ70: 0.03 | DA70: 0.03 | DB70: 0.03 | DC70: 0.03 | DD70: 0.03 | DE70: 0.03 | DF70: 0.03 | DG70: 0.03 | DH70: 0.03 | DI70: 0.03 | DJ70: 0.03 | DK70: 0.03 | DL70: 0.03 | DM70: 0.03 | DN70: 0.03 | DO70: 0.03 | DP70: 0.03 | DQ70: 0.03 | DR70: 0.03 | DS70: 0.03 | DT70: 0.03 | DU70: 0.03 | DV70: 0.03 | DW70: 0.03 | DX70: 0.03 | DY70: 0.03 | DZ70: 0.03 | EA70: 0.03 | EB70: 0.03 | EC70: 0.03 | ED70: 0.03 | EE70: 0.03 | EF70: 0.03 | EG70: 0.03 | EH70: 0.03 | EI70: 0.03 | EJ70: 0.03 | EK70: 0.03 | EL70: 0.03 | EM70: 0.03 | EN70: 0.03 | EO70: 0.03 | EP70: 0.03 | EQ70: 0.03 | ER70: 0.03 | ES70: 0.03 | ET70: 0.03 | EU70: 0.03 | EV70: 0.03 | EW70: 0.03 | EX70: 0.03 | EY70: 0.03 | EZ70: 0.03 | FA70: 0.03 | FB70: 0.03 | FC70: 0.03 | FD70: 0.03 | FE70: 0.03 | FF70: 0.03 | FG70: 0.03 | FH70: 0.03 | FI70: 0.03 | FJ70: 0.03
B71: Keski | C71: % | D71: 0.05 | E71: 0.05 | F71: 0.05 | G71: 0.05 | H71: 0.05 | I71: 0.05 | J71: 0.05 | K71: 0.05 | L71: 0.05 | M71: 0.05 | N71: 0.05 | O71: 0.05 | P71: 0.05 | Q71: 0.05 | R71: 0.05 | S71: 0.05 | T71: 0.05 | U71: 0.05 | V71: 0.05 | W71: 0.05 | X71: 0.05 | Y71: 0.05 | Z71: 0.05 | AA71: 0.05 | AB71: 0.05 | AC71: 0.05 | AD71: 0.05 | AE71: 0.05 | AF71: 0.05 | AG71: 0.05 | AH71: 0.05 | AI71: 0.05 | AJ71: 0.05 | AK71: 0.05 | AL71: 0.05 | AM71: 0.05 | AN71: 0.05 | AO71: 0.05 | AP71: 0.05 | AQ71: 0.05 | AR71: 0.05 | AS71: 0.05 | AT71: 0.05 | AU71: 0.05 | AV71: 0.05 | AW71: 0.05 | AX71: 0.05 | AY71: 0.05 | AZ71: 0.05 | BA71: 0.05 | BB71: 0.05 | BC71: 0.05 | BD71: 0.05 | BE71: 0.05 | BF71: 0.05 | BG71: 0.05 | BH71: 0.05 | BI71: 0.05 | BJ71: 0.05 | BK71: 0.05 | BL71: 0.05 | BM71: 0.05 | BN71: 0.05 | BO71: 0.05 | BP71: 0.05 | BQ71: 0.05 | BR71: 0.05 | BS71: 0.05 | BT71: 0.05 | BU71: 0.05 | BV71: 0.05 | BW71: 0.05 | BX71: 0.05 | BY71: 0.05 | BZ71: 0.05 | CA71: 0.05 | CB71: 0.05 | CC71: 0.05 | CD71: 0.05 | CE71: 0.05 | CF71: 0.05 | CG71: 0.05 | CH71: 0.05 | CI71: 0.05 | CJ71: 0.05 | CK71: 0.05 | CL71: 0.05 | CM71: 0.05 | CN71: 0.05 | CO71: 0.05 | CP71: 0.05 | CQ71: 0.05 | CR71: 0.05 | CS71: 0.05 | CT71: 0.05 | CU71: 0.05 | CV71: 0.05 | CW71: 0.05 | CX71: 0.05 | CY71: 0.05 | CZ71: 0.05 | DA71: 0.05 | DB71: 0.05 | DC71: 0.05 | DD71: 0.05 | DE71: 0.05 | DF71: 0.05 | DG71: 0.05 | DH71: 0.05 | DI71: 0.05 | DJ71: 0.05 | DK71: 0.05 | DL71: 0.05 | DM71: 0.05 | DN71: 0.05 | DO71: 0.05 | DP71: 0.05 | DQ71: 0.05 | DR71: 0.05 | DS71: 0.05 | DT71: 0.05 | DU71: 0.05 | DV71: 0.05 | DW71: 0.05 | DX71: 0.05 | DY71: 0.05 | DZ71: 0.05 | EA71: 0.05 | EB71: 0.05 | EC71: 0.05 | ED71: 0.05 | EE71: 0.05 | EF71: 0.05 | EG71: 0.05 | EH71: 0.05 | EI71: 0.05 | EJ71: 0.05 | EK71: 0.05 | EL71: 0.05 | EM71: 0.05 | EN71: 0.05 | EO71: 0.05 | EP71: 0.05 | EQ71: 0.05 | ER71: 0.05 | ES71: 0.05 | ET71: 0.05 | EU71: 0.05 | EV71: 0.05 | EW71: 0.05 | EX71: 0.05 | EY71: 0.05 | EZ71: 0.05 | FA71: 0.05 | FB71: 0.05 | FC71: 0.05 | FD71: 0.05 | FE71: 0.05 | FF71: 0.05 | FG71: 0.05 | FH71: 0.05 | FI71: 0.05 | FJ71: 0.05 | FK71: 0.15 | FL71: 0.15 | FM71: 0.05 | FN71: 0.05
B72: Korkea | C72: % | D72: 0.1 | E72: 0.1 | F72: 0.1 | G72: 0.1 | H72: 0.1 | I72: 0.1 | J72: 0.1 | K72: 0.1 | L72: 0.1 | M72: 0.1 | N72: 0.1 | O72: 0.1 | P72: 0.1 | Q72: 0.1 | R72: 0.1 | S72: 0.1 | T72: 0.1 | U72: 0.1 | V72: 0.1 | W72: 0.1 | X72: 0.1 | Y72: 0.1 | Z72: 0.1 | AA72: 0.1 | AB72: 0.1 | AC72: 0.1 | AD72: 0.1 | AE72: 0.1 | AF72: 0.1 | AG72: 0.1 | AH72: 0.1 | AI72: 0.1 | AJ72: 0.1 | AK72: 0.1 | AL72: 0.1 | AM72: 0.1 | AN72: 0.1 | AO72: 0.1 | AP72: 0.1 | AQ72: 0.1 | AR72: 0.1 | AS72: 0.1 | AT72: 0.1 | AU72: 0.1 | AV72: 0.1 | AW72: 0.1 | AX72: 0.1 | AY72: 0.1 | AZ72: 0.1 | BA72: 0.1 | BB72: 0.1 | BC72: 0.1 | BD72: 0.1 | BE72: 0.1 | BF72: 0.1 | BG72: 0.1 | BH72: 0.1 | BI72: 0.1 | BJ72: 0.1 | BK72: 0.1 | BL72: 0.1 | BM72: 0.1 | BN72: 0.1 | BO72: 0.1 | BP72: 0.1 | BQ72: 0.1 | BR72: 0.1 | BS72: 0.1 | BT72: 0.1 | BU72: 0.1 | BV72: 0.1 | BW72: 0.1 | BX72: 0.1 | BY72: 0.1 | BZ72: 0.1 | CA72: 0.1 | CB72: 0.1 | CC72: 0.1 | CD72: 0.1 | CE72: 0.1 | CF72: 0.1 | CG72: 0.1 | CH72: 0.1 | CI72: 0.1 | CJ72: 0.1 | CK72: 0.1 | CL72: 0.1 | CM72: 0.1 | CN72: 0.1 | CO72: 0.1 | CP72: 0.1 | CQ72: 0.1 | CR72: 0.1 | CS72: 0.1 | CT72: 0.1 | CU72: 0.1 | CV72: 0.1 | CW72: 0.1 | CX72: 0.1 | CY72: 0.1 | CZ72: 0.1 | DA72: 0.1 | DB72: 0.1 | DC72: 0.1 | DD72: 0.1 | DE72: 0.1 | DF72: 0.1 | DG72: 0.1 | DH72: 0.1 | DI72: 0.1 | DJ72: 0.1 | DK72: 0.1 | DL72: 0.1 | DM72: 0.1 | DN72: 0.1 | DO72: 0.1 | DP72: 0.1 | DQ72: 0.1 | DR72: 0.1 | DS72: 0.1 | DT72: 0.1 | DU72: 0.1 | DV72: 0.1 | DW72: 0.1 | DX72: 0.1 | DY72: 0.1 | DZ72: 0.1 | EA72: 0.1 | EB72: 0.1 | EC72: 0.1 | ED72: 0.1 | EE72: 0.1 | EF72: 0.1 | EG72: 0.1 | EH72: 0.1 | EI72: 0.1 | EJ72: 0.1 | EK72: 0.1 | EL72: 0.1 | EM72: 0.1 | EN72: 0.1 | EO72: 0.1 | EP72: 0.1 | EQ72: 0.1 | ER72: 0.1 | ES72: 0.1 | ET72: 0.1 | EU72: 0.1 | EV72: 0.1 | EW72: 0.1 | EX72: 0.1 | EY72: 0.1 | EZ72: 0.1 | FA72: 0.1 | FB72: 0.1 | FC72: 0.1 | FD72: 0.1 | FE72: 0.1 | FF72: 0.1 | FG72: 0.1 | FH72: 0.1 | FI72: 0.1 | FJ72: 0.1
A73: Purkamisen viive | C73: vuotta | D73: 0 | E73: 0 | F73: 0 | G73: 0 | H73: 0 | I73: 0 | J73: 0 | K73: 0 | L73: 0 | M73: 0 | N73: 0 | O73: 0 | P73: 0 | Q73: 0 | R73: 0 | S73: 0 | T73: 0 | U73: 0 | V73: 0 | W73: 0 | X73: 0 | Y73: 0 | Z73: 0 | AA73: 0 | AB73: 0 | AC73: 0 | AD73: 0 | AE73: 0 | AF73: 0 | AG73: 0 | AH73: 0 | AI73: 0 | AJ73: 0 | AK73: 0 | AL73: 0 | AM73: 0 | AN73: 0 | AO73: 0 | AP73: 0 | AQ73: 0 | AR73: 0 | AS73: 0 | AT73: 0 | AU73: 0 | AV73: 0 | AW73: 0 | AX73: 0 | AY73: 0 | AZ73: 0 | BA73: 0 | BB73: 0 | BC73: 0 | BD73: 0 | BE73: 0 | BF73: 0 | BG73: 0 | BH73: 0 | BI73: 0 | BJ73: 0 | BK73: 0 | BL73: 0 | BM73: 0 | BN73: 0 | BO73: 0 | BP73: 0 | BQ73: 0 | BR73: 0 | BS73: 0 | BT73: 0 | BU73: 0 | BV73: 0 | BW73: 0 | BX73: 0 | BY73: 0 | BZ73: 0 | CA73: 0 | CB73: 0 | CC73: 0 | CD73: 0 | CE73: 0 | CF73: 0 | CG73: 0 | CH73: 0 | CI73: 0 | CJ73: 0 | CK73: 0 | CL73: 0 | CM73: 0 | CN73: 0 | CO73: 0 | CP73: 0 | CQ73: 0 | CR73: 0 | CS73: 0 | CT73: 0 | CU73: 0 | CV73: 0 | CW73: 0 | CX73: 0 | CY73: 0 | CZ73: 0 | DA73: 0 | DB73: 0 | DC73: 0 | DD73: 0 | DE73: 0 | DF73: 0 | DG73: 0 | DH73: 0 | DI73: 0 | DJ73: 0 | DK73: 0 | DL73: 0 | DM73: 0 | DN73: 0 | DO73: 0 | DP73: 0 | DQ73: 0 | DR73: 0 | DS73: 0 | DT73: 0 | DU73: 0 | DV73: 0 | DW73: 0 | DX73: 0 | DY73: 0 | DZ73: 0 | EA73: 0 | EB73: 0 | EC73: 0 | ED73: 0 | EE73: 0 | EF73: 0 | EG73: 0 | EH73: 0 | EI73: 0 | EJ73: 0 | EK73: 0 | EL73: 0 | EM73: 0 | EN73: 0 | EO73: 0 | EP73: 0 | EQ73: 0 | ER73: 0 | ES73: 0 | ET73: 0 | EU73: 0 | EV73: 0 | EW73: 0 | EX73: 0 | EY73: 0 | EZ73: 0 | FA73: 0 | FB73: 0 | FC73: 0 | FD73: 0 | FE73: 0 | FF73: 0 | FG73: 0 | FH73: 0 | FI73: 0 | FJ73: 0 | FK73: 10 | FL73: 10 | FM73: 0 | FN73: 0
A75: Rakentaminen per kW kapasiteettia | B75: Low | C75: EUR/kW | D75: 9813.519 | E75: 9674.3406 | F75: 9674.3406 | G75: 9674.3406 | H75: 60103.414 | I75: 60103.414 | J75: 60103.414 | K75: 60103.414 | L75: 17915.757 | M75: 17915.757 | N75: 17915.757 | O75: 17915.757 | P75: 27823.022 | Q75: 27823.022 | R75: 27823.022 | S75: 27823.022 | T75: 32400.033 | U75: 32400.033 | V75: 32400.033 | W75: 32400.033 | X75: 33686.789 | Y75: 33686.789 | Z75: 33686.789 | AA75: 33686.789 | AB75: 96579.029 | AC75: 96579.029 | AD75: 96579.029 | AE75: 96579.029 | AF75: 17915.757 | AG75: 17915.757 | AH75: 17915.757 | AI75: 17915.757 | AJ75: 27823.022 | AK75: 27823.022 | AL75: 27823.022 | AM75: 27823.022 | AN75: 32400.033 | AO75: 32400.033 | AP75: 32400.033 | AQ75: 32400.033 | AR75: 33686.789 | AS75: 33686.789 | AT75: 33686.789 | AU75: 33686.789 | AV75: 96579.029 | AW75: 96579.029 | AX75: 96579.029 | AY75: 96579.029 | AZ75: 32171.704 | BA75: 32171.704 | BB75: 32171.704 | BC75: 32171.704 | BD75: 32171.704 | BE75: 32171.704 | BF75: 32171.704 | BG75: 32171.704 | BH75: 32171.704 | BI75: 32171.704 | BJ75: 32171.704 | BK75: 32171.704 | BL75: 51447.056 | BM75: 51447.056 | BN75: 51447.056 | BO75: 51447.056 | BP75: 51447.056 | BQ75: 51447.056 | BR75: 51447.056 | BS75: 51447.056 | BT75: 13831.198 | BU75: 13831.198 | BV75: 13831.198 | BW75: 13831.198 | BX75: 77312.878 | BY75: 77312.878 | BZ75: 77312.878 | CA75: 77312.878 | CB75: 68628.847 | CC75: 68628.847 | CD75: 68628.847 | CE75: 68628.847 | CF75: 72964.682 | CG75: 72864.682 | CH75: 72764.682 | CI75: 72764.682 | CJ75: 83405.976 | CK75: 83405.976 | CL75: 83305.976 | CM75: 83305.976 | CQ75: 700 | CR75: 700 | CS75: 700 | CT75: 700 | CU75: 900 | CV75: 900 | CW75: 900 | CX75: 900 | CY75: 1100 | CZ75: 1000 | DA75: 1000 | DB75: 1000 | DC75: 128940.68 | DD75: 128840.68 | DE75: 128840.68 | DF75: 128840.68 | DG75: 182148.28 | DH75: 182048.28 | DI75: 181948.28 | DJ75: 181948.28 | DK75: 323272.71 | DL75: 323272.71 | DM75: 323272.71 | DN75: 323272.71 | DO75: 323772.71 | DP75: 323772.71 | DQ75: 323772.71 | DR75: 323772.71 | DS75: 121746.62 | DT75: 121446.62 | DU75: 121346.62 | DV75: 121346.62 | DW75: 97274.001 | DX75: 97074.001 | DY75: 96974.001 | DZ75: 96874.001 | EA75: 204912.48 | EB75: 204712.48 | EC75: 204512.48 | ED75: 204512.48 | EE75: 320527.55 | EF75: 320527.55 | EG75: 320527.55 | EH75: 320527.55 | EI75: 45312.721 | EJ75: 45312.721 | EK75: 45312.721 | EL75: 45312.721 | EM75: 88638.839 | EN75: 88538.839 | EO75: 88538.839 | EP75: 88538.839 | EQ75: 0 | ER75: 0 | ES75: 0 | ET75: 0 | EU75: 1863.9178 | EV75: 1863.9178 | EW75: 1863.9178 | EX75: 1863.9178 | EY75: 485998.71 | EZ75: 485298.71 | FA75: 485098.71 | FB75: 485098.71 | FC75: 19575.076 | FD75: 19575.076 | FE75: 19575.076 | FF75: #DIV/0! | FG75: #DIV/0! | FH75: #DIV/0! | FI75: #DIV/0! | FJ75: 19042.427
A76: sis. Infrastruktuuri | B76: Medium | C76: EUR/kW | D76: 19209.442 | E76: 19042.427 | F76: 19042.427 | G76: 19042.427 | H76: 118833.12 | I76: 118833.12 | J76: 118833.12 | K76: 118833.12 | L76: 35710.483 | M76: 35710.483 | N76: 35710.483 | O76: 35710.483 | P76: 55727.282 | Q76: 55727.282 | R76: 55727.282 | S76: 55727.282 | T76: 64250.667 | U76: 64250.667 | V76: 64250.667 | W76: 64250.667 | X76: 66820.467 | Y76: 66820.467 | Z76: 66820.467 | AA76: 66820.467 | AB76: 192568.57 | AC76: 192568.57 | AD76: 192568.57 | AE76: 192568.57 | AF76: 35710.483 | AG76: 35710.483 | AH76: 35710.483 | AI76: 35710.483 | AJ76: 55727.282 | AK76: 55727.282 | AL76: 55727.282 | AM76: 55727.282 | AN76: 64250.667 | AO76: 64250.667 | AP76: 64250.667 | AQ76: 64250.667 | AR76: 66820.467 | AS76: 66820.467 | AT76: 66820.467 | AU76: 66820.467 | AV76: 192568.57 | AW76: 192568.57 | AX76: 192568.57 | AY76: 192568.57 | AZ76: 160107.38 | BA76: 160107.38 | BB76: 160107.38 | BC76: 160107.38 | BD76: 160107.38 | BE76: 160107.38 | BF76: 160107.38 | BG76: 160107.38 | BH76: 160107.38 | BI76: 160107.38 | BJ76: 160107.38 | BK76: 160107.38 | BL76: 249592.36 | BM76: 249592.36 | BN76: 249592.36 | BO76: 249592.36 | BP76: 249592.36 | BQ76: 249592.36 | BR76: 249592.36 | BS76: 249592.36 | BT76: 31156.552 | BU76: 31156.552 | BV76: 31156.552 | BW76: 31156.552 | BX76: 97294.707 | BY76: 97294.707 | BZ76: 97294.707 | CA76: 97294.707 | CB76: 96516.301 | CC76: 96516.301 | CD76: 96516.301 | CE76: 96516.301 | CF76: 83864.529 | CG76: 84122.469 | CH76: 84086.386 | CI76: 84086.386 | CJ76: 89948.894 | CK76: 89848.894 | CL76: 89748.894 | CM76: 89748.894 | CQ76: 1000 | CR76: 900 | CS76: 900 | CT76: 900 | CU76: 1200 | CV76: 1100 | CW76: 1100 | CX76: 1100 | CY76: 1400 | CZ76: 1400 | DA76: 1400 | DB76: 1400 | DC76: 235375.41 | DD76: 235275.41 | DE76: 235175.41 | DF76: 235175.41 | DG76: 362219.86 | DH76: 362019.86 | DI76: 361919.86 | DJ76: 361819.86 | DK76: 516141.28 | DL76: 516141.28 | DM76: 516141.28 | DN76: 516141.28 | DO76: 516741.28 | DP76: 516741.28 | DQ76: 516741.28 | DR76: 516741.28 | DS76: 177216.03 | DT76: 176816.03 | DU76: 176716.03 | DV76: 176716.03 | DW76: 143846.1 | DX76: 143446.1 | DY76: 143146.1 | DZ76: 143046.1 | EA76: 300683.88 | EB76: 300283.88 | EC76: 299883.88 | ED76: 299783.88 | EE76: 513906.64 | EF76: 513906.64 | EG76: 513906.64 | EH76: 513906.64 | EI76: 91637.398 | EJ76: 91637.398 | EK76: 91637.398 | EL76: 91637.398 | EM76: 178200.98 | EN76: 178100.98 | EO76: 178000.98 | EP76: 178000.98 | EQ76: 3776.7014 | ER76: 3776.7014 | ES76: 3776.7014 | ET76: 3776.7014 | EU76: 3476.7014 | EV76: 3476.7014 | EW76: 3476.7014 | EX76: 3476.7014 | EY76: 829221.69 | EZ76: 828021.69 | FA76: 827621.69 | FB76: 827621.69 | FC76: 22125.26 | FD76: 22125.26 | FE76: 22125.26 | FF76: #DIV/0! | FG76: #DIV/0! | FH76: #DIV/0! | FI76: #DIV/0! | FJ76: 19894.665
B77: High | C77: EUR/kW | D77: 37779.705 | E77: 37584.855 | F77: 37584.855 | G77: 37584.855 | H77: 237002.32 | I77: 237002.32 | J77: 237002.32 | K77: 237002.32 | L77: 71108.183 | M77: 71208.183 | N77: 71208.183 | O77: 71208.183 | P77: 111029 | Q77: 111029 | R77: 111029 | S77: 111029 | T77: 128275.77 | U77: 128275.77 | V77: 128275.77 | W77: 128275.77 | X77: 133389.8 | Y77: 133389.8 | Z77: 133389.8 | AA77: 133389.8 | AB77: 383216.04 | AC77: 383216.04 | AD77: 383216.04 | AE77: 383216.04 | AF77: 71108.183 | AG77: 71208.183 | AH77: 71208.183 | AI77: 71208.183 | AJ77: 111029 | AK77: 111029 | AL77: 111029 | AM77: 111029 | AN77: 128275.77 | AO77: 128275.77 | AP77: 128275.77 | AQ77: 128275.77 | AR77: 133389.8 | AS77: 133389.8 | AT77: 133389.8 | AU77: 133389.8 | AV77: 383216.04 | AW77: 383216.04 | AX77: 383216.04 | AY77: 383216.04 | AZ77: 473317.58 | BA77: 473317.58 | BB77: 473317.58 | BC77: 473317.58 | BD77: 473317.58 | BE77: 473317.58 | BF77: 473317.58 | BG77: 473317.58 | BH77: 473317.58 | BI77: 473317.58 | BJ77: 473317.58 | BK77: 473317.58 | BL77: 754656.08 | BM77: 754656.08 | BN77: 754656.08 | BO77: 754656.08 | BP77: 754656.08 | BQ77: 754656.08 | BR77: 754656.08 | BS77: 754656.08 | BT77: 37378.542 | BU77: 37278.542 | BV77: 37278.542 | BW77: 37278.542 | BX77: 126261.06 | BY77: 126261.06 | BZ77: 126161.06 | CA77: 126161.06 | CB77: 119277.81 | CC77: 119277.81 | CD77: 119277.81 | CE77: 119277.81 | CF77: 96981.91 | CG77: 96975.932 | CH77: 97453.461 | CI77: 97453.461 | CJ77: 96417.379 | CK77: 96317.379 | CL77: 96317.379 | CM77: 96217.379 | CQ77: 1200 | CR77: 1100 | CS77: 1100 | CT77: 1100 | CU77: 1500 | CV77: 1400 | CW77: 1400 | CX77: 1400 | CY77: 1800 | CZ77: 1700 | DA77: 1700 | DB77: 1700 | DC77: 334164.46 | DD77: 334064.46 | DE77: 333964.46 | DF77: 333964.46 | DG77: 513737.08 | DH77: 513437.08 | DI77: 513237.08 | DJ77: 513137.08 | DK77: 773266.04 | DL77: 773266.04 | DM77: 773266.04 | DN77: 773266.04 | DO77: 774066.04 | DP77: 774066.04 | DQ77: 774066.04 | DR77: 774066.04 | DS77: 199800.94 | DT77: 199400.94 | DU77: 199200.94 | DV77: 199200.94 | DW77: 164734.58 | DX77: 164134.58 | DY77: 163734.58 | DZ77: 163534.58 | EA77: 342052.08 | EB77: 341352.08 | EC77: 340852.08 | ED77: 340552.08 | EE77: 771190.78 | EF77: 771190.78 | EG77: 771190.78 | EH77: 771190.78 | EI77: 136449.29 | EJ77: 136449.29 | EK77: 136449.29 | EL77: 136449.29 | EM77: 223651.22 | EN77: 223451.22 | EO77: 223251.22 | EP77: 223251.22 | EQ77: 0 | ER77: 0 | ES77: 0 | ET77: 0 | EU77: 3947.4249 | EV77: 3947.4249 | EW77: 3947.4249 | EX77: 3947.4249 | EY77: 1143800.7 | EZ77: 1142200.7 | FA77: 1141600.7 | FB77: 1141600.7 | FC77: 24794.757 | FD77: 24794.757 | FE77: 24794.757 | FF77: #DIV/0! | FG77: #DIV/0! | FH77: #DIV/0! | FI77: #DIV/0! | FJ77: 20853.433
A78: Kiinteät kulut per kW | C78: EUR/kW | D78: 25.822807 | E78: 25.822807 | F78: 25.822807 | G78: 25.822807 | H78: 50.367258 | I78: 50.367258 | J78: 50.367258 | K78: 50.367258 | L78: 11.760883 | M78: 11.760883 | N78: 11.760883 | O78: 11.760883 | P78: 13.039239 | Q78: 13.039239 | R78: 13.039239 | S78: 13.039239 | T78: 15.08461 | U78: 15.08461 | V78: 15.08461 | W78: 15.08461 | X78: 15.08461 | Y78: 15.08461 | Z78: 15.08461 | AA78: 15.08461 | AB78: 21.60423 | AC78: 21.60423 | AD78: 21.60423 | AE78: 21.60423 | AF78: 15.340282 | AG78: 15.340282 | AH78: 15.340282 | AI78: 15.340282 | AJ78: 17.002145 | AK78: 17.002145 | AL78: 17.002145 | AM78: 17.002145 | AN78: 19.942366 | AO78: 19.942366 | AP78: 19.942366 | AQ78: 19.942366 | AR78: 19.942366 | AS78: 19.942366 | AT78: 19.942366 | AU78: 19.942366 | AV78: 29.018699 | AW78: 29.018699 | AX78: 29.018699 | AY78: 29.018699 | AZ78: -30.680563 | BA78: -30.680563 | BB78: -30.680563 | BC78: -30.680563 | BD78: -25.694972 | BE78: -25.694972 | BF78: -25.694972 | BG78: -25.694972 | BH78: -24.927958 | BI78: -24.927958 | BJ78: -24.927958 | BK78: -24.927958 | BL78: -30.680563 | BM78: -30.680563 | BN78: -30.680563 | BO78: -30.680563 | BP78: -25.694972 | BQ78: -25.694972 | BR78: -25.694972 | BS78: -25.694972 | BT78: 131.54291 | BU78: 131.54291 | BV78: 131.54291 | BW78: 131.54291 | BX78: 445.37951 | BY78: 444.86817 | BZ78: 444.86817 | CA78: 444.86817 | CB78: 39.245554 | CC78: 39.373389 | CD78: 39.629061 | CE78: 40.012568 | CF78: 116.4583 | CG78: 113.26241 | CH78: 113.39025 | CI78: 114.02943 | CJ78: 11.888718 | CK78: 11.121704 | CL78: 10.610361 | CM78: 9.8433474 | CQ78: 9.8433474 | CR78: 8.9484976 | CS78: 8.9484976 | CT78: 8.9484976 | CU78: 9.8433474 | CV78: 9.587676 | CW78: 9.587676 | CX78: 9.587676 | CY78: 24.416615 | CZ78: 23.649601 | DA78: 23.649601 | DB78: 23.649601 | DC78: 261.42397 | DD78: 257.46106 | DE78: 257.46106 | DF78: 257.46106 | DG78: 357.04505 | DH78: 351.67596 | DI78: 351.67596 | DJ78: 351.67596 | DK78: 212.33506 | DL78: 212.33506 | DM78: 212.33506 | DN78: 212.33506 | DO78: 291.20968 | DP78: 291.20968 | DQ78: 291.20968 | DR78: 291.20968 | DS78: 419.17319 | DT78: 407.15664 | DU78: 407.15664 | DV78: 407.15664 | DW78: 352.57081 | DX78: 342.47179 | DY78: 342.47179 | DZ78: 342.47179 | EA78: 352.57081 | EB78: 342.47179 | EC78: 342.47179 | ED78: 342.47179 | EE78: 130.39239 | EF78: 130.39239 | EG78: 130.39239 | EH78: 130.39239 | EI78: 143.43163 | EJ78: 143.43163 | EK78: 143.43163 | EL78: 143.43163 | EM78: 139.85223 | EN78: 139.85223 | EO78: 139.85223 | EP78: 139.85223 | EQ78: 49.983751 | ER78: 49.983751 | ES78: 49.983751 | ET78: 49.983751 | EU78: 65.835375 | EV78: 65.835375 | EW78: 65.835375 | EX78: 65.835375 | EY78: 110.06652 | EZ78: 75.550887 | FA78: 75.550887 | FB78: 75.550887 | FC78: 28.251685 | FD78: 28.251685 | FE78: 28.251685 | FF78: 0 | FG78: 0 | FH78: 0 | FI78: 0 | FJ78: 25.950643
A79: Kulut per käyttövuosi | B79: Low | C79: EUR/kW | D79: 418.36357 | E79: 412.79643 | F79: 412.79643 | G79: 412.79643 | H79: 2454.5038 | I79: 2454.5038 | J79: 2454.5038 | K79: 2454.5038 | L79: 728.39115 | M79: 728.39115 | N79: 728.39115 | O79: 728.39115 | P79: 1125.9601 | Q79: 1125.9601 | R79: 1125.9601 | S79: 1125.9601 | T79: 1311.0859 | U79: 1311.0859 | V79: 1311.0859 | W79: 1311.0859 | X79: 1362.5562 | Y79: 1362.5562 | Z79: 1362.5562 | AA79: 1362.5562 | AB79: 3884.7654 | AC79: 3884.7654 | AD79: 3884.7654 | AE79: 3884.7654 | AF79: 731.97055 | AG79: 731.97055 | AH79: 731.97055 | AI79: 731.97055 | AJ79: 1129.923 | AK79: 1129.923 | AL79: 1129.923 | AM79: 1129.923 | AN79: 1315.9437 | AO79: 1315.9437 | AP79: 1315.9437 | AQ79: 1315.9437 | AR79: 1367.4139 | AS79: 1367.4139 | AT79: 1367.4139 | AU79: 1367.4139 | AV79: 3892.1798 | AW79: 3892.1798 | AX79: 3892.1798 | AY79: 3892.1798 | AZ79: 2114.0997 | BA79: 2114.0997 | BB79: 2114.0997 | BC79: 2114.0997 | BD79: 2119.0853 | BE79: 2119.0853 | BF79: 2119.0853 | BG79: 2119.0853 | BH79: 2119.8523 | BI79: 2119.8523 | BJ79: 2119.8523 | BK79: 2119.8523 | BL79: 3399.1231 | BM79: 3399.1231 | BN79: 3399.1231 | BO79: 3399.1231 | BP79: 3404.1087 | BQ79: 3404.1087 | BR79: 3404.1087 | BS79: 3404.1087 | BT79: 684.79084 | BU79: 684.79084 | BV79: 684.79084 | BW79: 684.79084 | BX79: 3666.7494 | BY79: 3666.2381 | BZ79: 3666.2381 | CA79: 3666.2381 | CB79: 2784.3994 | CC79: 2784.5273 | CD79: 2784.7829 | CE79: 2785.1665 | CF79: 2548.6144 | CG79: 2542.0852 | CH79: 2538.8797 | CI79: 2539.5188 | CJ79: 2394.9166 | CK79: 2394.1496 | CL79: 2390.7811 | CM79: 2390.0141 | CQ79: 33.176681 | CR79: 32.281831 | CS79: 32.281831 | CT79: 32.281831 | CU79: 39.843347 | CV79: 39.587676 | CW79: 39.587676 | CX79: 39.587676 | CY79: 61.083282 | CZ79: 56.982934 | DA79: 56.982934 | DB79: 56.982934 | DC79: 3945.4433 | DD79: 3938.6233 | DE79: 3938.6233 | DF79: 3938.6233 | DG79: 7103.2776 | DH79: 7094.2048 | DI79: 7090.5011 | DJ79: 7090.5011 | DK79: 16375.97 | DL79: 16375.97 | DM79: 16375.97 | DN79: 16375.97 | DO79: 16479.845 | DP79: 16479.845 | DQ79: 16479.845 | DR79: 16479.845 | DS79: 5289.0382 | DT79: 5265.0216 | DU79: 5261.0216 | DV79: 5261.0216 | DW79: 3955.3116 | DX79: 3937.8052 | DY79: 3934.1015 | DZ79: 3930.3978 | EA79: 8549.0698 | EB79: 8530.9708 | EC79: 8522.9708 | ED79: 8522.9708 | EE79: 11577.805 | EF79: 11577.805 | EG79: 11577.805 | EH79: 11577.805 | EI79: 2409.0677 | EJ79: 2409.0677 | EK79: 2409.0677 | EL79: 2409.0677 | EM79: 3685.4058 | EN79: 3681.4058 | EO79: 3681.4058 | EP79: 3681.4058 | EQ79: 49.983751 | ER79: 49.983751 | ES79: 49.983751 | ET79: 49.983751 | EU79: 111.29679 | EV79: 111.29679 | EW79: 111.29679 | EX79: 111.29679 | EY79: 24410.002 | EZ79: 24340.486 | FA79: 24330.486 | FB79: 24330.486 | FC79: 811.25473 | FD79: 811.25473 | FE79: 811.25473 | FF79: #DIV/0! | FG79: #DIV/0! | FH79: #DIV/0! | FI79: #DIV/0! | FJ79: 787.64774
B80: Medium | C80: EUR/kW | D80: 794.20047 | E80: 787.5199 | F80: 787.5199 | G80: 787.5199 | H80: 4803.692 | I80: 4803.692 | J80: 4803.692 | K80: 4803.692 | L80: 1440.1802 | M80: 1440.1802 | N80: 1440.1802 | O80: 1440.1802 | P80: 2242.1305 | Q80: 2242.1305 | R80: 2242.1305 | S80: 2242.1305 | T80: 2585.1113 | U80: 2585.1113 | V80: 2585.1113 | W80: 2585.1113 | X80: 2687.9033 | Y80: 2687.9033 | Z80: 2687.9033 | AA80: 2687.9033 | AB80: 7724.3471 | AC80: 7724.3471 | AD80: 7724.3471 | AE80: 7724.3471 | AF80: 1443.7596 | AG80: 1443.7596 | AH80: 1443.7596 | AI80: 1443.7596 | AJ80: 2246.0934 | AK80: 2246.0934 | AL80: 2246.0934 | AM80: 2246.0934 | AN80: 2589.9691 | AO80: 2589.9691 | AP80: 2589.9691 | AQ80: 2589.9691 | AR80: 2692.761 | AS80: 2692.761 | AT80: 2692.761 | AU80: 2692.761 | AV80: 7731.7616 | AW80: 7731.7616 | AX80: 7731.7616 | AY80: 7731.7616 | AZ80: 10643.145 | BA80: 10643.145 | BB80: 10643.145 | BC80: 10643.145 | BD80: 10648.131 | BE80: 10648.131 | BF80: 10648.131 | BG80: 10648.131 | BH80: 10648.898 | BI80: 10648.898 | BJ80: 10648.898 | BK80: 10648.898 | BL80: 16608.81 | BM80: 16608.81 | BN80: 16608.81 | BO80: 16608.81 | BP80: 16613.796 | BQ80: 16613.796 | BR80: 16613.796 | BS80: 16613.796 | BT80: 1377.805 | BU80: 1377.805 | BV80: 1377.805 | BW80: 1377.805 | BX80: 4499.3256 | BY80: 4498.8143 | BZ80: 4498.8143 | CA80: 4498.8143 | CB80: 3899.8976 | CC80: 3900.0254 | CD80: 3900.2811 | CE80: 3900.6646 | CF80: 2911.9426 | CG80: 2917.3447 | CH80: 2916.2698 | CI80: 2916.909 | CJ80: 2581.8571 | CK80: 2578.233 | CL80: 2574.8645 | CM80: 2574.0975 | CQ80: 43.176681 | CR80: 38.948498 | CS80: 38.948498 | CT80: 38.948498 | CU80: 49.843347 | CV80: 46.254343 | CW80: 46.254343 | CX80: 46.254343 | CY80: 71.083282 | CZ80: 70.316267 | DA80: 70.316267 | DB80: 70.316267 | DC80: 6986.4356 | DD80: 6979.6156 | DE80: 6976.7584 | DF80: 6976.7584 | DG80: 13772.595 | DH80: 13759.819 | DI80: 13756.115 | DJ80: 13752.411 | DK80: 26019.399 | DL80: 26019.399 | DM80: 26019.399 | DN80: 26019.399 | DO80: 26128.274 | DP80: 26128.274 | DQ80: 26128.274 | DR80: 26128.274 | DS80: 7507.8143 | DT80: 7479.7978 | DU80: 7475.7978 | DV80: 7475.7978 | DW80: 5680.2042 | DX80: 5655.2904 | DY80: 5644.1793 | DZ80: 5640.4756 | EA80: 12379.926 | EB80: 12353.827 | EC80: 12337.827 | ED80: 12333.827 | EE80: 18484.201 | EF80: 18484.201 | EG80: 18484.201 | EH80: 18484.201 | EI80: 4725.3015 | EJ80: 4725.3015 | EK80: 4725.3015 | EL80: 4725.3015 | EM80: 7267.8913 | EN80: 7263.8913 | EO80: 7259.8913 | EP80: 7259.8913 | EQ80: 142.09842 | ER80: 142.09842 | ES80: 142.09842 | ET80: 142.09842 | EU80: 150.63297 | EV80: 150.63297 | EW80: 150.63297 | EX80: 150.63297 | EY80: 41571.151 | EZ80: 41476.635 | FA80: 41456.635 | FB80: 41456.635 | FC80: 913.26208 | FD80: 913.26208 | FE80: 913.26208 | FF80: #DIV/0! | FG80: #DIV/0! | FH80: #DIV/0! | FI80: #DIV/0! | FJ80: 821.73726
B81: High | C81: EUR/kW | D81: 1537.011 | E81: 1529.217 | F81: 1529.217 | G81: 1529.217 | H81: 9530.46 | I81: 9530.46 | J81: 9530.46 | K81: 9530.46 | L81: 2856.0882 | M81: 2860.0882 | N81: 2860.0882 | O81: 2860.0882 | P81: 4454.1991 | Q81: 4454.1991 | R81: 4454.1991 | S81: 4454.1991 | T81: 5146.1153 | U81: 5146.1153 | V81: 5146.1153 | W81: 5146.1153 | X81: 5350.6766 | Y81: 5350.6766 | Z81: 5350.6766 | AA81: 5350.6766 | AB81: 15350.246 | AC81: 15350.246 | AD81: 15350.246 | AE81: 15350.246 | AF81: 2859.6676 | AG81: 2863.6676 | AH81: 2863.6676 | AI81: 2863.6676 | AJ81: 4458.162 | AK81: 4458.162 | AL81: 4458.162 | AM81: 4458.162 | AN81: 5150.973 | AO81: 5150.973 | AP81: 5150.973 | AQ81: 5150.973 | AR81: 5355.5343 | AS81: 5355.5343 | AT81: 5355.5343 | AU81: 5355.5343 | AV81: 15357.66 | AW81: 15357.66 | AX81: 15357.66 | AY81: 15357.66 | AZ81: 31523.825 | BA81: 31523.825 | BB81: 31523.825 | BC81: 31523.825 | BD81: 31528.811 | BE81: 31528.811 | BF81: 31528.811 | BG81: 31528.811 | BH81: 31529.578 | BI81: 31529.578 | BJ81: 31529.578 | BK81: 31529.578 | BL81: 50279.725 | BM81: 50279.725 | BN81: 50279.725 | BO81: 50279.725 | BP81: 50284.71 | BQ81: 50284.71 | BR81: 50284.71 | BS81: 50284.71 | BT81: 1626.6846 | BU81: 1622.6846 | BV81: 1622.6846 | BW81: 1622.6846 | BX81: 5706.257 | BY81: 5705.7456 | BZ81: 5701.579 | CA81: 5701.579 | CB81: 4810.3578 | CC81: 4810.4857 | CD81: 4810.7413 | CE81: 4811.1249 | CF81: 3349.1886 | CG81: 3345.7935 | CH81: 3361.839 | CI81: 3362.4781 | CJ81: 2766.671 | CK81: 2763.0468 | CL81: 2762.5355 | CM81: 2758.9113 | CQ81: 49.843347 | CR81: 45.615164 | CS81: 45.615164 | CT81: 45.615164 | CU81: 59.843347 | CV81: 56.254343 | CW81: 56.254343 | CX81: 56.254343 | CY81: 84.416615 | CZ81: 80.316267 | DA81: 80.316267 | DB81: 80.316267 | DC81: 9808.98 | DD81: 9802.1599 | DE81: 9799.3028 | DF81: 9799.3028 | DG81: 19384.344 | DH81: 19367.864 | DI81: 19360.457 | DJ81: 19356.753 | DK81: 38875.637 | DL81: 38875.637 | DM81: 38875.637 | DN81: 38875.637 | DO81: 38994.512 | DP81: 38994.512 | DQ81: 38994.512 | DR81: 38994.512 | DS81: 8411.211 | DT81: 8383.1944 | DU81: 8375.1944 | DV81: 8375.1944 | DW81: 6453.8514 | DX81: 6421.5301 | DY81: 6406.7153 | DZ81: 6399.3079 | EA81: 14034.654 | EB81: 13996.555 | EC81: 13976.555 | ED81: 13964.555 | EE81: 27672.92 | EF81: 27672.92 | EG81: 27672.92 | EH81: 27672.92 | EI81: 6965.8962 | EJ81: 6965.8962 | EK81: 6965.8962 | EL81: 6965.8962 | EM81: 9085.901 | EN81: 9077.901 | EO81: 9069.901 | EP81: 9069.901 | EQ81: 49.983751 | ER81: 49.983751 | ES81: 49.983751 | ET81: 49.983751 | EU81: 162.11403 | EV81: 162.11403 | EW81: 162.11403 | EX81: 162.11403 | EY81: 57300.1 | EZ81: 57185.584 | FA81: 57155.584 | FB81: 57155.584 | FC81: 1020.042 | FD81: 1020.042 | FE81: 1020.042 | FF81: #DIV/0! | FG81: #DIV/0! | FH81: #DIV/0! | FI81: #DIV/0! | FJ81: 860.08796
E85: =1.1632*1.099 -> 1.2783568 | F85: 1.2783568

Sheet Polttoainekustannukset
A3: Input | B3: Polttoaine | C3: Case | D3: Case_ID | E3: ID | F3: Lähde | G3: Data vuodelta | H3: Huom | I3: Yksikkö | J3: 2020 | K3: 2021 | L3: 2022 | M3: 2023 | N3: 2024 | O3: 2025 | P3: 2026 | Q3: 2027 | R3: 2028 | S3: 2029 | T3: 2030 | U3: 2031 | V3: 2032 | W3: 2033 | X3: 2034 | Y3: 2035 | Z3: 2036 | AA3: 2037 | AB3: 2038 | AC3: 2039 | AD3: 2040 | AE3: 2041 | AF3: 2042 | AG3: 2043 | AH3: 2044 | AI3: 2045 | AJ3: 2046 | AK3: 2047 | AL3: 2048 | AM3: 2049 | AN3: 2050 | AO3: 2051 | AP3: 2052 | AQ3: 2053 | AR3: 2054 | AS3: 2055 | AT3: 2056 | AU3: 2057 | AV3: 2058 | AW3: 2059 | AX3: 2060 | AY3: 2061 | AZ3: 2062 | BA3: 2063 | BB3: 2064 | BC3: 2065 | BD3: 2066 | BE3: 2067 | BF3: 2068 | BG3: 2069 | BH3: 2070 | BI3: 2071 | BJ3: 2072 | BK3: 2073 | BL3: 2074 | BM3: 2075 | BN3: 2076 | BO3: 2077 | BP3: 2078 | BQ3: 2079 | BR3: 2080 | BS3: 2081 | BT3: 2082 | BU3: 2083 | BV3: 2084 | BW3: 2085 | BX3: 2086 | BY3: 2087 | BZ3: 2088 | CA3: 2089 | CB3: 2090 | CC3: 2091 | CD3: 2092 | CE3: 2093 | CF3: 2094 | CG3: 2095 | CH3: 2096 | CI3: 2097 | CJ3: 2098 | CK3: 2099 | CL3: 2100 | CM3: 2101 | CN3: 2102 | CO3: 2103 | CP3: 2104 | CQ3: 2105 | CR3: 2106 | CS3: 2107 | CT3: 2108 | CU3: 2109 | CV3: 2110 | CW3: 2111 | CX3: 2112 | CY3: 2113 | CZ3: 2114 | DA3: 2115 | DB3: 2116 | DC3: 2117 | DD3: 2118 | DE3: 2119 | DF3: 2120
B4: Uraani | C4: Suomi, 2010 hinnat | D4: 6 | E4: =_xlfn.CONCAT(B4,", ",C4) -> Uraani, Suomi, 2010 hinnat | H4: Vakkilainen2017 | I4: 2022 EUR/MWh | J4: 2.352 | K4: 2.352 | L4: 2.352 | M4: 2.352 | N4: 2.352 | O4: 2.352 | P4: 2.352 | Q4: 2.352 | R4: 2.352 | S4: 2.352 | T4: 2.352 | U4: 2.352 | V4: 2.352 | W4: 2.352 | X4: 2.352 | Y4: 2.352 | Z4: 2.352 | AA4: 2.352 | AB4: 2.352 | AC4: 2.352 | AD4: 2.352 | AE4: 2.352 | AF4: 2.352 | AG4: 2.352 | AH4: 2.352 | AI4: 2.352 | AJ4: 2.352 | AK4: 2.352 | AL4: 2.352 | AM4: 2.352 | AN4: 2.352 | AO4: 2.352 | AP4: 2.352 | AQ4: 2.352 | AR4: 2.352 | AS4: 2.352 | AT4: 2.352 | AU4: 2.352 | AV4: 2.352 | AW4: 2.352 | AX4: 2.352 | AY4: 2.352 | AZ4: 2.352 | BA4: 2.352 | BB4: 2.352 | BC4: 2.352 | BD4: 2.352 | BE4: 2.352 | BF4: 2.352 | BG4: 2.352 | BH4: 2.352 | BI4: 2.352 | BJ4: 2.352 | BK4: 2.352 | BL4: 2.352 | BM4: 2.352 | BN4: 2.352 | BO4: 2.352 | BP4: 2.352 | BQ4: 2.352 | BR4: 2.352 | BS4: 2.352 | BT4: 2.352 | BU4: 2.352 | BV4: 2.352 | BW4: 2.352 | BX4: 2.352 | BY4: 2.352 | BZ4: 2.352 | CA4: 2.352 | CB4: 2.352 | CC4: 2.352 | CD4: 2.352 | CE4: 2.352 | CF4: 2.352 | CG4: 2.352 | CH4: 2.352 | CI4: 2.352 | CJ4: 2.352 | CK4: 2.352 | CL4: 2.352 | CM4: 2.352 | CN4: 2.352 | CO4: 2.352 | CP4: 2.352 | CQ4: 2.352 | CR4: 2.352 | CS4: 2.352 | CT4: 2.352 | CU4: 2.352 | CV4: 2.352 | CW4: 2.352 | CX4: 2.352 | CY4: 2.352 | CZ4: 2.352 | DA4: 2.352 | DB4: 2.352 | DC4: 2.352 | DD4: 2.352 | DE4: 2.352 | DF4: 2.352
A5: Maakaasu | B5: Maakaasu | C5: Matala | D5: 1 | E5: Maakaasu, Matala | F5: Kost2021 | G5: 2021 | H5: Oletukset Fraunhofer ISE (Kost2021) | I5: 2022 EUR/MWh | J5: 28.435 | K5: 28.435 | L5: 28.435 | M5: 28.435 | N5: 28.435 | O5: 28.435 | P5: 26.38768 | Q5: 24.34036 | R5: 22.29304 | S5: 20.24572 | T5: 18.1984 | U5: 18.1984 | V5: 18.1984 | W5: 18.1984 | X5: 18.1984 | Y5: 18.1984 | Z5: 18.42588 | AA5: 18.65336 | AB5: 18.88084 | AC5: 19.10832 | AD5: 19.3358 | AE5: 19.3358 | AF5: 19.3358 | AG5: 19.3358 | AH5: 19.3358 | AI5: 19.3358 | AJ5: 19.3358 | AK5: 19.3358 | AL5: 19.3358 | AM5: 19.3358 | AN5: 19.3358 | AO5: 19.3358 | AP5: 19.3358 | AQ5: 19.3358 | AR5: 19.3358 | AS5: 19.3358 | AT5: 19.3358 | AU5: 19.3358 | AV5: 19.3358 | AW5: 19.3358 | AX5: 19.3358 | AY5: 19.3358 | AZ5: 19.3358 | BA5: 19.3358 | BB5: 19.3358 | BC5: 19.3358 | BD5: 19.3358 | BE5: 19.3358 | BF5: 19.3358 | BG5: 19.3358 | BH5: 19.3358 | BI5: 19.3358 | BJ5: 19.3358 | BK5: 19.3358 | BL5: 19.3358 | BM5: 19.3358 | BN5: 19.3358 | BO5: 19.3358 | BP5: 19.3358 | BQ5: 19.3358 | BR5: 19.3358 | BS5: 19.3358 | BT5: 19.3358 | BU5: 19.3358 | BV5: 19.3358 | BW5: 19.3358 | BX5: 19.3358 | BY5: 19.3358 | BZ5: 19.3358 | CA5: 19.3358 | CB5: 19.3358 | CC5: 19.3358 | CD5: 19.3358 | CE5: 19.3358 | CF5: 19.3358 | CG5: 19.3358 | CH5: 19.3358 | CI5: 19.3358 | CJ5: 19.3358 | CK5: 19.3358 | CL5: 19.3358 | CM5: 19.3358 | CN5: 19.3358 | CO5: 19.3358 | CP5: 19.3358 | CQ5: 19.3358 | CR5: 19.3358 | CS5: 19.3358 | CT5: 19.3358 | CU5: 19.3358 | CV5: 19.3358 | CW5: 19.3358 | CX5: 19.3358 | CY5: 19.3358 | CZ5: 19.3358 | DA5: 19.3358 | DB5: 19.3358 | DC5: 19.3358 | DD5: 19.3358 | DE5: 19.3358 | DF5: 19.3358
B6: Maakaasu | C6: Keski | D6: 2 | E6: Maakaasu, Keski | F6: https://www.investing.com/commodities/dutch-ttf-gas-c1-futures-historical-data , https://www.ice.com/products/27996665/Dutch-TTF-Natural-Gas-Futures/data?marketId=6277412 , https://www.gov.uk/government/publications/electricity-generation-costs-2023 | G6: 2023 | H6: Dutch TTF. 2020-2022 vuoden keskiarvo, muutettu 2023 EUR/MWh. 2023 toteutuneen ja futuurin keskiarvo. 2024-26 futuurit; 2027 alkaen brittien oletukset 2023 (DESNZ 2023) | I6: 2022 EUR/MWh | J6: 11.797 | K6: 52.4802 | L6: 139.0354 | M6: 41.2096 | N6: 47.5546 | O6: 43.804 | P6: 34.968 | Q6: 26.291072 | R6: 26.729256 | S6: 27.605625 | T6: 28.04381 | U6: 28.481994 | V6: 28.920179 | W6: 29.358364 | X6: 29.796548 | Y6: 30.234733 | Z6: 30.234733 | AA6: 30.234733 | AB6: 30.234733 | AC6: 30.234733 | AD6: 30.234733 | AE6: 30.234733 | AF6: 30.234733 | AG6: 30.234733 | AH6: 30.234733 | AI6: 30.234733 | AJ6: 30.234733 | AK6: 30.234733 | AL6: 30.234733 | AM6: 30.234733 | AN6: 30.234733 | AO6: 30.234733 | AP6: 30.234733 | AQ6: 30.234733 | AR6: 30.234733 | AS6: 30.234733 | AT6: 30.234733 | AU6: 30.234733 | AV6: 30.234733 | AW6: 30.234733 | AX6: 30.234733 | AY6: 30.234733 | AZ6: 30.234733 | BA6: 30.234733 | BB6: 30.234733 | BC6: 30.234733 | BD6: 30.234733 | BE6: 30.234733 | BF6: 30.234733 | BG6: 30.234733 | BH6: 30.234733 | BI6: 30.234733 | BJ6: 30.234733 | BK6: 30.234733 | BL6: 30.234733 | BM6: 30.234733 | BN6: 30.234733 | BO6: 30.234733 | BP6: 30.234733 | BQ6: 30.234733 | BR6: 30.234733 | BS6: 30.234733 | BT6: 30.234733 | BU6: 30.234733 | BV6: 30.234733 | BW6: 30.234733 | BX6: 30.234733 | BY6: 30.234733 | BZ6: 30.234733 | CA6: 30.234733 | CB6: 30.234733 | CC6: 30.234733 | CD6: 30.234733 | CE6: 30.234733 | CF6: 30.234733 | CG6: 30.234733 | CH6: 30.234733 | CI6: 30.234733 | CJ6: 30.234733 | CK6: 30.234733 | CL6: 30.234733 | CM6: 30.234733 | CN6: 30.234733 | CO6: 30.234733 | CP6: 30.234733 | CQ6: 30.234733 | CR6: 30.234733 | CS6: 30.234733 | CT6: 30.234733 | CU6: 30.234733 | CV6: 30.234733 | CW6: 30.234733 | CX6: 30.234733 | CY6: 30.234733 | CZ6: 30.234733 | DA6: 30.234733 | DB6: 30.234733 | DC6: 30.234733 | DD6: 30.234733 | DE6: 30.234733 | DF6: 30.234733
B7: Maakaasu | C7: Korkea | D7: 3 | E7: Maakaasu, Korkea | F7: https://www.investing.com/commodities/dutch-ttf-gas-c1-futures-historical-data , https://www.ice.com/products/27996665/Dutch-TTF-Natural-Gas-Futures/data?marketId=6277412 , Kost2021 | G7: 2023 | H7: 1,5 kertaa keskicase | I7: 2022 EUR/MWh | J7: 17.6955 | K7: 78.7203 | L7: 208.5531 | M7: 61.8144 | N7: 71.3319 | O7: 65.706 | P7: 52.452 | Q7: 39.436608 | R7: 40.093885 | S7: 41.408438 | T7: 42.065715 | U7: 42.722992 | V7: 43.380268 | W7: 44.037545 | X7: 44.694822 | Y7: 45.352099 | Z7: 45.352099 | AA7: 45.352099 | AB7: 45.352099 | AC7: 45.352099 | AD7: 45.352099 | AE7: 45.352099 | AF7: 45.352099 | AG7: 45.352099 | AH7: 45.352099 | AI7: 45.352099 | AJ7: 45.352099 | AK7: 45.352099 | AL7: 45.352099 | AM7: 45.352099 | AN7: 45.352099 | AO7: 45.352099 | AP7: 45.352099 | AQ7: 45.352099 | AR7: 45.352099 | AS7: 45.352099 | AT7: 45.352099 | AU7: 45.352099 | AV7: 45.352099 | AW7: 45.352099 | AX7: 45.352099 | AY7: 45.352099 | AZ7: 45.352099 | BA7: 45.352099 | BB7: 45.352099 | BC7: 45.352099 | BD7: 45.352099 | BE7: 45.352099 | BF7: 45.352099 | BG7: 45.352099 | BH7: 45.352099 | BI7: 45.352099 | BJ7: 45.352099 | BK7: 45.352099 | BL7: 45.352099 | BM7: 45.352099 | BN7: 45.352099 | BO7: 45.352099 | BP7: 45.352099 | BQ7: 45.352099 | BR7: 45.352099 | BS7: 45.352099 | BT7: 45.352099 | BU7: 45.352099 | BV7: 45.352099 | BW7: 45.352099 | BX7: 45.352099 | BY7: 45.352099 | BZ7: 45.352099 | CA7: 45.352099 | CB7: 45.352099 | CC7: 45.352099 | CD7: 45.352099 | CE7: 45.352099 | CF7: 45.352099 | CG7: 45.352099 | CH7: 45.352099 | CI7: 45.352099 | CJ7: 45.352099 | CK7: 45.352099 | CL7: 45.352099 | CM7: 45.352099 | CN7: 45.352099 | CO7: 45.352099 | CP7: 45.352099 | CQ7: 45.352099 | CR7: 45.352099 | CS7: 45.352099 | CT7: 45.352099 | CU7: 45.352099 | CV7: 45.352099 | CW7: 45.352099 | CX7: 45.352099 | CY7: 45.352099 | CZ7: 45.352099 | DA7: 45.352099 | DB7: 45.352099 | DC7: 45.352099 | DD7: 45.352099 | DE7: 45.352099 | DF7: 45.352099
B8: Maakaasu | C8: Viimeisin (2023) | D8: 4 | E8: Maakaasu, Viimeisin (2023) | F8: https://www.investing.com/commodities/dutch-ttf-gas-c1-futures-historical-data | G8: 2023 | H8: Dutch TTF, heinäkuu 2023 keskiarvo | I8: 2022 EUR/MWh | J8: 26.6678 | K8: 26.6678 | L8: 26.6678 | M8: 26.6678 | N8: 26.6678 | O8: 26.6678 | P8: 26.6678 | Q8: 26.6678 | R8: 26.6678 | S8: 26.6678 | T8: 26.6678 | U8: 26.6678 | V8: 26.6678 | W8: 26.6678 | X8: 26.6678 | Y8: 26.6678 | Z8: 26.6678 | AA8: 26.6678 | AB8: 26.6678 | AC8: 26.6678 | AD8: 26.6678 | AE8: 26.6678 | AF8: 26.6678 | AG8: 26.6678 | AH8: 26.6678 | AI8: 26.6678 | AJ8: 26.6678 | AK8: 26.6678 | AL8: 26.6678 | AM8: 26.6678 | AN8: 26.6678 | AO8: 26.6678 | AP8: 26.6678 | AQ8: 26.6678 | AR8: 26.6678 | AS8: 26.6678 | AT8: 26.6678 | AU8: 26.6678 | AV8: 26.6678 | AW8: 26.6678 | AX8: 26.6678 | AY8: 26.6678 | AZ8: 26.6678 | BA8: 26.6678 | BB8: 26.6678 | BC8: 26.6678 | BD8: 26.6678 | BE8: 26.6678 | BF8: 26.6678 | BG8: 26.6678 | BH8: 26.6678 | BI8: 26.6678 | BJ8: 26.6678 | BK8: 26.6678 | BL8: 26.6678 | BM8: 26.6678 | BN8: 26.6678 | BO8: 26.6678 | BP8: 26.6678 | BQ8: 26.6678 | BR8: 26.6678 | BS8: 26.6678 | BT8: 26.6678 | BU8: 26.6678 | BV8: 26.6678 | BW8: 26.6678 | BX8: 26.6678 | BY8: 26.6678 | BZ8: 26.6678 | CA8: 26.6678 | CB8: 26.6678 | CC8: 26.6678 | CD8: 26.6678 | CE8: 26.6678 | CF8: 26.6678 | CG8: 26.6678 | CH8: 26.6678 | CI8: 26.6678 | CJ8: 26.6678 | CK8: 26.6678 | CL8: 26.6678 | CM8: 26.6678 | CN8: 26.6678 | CO8: 26.6678 | CP8: 26.6678 | CQ8: 26.6678 | CR8: 26.6678 | CS8: 26.6678 | CT8: 26.6678 | CU8: 26.6678 | CV8: 26.6678 | CW8: 26.6678 | CX8: 26.6678 | CY8: 26.6678 | CZ8: 26.6678 | DA8: 26.6678 | DB8: 26.6678 | DC8: 26.6678 | DD8: 26.6678 | DE8: 26.6678 | DF8: 26.6678
B9: Maakaasu | C9: Vuoden 2010 hinnat | D9: 5 | E9: Maakaasu, Vuoden 2010 hinnat | F9: World Bank | G9: 2023 | H9: Dutch TTF, keskiarvo 2010. Muutettu 2023 EUR/MWh. | I9: 2022 EUR/MWh | J9: 28.388 | K9: 28.388 | L9: 28.388 | M9: 28.388 | N9: 28.388 | O9: 28.388 | P9: 28.388 | Q9: 28.388 | R9: 28.388 | S9: 28.388 | T9: 28.388 | U9: 28.388 | V9: 28.388 | W9: 28.388 | X9: 28.388 | Y9: 28.388 | Z9: 28.388 | AA9: 28.388 | AB9: 28.388 | AC9: 28.388 | AD9: 28.388 | AE9: 28.388 | AF9: 28.388 | AG9: 28.388 | AH9: 28.388 | AI9: 28.388 | AJ9: 28.388 | AK9: 28.388 | AL9: 28.388 | AM9: 28.388 | AN9: 28.388 | AO9: 28.388 | AP9: 28.388 | AQ9: 28.388 | AR9: 28.388 | AS9: 28.388 | AT9: 28.388 | AU9: 28.388 | AV9: 28.388 | AW9: 28.388 | AX9: 28.388 | AY9: 28.388 | AZ9: 28.388 | BA9: 28.388 | BB9: 28.388 | BC9: 28.388 | BD9: 28.388 | BE9: 28.388 | BF9: 28.388 | BG9: 28.388 | BH9: 28.388 | BI9: 28.388 | BJ9: 28.388 | BK9: 28.388 | BL9: 28.388 | BM9: 28.388 | BN9: 28.388 | BO9: 28.388 | BP9: 28.388 | BQ9: 28.388 | BR9: 28.388 | BS9: 28.388 | BT9: 28.388 | BU9: 28.388 | BV9: 28.388 | BW9: 28.388 | BX9: 28.388 | BY9: 28.388 | BZ9: 28.388 | CA9: 28.388 | CB9: 28.388 | CC9: 28.388 | CD9: 28.388 | CE9: 28.388 | CF9: 28.388 | CG9: 28.388 | CH9: 28.388 | CI9: 28.388 | CJ9: 28.388 | CK9: 28.388 | CL9: 28.388 | CM9: 28.388 | CN9: 28.388 | CO9: 28.388 | CP9: 28.388 | CQ9: 28.388 | CR9: 28.388 | CS9: 28.388 | CT9: 28.388 | CU9: 28.388 | CV9: 28.388 | CW9: 28.388 | CX9: 28.388 | CY9: 28.388 | CZ9: 28.388 | DA9: 28.388 | DB9: 28.388 | DC9: 28.388 | DD9: 28.388 | DE9: 28.388 | DF9: 28.388
B10: Maakaasu | C10: Suomi, 2010 hinnat | D10: 6 | E10: Maakaasu, Suomi, 2010 hinnat | F10: https://aurisenergia.fi/suomen-kaasuenergian-toiminta-kaasutoimitusten-mahdollisissa-hairioissa/ | G10: 2023 | H10: Syksylle 2023 ennustettu hintataso, EUR/MWh | I10: 2022 EUR/MWh | J10: 47 | K10: 47 | L10: 47 | M10: 47 | N10: 47 | O10: 47 | P10: 47 | Q10: 47 | R10: 47 | S10: 47 | T10: 47 | U10: 47 | V10: 47 | W10: 47 | X10: 47 | Y10: 47 | Z10: 47 | AA10: 47 | AB10: 47 | AC10: 47 | AD10: 47 | AE10: 47 | AF10: 47 | AG10: 47 | AH10: 47 | AI10: 47 | AJ10: 47 | AK10: 47 | AL10: 47 | AM10: 47 | AN10: 47 | AO10: 47 | AP10: 47 | AQ10: 47 | AR10: 47 | AS10: 47 | AT10: 47 | AU10: 47 | AV10: 47 | AW10: 47 | AX10: 47 | AY10: 47 | AZ10: 47 | BA10: 47 | BB10: 47 | BC10: 47 | BD10: 47 | BE10: 47 | BF10: 47 | BG10: 47 | BH10: 47 | BI10: 47 | BJ10: 47 | BK10: 47 | BL10: 47 | BM10: 47 | BN10: 47 | BO10: 47 | BP10: 47 | BQ10: 47 | BR10: 47 | BS10: 47 | BT10: 47 | BU10: 47 | BV10: 47 | BW10: 47 | BX10: 47 | BY10: 47 | BZ10: 47 | CA10: 47 | CB10: 47 | CC10: 47 | CD10: 47 | CE10: 47 | CF10: 47 | CG10: 47 | CH10: 47 | CI10: 47 | CJ10: 47 | CK10: 47 | CL10: 47 | CM10: 47 | CN10: 47 | CO10: 47 | CP10: 47 | CQ10: 47 | CR10: 47 | CS10: 47 | CT10: 47 | CU10: 47 | CV10: 47 | CW10: 47 | CX10: 47 | CY10: 47 | CZ10: 47 | DA10: 47 | DB10: 47 | DC10: 47 | DD10: 47 | DE10: 47 | DF10: 47
B11: Maakaasu | C11: Suomi, viimeisin (2023) | D11: 7 | E11: Maakaasu, Suomi, viimeisin (2023) | F11: https://energiavirasto.fi/maakaasun-hintatilastot | G11: 2010 | H11: Suomi, Energiavirasto. Teollisuusasiakkaiden 2010 keskiarvo siirtohintoineen 23,88 EUR/MWh (lhv), veroton. Muutettu 2022 euroiksi Tilastokeskuksen kertoimella 1,2339. | I11: 2022 EUR/MWh | J11: 27.6976 | K11: 27.6976 | L11: 27.6976 | M11: 27.6976 | N11: 27.6976 | O11: 27.6976 | P11: 27.6976 | Q11: 27.6976 | R11: 27.6976 | S11: 27.6976 | T11: 27.6976 | U11: 27.6976 | V11: 27.6976 | W11: 27.6976 | X11: 27.6976 | Y11: 27.6976 | Z11: 27.6976 | AA11: 27.6976 | AB11: 27.6976 | AC11: 27.6976 | AD11: 27.6976 | AE11: 27.6976 | AF11: 27.6976 | AG11: 27.6976 | AH11: 27.6976 | AI11: 27.6976 | AJ11: 27.6976 | AK11: 27.6976 | AL11: 27.6976 | AM11: 27.6976 | AN11: 27.6976 | AO11: 27.6976 | AP11: 27.6976 | AQ11: 27.6976 | AR11: 27.6976 | AS11: 27.6976 | AT11: 27.6976 | AU11: 27.6976 | AV11: 27.6976 | AW11: 27.6976 | AX11: 27.6976 | AY11: 27.6976 | AZ11: 27.6976 | BA11: 27.6976 | BB11: 27.6976 | BC11: 27.6976 | BD11: 27.6976 | BE11: 27.6976 | BF11: 27.6976 | BG11: 27.6976 | BH11: 27.6976 | BI11: 27.6976 | BJ11: 27.6976 | BK11: 27.6976 | BL11: 27.6976 | BM11: 27.6976 | BN11: 27.6976 | BO11: 27.6976 | BP11: 27.6976 | BQ11: 27.6976 | BR11: 27.6976 | BS11: 27.6976 | BT11: 27.6976 | BU11: 27.6976 | BV11: 27.6976 | BW11: 27.6976 | BX11: 27.6976 | BY11: 27.6976 | BZ11: 27.6976 | CA11: 27.6976 | CB11: 27.6976 | CC11: 27.6976 | CD11: 27.6976 | CE11: 27.6976 | CF11: 27.6976 | CG11: 27.6976 | CH11: 27.6976 | CI11: 27.6976 | CJ11: 27.6976 | CK11: 27.6976 | CL11: 27.6976 | CM11: 27.6976 | CN11: 27.6976 | CO11: 27.6976 | CP11: 27.6976 | CQ11: 27.6976 | CR11: 27.6976 | CS11: 27.6976 | CT11: 27.6976 | CU11: 27.6976 | CV11: 27.6976 | CW11: 27.6976 | CX11: 27.6976 | CY11: 27.6976 | CZ11: 27.6976 | DA11: 27.6976 | DB11: 27.6976 | DC11: 27.6976 | DD11: 27.6976 | DE11: 27.6976 | DF11: 27.6976
